Workbook

Sheet Summary Dashboard
A1: INDICATORS | B1: ACTIVITIES | C1: TARGET | D1: ACHIEVED | E1: VARIANCE | F1: PERCENTAGE ACHIEVED
A2: RESULT 2:Local partners effectively respond to GBV and protection risks among new arrivals appropriate to their age, gender, and disability.
A3: Indicator 1 Number of survivors who receive an appropriate response to GBV | B3: GBV Case Management | C3: 550 | D3: =SUM('Activity Tracking Table'!KG4+'Activity Tracking Table'!KG5) -> 467 | E3: ='Summary Dashboard'!C3-'Summary Dashboard'!D3 -> 83 | F3: =D3/C3 -> 0.84909091 | G3: =(F5+F3)/2 -> 0.92454545
B4: Provide in kind material support to GBV survivors (dignity kits) -(through referrals) | C4: 300 | D4: 64 | E4: =C4-D4 -> 236 | F4: =D4/C4 -> 0.21333333
B5: GBV Case Conferencing | C5: 2 | D5: 2 | E5: =C5-D5 -> 0 | F5: =D5/C5 -> 1
A6: Indicator 2 Number of participants showing an increased knowledge on the protection subject in focus | B6: Training GBV Community Structures | C6: 130 | D6: ='Activity Tracking Table'!KG10 -> 97 | E6: =C6-D6 -> 33 | F6: =D6/C6 -> 0.74615385 | G6: =F6 -> 0.74615385
B7: Clinical Health Training for 30 health workers, clinical care sexual assault. 30 police officers | C7: 60 | D7: ='Activity Tracking Table'!KG11 -> 0 | E7: =C7-D7 -> 60 | F7: =D7/C7 -> 0
A8: Indicator 3 Number of persons effectively referred to other specialised service or assistance providers | B8: GBV Referrals | C8: 550 | D8: ='Activity Tracking Table'!#REF! -> #REF! | E8: =C8-D8 -> #REF! | F8: =D8/C8 -> #REF! | G8: =F8 -> #REF!
A9: Indicator 4 Number of persons with increased/appropriate information on relevant rights and/or entitlements | B9: Training WGSS CMCS on leadership and safe space management and income generating activities [IGA] | C9: 25 | D9: ='Activity Tracking Table'!KG12 -> 48 | E9: =C9-D9 -> -23 | F9: =D9/C9 -> 1.92 | G9: =(F9+F11)/2 -> 1.46
B10: Training Facilitators for Women and Girls Safe Spaces | C10: 2 | D10: ='Activity Tracking Table'!KG13 -> 0 | E10: =C10-D10 -> 2 | F10: =D10/C10 -> 0
B11: Provide working Tools to GBV Structures | C11: 50 | D11: ='Activity Tracking Table'!KG14 -> 50 | E11: =C11-D11 -> 0 | F11: =D11/C11 -> 1
B12: Sensitization dialogues & Awarenes Sessions | D12: ='Activity Tracking Table'!KG22+'Activity Tracking Table'!KG23+'Activity Tracking Table'!KG24 -> 13550
A13: Indicator 5 Percentage of women and girls with specific protection needs (e.g., survivors of gender-based violence, persons with disabilities, pregnant or lactating women) who report feeling safe and supported after accessing services at the women and girls safe spaces. | B13: Provide integrated services to women and girls at the safe spaces | C13: 4500 | D13: ='Activity Tracking Table'!#REF! -> #REF! | E13: =C13-D13 -> #REF! | F13: =D13/C13 -> #REF! | G13: =(F13+F16+F17)/3 -> #REF!
B15: Referrals made from Women and Girls Safe Spaces | C15: 45 | D15: ='Activity Tracking Table'!KG16 -> 22 | E15: =C15-D15 -> 23 | F15: =D15/C15 -> 0.48888889
B16: Establish or Maintain Girl's Safe Spaces | C16: 3 | D16: 2 | E16: =C16-D16 -> 1 | F16: =D16/C16 -> 0.66666667
B17: Comic Books Sessions | C17: 450 | D17: ='Activity Tracking Table'!KG35 -> 275 | E17: =C17-D17 -> 175 | F17: =D17/C17 -> 0.61111111
B18: Skilling to girls | C18: 225 | D18: ='Activity Tracking Table'!KG17 -> 0 | E18: =C18-D18 -> 225 | F18: =D18/C18 -> 0
A20: RESULT 3:Local partners effectively respond to Child Protection risks among new arrivals appropriate to their age, gender, and disability
A21: Indicator 1: Number of persons who receive an appropriate response | B21: Case Management (Children) Nakivale | C21: 1350 | D21: ='Activity Tracking Table'!KG34 -> 429 | E21: =C21-D21 -> 921 | F21: =D21/C21 -> 0.31777778 | G21: =(F21+F22+F25+F26+F31+F30)/6 -> 0.9425463
B22: Case Management (Children) Nyakabande | C22: 2000 | D22: ='Activity Tracking Table'!KG35 -> 275 | E22: =C22-D22 -> 1725 | F22: =D22/C22 -> 0.1375
B23: Identify register, assess and support children to access different services through the referral pathway (Nakivale) | C23: 1200 | D23: ='Activity Tracking Table'!KG36 -> 1000 | E23: =C23-D23 -> 200 | F23: =D23/C23 -> 0.83333333
B24: Identify register, assess and support children to access different services through the referral pathway (Nyakabande) | C24: 200 | D24: ='Activity Tracking Table'!KG37 -> 134 | E24: =C24-D24 -> 66 | F24: =D24/C24 -> 0.67
B25: Case Conferencing | C25: 5 | D25: ='Activity Tracking Table'!KG38 -> 6 | E25: =C25-D25 -> -1 | F25: =D25/C25 -> 1.2
B26: Team UP | C26: 240 | D26: ='Activity Tracking Table'!KG39 -> 240 | E26: =C26-D26 -> 0 | F26: =D26/C26 -> 1
B27: Training Team Up facilitators | D27: ='Activity Tracking Table'!KG55 -> 9 | E27: ='Activity Tracking Table'!BG319 -> 0
B28: Facilitate CFS Facilitators to support activities at the CFS centers | C28: 6 | D28: 7 | E28: =C28-D28 -> -1 | F28: =D28/C28 -> 1.1666667
B29: Provide material support to foster parents and care givers | C29: 50 | D29: ='Activity Tracking Table'!KG41 -> 69 | E29: =C29-D29 -> -19 | F29: =D29/C29 -> 1.38
B30: Support to lactating mothers | C30: 50 | D30: ='Activity Tracking Table'!KG42 -> 100 | E30: =C30-D30 -> -50 | F30: =D30/C30 -> 2
B31: Provide Individual Protection Assistance to children like blankets, sleeping mats, clothes.etc | C31: 600 | D31: ='Activity Tracking Table'!KG43 -> 600 | E31: =C31-D31 -> 0 | F31: =D31/C31 -> 1
A32: Indicator 2: Number of unaccompanied and/or separated children who are reunited with their caregivers OR in appropriate protective arrangements based on BIA. | B32: Conduct child family tracing and reunification | C32: 10 | D32: ='Activity Tracking Table'!KG47 -> 70 | E32: =C32-D32 -> -60 | F32: =D32/C32 -> 7
B33: Unaccompanied & seperated Children supported | D33: ='Activity Tracking Table'!KG48 -> 135
B34: Foster parents identified | C34: 100 | D34: ='Activity Tracking Table'!KG49 -> 30 | E34: =C34-D34 -> 70
B35: Children placed under foster care | D35: ='Activity Tracking Table'!KG50 -> 48
A36: Indicator 3: Number of participants showing an increased knowledge on the protection subject in focus. | B36: Training and mentorship of community-level actors and structures Support to parasocial workers, shelter leaders, community leaders. (Strengthening the capacity of community structures) | C36: 150 | D36: ='Activity Tracking Table'!KG51 -> 150 | E36: =C36-D36 -> 0 | F36: =D36/C36 -> 1
A37: Indicator 4: Number of parents, caregivers, foster families, and community stakeholders who receive training, guidance and support to address child protection concerns | B37: Positive Parenting and Parenting without violence approaches (Nakivale & Nyakabande) | C37: 350 | D37: ='Activity Tracking Table'!KG62 -> 866 | E37: =C37-D37 -> -516 | F37: =(D38+D37)/1350 -> 1.322963 | H37: New Target for both activities is 1350 👈Achieved Percentage is for both Activities in comparison with new target.
B38: Sensitize parents, caregivers, and community members on the prevention of abuse and neglect of children (Nakivale & Nyakabande) | C38: 960 | D38: ='Activity Tracking Table'!KG63 -> 920 | E38: =C38-D38 -> 40 | F38: =D38/C38 -> 0.95833333
B39: Train CPCs, Parasocial workers, shelter leaders and community leaders. | C39: 5 | D39: ='Activity Tracking Table'!KG54 -> 0 | E39: =C39-D39 -> 5 | F39: =D39/C39 -> 0
B40: Training and mentoring for district local government staff (Nakivale and Nyakabande) | C40: 120 | D40: ='Activity Tracking Table'!KG53 -> 0 | E40: =C40-D40 -> 120 | F40: =D40/C40 -> 0
B41: Facilitation for Follow-up through home visits for children at high protection risks (To be conducted by the LG, in coordination with the CPCs to follow-up on the safety of these children. SubCounty and District specific CPCs will be supported to meet regularly through this action.) | C41: 4 | D41: ='Activity Tracking Table'!KG65 -> 15 | E41: =C41-D41 -> -11 | F41: =D41/C41 -> 3.75
B42: Traning CPS and Shelter leaders (5 CPCs and 5 Shelter Leaders) | C42: 10 | D42: ='Activity Tracking Table'!#REF! -> #REF! | E42: =C42-D42 -> #REF! | F42: =D42/C42 -> #REF!
B43: Hold monthly supervision meetings with CPs and shelter leaders | C43: 13 | D43: ='Activity Tracking Table'!KG68 -> 0 | E43: =C43-D43 -> 13 | F43: =D43/C43 -> 0
B44: Support of Children's Rights Clubs at School | C44: 3 | D44: ='Activity Tracking Table'!KG69 -> 0 | E44: =C44-D44 -> 3 | F44: =D44/C44 -> 0
A45: Indicator 5: Number of functional community action plans developed by communities to address specific CP concerns in their communities. | B45: Develop Community Action Plans | C45: 2 | D45: 2 | E45: =C45-D45 -> 0 | F45: =D45/C45 -> 1
B46: Establish and / or maintain child friendly spaces | C46: 2 | D46: 0 | E46: =C46-D46 -> 2 | F46: =D46/C46 -> 0
B47: Operationalise child friendly spaces | C47: 1 | D47: 4 | E47: =C47-D47 -> -3 | F47: =D47/C47 -> 4
B48: Train CSF Facilitators to support peer to peer group ativities at the CFS centres. | C48: 20 | D48: 7 | E48: =C48-D48 -> 13 | F48: =D48/C48 -> 0.35
B49: Map community-based child protection mechanisms | C49: 1 | D49: 1 | E49: =C49-D49 -> 0 | F49: =D49/C49 -> 1
A50: Indicator 6: Number of children and parents/ caregiver who have been reached by environmental conservation initiatives by the end of the intervention compared to the beginning. | B50: Environmental conservation and climate education | C50: 2800 | D50: ='Activity Tracking Table'!KG74 -> 2168 | E50: =C50-D50 -> 632 | F50: =D50/C50 -> 0.77428571 | G50: =F50 -> 0.77428571
B51: Sensitization dialogues & Awarenes Sessions (Including World Breastfeeding day) | D51: ='Activity Tracking Table'!KG76 -> 0
B53: Update the referral pathways together with other implementing partners. | C53: 1 | D53: ='Activity Tracking Table'!KG78 -> 0 | E53: =C53-D53 -> 1 | F53: =D53/C53 -> 0
B54: Establish complaints and feedback mechanisms to solicit and give feedback to the community. | C54: 70 | D54: ='Activity Tracking Table'!KG79 -> 350 | E54: =C54-D54 -> -280 | F54: =D54/C54 -> 5

Sheet Activity Tracking Table
A1: STEPS - Sustainable Transition to Locally Led Emergency Protection Services | C1: Location | D1: Target | E1: 45474 | K1: Jul Totals | O1: 45505 | U1: Aug Totals | Y1: 45536 | AE1: Sep Totals | AI1: 45566 | AO1: Oct Totals | AT1: Quarter 1 Totals | AW1: Quarter 1 | AZ1: Total Female Refugees | BA1: Total Male Refugees | BB1: Total Female Host | BC1: Total Male Host | BD1: 45597 | BJ1: Nov Totals | BN1: 45627 | BT1: Dec Totals | CC1: 45658 | CI1: Jan Totals | CM1: 45689 | CS1: Feb Totals | CW1: Quarter 2 | DA1: Quarter 2 | DD1: Total Female Refugees | DE1: Total Male Refugees | DF1: Total Female Host | DG1: Total Male Host | DH1: Total Achievement Year 1 | DI1: 45717 | DO1: Mar Totals | DS1: 45748 | DY1: Apr Totals | EC1: 45778 | EI1: May Totals | EM1: 45809 | ES1: Jun Totals | EW1: Quarter 3 | FA1: Quarter 3 | FD1: Total Female Refugees | FE1: Total Male Refugees | FF1: Total Female Host | FG1: Total Male Host | FH1: Total Female Jan-Jun | FI1: Total Male Jan-Jun | FJ1: Total | FN1: 45839 | FT1: Jul Totals | FX1: 45870 | GD1: Aug Totals | GH1: 45901 | GN1: Sep Totals | GR1: Nov 2024- Sep 2025 Totals | GX1: 45931 | HD1: Oct Totals | HH1: Quarter 4 | HN1: Quarter 4 | HQ1: Total Female Refugees | HR1: Total Male Refugees | HS1: Total Female Host | HT1: Total Male Host | HU1: 45962 | IA1: Nov Totals | IE1: 45992 | IK1: Dec Totals | IO1: 46023 | IU1: Jan Totals | IY1: 46054 | JE1: Feb Totals | JI1: Quarter 5 | JM1: Quarter 5 | JP1: 46082 | JV1: Mar Totals | JZ1: Total Year 2 | KA1: Disagregated Totals | KG1: Total Reach
E2: Refugee | H2: National | O2: Refugee | R2: National | Y2: Refugee | AB2: National | AI2: Refugee | AL2: National | BD2: Refugee | BG2: National | BN2: Refugee | BQ2: National | BX2: Total Female Refugees | BY2: Total Male Refugees | BZ2: Total Female Host | CA2: Total Male Host | CB2: Total Achievement Year 1 | CC2: Refugee | CF2: National | CM2: Refugee | CP2: National | DI2: Refugee | DL2: National | DS2: Refugee | DV2: National | EC2: Refugee | EF2: National | EM2: Refugee | EP2: National | FK2: Cumulative Female | FL2: Cumulative Male | FM2: Cumulative Total | FN2: Refugee | FQ2: National | FX2: Refugee | GA2: National | GH2: Refugee | GK2: National | GR2: Total Female | GS2: Total Male | GT2: Total Female Refugees | GU2: Total Male Refugees | GV2: Total Female Host | GW2: Total Male Host | GX2: Refugee | HA2: National | HH2: Total Female Q! | HI2: Total Male Q1 | HJ2: Total Female Refugees | HK2: Total Male Refugees | HL2: Total Female Host | HM2: Total Male Host | HN2: Target | HO2: Achieved | HP2: % Achieved | HU2: Refugee | HX2: National | IE2: Refugee | IH2: National | IO2: Refugee | IR2: National | IY2: Refugee | JB2: National | JP2: Refugee | JS2: National | KA2: Total Female | KB2: Total Male | KC2: Total Female Refugees | KD2: Total Male Refugees | KE2: Total Female Host | KF2: Total Male Host
A3: RESULT 2:Local partners effectively respond to GBV and protection risks among new arrivals appropriate to their age, gender, and disability. | E3: Female | F3: Male | G3: Total | H3: Female | I3: Male | J3: Total | K3: Total Female | L3: Total Male | M3: Total | N3: Sessions | O3: Female | P3: Male | Q3: Total | R3: Female | S3: Male | T3: Total | U3: Total Female | V3: Total Male | W3: Total | X3: Sessions | Y3: Female | Z3: Male | AA3: Total | AB3: Female | AC3: Male | AD3: Total | AE3: Total Female | AF3: Total Male | AG3: Total | AH3: Sessions | AI3: Female | AJ3: Male | AK3: Total | AL3: Female | AM3: Male | AN3: Total | AO3: Total Female | AP3: Total Male | AQ3: Total | AR3: Sessions | AS3: Total Female Q! | AT3: Total Male Q1 | AU3: Total Refugees Q1 | AV3: Total Nationals Q1 | AW3: Target | AX3: Achieved | AY3: % Achieved | BD3: Female | BE3: Male | BF3: Total | BG3: Female | BH3: Male | BI3: Total | BJ3: Total Female | BK3: Total Male | BL3: Total | BM3: Sessions | BN3: Female | BO3: Male | BP3: Total | BQ3: Female | BR3: Male | BS3: Total | BT3: Total Female | BU3: Total Male | BV3: Total | BW3: Sessions | CC3: Female | CD3: Male | CE3: Total | CF3: Female | CG3: Male | CH3: Total | CI3: Total Female | CJ3: Total Male | CK3: Total | CL3: Sessions | CM3: Female | CN3: Male | CO3: Total | CP3: Female | CQ3: Male | CR3: Total | CS3: Total Female | CT3: Total Male | CU3: Total | CV3: Sessions | CW3: Total Female Q2 | CX3: Total Male Q2 | CY3: Total Refugees Q2 | CZ3: Total Nationals Q2 | DA3: Target | DB3: Achieved | DC3: % Achieved | DI3: Female | DJ3: Male | DK3: Total | DL3: Female | DM3: Male | DN3: Total | DO3: Total Female | DP3: Total Male | DQ3: Total | DR3: Sessions | DS3: Female | DT3: Male | DU3: Total | DV3: Female | DW3: Male | DX3: Total | DY3: Total Female | DZ3: Total Male | EA3: Total | EB3: Sessions | EC3: Female | ED3: Male | EE3: Total | EF3: Female | EG3: Male | EH3: Total | EI3: Total Female | EJ3: Total Male | EK3: Total | EL3: Sessions | EM3: Female | EN3: Male | EO3: Total | EP3: Female | EQ3: Male | ER3: Total | ES3: Total Female | ET3: Total Male | EU3: Total | EV3: Sessions | EW3: Total Female Q3 | EX3: Total Male Q3 | EY3: Total Refugees Q3 | EZ3: Total Nationals Q3 | FA3: Target | FB3: Achieved | FC3: % Achieved | FN3: Female | FO3: Male | FP3: Total | FQ3: Female | FR3: Male | FS3: Total | FT3: Total Female | FU3: Total Male | FV3: Total | FW3: Sessions | FX3: Female | FY3: Male | FZ3: Total | GA3: Female | GB3: Male | GC3: Total | GD3: Total Female | GE3: Total Male | GF3: Total | GG3: Sessions | GH3: Female | GI3: Male | GJ3: Total | GK3: Female | GL3: Male | GM3: Total | GN3: Total Female | GO3: Total Male | GP3: Total | GQ3: Sessions | GX3: Female | GY3: Male | GZ3: Total | HA3: Female | HB3: Male | HC3: Total | HD3: Total Female | HE3: Total Male | HF3: Total | HG3: Sessions | HU3: Female | HV3: Male | HW3: Total | HX3: Female | HY3: Male | HZ3: Total | IA3: Total Female | IB3: Total Male | IC3: Total | ID3: Sessions | IE3: Female | IF3: Male | IG3: Total | IH3: Female | II3: Male | IJ3: Total | IK3: Total Female | IL3: Total Male | IM3: Total | IN3: Sessions | IO3: Female | IP3: Male | IQ3: Total | IR3: Female | IS3: Male | IT3: Total | IU3: Total Female | IV3: Total Male | IW3: Total | IX3: Sessions | IY3: Female | IZ3: Male | JA3: Total | JB3: Female | JC3: Male | JD3: Total | JE3: Total Female | JF3: Total Male | JG3: Total | JI3: Total Female Q! | JJ3: Total Male Q1 | JK3: Total Refugees Q1 | JL3: Total Nationals Q1 | JM3: Target | JN3: Achieved | JO3: % Achieved | JP3: Female | JQ3: Male | JR3: Total | JS3: Female | JT3: Male | JU3: Total | JV3: Total Female | JW3: Total Male | JX3: Total | JY3: Sessions | KG3: Total Reach | KH3: Target | KI3: Variance | KJ3: Achieved
A4: Indicator 1 Number of survivors who receive an appropriate response to GBV | B4: GBV Case Management | C4: Nakivale | D4: 550 | O4: 8 | P4: 1 | Q4: =SUM(O4:P4) -> 9 | R4: 0 | S4: 0 | T4: =SUM(R4:S4) -> 0 | U4: =SUM(O4+R4) -> 8 | V4: =SUM(P4+S4) -> 1 | W4: =SUM(U4:V4) -> 9 | Y4: 11 | Z4: 1 | AA4: =SUM(Y4:Z4) -> 12 | AB4: 1 | AC4: 0 | AD4: =SUM(AB4:AC4) -> 1 | AE4: =SUM(Y4+AB4) -> 12 | AF4: =SUM(Z4+AC4) -> 1 | AG4: =SUM(AE4:AF4) -> 13 | AI4: 17 | AJ4: 0 | AK4: =SUM(AI4:AJ4) -> 17 | AL4: 0 | AM4: 0 | AN4: =SUM(AL4:AM4) -> 0 | AO4: =SUM(AI4+AL4) -> 17 | AP4: =SUM(AJ4+AM4) -> 0 | AQ4: =SUM(AO4:AP4) -> 17 | AS4: =AO4+AE4+U4+K4 -> 37 | AT4: =AP4+AF4+V4+L4 -> 2 | AU4: =AK4+AA4+Q4+G4 -> 38 | AV4: =J4+T4+AD4+AN4 -> 1 | AW4: 220 | AX4: =SUM(AQ4+AG4+W4+M4) -> 39 | AY4: =AX4/AW4 -> 0.17727273 | AZ4: =SUM(E4+O4+Y4+AI4) -> 36 | BA4: =F4+P4+Z4+AJ4 -> 2 | BB4: =H4+R4+AB4+AL4 -> 1 | BC4: =I4+S4+AC4+AM4 -> 0 | BD4: 19 | BE4: 0 | BF4: =SUM(BD4:BE4) -> 19 | BG4: 1 | BH4: 0 | BI4: =SUM(BG4:BH4) -> 1 | BJ4: =SUM(BD4+BG4) -> 20 | BK4: =SUM(BE4+BH4) -> 0 | BL4: =SUM(BJ4:BK4) -> 20 | BN4: 9 | BO4: 0 | BP4: =SUM(BN4:BO4) -> 9 | BQ4: 0 | BR4: 0 | BS4: =SUM(BQ4:BR4) -> 0 | BT4: =SUM(BN4+BQ4) -> 9 | BU4: =SUM(BO4+BR4) -> 0 | BV4: =SUM(BT4:BU4) -> 9 | BX4: =BN4+BD4+AI4+Y4+O4+E4 -> 64 | BY4: =BO4+BE4+AJ4+Z4+P4+F4 -> 2 | BZ4: =BQ4+BG4+AL4+AB4+R4+H4 -> 2 | CA4: =BR4+BH4+AM4+AC4+S4+I4 -> 0 | CB4: =BX4+BY4+BZ4+CA4 -> 68 | CC4: 11 | CD4: 0 | CE4: =SUM(CC4:CD4) -> 11 | CF4: 0 | CG4: 0 | CH4: =SUM(CF4:CG4) -> 0 | CI4: =SUM(CC4+CF4) -> 11 | CJ4: =SUM(CD4+CG4) -> 0 | CK4: =SUM(CI4:CJ4) -> 11 | CM4: 18 | CN4: 0 | CO4: =SUM(CM4:CN4) -> 18 | CP4: 0 | CQ4: 0 | CR4: =SUM(CP4:CQ4) -> 0 | CS4: 18 | CT4: =SUM(CN4+CQ4) -> 0 | CU4: =SUM(CS4:CT4) -> 18 | CW4: =SUM(CS4+CI4+BT4+BJ4) -> 58 | CX4: =SUM(CT4+CJ4+BU4+BK4) -> 0 | CY4: =SUM(CU4+CK4+BV4+BL4) -> 58 | CZ4: =SUM(CR4+CH4+BS4+BI4) -> 1 | DA4: 220 | DB4: =SUM(CW4:CX4) -> 58 | DC4: =DB4/DA4 -> 0.26363636 | DD4: =BD4+BN4+CC4+CM4 -> 57 | DE4: =BE4+BO4+CD4+CN4 -> 0 | DF4: =BG4+BQ4+CF4+CP4 -> 1 | DG4: =BH4+BR4+CG4+CQ4 -> 0 | DH4: =DB4+AX4 -> 97 | DI4: 20 | DJ4: 0 | DK4: =SUM(DI4:DJ4) -> 20 | DL4: 0 | DM4: 0 | DN4: =SUM(DL4:DM4) -> 0 | DO4: =SUM(DI4+DL4) -> 20 | DP4: 0 | DQ4: =SUM(DO4:DP4) -> 20 | DS4: 24 | DT4: 0 | DU4: =SUM(DS4:DT4) -> 24 | DV4: 0 | DW4: 0 | DX4: =SUM(DV4:DX4) -> 0 | DY4: =SUM(DS4+DV4) -> 24 | DZ4: =SUM(DT4+DW4) -> 0 | EA4: =SUM(DY4:DZ4) -> 24 | EC4: 14 | ED4: 0 | EE4: =SUM(EC4:ED4) -> 14 | EF4: 0 | EG4: 0 | EH4: =SUM(EF4:EG4) -> 0 | EI4: 14 | EJ4: =SUM(ED4+EG4) -> 0 | EK4: =SUM(EI4:EJ4) -> 14 | EM4: 17 | EN4: 0 | EO4: =SUM(EM4:EN4) -> 17 | EP4: 0 | EQ4: 0 | ER4: =SUM(EP4:EQ4) -> 0 | ES4: =SUM(EM4+EP4) -> 17 | ET4: =SUM(EN4+EQ4) -> 0 | EU4: =SUM(ES4:ET4) -> 17 | EW4: =SUM(ES4+EI4+DY4+DO4) -> 75 | EX4: =SUM(ET4+EJ4+DZ4+DP4) -> 0 | EY4: =SUM(EO4+EE4+DU4+DK4) -> 75 | EZ4: =SUM(ER4+EH4+DX4+DN4) -> 0 | FA4: 75 | FB4: =SUM(EW4:EX4) -> 75 | FC4: =FB4/FA4 -> 1 | FD4: =DI4+DS4+EC4+EM4+CM4+CC4 -> 104 | FE4: =DJ4+DT4+ED4+EN4+CD4+CN4 -> 0 | FF4: =DL4+DV4+EF4+EP4+CP4+CF4 -> 0 | FG4: =DM4+DW4+EG4+EQ4+CG4+CQ4 -> 0 | FH4: =FD4+FF4 -> 104 | FI4: =FE4+FG4 -> 0 | FJ4: =FH4+FI4 -> 104 | FK4: =EW4+CW4+AS4 -> 170 | FL4: =EX4+CX4+AT4 -> 2 | FM4: =FK4+FL4 -> 172 | FN4: 15 | FO4: 0 | FP4: =SUM(FN4:FO4) -> 15 | FQ4: 0 | FR4: 0 | FS4: =SUM(FQ4:FR4) -> 0 | FT4: =FN4+FQ4 -> 15 | FU4: =FO4+FR4 -> 0 | FV4: =SUM(FT4:FU4) -> 15 | FX4: 31 | FY4: 0 | FZ4: =SUM(FX4:FY4) -> 31 | GA4: 0 | GB4: 0 | GC4: =SUM(GA4:GB4) -> 0 | GD4: =FX4+GA4 -> 31 | GE4: =FY4+GB4 -> 0 | GF4: =GD4+GE4 -> 31 | GH4: 21 | GI4: 0 | GJ4: =SUM(GH4:GI4) -> 21 | GK4: 0 | GL4: 0 | GM4: =SUM(GK4:GL4) -> 0 | GN4: =GH4+GK4 -> 21 | GO4: =GI4+GL4 -> 0 | GP4: =GN4+GO4 -> 21 | GR4: =GN4+GD4+FT4+ES4+EI4+DY4+DO4+CS4+CI4+BT4+BJ4 -> 200 | GS4: =GO4+GE4+FU4+ET4+EJ4+DZ4+DP4+CT4+CJ4+BU4+BK4 -> 0 | GT4: =GH4+FX4+FN4+EM4+EC4+DS4+DI4+CM4+CC4+BN4+BD4 -> 199 | GU4: =GI4+FY4+FO4+EN4+ED4+DT4+DJ4+CN4+CD4+BO4+BE4 -> 0 | GV4: =GK4+GA4+FQ4+EP4+EF4+DV4+DL4+CP4+CF4+BQ4+BG4 -> 1 | GW4: =GL4+GB4+FR4+EQ4+EG4+DW4+DM4+CQ4+CG4+BR4+BH4 -> 0 | GX4: 16 | GY4: 0 | GZ4: =GX4+GY4 -> 16 | HA4: 0 | HB4: 0 | HC4: =HA4+HB4 -> 0 | HD4: =GX4+HA4 -> 16 | HE4: =GY4+HB4 -> 0 | HF4: =HD4+HE4 -> 16 | HH4: =HD4+GN4+GD4+FT4 -> 83 | HI4: =GO4+GE4+FU4+HE4 -> 0 | HJ4: =GX4+GH4+FX4+FN4 -> 83 | HK4: =GI4+FY4+GY4+FO4 -> 0 | HL4: =GK4+GA4+FQ4+HA4 -> 0 | HM4: =GL4+HB4+GB4+FR4 -> 0 | HO4: =HF4+GP4+GF4+FV4 -> 83 | HP4: =HO4/HN4 -> #DIV/0! | HQ4: =FN4+FX4+GH4+GX4 -> 83 | HR4: =FO4+FY4+GI4+GY4 -> 0 | HS4: =FQ4+GA4+GK4+HA4 -> 0 | HT4: =FR4+GB4+GL4+HB4 -> 0 | HU4: 11 | HV4: 0 | HW4: =HU4+HV4 -> 11 | HX4: 1 | HY4: 0 | HZ4: =HX4+HY4 -> 1 | IA4: =HU4+HX4 -> 12 | IB4: =HV4+HY4 -> 0 | IC4: =IA4+IB4 -> 12 | JN4: =JG4+IW4+IM4+IC4 -> 12 | JO4: =JN4/JM4 -> #DIV/0! | JZ4: =JX4+JN4+HO4+FB4 -> 170 | KA4: =SUM(JV4+JE4+IU4+IK4+IA4+HD4+GN4+GD4+FT4+ES4+EI4+DY4+DO4+CS4+CI4+BT4+BJ4+AO4+AE4+U4+K4) -> 265 | KB4: =SUM(JW4+JF4+IV4+IL4+IB4+HE4+GO4+GE4+FU4+ET4+EJ4+DZ4+DP4+CT4+CJ4+BU4+BK4+AP4+AF4+V4+L4) -> 2 | KC4: =SUM(JP4+IY4+IO4+IE4+HU4+GX4+GH4+FX4+FN4+EM4+EC4+DS4+DI4+CM4+CC4+BN4+BD4+AI4+Y4+O4+E4) -> 262 | KD4: =SUM(JQ4+IZ4+IP4+IF4+HV4+GY4+GI4+FY4+FO4+EN4+ED4+DT4+DJ4+CN4+CD4+BO4+BE4+AJ4+Z4+P4+F4) -> 2 | KE4: =SUM(JS4+JB4+IR4+IH4+HX4+HA4+GK4+GA4+FQ4+EP4+EF4+DV4+DL4+CP4+CF4+BQ4+BG4+AL4+AB4+R4+H4) -> 3 | KF4: =SUM(JT4+JC4+IS4+II4+HY4+HB4+GL4+GB4+FR4+EQ4+EG4+DW4+DM4+CQ4+CG4+BR4+BH4+AM4+AC4+S4+I4) -> 0 | KG4: =SUM(KA4:KB4) -> 267 | KH4: 550 | KI4: =KH4-(KG4+KG5) -> 83 | KJ4: =(KG4+KG5)/KH4 -> 0.84909091 | KK4: =KG4+KG5 -> 467
B5: GBV Case Management | C5: Nyakabande | AS5: =AO5+AE5+U5+K5 -> 0 | AT5: =AP5+AF5+V5+L5 -> 0 | AU5: =AK5+AA5+Q5+G5 -> 0 | AV5: =AN5 -> 0 | AX5: =SUM(AQ5+AG5+W5+M5) -> 0 | AZ5: =SUM(E5+O5+Y5+AI5) -> 0 | BA5: =F5+P5+Z5+AJ5 -> 0 | BB5: =H5+R5+AB5+AL5 -> 0 | BC5: =I5+S5+AC5+AM5 -> 0 | BX5: =BN5+BD5+AI5+Y5+O5+E5 -> 0 | BY5: =BO5+BE5+AJ5+Z5+P5+F5 -> 0 | BZ5: =BQ5+BG5+AL5+AB5+R5+H5 -> 0 | CA5: =BR5+BH5+AM5+AC5+S5+I5 -> 0 | CB5: =BX5+BY5+BZ5+CA5 -> 0 | CM5: 20 | CO5: =SUM(CM5:CN5) -> 20 | CP5: 0 | CQ5: 0 | CR5: 0 | CS5: 20 | CT5: =(CN5+CQ5) -> 0 | CU5: =SUM(CS5:CT5) -> 20 | CW5: =SUM(CS5+CI5+BT5+BJ5) -> 20 | CX5: =SUM(CT5+CJ5+BU5+BK5) -> 0 | CY5: =SUM(CU5+CK5+BV5+BL5) -> 20 | CZ5: =SUM(CR5+CH5+BS5+BI5) -> 0 | DB5: =CU5+CK5 -> 20 | DD5: =BD5+BN5+CC5+CM5 -> 20 | DE5: =BE5+BO5+CD5+CN5 -> 0 | DF5: =BG5+BQ5+CF5+CP5 -> 0 | DG5: =BH5+BR5+CG5+CQ5 -> 0 | DH5: =DB5+AX5 -> 20 | DI5: 54 | DJ5: 0 | DK5: =SUM(DI5:DJ5) -> 54 | DL5: 0 | DM5: 0 | DN5: 0 | DO5: =DI5+DL5 -> 54 | DP5: 0 | DQ5: =SUM(DO5:DP5) -> 54 | DS5: 32 | DT5: 0 | DU5: =SUM(DS5:DT5) -> 32 | DV5: 0 | DW5: 0 | DX5: =SUM(DV5:DW5) -> 0 | DY5: =SUM(DS5+DV5) -> 32 | DZ5: =SUM(DT5+DW5) -> 0 | EA5: =SUM(DY5:DZ5) -> 32 | EC5: 30 | ED5: 1 | EE5: =SUM(EC5:ED5) -> 31 | EF5: 0 | EG5: 0 | EH5: =SUM(EF5:EG5) -> 0 | EI5: 30 | EJ5: =SUM(ED5+EG5) -> 1 | EK5: =SUM(EI5:EJ5) -> 31 | EM5: 17 | EN5: 0 | EO5: =SUM(EM5:EN5) -> 17 | EP5: 0 | EQ5: 0 | ER5: =SUM(EP5:EQ5) -> 0 | ES5: =SUM(EM5+EP5) -> 17 | ET5: =SUM(EN5+EQ5) -> 0 | EU5: =SUM(ES5:ET5) -> 17 | EW5: =SUM(ES5+EI5+DY5+DO5) -> 133 | EX5: =SUM(ET5+EJ5+DZ5+DP5) -> 1 | EY5: =SUM(EO5+EE5+DU5+DK5) -> 134 | EZ5: =SUM(ER5+EH5+DX5+DN5) -> 0 | FB5: =SUM(EW5:EX5) -> 134 | FD5: =DI5+DS5+EC5+EM5+CM5+CC5 -> 153 | FE5: =DJ5+DT5+ED5+EN5+CD5+CN5 -> 1 | FF5: =DL5+DV5+EF5+EP5+CP5+CF5 -> 0 | FG5: =DM5+DW5+EG5+EQ5+CG5+CQ5 -> 0 | FH5: =FD5+FF5 -> 153 | FI5: =FE5+FG5 -> 1 | FJ5: =FH5+FI5 -> 154 | FK5: =EW5+CW5+AS5 -> 153 | FL5: =EX5+CX5+AT5 -> 1 | FM5: =FK5+FL5 -> 154 | FN5: 10 | FO5: 0 | FP5: =SUM(FN5:FO5) -> 10 | FQ5: 0 | FR5: 0 | FS5: =SUM(FQ5:FR5) -> 0 | FT5: =FN5+FQ5 -> 10 | FU5: =FO5+FR5 -> 0 | FV5: =SUM(FT5:FU5) -> 10 | FX5: 7 | FY5: 0 | FZ5: =SUM(FX5:FY5) -> 7 | GA5: 0 | GB5: 0 | GD5: =FX5+GA5 -> 7 | GE5: =FY5+GB5 -> 0 | GF5: =GD5+GE5 -> 7 | GH5: 9 | GI5: 0 | GJ5: =SUM(GH5:GI5) -> 9 | GK5: 0 | GL5: 0 | GM5: =SUM(GK5:GL5) -> 0 | GN5: =GH5+GK5 -> 9 | GO5: =GI5+GL5 -> 0 | GP5: =GN5+GO5 -> 9 | GR5: =GN5+GD5+FT5+ES5+EI5+DY5+DO5+CS5+CI5+BT5+BJ5 -> 179 | GS5: =GO5+GE5+FU5+ET5+EJ5+DZ5+DP5+CT5+CJ5+BU5+BK5 -> 1 | GT5: =GH5+FX5+FN5+EM5+EC5+DS5+DI5+CM5+CC5+BN5+BD5 -> 179 | GU5: =GI5+FY5+FO5+EN5+ED5+DT5+DJ5+CN5+CD5+BO5+BE5 -> 1 | GV5: =GK5+GA5+FQ5+EP5+EF5+DV5+DL5+CP5+CF5+BQ5+BG5 -> 0 | GW5: =GL5+GB5+FR5+EQ5+EG5+DW5+DM5+CQ5+CG5+BR5+BH5 -> 0 | GX5: 6 | GY5: 0 | GZ5: =GX5+GY5 -> 6 | HA5: 0 | HB5: 0 | HC5: =HA5+HB5 -> 0 | HD5: =GX5+HA5 -> 6 | HE5: =GY5+HB5 -> 0 | HF5: =HD5+HE5 -> 6 | HH5: =HD5+GN5+GD5+FT5 -> 32 | HI5: =GO5+GE5+FU5+HE5 -> 0 | HJ5: =GX5+GH5+FX5+FN5 -> 32 | HK5: =GI5+FY5+GY5+FO5 -> 0 | HL5: =GK5+GA5+FQ5+HA5 -> 0 | HM5: =GL5+HB5+GB5+FR5 -> 0 | HO5: =HF5+GP5+GF5+FV5 -> 32 | HQ5: =FN5+FX5+GH5+GX5 -> 32 | HR5: =FO5+FY5+GI5+GY5 -> 0 | HS5: =FQ5+GA5+GK5+HA5 -> 0 | HT5: =FR5+GB5+GL5+HB5 -> 0 | HU5: 14 | HV5: 0 | HW5: =HU5+HV5 -> 14 | HX5: 0 | HY5: 0 | HZ5: =HX5+HY5 -> 0 | IA5: =HU5+HX5 -> 14 | IB5: =HV5+HY5 -> 0 | IC5: =IA5+IB5 -> 14 | JN5: =JG5+IW5+IM5+IC5 -> 14 | JZ5: =JX5+JN5+HO5+FB5 -> 180 | KA5: =SUM(JV5+JE5+IU5+IK5+IA5+HD5+GN5+GD5+FT5+ES5+EI5+DY5+DO5+CS5+CI5+BT5+BJ5+AO5+AE5+U5+K5) -> 199 | KB5: =SUM(JW5+JF5+IV5+IL5+IB5+HE5+GO5+GE5+FU5+ET5+EJ5+DZ5+DP5+CT5+CJ5+BU5+BK5+AP5+AF5+V5+L5) -> 1 | KC5: =SUM(JP5+IY5+IO5+IE5+HU5+GX5+GH5+FX5+FN5+EM5+EC5+DS5+DI5+CM5+CC5+BN5+BD5+AI5+Y5+O5+E5) -> 199 | KD5: =SUM(JQ5+IZ5+IP5+IF5+HV5+GY5+GI5+FY5+FO5+EN5+ED5+DT5+DJ5+CN5+CD5+BO5+BE5+AJ5+Z5+P5+F5) -> 1 | KE5: =SUM(JS5+JB5+IR5+IH5+HX5+HA5+GK5+GA5+FQ5+EP5+EF5+DV5+DL5+CP5+CF5+BQ5+BG5+AL5+AB5+R5+H5) -> 0 | KF5: =SUM(JT5+JC5+IS5+II5+HY5+HB5+GL5+GB5+FR5+EQ5+EG5+DW5+DM5+CQ5+CG5+BR5+BH5+AM5+AC5+S5+I5) -> 0 | KG5: =SUM(KA5:KB5) -> 200 | KK5: =FY326 -> 0 | KL5: =SUM(KH4-KK5) -> 550
B6: Support GBV screening and registration survivors at the reception and transit centres. (Survivors need based assessment support [ case by case]) | C6: Nakivale & Nyakabande | T6: =SUM(R6:S6) -> 0 | U6: =SUM(O6+R6) -> 0 | V6: =SUM(P6+S6) -> 0 | W6: =SUM(U6:V6) -> 0 | AA6: =SUM(Y6:Z6) -> 0 | AD6: =SUM(AB6:AC6) -> 0 | AE6: =SUM(Y6+AB6) -> 0 | AF6: =SUM(Z6+AC6) -> 0 | AG6: =SUM(AE6:AF6) -> 0 | AS6: =AO6+AE6+U6+K6 -> 0 | AT6: =AP6+AF6+V6+L6 -> 0 | AU6: =AK6+AA6+Q6+G6 -> 0 | AV6: =AN6 -> 0 | AX6: =SUM(AQ6+AG6+W6+M6) -> 0 | AY6: =AX6/AW6 -> #DIV/0! | AZ6: =SUM(E6+O6+Y6+AI6) -> 0 | BA6: =F6+P6+Z6+AJ6 -> 0 | BB6: =H6+R6+AB6+AL6 -> 0 | BC6: =I6+S6+AC6+AM6 -> 0 | BF6: =SUM(BD6:BE6) -> 0 | BI6: =SUM(BG6:BH6) -> 0 | BJ6: =SUM(BD6+BG6) -> 0 | BK6: =SUM(BE6+BH6) -> 0 | BL6: =SUM(BJ6:BK6) -> 0 | BX6: =BN6+BD6+AI6+Y6+O6+E6 -> 0 | BY6: =BO6+BE6+AJ6+Z6+P6+F6 -> 0 | BZ6: =BQ6+BG6+AL6+AB6+R6+H6 -> 0 | CA6: =BR6+BH6+AM6+AC6+S6+I6 -> 0 | CB6: =BX6+BY6+BZ6+CA6 -> 0 | CW6: =SUM(CS6+CI6+BT6+BJ6) -> 0 | CX6: =SUM(CT6+CJ6+BU6+BK6) -> 0 | CY6: =SUM(CU6+CK6+BV6+BL6) -> 0 | CZ6: =SUM(CR6+CH6+BS6+BI6) -> 0 | DB6: =SUM(CW6:CX6) -> 0 | DC6: =DB6/DA6 -> #DIV/0! | DD6: =BD6+BN6+CC6+CM6 -> 0 | DE6: =BE6+BO6+CD6+CN6 -> 0 | DF6: =BG6+BQ6+CF6+CP6 -> 0 | DG6: =BH6+BR6+CG6+CQ6 -> 0 | DH6: =DB6+AX6 -> 0 | DU6: =SUM(DS6:DT6) -> 0 | DX6: =SUM(DV6:DW6) -> 0 | DY6: =SUM(DS6+DV6) -> 0 | DZ6: =SUM(DT6+DW6) -> 0 | EA6: =SUM(DY6:DZ6) -> 0 | EW6: =SUM(ES6+EI6+DY6+DO6) -> 0 | EX6: =SUM(ET6+EJ6+DZ6+DP6) -> 0 | EY6: =SUM(EO6+EE6+DU6+DK6) -> 0 | EZ6: =SUM(ER6+EH6+DX6+DN6) -> 0 | FB6: =SUM(EW6:EX6) -> 0 | FD6: =DI6+DS6+EC6+EM6+CM6+CC6 -> 0 | FE6: =DJ6+DT6+ED6+EN6+CD6+CN6 -> 0 | FF6: =DL6+DV6+EF6+EP6+CP6+CF6 -> 0 | FG6: =DM6+DW6+EG6+EQ6+CG6+CQ6 -> 0 | FH6: =FD6+FF6 -> 0 | FI6: =FE6+FG6 -> 0 | FJ6: =FH6+FI6 -> 0 | FK6: =EW6+CW6+AS6 -> 0 | FL6: =EX6+CX6+AT6 -> 0 | FM6: =FK6+FL6 -> 0 | FN6: 0 | FO6: 0 | FP6: =SUM(FN6:FO6) -> 0 | FQ6: 0 | FR6: 0 | FS6: =SUM(FQ6:FR6) -> 0 | FT6: =FN6+FQ6 -> 0 | FU6: =FO6+FR6 -> 0 | FV6: =SUM(FT6:FU6) -> 0 | GD6: =FX6+GA6 -> 0 | GE6: =FY6+GB6 -> 0 | GF6: =GD6+GE6 -> 0 | GN6: =GH6+GK6 -> 0 | GO6: =GI6+GL6 -> 0 | GP6: =GN6+GO6 -> 0 | GR6: =GN6+GD6+FT6+ES6+EI6+DY6+DO6+CS6+CI6+BT6+BJ6 -> 0 | GS6: =GO6+GE6+FU6+ET6+EJ6+DZ6+DP6+CT6+CJ6+BU6+BK6 -> 0 | GT6: =GH6+FX6+FN6+EM6+EC6+DS6+DI6+CM6+CC6+BN6+BD6 -> 0 | GU6: =GI6+FY6+FO6+EN6+ED6+DT6+DJ6+CN6+CD6+BO6+BE6 -> 0 | GV6: =GK6+GA6+FQ6+EP6+EF6+DV6+DL6+CP6+CF6+BQ6+BG6 -> 0 | GW6: =GL6+GB6+FR6+EQ6+EG6+DW6+DM6+CQ6+CG6+BR6+BH6 -> 0 | GZ6: =GX6+GY6 -> 0 | HC6: =HA6+HB6 -> 0 | HD6: =GX6+HA6 -> 0 | HE6: =GY6+HB6 -> 0 | HF6: =HD6+HE6 -> 0 | HH6: =HD6+GN6+GD6+FT6 -> 0 | HI6: =GO6+GE6+FU6+HE6 -> 0 | HJ6: =GX6+GH6+FX6+FN6 -> 0 | HK6: =GI6+FY6+GY6+FO6 -> 0 | HL6: =GK6+GA6+FQ6+HA6 -> 0 | HM6: =GL6+HB6+GB6+FR6 -> 0 | HO6: =HF6+GP6+GF6+FV6 -> 0 | HP6: =HO6/HN6 -> #DIV/0! | HQ6: =FN6+FX6+GH6+GX6 -> 0 | HR6: =FO6+FY6+GI6+GY6 -> 0 | HS6: =FQ6+GA6+GK6+HA6 -> 0 | HT6: =FR6+GB6+GL6+HB6 -> 0 | HW6: =HU6+HV6 -> 0 | HZ6: =HX6+HY6 -> 0 | IA6: =HU6+HX6 -> 0 | IB6: =HV6+HY6 -> 0 | IC6: =IA6+IB6 -> 0 | JN6: =JG6+IW6+IM6+IC6 -> 0 | JO6: =JN6/JM6 -> #DIV/0! | JZ6: =JX6+JN6+HO6+FB6 -> 0 | KA6: =SUM(JV6+JE6+IU6+IK6+IA6+HD6+GN6+GD6+FT6+ES6+EI6+DY6+DO6+CS6+CI6+BT6+BJ6+AO6+AE6+U6+K6) -> 0 | KB6: =SUM(JW6+JF6+IV6+IL6+IB6+HE6+GO6+GE6+FU6+ET6+EJ6+DZ6+DP6+CT6+CJ6+BU6+BK6+AP6+AF6+V6+L6) -> 0 | KC6: =SUM(JP6+IY6+IO6+IE6+HU6+GX6+GH6+FX6+FN6+EM6+EC6+DS6+DI6+CM6+CC6+BN6+BD6+AI6+Y6+O6+E6) -> 0 | KD6: =SUM(JQ6+IZ6+IP6+IF6+HV6+GY6+GI6+FY6+FO6+EN6+ED6+DT6+DJ6+CN6+CD6+BO6+BE6+AJ6+Z6+P6+F6) -> 0 | KE6: =SUM(JS6+JB6+IR6+IH6+HX6+HA6+GK6+GA6+FQ6+EP6+EF6+DV6+DL6+CP6+CF6+BQ6+BG6+AL6+AB6+R6+H6) -> 0 | KF6: =SUM(JT6+JC6+IS6+II6+HY6+HB6+GL6+GB6+FR6+EQ6+EG6+DW6+DM6+CQ6+CG6+BR6+BH6+AM6+AC6+S6+I6) -> 0 | KG6: =SUM(KA6:KB6) -> 0 | KI6: =KH6-KG6 -> 0 | KJ6: =KG6/KH6 -> #DIV/0! | KK6: =KA4+KA5 -> 464
B7: IPA support to GBV survivors | AZ7: =SUM(E7+O7+Y7+AI7) -> 0 | BA7: =F7+P7+Z7+AJ7 -> 0 | BB7: =H7+R7+AB7+AL7 -> 0 | BC7: =I7+S7+AC7+AM7 -> 0 | BX7: =BN7+BD7+AI7+Y7+O7+E7 -> 0 | BY7: =BO7+BE7+AJ7+Z7+P7+F7 -> 0 | BZ7: =BQ7+BG7+AL7+AB7+R7+H7 -> 0 | CA7: =BR7+BH7+AM7+AC7+S7+I7 -> 0 | CB7: =BX7+BY7+BZ7+CA7 -> 0 | DD7: =BD7+BN7+CC7+CM7 -> 0 | DE7: =BE7+BO7+CD7+CN7 -> 0 | DF7: =BG7+BQ7+CF7+CP7 -> 0 | DG7: =BH7+BR7+CG7+CQ7 -> 0 | DH7: =DB7+AX7 -> 0 | EC7: 2 | ED7: 0 | EE7: =SUM(EC7:ED7) -> 2 | EF7: 0 | EG7: 0 | EH7: =SUM(EF7:EG7) -> 0 | EI7: =SUM(EC7+EF7) -> 2 | EJ7: =SUM(ED7+EG7) -> 0 | EK7: =SUM(EI7:EJ7) -> 2 | EW7: =SUM(ES7+EI7+DY7+DO7) -> 2 | EX7: =SUM(ET7+EJ7+DZ7+DP7) -> 0 | EY7: =SUM(EO7+EE7+DU7+DK7) -> 2 | EZ7: =SUM(ER7+EH7+DX7+DN7) -> 0 | FB7: =SUM(EW7:EX7) -> 2 | FD7: =DI7+DS7+EC7+EM7+CM7+CC7 -> 2 | FE7: =DJ7+DT7+ED7+EN7+CD7+CN7 -> 0 | FF7: =DL7+DV7+EF7+EP7+CP7+CF7 -> 0 | FG7: =DM7+DW7+EG7+EQ7+CG7+CQ7 -> 0 | FH7: =FD7+FF7 -> 2 | FI7: =FE7+FG7 -> 0 | FJ7: =FH7+FI7 -> 2 | FK7: =EW7+CW7+AS7 -> 2 | FL7: =EX7+CX7+AT7 -> 0 | FM7: =FK7+FL7 -> 2 | FN7: 0 | FO7: 0 | FP7: =SUM(FN7:FO7) -> 0 | FQ7: 0 | FR7: 0 | FS7: =SUM(FQ7:FR7) -> 0 | FT7: =FN7+FQ7 -> 0 | FU7: =FO7+FR7 -> 0 | FV7: =SUM(FT7:FU7) -> 0 | GD7: =FX7+GA7 -> 0 | GE7: =FY7+GB7 -> 0 | GF7: =GD7+GE7 -> 0 | GN7: =GH7+GK7 -> 0 | GO7: =GI7+GL7 -> 0 | GP7: =GN7+GO7 -> 0 | GR7: =GN7+GD7+FT7+ES7+EI7+DY7+DO7+CS7+CI7+BT7+BJ7 -> 2 | GS7: =GO7+GE7+FU7+ET7+EJ7+DZ7+DP7+CT7+CJ7+BU7+BK7 -> 0 | GT7: =GH7+FX7+FN7+EM7+EC7+DS7+DI7+CM7+CC7+BN7+BD7 -> 2 | GU7: =GI7+FY7+FO7+EN7+ED7+DT7+DJ7+CN7+CD7+BO7+BE7 -> 0 | GV7: =GK7+GA7+FQ7+EP7+EF7+DV7+DL7+CP7+CF7+BQ7+BG7 -> 0 | GW7: =GL7+GB7+FR7+EQ7+EG7+DW7+DM7+CQ7+CG7+BR7+BH7 -> 0 | GZ7: =GX7+GY7 -> 0 | HC7: =HA7+HB7 -> 0 | HD7: =GX7+HA7 -> 0 | HE7: =GY7+HB7 -> 0 | HF7: =HD7+HE7 -> 0 | HH7: =HD7+GN7+GD7+FT7 -> 0 | HI7: =GO7+GE7+FU7+HE7 -> 0 | HJ7: =GX7+GH7+FX7+FN7 -> 0 | HK7: =GI7+FY7+GY7+FO7 -> 0 | HL7: =GK7+GA7+FQ7+HA7 -> 0 | HM7: =GL7+HB7+GB7+FR7 -> 0 | HO7: =HF7+GP7+GF7+FV7 -> 0 | HQ7: =FN7+FX7+GH7+GX7 -> 0 | HR7: =FO7+FY7+GI7+GY7 -> 0 | HS7: =FQ7+GA7+GK7+HA7 -> 0 | HT7: =FR7+GB7+GL7+HB7 -> 0 | HW7: =HU7+HV7 -> 0 | HZ7: =HX7+HY7 -> 0 | IA7: =HU7+HX7 -> 0 | IB7: =HV7+HY7 -> 0 | IC7: =IA7+IB7 -> 0 | JN7: =JG7+IW7+IM7+IC7 -> 0 | JZ7: =JX7+JN7+HO7+FB7 -> 2 | KA7: =SUM(JV7+JE7+IU7+IK7+IA7+HD7+GN7+GD7+FT7+ES7+EI7+DY7+DO7+CS7+CI7+BT7+BJ7+AO7+AE7+U7+K7) -> 2 | KB7: =SUM(JW7+JF7+IV7+IL7+IB7+HE7+GO7+GE7+FU7+ET7+EJ7+DZ7+DP7+CT7+CJ7+BU7+BK7+AP7+AF7+V7+L7) -> 0 | KC7: =SUM(JP7+IY7+IO7+IE7+HU7+GX7+GH7+FX7+FN7+EM7+EC7+DS7+DI7+CM7+CC7+BN7+BD7+AI7+Y7+O7+E7) -> 2 | KD7: =SUM(JQ7+IZ7+IP7+IF7+HV7+GY7+GI7+FY7+FO7+EN7+ED7+DT7+DJ7+CN7+CD7+BO7+BE7+AJ7+Z7+P7+F7) -> 0 | KE7: =SUM(JS7+JB7+IR7+IH7+HX7+HA7+GK7+GA7+FQ7+EP7+EF7+DV7+DL7+CP7+CF7+BQ7+BG7+AL7+AB7+R7+H7) -> 0 | KF7: =SUM(JT7+JC7+IS7+II7+HY7+HB7+GL7+GB7+FR7+EQ7+EG7+DW7+DM7+CQ7+CG7+BR7+BH7+AM7+AC7+S7+I7) -> 0
B8: Provide in kind material support to GBV survivors (dignity kits) -(through referrals) | C8: Nakivale | D8: 100 | AI8: 2 | AJ8: 0 | AK8: =AI8+AJ8 -> 2 | AL8: 0 | AM8: 0 | AN8: =AL8+AM8 -> 0 | AO8: =AI8+AL8 -> 2 | AP8: =AJ8+AM8 -> 0 | AQ8: =AP8+AO8 -> 2 | AS8: =AO8+AE8+U8+K8 -> 2 | AT8: =AP8+AF8+V8+L8 -> 0 | AU8: =AK8+AA8+Q8+G8 -> 2 | AV8: =AN8 -> 0 | AX8: =SUM(AQ8+AG8+W8+M8) -> 2 | AZ8: =SUM(E8+O8+Y8+AI8) -> 2 | BA8: =F8+P8+Z8+AJ8 -> 0 | BB8: =H8+R8+AB8+AL8 -> 0 | BC8: =I8+S8+AC8+AM8 -> 0 | BD8: 2 | BE8: 0 | BF8: =BD8+BE8 -> 2 | BG8: 0 | BH8: 0 | BI8: =BG8+BH8 -> 0 | BJ8: =BD8+BG8 -> 2 | BK8: =BE8+BH8 -> 0 | BL8: =BJ8+BK8 -> 2 | BX8: =BN8+BD8+AI8+Y8+O8+E8 -> 4 | BY8: =BO8+BE8+AJ8+Z8+P8+F8 -> 0 | BZ8: =BQ8+BG8+AL8+AB8+R8+H8 -> 0 | CA8: =BR8+BH8+AM8+AC8+S8+I8 -> 0 | CB8: =BX8+BY8+BZ8+CA8 -> 4 | CC8: 4 | CD8: 0 | CE8: =SUM(CC8:CD8) -> 4 | CF8: 0 | CG8: 0 | CH8: =SUM(CF8:CG8) -> 0 | CI8: =SUM(CC8+CF8) -> 4 | CJ8: =SUM(CD8+CG8) -> 0 | CK8: =SUM(CI8:CJ8) -> 4 | CW8: =SUM(CS8+CI8+BT8+BJ8) -> 6 | CX8: =SUM(CT8+CJ8+BU8+BK8) -> 0 | CY8: =SUM(CU8+CK8+BV8+BL8) -> 6 | CZ8: =SUM(CR8+CH8+BS8+BI8) -> 0 | DA8: 1000 | DB8: =SUM(CW8:CX8) -> 6 | DD8: =BD8+BN8+CC8+CM8 -> 6 | DE8: =BE8+BO8+CD8+CN8 -> 0 | DF8: =BG8+BQ8+CF8+CP8 -> 0 | DG8: =BH8+BR8+CG8+CQ8 -> 0 | DH8: =DB8+AX8 -> 8 | DS8: 3 | DT8: 0 | DU8: =SUM(DS8:DT8) -> 3 | DV8: 0 | DW8: 0 | DX8: =SUM(DV8:DW8) -> 0 | DY8: =SUM(DS8+DV8) -> 3 | DZ8: =SUM(DT8+DW8) -> 0 | EA8: =SUM(DY8:DZ8) -> 3 | EC8: 21 | ED8: 0 | EE8: =SUM(EC8:ED8) -> 21 | EF8: 0 | EG8: 0 | EH8: =SUM(EF8:EG8) -> 0 | EI8: =SUM(EC8+EF8) -> 21 | EJ8: =SUM(ED8+EG8) -> 0 | EK8: =SUM(EI8:EJ8) -> 21 | EM8: 13 | EN8: 0 | EO8: =SUM(EM8:EN8) -> 13 | EP8: 0 | EQ8: 0 | ER8: =SUM(EP8:EQ8) -> 0 | ES8: =SUM(EM8+EP8) -> 13 | ET8: =SUM(EN8+EQ8) -> 0 | EU8: =SUM(ES8:ET8) -> 13 | EW8: =SUM(ES8+EI8+DY8+DO8) -> 37 | EX8: =SUM(ET8+EJ8+DZ8+DP8) -> 0 | EY8: =SUM(EO8+EE8+DU8+DK8) -> 37 | EZ8: =SUM(ER8+EH8+DX8+DN8) -> 0 | FB8: =SUM(EW8:EX8) -> 37 | FD8: =DI8+DS8+EC8+EM8+CM8+CC8 -> 41 | FE8: =DJ8+DT8+ED8+EN8+CD8+CN8 -> 0 | FF8: =DL8+DV8+EF8+EP8+CP8+CF8 -> 0 | FG8: =DM8+DW8+EG8+EQ8+CG8+CQ8 -> 0 | FH8: =FD8+FF8 -> 41 | FI8: =FE8+FG8 -> 0 | FJ8: =FH8+FI8 -> 41 | FK8: =EW8+CW8+AS8 -> 45 | FL8: =EX8+CX8+AT8 -> 0 | FM8: =FK8+FL8 -> 45 | FN8: 7 | FO8: 0 | FP8: =SUM(FN8:FO8) -> 7 | FQ8: 0 | FR8: 0 | FS8: =SUM(FQ8:FR8) -> 0 | FT8: =FN8+FQ8 -> 7 | FU8: =FO8+FR8 -> 0 | FV8: =SUM(FT8:FU8) -> 7 | GD8: =FX8+GA8 -> 0 | GE8: =FY8+GB8 -> 0 | GF8: =GD8+GE8 -> 0 | GN8: =GH8+GK8 -> 0 | GO8: =GI8+GL8 -> 0 | GP8: =GN8+GO8 -> 0 | GR8: =GN8+GD8+FT8+ES8+EI8+DY8+DO8+CS8+CI8+BT8+BJ8 -> 50 | GS8: =GO8+GE8+FU8+ET8+EJ8+DZ8+DP8+CT8+CJ8+BU8+BK8 -> 0 | GT8: =GH8+FX8+FN8+EM8+EC8+DS8+DI8+CM8+CC8+BN8+BD8 -> 50 | GU8: =GI8+FY8+FO8+EN8+ED8+DT8+DJ8+CN8+CD8+BO8+BE8 -> 0 | GV8: =GK8+GA8+FQ8+EP8+EF8+DV8+DL8+CP8+CF8+BQ8+BG8 -> 0 | GW8: =GL8+GB8+FR8+EQ8+EG8+DW8+DM8+CQ8+CG8+BR8+BH8 -> 0 | GZ8: =GX8+GY8 -> 0 | HC8: =HA8+HB8 -> 0 | HD8: =GX8+HA8 -> 0 | HE8: =GY8+HB8 -> 0 | HF8: =HD8+HE8 -> 0 | HH8: =HD8+GN8+GD8+FT8 -> 7 | HI8: =GO8+GE8+FU8+HE8 -> 0 | HJ8: =GX8+GH8+FX8+FN8 -> 7 | HK8: =GI8+FY8+GY8+FO8 -> 0 | HL8: =GK8+GA8+FQ8+HA8 -> 0 | HM8: =GL8+HB8+GB8+FR8 -> 0 | HN8: 100 | HO8: =HF8+GP8+GF8+FV8 -> 7 | HQ8: =FN8+FX8+GH8+GX8 -> 7 | HR8: =FO8+FY8+GI8+GY8 -> 0 | HS8: =FQ8+GA8+GK8+HA8 -> 0 | HT8: =FR8+GB8+GL8+HB8 -> 0 | HW8: =HU8+HV8 -> 0 | HZ8: =HX8+HY8 -> 0 | IA8: =HU8+HX8 -> 0 | IB8: =HV8+HY8 -> 0 | IC8: =IA8+IB8 -> 0 | JI8: =SUM(JE8+IU8+IK8+IA8) -> 0 | JJ8: 0 | JM8: 100 | JN8: =JG8+IW8+IM8+IC8 -> 0 | JZ8: =JX8+JN8+HO8+FB8 -> 44 | KA8: =SUM(JV8+JE8+IU8+IK8+IA8+HD8+GN8+GD8+FT8+ES8+EI8+DY8+DO8+CS8+CI8+BT8+BJ8+AO8+AE8+U8+K8) -> 52 | KB8: =SUM(JW8+JF8+IV8+IL8+IB8+HE8+GO8+GE8+FU8+ET8+EJ8+DZ8+DP8+CT8+CJ8+BU8+BK8+AP8+AF8+V8+L8) -> 0 | KC8: =SUM(JP8+IY8+IO8+IE8+HU8+GX8+GH8+FX8+FN8+EM8+EC8+DS8+DI8+CM8+CC8+BN8+BD8+AI8+Y8+O8+E8) -> 52 | KD8: =SUM(JQ8+IZ8+IP8+IF8+HV8+GY8+GI8+FY8+FO8+EN8+ED8+DT8+DJ8+CN8+CD8+BO8+BE8+AJ8+Z8+P8+F8) -> 0 | KE8: =SUM(JS8+JB8+IR8+IH8+HX8+HA8+GK8+GA8+FQ8+EP8+EF8+DV8+DL8+CP8+CF8+BQ8+BG8+AL8+AB8+R8+H8) -> 0 | KF8: =SUM(JT8+JC8+IS8+II8+HY8+HB8+GL8+GB8+FR8+EQ8+EG8+DW8+DM8+CQ8+CG8+BR8+BH8+AM8+AC8+S8+I8) -> 0 | KG8: =SUM(KA8:KB8) -> 52 | KH8: 100 | KI8: =KH8-KG8 -> 48 | KJ8: =KG8/KH8 -> 0.52
B9: GBV Case Conferencing | C9: Nakivale | D9: 9 | T9: =SUM(R9:S9) -> 0 | U9: =SUM(O9+R9) -> 0 | V9: =SUM(P9+S9) -> 0 | W9: =SUM(U9:V9) -> 0 | AO9: =SUM(AI9+AL9) -> 0 | AP9: =SUM(AJ9+AM9) -> 0 | AQ9: =SUM(AO9:AP9) -> 0 | AS9: =AO9+AE9+U9+K9 -> 0 | AT9: =AP9+AF9+V9+L9 -> 0 | AU9: =AK9+AA9+Q9+G9 -> 0 | AV9: =AN9 -> 0 | AX9: =SUM(AQ9+AG9+W9+M9) -> 0 | AY9: =AX9/AW9 -> #DIV/0! | AZ9: =SUM(E9+O9+Y9+AI9) -> 0 | BA9: =F9+P9+Z9+AJ9 -> 0 | BB9: =H9+R9+AB9+AL9 -> 0 | BC9: =I9+S9+AC9+AM9 -> 0 | BF9: =SUM(BD9:BE9) -> 0 | BI9: =SUM(BG9:BH9) -> 0 | BJ9: =SUM(BD9+BG9) -> 0 | BK9: =SUM(BE9+BH9) -> 0 | BL9: 1 | BS9: =SUM(BQ9:BR9) -> 0 | BT9: =SUM(BN9+BQ9) -> 0 | BU9: =SUM(BO9+BR9) -> 0 | BV9: =SUM(BT9:BU9) -> 0 | BX9: =BN9+BD9+AI9+Y9+O9+E9 -> 0 | BY9: =BO9+BE9+AJ9+Z9+P9+F9 -> 0 | BZ9: =BQ9+BG9+AL9+AB9+R9+H9 -> 0 | CA9: =BR9+BH9+AM9+AC9+S9+I9 -> 0 | CB9: =BX9+BY9+BZ9+CA9 -> 0 | CH9: =SUM(CF9:CG9) -> 0 | CI9: =SUM(CC9+CF9) -> 0 | CJ9: =SUM(CD9+CG9) -> 0 | CK9: =SUM(CI9:CJ9) -> 0 | CR9: =SUM(CP9:CQ9) -> 0 | CS9: =SUM(CM9+CP9) -> 0 | CT9: =SUM(CN9+CQ9) -> 0 | CU9: =SUM(CS9:CT9) -> 0 | CW9: =SUM(CS9+CI9+BT9+BJ9) -> 0 | CX9: =SUM(CT9+CJ9+BU9+BK9) -> 0 | CY9: =SUM(CU9+CK9+BV9+BL9) -> 1 | CZ9: =SUM(CR9+CH9+BS9+BI9) -> 0 | DA9: 9 | DB9: =SUM(CW9:CX9) -> 0 | DC9: =DB9/DA9 -> 0 | DD9: =BD9+BN9+CC9+CM9 -> 0 | DE9: =BE9+BO9+CD9+CN9 -> 0 | DF9: =BG9+BQ9+CF9+CP9 -> 0 | DG9: =BH9+BR9+CG9+CQ9 -> 0 | DH9: =DB9+AX9 -> 0 | DN9: =SUM(DL9:DM9) -> 0 | DO9: =SUM(DI9+DL9) -> 0 | DP9: =SUM(DJ9+DM9) -> 0 | DQ9: =SUM(DO9:DP9) -> 0 | DU9: =SUM(DS9:DT9) -> 0 | DX9: =SUM(DV9:DW9) -> 0 | DY9: =SUM(DS9+DV9) -> 0 | DZ9: =SUM(DT9+DW9) -> 0 | EA9: =SUM(DY9:DZ9) -> 0 | EH9: =SUM(EF9:EG9) -> 0 | EI9: =SUM(EC9+EF9) -> 0 | EJ9: =SUM(ED9+EG9) -> 0 | EK9: 0 | ER9: =SUM(EP9:EQ9) -> 0 | ES9: =SUM(EM9+EP9) -> 0 | ET9: =SUM(EN9+EQ9) -> 0 | EU9: 1 | EW9: =SUM(ES9+EI9+DY9+DO9) -> 0 | EX9: =SUM(ET9+EJ9+DZ9+DP9) -> 0 | EY9: =SUM(EO9+EE9+DU9+DK9) -> 0 | EZ9: =SUM(ER9+EH9+DX9+DN9) -> 0 | FB9: 1 | FC9: =FB9/FA9 -> #DIV/0! | FD9: =DI9+DS9+EC9+EM9+CM9+CC9 -> 0 | FE9: =DJ9+DT9+ED9+EN9+CD9+CN9 -> 0 | FF9: =DL9+DV9+EF9+EP9+CP9+CF9 -> 0 | FG9: =DM9+DW9+EG9+EQ9+CG9+CQ9 -> 0 | FH9: =FD9+FF9 -> 0 | FI9: =FE9+FG9 -> 0 | FJ9: 2 | FK9: =EW9+CW9+AS9 -> 0 | FL9: =EX9+CX9+AT9 -> 0 | FM9: =FK9+FL9 -> 0 | FN9: 0 | FO9: 0 | FP9: =SUM(FN9:FO9) -> 0 | FQ9: 0 | FR9: 0 | FS9: =SUM(FQ9:FR9) -> 0 | FT9: =FN9+FQ9 -> 0 | FU9: =FO9+FR9 -> 0 | FV9: =SUM(FT9:FU9) -> 0 | GC9: =SUM(GA9:GB9) -> 0 | GD9: =FX9+GA9 -> 0 | GE9: =FY9+GB9 -> 0 | GF9: =GD9+GE9 -> 0 | GM9: =SUM(GK9:GL9) -> 0 | GN9: =GH9+GK9 -> 0 | GO9: =GI9+GL9 -> 0 | GP9: =GN9+GO9 -> 0 | GR9: =GN9+GD9+FT9+ES9+EI9+DY9+DO9+CS9+CI9+BT9+BJ9 -> 0 | GS9: =GO9+GE9+FU9+ET9+EJ9+DZ9+DP9+CT9+CJ9+BU9+BK9 -> 0 | GT9: =GH9+FX9+FN9+EM9+EC9+DS9+DI9+CM9+CC9+BN9+BD9 -> 0 | GU9: =GI9+FY9+FO9+EN9+ED9+DT9+DJ9+CN9+CD9+BO9+BE9 -> 0 | GV9: =GK9+GA9+FQ9+EP9+EF9+DV9+DL9+CP9+CF9+BQ9+BG9 -> 0 | GW9: =GL9+GB9+FR9+EQ9+EG9+DW9+DM9+CQ9+CG9+BR9+BH9 -> 0 | GZ9: =GX9+GY9 -> 0 | HC9: =HA9+HB9 -> 0 | HD9: =GX9+HA9 -> 0 | HE9: =GY9+HB9 -> 0 | HF9: =HD9+HE9 -> 0 | HH9: =HD9+GN9+GD9+FT9 -> 0 | HI9: =GO9+GE9+FU9+HE9 -> 0 | HJ9: =GX9+GH9+FX9+FN9 -> 0 | HK9: =GI9+FY9+GY9+FO9 -> 0 | HL9: =GK9+GA9+FQ9+HA9 -> 0 | HM9: =GL9+HB9+GB9+FR9 -> 0 | HO9: =HF9+GP9+GF9+FV9 -> 0 | HP9: =HO9/HN9 -> #DIV/0! | HQ9: =FN9+FX9+GH9+GX9 -> 0 | HR9: =FO9+FY9+GI9+GY9 -> 0 | HS9: =FQ9+GA9+GK9+HA9 -> 0 | HT9: =FR9+GB9+GL9+HB9 -> 0 | HW9: =HU9+HV9 -> 0 | HZ9: =HX9+HY9 -> 0 | IA9: =HU9+HX9 -> 0 | IB9: =HV9+HY9 -> 0 | IC9: =IA9+IB9 -> 0 | IJ9: =SUM(IH9:II9) -> 0 | IK9: =SUM(IE9+IH9) -> 0 | IL9: =SUM(IF9+II9) -> 0 | IM9: =SUM(IK9:IL9) -> 0 | IT9: =SUM(IR9:IS9) -> 0 | IU9: =SUM(IO9+IR9) -> 0 | IV9: =SUM(IP9+IS9) -> 0 | IW9: =SUM(IU9:IV9) -> 0 | JD9: =SUM(JB9:JC9) -> 0 | JE9: =SUM(IY9+JB9) -> 0 | JF9: =SUM(IZ9+JC9) -> 0 | JG9: =SUM(JE9:JF9) -> 0 | JI9: =SUM(IA9+IK9+IU9) -> 0 | JJ9: =SUM(IB9+IL9+IV9) -> 0 | JK9: =SUM(IG9+IQ9+HW9) -> 0 | JL9: =SUM(HZ9+IJ9+IT9) -> 0 | JN9: =JG9+IW9+IM9+IC9 -> 0 | JO9: =JN9/JM9 -> #DIV/0! | JU9: =SUM(JS9:JT9) -> 0 | JV9: =SUM(JP9+JS9) -> 0 | JW9: =SUM(JQ9+JT9) -> 0 | JX9: =SUM(JV9:JW9) -> 0 | JZ9: =JX9+JN9+HO9+FB9 -> 1 | KA9: =SUM(JV9+JE9+IU9+IK9+IA9+HD9+GN9+GD9+FT9+ES9+EI9+DY9+DO9+CS9+CI9+BT9+BJ9+AO9+AE9+U9+K9) -> 0 | KB9: =SUM(JW9+JF9+IV9+IL9+IB9+HE9+GO9+GE9+FU9+ET9+EJ9+DZ9+DP9+CT9+CJ9+BU9+BK9+AP9+AF9+V9+L9) -> 0 | KC9: =SUM(JP9+IY9+IO9+IE9+HU9+GX9+GH9+FX9+FN9+EM9+EC9+DS9+DI9+CM9+CC9+BN9+BD9+AI9+Y9+O9+E9) -> 0 | KD9: =SUM(JQ9+IZ9+IP9+IF9+HV9+GY9+GI9+FY9+FO9+EN9+ED9+DT9+DJ9+CN9+CD9+BO9+BE9+AJ9+Z9+P9+F9) -> 0 | KE9: 2 | KF9: =SUM(JT9+JC9+IS9+II9+HY9+HB9+GL9+GB9+FR9+EQ9+EG9+DW9+DM9+CQ9+CG9+BR9+BH9+AM9+AC9+S9+I9) -> 0 | KG9: 2 | KH9: 9 | KI9: =KH9-KG9 -> 7 | KJ9: =KG9/KH9 -> 0.22222222
A10: Indicator 2 Number of participants showing an increased knowledge on the protection subject in focus | B10: Training GBVCommunity Structures | C10: Nakivale | D10: 130 | Y10: 16 | Z10: 17 | AA10: =SUM(Y10:Z10) -> 33 | AB10: 7 | AC10: 5 | AD10: =SUM(AB10:AC10) -> 12 | AE10: =SUM(Y10+AB10) -> 23 | AF10: =SUM(Z10+AC10) -> 22 | AG10: =SUM(AE10:AF10) -> 45 | AS10: =AO10+AE10+U10+K10 -> 23 | AT10: =AP10+AF10+V10+L10 -> 22 | AU10: =AK10+AA10+Q10+G10 -> 33 | AV10: =AN10 -> 0 | AX10: =SUM(AQ10+AG10+W10+M10) -> 45 | AY10: =AX10/AW10 -> #DIV/0! | AZ10: =SUM(E10+O10+Y10+AI10) -> 16 | BA10: =F10+P10+Z10+AJ10 -> 17 | BB10: =H10+R10+AB10+AL10 -> 7 | BC10: =I10+S10+AC10+AM10 -> 5 | BD10: 20 | BE10: 20 | BF10: =SUM(BD10:BE10) -> 40 | BG10: 0 | BH10: 0 | BI10: =SUM(BG10:BH10) -> 0 | BJ10: =SUM(BD10+BG10) -> 20 | BK10: =SUM(BE10+BH10) -> 20 | BL10: =SUM(BJ10:BK10) -> 40 | BM10: 1 | BX10: =BN10+BD10+AI10+Y10+O10+E10 -> 36 | BY10: =BO10+BE10+AJ10+Z10+P10+F10 -> 37 | BZ10: =BQ10+BG10+AL10+AB10+R10+H10 -> 7 | CA10: =BR10+BH10+AM10+AC10+S10+I10 -> 5 | CB10: =BX10+BY10+BZ10+CA10 -> 85 | CW10: =SUM(CS10+CI10+BT10+BJ10) -> 20 | CX10: =SUM(CT10+CJ10+BU10+BK10) -> 20 | CY10: =SUM(CU10+CK10+BV10+BL10) -> 40 | CZ10: =SUM(CR10+CH10+BS10+BI10) -> 0 | DB10: =SUM(CW10:CX10) -> 40 | DC10: =DB10/DA10 -> #DIV/0! | DD10: =BD10+BN10+CC10+CM10 -> 20 | DE10: =BE10+BO10+CD10+CN10 -> 20 | DF10: =BG10+BQ10+CF10+CP10 -> 0 | DG10: =BH10+BR10+CG10+CQ10 -> 0 | DH10: =DB10+AX10 -> 85 | DU10: =SUM(DS10:DT10) -> 0 | DX10: =SUM(DV10:DW10) -> 0 | DY10: =SUM(DS10+DV10) -> 0 | DZ10: =SUM(DT10+DW10) -> 0 | EA10: =SUM(DY10:DZ10) -> 0 | EU10: 0 | EW10: =SUM(ES10+EI10+DY10+DO10) -> 0 | EX10: =SUM(ET10+EJ10+DZ10+DP10) -> 0 | EY10: =SUM(EO10+EE10+DU10+DK10) -> 0 | EZ10: =SUM(ER10+EH10+DX10+DN10) -> 0 | FB10: =SUM(EW10:EX10) -> 0 | FC10: =FB10/FA10 -> #DIV/0! | FD10: =DI10+DS10+EC10+EM10+CM10+CC10 -> 0 | FE10: =DJ10+DT10+ED10+EN10+CD10+CN10 -> 0 | FF10: =DL10+DV10+EF10+EP10+CP10+CF10 -> 0 | FG10: =DM10+DW10+EG10+EQ10+CG10+CQ10 -> 0 | FH10: =FD10+FF10 -> 0 | FI10: =FE10+FG10 -> 0 | FJ10: =FH10+FI10 -> 0 | FK10: =EW10+CW10+AS10 -> 43 | FL10: =EX10+CX10+AT10 -> 42 | FM10: =FK10+FL10 -> 85 | FN10: 0 | FO10: 0 | FP10: =SUM(FN10:FO10) -> 0 | FQ10: 0 | FR10: 0 | FS10: =SUM(FQ10:FR10) -> 0 | FT10: =FN10+FQ10 -> 0 | FU10: =FO10+FR10 -> 0 | FV10: =SUM(FT10:FU10) -> 0 | FX10: 5 | FY10: 7 | FZ10: =SUM(FX10:FY10) -> 12 | GA10: 0 | GB10: 0 | GC10: =SUM(GA10:GB10) -> 0 | GD10: =FX10+GA10 -> 5 | GE10: =FY10+GB10 -> 7 | GF10: =GD10+GE10 -> 12 | GN10: =GH10+GK10 -> 0 | GO10: =GI10+GL10 -> 0 | GP10: =GN10+GO10 -> 0 | GR10: =GN10+GD10+FT10+ES10+EI10+DY10+DO10+CS10+CI10+BT10+BJ10 -> 25 | GS10: =GO10+GE10+FU10+ET10+EJ10+DZ10+DP10+CT10+CJ10+BU10+BK10 -> 27 | GT10: =GH10+FX10+FN10+EM10+EC10+DS10+DI10+CM10+CC10+BN10+BD10 -> 25 | GU10: =GI10+FY10+FO10+EN10+ED10+DT10+DJ10+CN10+CD10+BO10+BE10 -> 27 | GV10: =GK10+GA10+FQ10+EP10+EF10+DV10+DL10+CP10+CF10+BQ10+BG10 -> 0 | GW10: =GL10+GB10+FR10+EQ10+EG10+DW10+DM10+CQ10+CG10+BR10+BH10 -> 0 | GZ10: =GX10+GY10 -> 0 | HC10: =HA10+HB10 -> 0 | HD10: =GX10+HA10 -> 0 | HE10: =GY10+HB10 -> 0 | HF10: =HD10+HE10 -> 0 | HH10: =HD10+GN10+GD10+FT10 -> 5 | HI10: =GO10+GE10+FU10+HE10 -> 7 | HJ10: =GX10+GH10+FX10+FN10 -> 5 | HK10: =GI10+FY10+GY10+FO10 -> 7 | HL10: =GK10+GA10+FQ10+HA10 -> 0 | HM10: =GL10+HB10+GB10+FR10 -> 0 | HO10: =HF10+GP10+GF10+FV10 -> 12 | HP10: =HO10/HN10 -> #DIV/0! | HQ10: =FN10+FX10+GH10+GX10 -> 5 | HR10: =FO10+FY10+GI10+GY10 -> 7 | HS10: =FQ10+GA10+GK10+HA10 -> 0 | HT10: =FR10+GB10+GL10+HB10 -> 0 | HW10: =HU10+HV10 -> 0 | HZ10: =HX10+HY10 -> 0 | IA10: =HU10+HX10 -> 0 | IB10: =HV10+HY10 -> 0 | IC10: =IA10+IB10 -> 0 | JN10: =JG10+IW10+IM10+IC10 -> 0 | JO10: =JN10/JM10 -> #DIV/0! | JZ10: =JX10+JN10+HO10+FB10 -> 12 | KA10: =SUM(JV10+JE10+IU10+IK10+IA10+HD10+GN10+GD10+FT10+ES10+EI10+DY10+DO10+CS10+CI10+BT10+BJ10+AO10+AE10+U10+K10) -> 48 | KB10: =SUM(JW10+JF10+IV10+IL10+IB10+HE10+GO10+GE10+FU10+ET10+EJ10+DZ10+DP10+CT10+CJ10+BU10+BK10+AP10+AF10+V10+L10) -> 49 | KC10: =SUM(JP10+IY10+IO10+IE10+HU10+GX10+GH10+FX10+FN10+EM10+EC10+DS10+DI10+CM10+CC10+BN10+BD10+AI10+Y10+O10+E10) -> 41 | KD10: =SUM(JQ10+IZ10+IP10+IF10+HV10+GY10+GI10+FY10+FO10+EN10+ED10+DT10+DJ10+CN10+CD10+BO10+BE10+AJ10+Z10+P10+F10) -> 44 | KE10: =SUM(JS10+JB10+IR10+IH10+HX10+HA10+GK10+GA10+FQ10+EP10+EF10+DV10+DL10+CP10+CF10+BQ10+BG10+AL10+AB10+R10+H10) -> 7 | KF10: =SUM(JT10+JC10+IS10+II10+HY10+HB10+GL10+GB10+FR10+EQ10+EG10+DW10+DM10+CQ10+CG10+BR10+BH10+AM10+AC10+S10+I10) -> 5 | KG10: =SUM(KA10:KB10) -> 97 | KH10: 130 | KI10: =KH10-KG10 -> 33 | KJ10: =KG10/KH10 -> 0.74615385
B11: Clinical Health Training for 30 health workers, clinical care sexual assault. 30 police officers | C11: Nakivale | D11: 60 | T11: =SUM(R11:S11) -> 0 | U11: =SUM(O11+R11) -> 0 | V11: =SUM(P11+S11) -> 0 | W11: =SUM(U11:V11) -> 0 | AA11: =SUM(Y11:Z11) -> 0 | AD11: =SUM(AB11:AC11) -> 0 | AE11: =SUM(Y11+AB11) -> 0 | AF11: =SUM(Z11+AC11) -> 0 | AG11: =SUM(AE11:AF11) -> 0 | AS11: =AO11+AE11+U11+K11 -> 0 | AT11: =AP11+AF11+V11+L11 -> 0 | AU11: =AK11+AA11+Q11+G11 -> 0 | AV11: =AN11 -> 0 | AX11: =SUM(AQ11+AG11+W11+M11) -> 0 | AY11: =AX11/AW11 -> #DIV/0! | AZ11: =SUM(E11+O11+Y11+AI11) -> 0 | BA11: =F11+P11+Z11+AJ11 -> 0 | BB11: =H11+R11+AB11+AL11 -> 0 | BC11: =I11+S11+AC11+AM11 -> 0 | BX11: =BN11+BD11+AI11+Y11+O11+E11 -> 0 | BY11: =BO11+BE11+AJ11+Z11+P11+F11 -> 0 | BZ11: =BQ11+BG11+AL11+AB11+R11+H11 -> 0 | CA11: =BR11+BH11+AM11+AC11+S11+I11 -> 0 | CB11: =BX11+BY11+BZ11+CA11 -> 0 | CW11: =SUM(CS11+CI11+BT11+BJ11) -> 0 | CX11: =SUM(CT11+CJ11+BU11+BK11) -> 0 | CY11: =SUM(CU11+CK11+BV11+BL11) -> 0 | CZ11: =SUM(CR11+CH11+BS11+BI11) -> 0 | DB11: =SUM(CW11:CX11) -> 0 | DC11: =DB11/DA11 -> #DIV/0! | DD11: =BD11+BN11+CC11+CM11 -> 0 | DE11: =BE11+BO11+CD11+CN11 -> 0 | DF11: =BG11+BQ11+CF11+CP11 -> 0 | DG11: =BH11+BR11+CG11+CQ11 -> 0 | DH11: =DB11+AX11 -> 0 | DU11: =SUM(DS11:DT11) -> 0 | DX11: =SUM(DV11:DW11) -> 0 | DY11: =SUM(DS11+DV11) -> 0 | DZ11: =SUM(DT11+DW11) -> 0 | EA11: =SUM(DY11:DZ11) -> 0 | EW11: =SUM(ES11+EI11+DY11+DO11) -> 0 | EX11: =SUM(ET11+EJ11+DZ11+DP11) -> 0 | EY11: =SUM(EO11+EE11+DU11+DK11) -> 0 | EZ11: =SUM(ER11+EH11+DX11+DN11) -> 0 | FB11: =SUM(EW11:EX11) -> 0 | FC11: =FB11/FA11 -> #DIV/0! | FD11: =DI11+DS11+EC11+EM11+CM11+CC11 -> 0 | FE11: =DJ11+DT11+ED11+EN11+CD11+CN11 -> 0 | FF11: =DL11+DV11+EF11+EP11+CP11+CF11 -> 0 | FG11: =DM11+DW11+EG11+EQ11+CG11+CQ11 -> 0 | FH11: =FD11+FF11 -> 0 | FI11: =FE11+FG11 -> 0 | FJ11: =FH11+FI11 -> 0 | FK11: =EW11+CW11+AS11 -> 0 | FL11: =EX11+CX11+AT11 -> 0 | FM11: =FK11+FL11 -> 0 | FN11: 0 | FO11: 0 | FP11: =SUM(FN11:FO11) -> 0 | FQ11: 0 | FR11: 0 | FS11: =SUM(FQ11:FR11) -> 0 | FT11: =FN11+FQ11 -> 0 | FU11: =FO11+FR11 -> 0 | FV11: =SUM(FT11:FU11) -> 0 | GD11: =FX11+GA11 -> 0 | GE11: =FY11+GB11 -> 0 | GF11: =GD11+GE11 -> 0 | GN11: =GH11+GK11 -> 0 | GO11: =GI11+GL11 -> 0 | GP11: =GN11+GO11 -> 0 | GR11: =GN11+GD11+FT11+ES11+EI11+DY11+DO11+CS11+CI11+BT11+BJ11 -> 0 | GS11: =GO11+GE11+FU11+ET11+EJ11+DZ11+DP11+CT11+CJ11+BU11+BK11 -> 0 | GT11: =GH11+FX11+FN11+EM11+EC11+DS11+DI11+CM11+CC11+BN11+BD11 -> 0 | GU11: =GI11+FY11+FO11+EN11+ED11+DT11+DJ11+CN11+CD11+BO11+BE11 -> 0 | GV11: =GK11+GA11+FQ11+EP11+EF11+DV11+DL11+CP11+CF11+BQ11+BG11 -> 0 | GW11: =GL11+GB11+FR11+EQ11+EG11+DW11+DM11+CQ11+CG11+BR11+BH11 -> 0 | GZ11: =GX11+GY11 -> 0 | HC11: =HA11+HB11 -> 0 | HD11: =GX11+HA11 -> 0 | HE11: =GY11+HB11 -> 0 | HF11: =HD11+HE11 -> 0 | HH11: =HD11+GN11+GD11+FT11 -> 0 | HI11: =GO11+GE11+FU11+HE11 -> 0 | HJ11: =GX11+GH11+FX11+FN11 -> 0 | HK11: =GI11+FY11+GY11+FO11 -> 0 | HL11: =GK11+GA11+FQ11+HA11 -> 0 | HM11: =GL11+HB11+GB11+FR11 -> 0 | HO11: =HF11+GP11+GF11+FV11 -> 0 | HP11: =HO11/HN11 -> #DIV/0! | HQ11: =FN11+FX11+GH11+GX11 -> 0 | HR11: =FO11+FY11+GI11+GY11 -> 0 | HS11: =FQ11+GA11+GK11+HA11 -> 0 | HT11: =FR11+GB11+GL11+HB11 -> 0 | HW11: =HU11+HV11 -> 0 | HZ11: =HX11+HY11 -> 0 | IA11: =HU11+HX11 -> 0 | IB11: =HV11+HY11 -> 0 | IC11: =IA11+IB11 -> 0 | JI11: =SUM(IA11+IK11+IU11) -> 0 | JJ11: =SUM(IB11+IL11+IV11) -> 0 | JK11: =SUM(HW11+IG11+IQ11) -> 0 | JL11: =SUM(IJ11+IC11+IT11) -> 0 | JN11: =JG11+IW11+IM11+IC11 -> 0 | JO11: =JN11/JM11 -> #DIV/0! | JZ11: =JX11+JN11+HO11+FB11 -> 0 | KA11: =SUM(JV11+JE11+IU11+IK11+IA11+HD11+GN11+GD11+FT11+ES11+EI11+DY11+DO11+CS11+CI11+BT11+BJ11+AO11+AE11+U11+K11) -> 0 | KB11: =SUM(JW11+JF11+IV11+IL11+IB11+HE11+GO11+GE11+FU11+ET11+EJ11+DZ11+DP11+CT11+CJ11+BU11+BK11+AP11+AF11+V11+L11) -> 0 | KC11: =SUM(JP11+IY11+IO11+IE11+HU11+GX11+GH11+FX11+FN11+EM11+EC11+DS11+DI11+CM11+CC11+BN11+BD11+AI11+Y11+O11+E11) -> 0 | KD11: =SUM(JQ11+IZ11+IP11+IF11+HV11+GY11+GI11+FY11+FO11+EN11+ED11+DT11+DJ11+CN11+CD11+BO11+BE11+AJ11+Z11+P11+F11) -> 0 | KE11: =SUM(JS11+JB11+IR11+IH11+HX11+HA11+GK11+GA11+FQ11+EP11+EF11+DV11+DL11+CP11+CF11+BQ11+BG11+AL11+AB11+R11+H11) -> 0 | KF11: =SUM(JT11+JC11+IS11+II11+HY11+HB11+GL11+GB11+FR11+EQ11+EG11+DW11+DM11+CQ11+CG11+BR11+BH11+AM11+AC11+S11+I11) -> 0 | KG11: =SUM(KA11:KB11) -> 0 | KH11: 60 | KI11: =KH11-KG11 -> 60 | KJ11: =KG11/KH11 -> 0
B12: Training WGSS CMCS on leadership and safe space management and income generating activities [IGA] | C12: Nakivale | D12: 25 | O12: 0 | P12: 0 | Q12: =SUM(O12:P12) -> 0 | T12: =SUM(R12:S12) -> 0 | U12: =SUM(O12+R12) -> 0 | V12: =SUM(P12+S12) -> 0 | W12: =SUM(U12:V12) -> 0 | AA12: =SUM(Y12:Z12) -> 0 | AD12: =SUM(AB12:AC12) -> 0 | AE12: =SUM(Y12+AB12) -> 0 | AF12: =SUM(Z12+AC12) -> 0 | AG12: =SUM(AE12:AF12) -> 0 | AK12: =SUM(AI12:AJ12) -> 0 | AN12: =SUM(AL12:AM12) -> 0 | AO12: =SUM(AI12+AL12) -> 0 | AP12: =SUM(AJ12+AM12) -> 0 | AQ12: =SUM(AO12:AP12) -> 0 | AS12: =AO12+AE12+U12+K12 -> 0 | AT12: =AP12+AF12+V12+L12 -> 0 | AU12: =AK12+AA12+Q12+G12 -> 0 | AV12: =AN12 -> 0 | AX12: =SUM(AQ12+AG12+W12+M12) -> 0 | AY12: =AX12/AW12 -> #DIV/0! | AZ12: =SUM(E12+O12+Y12+AI12) -> 0 | BA12: =F12+P12+Z12+AJ12 -> 0 | BB12: =H12+R12+AB12+AL12 -> 0 | BC12: =I12+S12+AC12+AM12 -> 0 | BI12: =SUM(BG12:BH12) -> 0 | BJ12: =SUM(BD12+BG12) -> 0 | BK12: =SUM(BE12+BH12) -> 0 | BL12: =SUM(BJ12:BK12) -> 0 | BS12: =SUM(BQ12:BR12) -> 0 | BT12: =SUM(BN12+BQ12) -> 0 | BU12: =SUM(BO12+BR12) -> 0 | BV12: =SUM(BT12:BU12) -> 0 | BX12: =BN12+BD12+AI12+Y12+O12+E12 -> 0 | BY12: =BO12+BE12+AJ12+Z12+P12+F12 -> 0 | BZ12: =BQ12+BG12+AL12+AB12+R12+H12 -> 0 | CA12: =BR12+BH12+AM12+AC12+S12+I12 -> 0 | CB12: =BX12+BY12+BZ12+CA12 -> 0 | CH12: =SUM(CF12:CG12) -> 0 | CI12: =SUM(CC12+CF12) -> 0 | CJ12: =SUM(CD12+CG12) -> 0 | CK12: =SUM(CI12:CJ12) -> 0 | CR12: =SUM(CP12:CQ12) -> 0 | CS12: =SUM(CM12+CP12) -> 0 | CT12: =SUM(CN12+CQ12) -> 0 | CU12: =SUM(CS12:CT12) -> 0 | CW12: =SUM(CS12+CI12+BT12+BJ12) -> 0 | CX12: =SUM(CT12+CJ12+BU12+BK12) -> 0 | CY12: =SUM(CU12+CK12+BV12+BL12) -> 0 | CZ12: =SUM(CR12+CH12+BS12+BI12) -> 0 | DB12: =SUM(CW12:CX12) -> 0 | DC12: =DB12/DA12 -> #DIV/0! | DD12: =BD12+BN12+CC12+CM12 -> 0 | DE12: =BE12+BO12+CD12+CN12 -> 0 | DF12: =BG12+BQ12+CF12+CP12 -> 0 | DG12: =BH12+BR12+CG12+CQ12 -> 0 | DH12: =DB12+AX12 -> 0 | DN12: =SUM(DL12:DM12) -> 0 | DO12: =SUM(DI12+DL12) -> 0 | DP12: =SUM(DJ12+DM12) -> 0 | DQ12: =SUM(DO12:DP12) -> 0 | DU12: =SUM(DS12:DT12) -> 0 | DX12: =SUM(DV12:DW12) -> 0 | DY12: =SUM(DS12+DV12) -> 0 | DZ12: =SUM(DT12+DW12) -> 0 | EA12: =SUM(DY12:DZ12) -> 0 | EH12: =SUM(EF12:EG12) -> 0 | EI12: =SUM(EC12+EF12) -> 0 | EJ12: =SUM(ED12+EG12) -> 0 | EK12: =SUM(EI12:EJ12) -> 0 | EM12: 26 | EN12: 0 | EO12: =SUM(EM12:EN12) -> 26 | EP12: 1 | EQ12: 0 | ER12: =SUM(EP12:EQ12) -> 1 | ES12: =SUM(EM12+EP12) -> 27 | ET12: =SUM(EN12+EQ12) -> 0 | EU12: =SUM(ES12:ET12) -> 27 | EW12: =SUM(ES12+EI12+DY12+DO12) -> 27 | EX12: =SUM(ET12+EJ12+DZ12+DP12) -> 0 | EY12: =SUM(EO12+EE12+DU12+DK12) -> 26 | EZ12: =SUM(ER12+EH12+DX12+DN12) -> 1 | FB12: =SUM(EW12:EX12) -> 27 | FC12: =FB12/FA12 -> #DIV/0! | FD12: =DI12+DS12+EC12+EM12+CM12+CC12 -> 26 | FE12: =DJ12+DT12+ED12+EN12+CD12+CN12 -> 0 | FF12: =DL12+DV12+EF12+EP12+CP12+CF12 -> 1 | FG12: =DM12+DW12+EG12+EQ12+CG12+CQ12 -> 0 | FH12: =FD12+FF12 -> 27 | FI12: =FE12+FG12 -> 0 | FJ12: =FH12+FI12 -> 27 | FK12: =EW12+CW12+AS12 -> 27 | FL12: =EX12+CX12+AT12 -> 0 | FM12: =FK12+FL12 -> 27 | FS12: =SUM(FQ12:FR12) -> 0 | FT12: =SUM(FN12+FQ12) -> 0 | FU12: =SUM(FO12+FR12) -> 0 | FV12: =SUM(FT12:FU12) -> 0 | GC12: =SUM(GA12:GB12) -> 0 | GD12: =FX12+GA12 -> 0 | GE12: =FY12+GB12 -> 0 | GF12: =GD12+GE12 -> 0 | GM12: =SUM(GK12:GL12) -> 0 | GN12: =GH12+GK12 -> 0 | GO12: =GI12+GL12 -> 0 | GP12: =GN12+GO12 -> 0 | GR12: =GN12+GD12+FT12+ES12+EI12+DY12+DO12+CS12+CI12+BT12+BJ12 -> 27 | GS12: =GO12+GE12+FU12+ET12+EJ12+DZ12+DP12+CT12+CJ12+BU12+BK12 -> 0 | GT12: =GH12+FX12+FN12+EM12+EC12+DS12+DI12+CM12+CC12+BN12+BD12 -> 26 | GU12: =GI12+FY12+FO12+EN12+ED12+DT12+DJ12+CN12+CD12+BO12+BE12 -> 0 | GV12: =GK12+GA12+FQ12+EP12+EF12+DV12+DL12+CP12+CF12+BQ12+BG12 -> 1 | GW12: =GL12+GB12+FR12+EQ12+EG12+DW12+DM12+CQ12+CG12+BR12+BH12 -> 0 | GZ12: =GX12+GY12 -> 0 | HC12: =HA12+HB12 -> 0 | HD12: =GX12+HA12 -> 0 | HE12: =GY12+HB12 -> 0 | HF12: =HD12+HE12 -> 0 | HH12: =HD12+GN12+GD12+FT12 -> 0 | HI12: =GO12+GE12+FU12+HE12 -> 0 | HJ12: =GX12+GH12+FX12+FN12 -> 0 | HK12: =GI12+FY12+GY12+FO12 -> 0 | HL12: =GK12+GA12+FQ12+HA12 -> 0 | HM12: =GL12+HB12+GB12+FR12 -> 0 | HO12: =HF12+GP12+GF12+FV12 -> 0 | HP12: =HO12/HN12 -> #DIV/0! | HQ12: =FN12+FX12+GH12+GX12 -> 0 | HR12: =FO12+FY12+GI12+GY12 -> 0 | HS12: =FQ12+GA12+GK12+HA12 -> 0 | HT12: =FR12+GB12+GL12+HB12 -> 0 | HU12: 21 | HV12: 0 | HW12: =HU12+HV12 -> 21 | HX12: 0 | HY12: 0 | HZ12: =HX12+HY12 -> 0 | IA12: =HU12+HX12 -> 21 | IB12: =HV12+HY12 -> 0 | IC12: =IA12+IB12 -> 21 | IJ12: =SUM(IH12:II12) -> 0 | IK12: =SUM(IE12+IH12) -> 0 | IL12: =SUM(IF12+II12) -> 0 | IM12: =SUM(IK12:IL12) -> 0 | IT12: =SUM(IR12:IS12) -> 0 | IU12: =SUM(IO12+IR12) -> 0 | IV12: =SUM(IP12+IS12) -> 0 | IW12: =SUM(IU12:IV12) -> 0 | JB12: 0 | JC12: 0 | JD12: =SUM(JB12:JC12) -> 0 | JE12: =SUM(IY12+JB12) -> 0 | JF12: =SUM(IZ12+JC12) -> 0 | JG12: =SUM(JE12:JF12) -> 0 | JI12: =SUM(IA12+IK12+IU12) -> 21 | JJ12: =SUM(IB12+IL12+IV12) -> 0 | JK12: =SUM(HW12+IG12+IQ12) -> 21 | JL12: =SUM(IJ12+HZ12+IT12) -> 0 | JM12: =SUM(JI12:JJ12) -> 21 | JN12: =JG12+IW12+IM12+IC12 -> 21 | JO12: =JN12/JM12 -> 1 | JS12: 0 | JT12: 0 | JU12: =SUM(JS12:JT12) -> 0 | JV12: =SUM(JP12+JS12) -> 0 | JW12: =SUM(JQ12+JT12) -> 0 | JX12: =SUM(JV12:JW12) -> 0 | JZ12: =JX12+JN12+HO12+FB12 -> 48 | KA12: =SUM(JV12+JE12+IU12+IK12+IA12+HD12+GN12+GD12+FT12+ES12+EI12+DY12+DO12+CS12+CI12+BT12+BJ12+AO12+AE12+U12+K12) -> 48 | KB12: =SUM(JW12+JF12+IV12+IL12+IB12+HE12+GO12+GE12+FU12+ET12+EJ12+DZ12+DP12+CT12+CJ12+BU12+BK12+AP12+AF12+V12+L12) -> 0 | KC12: =SUM(JP12+IY12+IO12+IE12+HU12+GX12+GH12+FX12+FN12+EM12+EC12+DS12+DI12+CM12+CC12+BN12+BD12+AI12+Y12+O12+E12) -> 47 | KD12: =SUM(JQ12+IZ12+IP12+IF12+HV12+GY12+GI12+FY12+FO12+EN12+ED12+DT12+DJ12+CN12+CD12+BO12+BE12+AJ12+Z12+P12+F12) -> 0 | KE12: =SUM(JS12+JB12+IR12+IH12+HX12+HA12+GK12+GA12+FQ12+EP12+EF12+DV12+DL12+CP12+CF12+BQ12+BG12+AL12+AB12+R12+H12) -> 1 | KF12: =SUM(JT12+JC12+IS12+II12+HY12+HB12+GL12+GB12+FR12+EQ12+EG12+DW12+DM12+CQ12+CG12+BR12+BH12+AM12+AC12+S12+I12) -> 0 | KG12: =SUM(KA12:KB12) -> 48 | KH12: 25 | KI12: =KH12-KG12 -> -23 | KJ12: =KG12/KH12 -> 1.92
B13: Training Facilitators for Women and Girls Safe Spaces | C13: Nakivale | D13: 2 | AS13: =AO13+AE13+U13+K13 -> 0 | AT13: =AP13+AF13+V13+L13 -> 0 | AU13: =AK13+AA13+Q13+G13 -> 0 | AV13: =AN13 -> 0 | AX13: =SUM(AQ13+AG13+W13+M13) -> 0 | AZ13: =SUM(E13+O13+Y13+AI13) -> 0 | BA13: =F13+P13+Z13+AJ13 -> 0 | BB13: =H13+R13+AB13+AL13 -> 0 | BC13: =I13+S13+AC13+AM13 -> 0 | BX13: =BN13+BD13+AI13+Y13+O13+E13 -> 0 | BY13: =BO13+BE13+AJ13+Z13+P13+F13 -> 0 | BZ13: =BQ13+BG13+AL13+AB13+R13+H13 -> 0 | CA13: =BR13+BH13+AM13+AC13+S13+I13 -> 0 | CB13: =BX13+BY13+BZ13+CA13 -> 0 | CW13: =SUM(CS13+CI13+BT13+BJ13) -> 0 | CX13: =SUM(CT13+CJ13+BU13+BK13) -> 0 | CY13: =SUM(CU13+CK13+BV13+BL13) -> 0 | CZ13: =SUM(CR13+CH13+BS13+BI13) -> 0 | DB13: =SUM(CW13:CX13) -> 0 | DD13: =BD13+BN13+CC13+CM13 -> 0 | DE13: =BE13+BO13+CD13+CN13 -> 0 | DF13: =BG13+BQ13+CF13+CP13 -> 0 | DG13: =BH13+BR13+CG13+CQ13 -> 0 | DH13: =DB13+AX13 -> 0 | DU13: =SUM(DS13:DT13) -> 0 | DX13: =SUM(DV13:DW13) -> 0 | DY13: =SUM(DS13+DV13) -> 0 | DZ13: =SUM(DT13+DW13) -> 0 | EA13: =SUM(DY13:DZ13) -> 0 | EW13: =SUM(ES13+EI13+DY13+DO13) -> 0 | EX13: =SUM(ET13+EJ13+DZ13+DP13) -> 0 | EY13: =SUM(EO13+EE13+DU13+DK13) -> 0 | EZ13: =SUM(ER13+EH13+DX13+DN13) -> 0 | FB13: =SUM(EW13:EX13) -> 0 | FD13: =DI13+DS13+EC13+EM13+CM13+CC13 -> 0 | FE13: =DJ13+DT13+ED13+EN13+CD13+CN13 -> 0 | FF13: =DL13+DV13+EF13+EP13+CP13+CF13 -> 0 | FG13: =DM13+DW13+EG13+EQ13+CG13+CQ13 -> 0 | FH13: =FD13+FF13 -> 0 | FI13: =FE13+FG13 -> 0 | FJ13: =FH13+FI13 -> 0 | FK13: =EW13+CW13+AS13 -> 0 | FL13: =EX13+CX13+AT13 -> 0 | FM13: =FK13+FL13 -> 0 | GD13: =FX13+GA13 -> 0 | GE13: =FY13+GB13 -> 0 | GF13: =GD13+GE13 -> 0 | GN13: =GH13+GK13 -> 0 | GO13: =GI13+GL13 -> 0 | GP13: =GN13+GO13 -> 0 | GR13: =GN13+GD13+FT13+ES13+EI13+DY13+DO13+CS13+CI13+BT13+BJ13 -> 0 | GS13: =GO13+GE13+FU13+ET13+EJ13+DZ13+DP13+CT13+CJ13+BU13+BK13 -> 0 | GT13: =GH13+FX13+FN13+EM13+EC13+DS13+DI13+CM13+CC13+BN13+BD13 -> 0 | GU13: =GI13+FY13+FO13+EN13+ED13+DT13+DJ13+CN13+CD13+BO13+BE13 -> 0 | GV13: =GK13+GA13+FQ13+EP13+EF13+DV13+DL13+CP13+CF13+BQ13+BG13 -> 0 | GW13: =GL13+GB13+FR13+EQ13+EG13+DW13+DM13+CQ13+CG13+BR13+BH13 -> 0 | GZ13: =GX13+GY13 -> 0 | HC13: =HA13+HB13 -> 0 | HD13: =GX13+HA13 -> 0 | HE13: =GY13+HB13 -> 0 | HF13: =HD13+HE13 -> 0 | HH13: =HD13+GN13+GD13+FT13 -> 0 | HI13: =GO13+GE13+FU13+HE13 -> 0 | HJ13: =GX13+GH13+FX13+FN13 -> 0 | HK13: =GI13+FY13+GY13+FO13 -> 0 | HL13: =GK13+GA13+FQ13+HA13 -> 0 | HM13: =GL13+HB13+GB13+FR13 -> 0 | HO13: =HF13+GP13+GF13+FV13 -> 0 | HQ13: =FN13+FX13+GH13+GX13 -> 0 | HR13: =FO13+FY13+GI13+GY13 -> 0 | HS13: =FQ13+GA13+GK13+HA13 -> 0 | HT13: =FR13+GB13+GL13+HB13 -> 0 | HW13: =HU13+HV13 -> 0 | HZ13: =HX13+HY13 -> 0 | IA13: =HU13+HX13 -> 0 | IB13: =HV13+HY13 -> 0 | IC13: =IA13+IB13 -> 0 | JN13: =JG13+IW13+IM13+IC13 -> 0 | JZ13: =JX13+JN13+HO13+FB13 -> 0 | KA13: =SUM(JV13+JE13+IU13+IK13+IA13+HD13+GN13+GD13+FT13+ES13+EI13+DY13+DO13+CS13+CI13+BT13+BJ13+AO13+AE13+U13+K13) -> 0 | KB13: =SUM(JW13+JF13+IV13+IL13+IB13+HE13+GO13+GE13+FU13+ET13+EJ13+DZ13+DP13+CT13+CJ13+BU13+BK13+AP13+AF13+V13+L13) -> 0 | KC13: =SUM(JP13+IY13+IO13+IE13+HU13+GX13+GH13+FX13+FN13+EM13+EC13+DS13+DI13+CM13+CC13+BN13+BD13+AI13+Y13+O13+E13) -> 0 | KD13: =SUM(JQ13+IZ13+IP13+IF13+HV13+GY13+GI13+FY13+FO13+EN13+ED13+DT13+DJ13+CN13+CD13+BO13+BE13+AJ13+Z13+P13+F13) -> 0 | KE13: =SUM(JS13+JB13+IR13+IH13+HX13+HA13+GK13+GA13+FQ13+EP13+EF13+DV13+DL13+CP13+CF13+BQ13+BG13+AL13+AB13+R13+H13) -> 0 | KF13: =SUM(JT13+JC13+IS13+II13+HY13+HB13+GL13+GB13+FR13+EQ13+EG13+DW13+DM13+CQ13+CG13+BR13+BH13+AM13+AC13+S13+I13) -> 0 | KG13: =SUM(KA13:KB13) -> 0 | KH13: 2 | KI13: =KH13-KG13 -> 2 | KJ13: =KG13/KH13 -> 0
B14: Provide working Tools to GBV Structures | C14: Nakivale | D14: 50 | AS14: =AO14+AE14+U14+K14 -> 0 | AT14: =AP14+AF14+V14+L14 -> 0 | AU14: =AK14+AA14+Q14+G14 -> 0 | AV14: =AN14 -> 0 | AX14: =SUM(AQ14+AG14+W14+M14) -> 0 | AY14: =AX14/AW14 -> #DIV/0! | AZ14: =SUM(E14+O14+Y14+AI14) -> 0 | BA14: =F14+P14+Z14+AJ14 -> 0 | BB14: =H14+R14+AB14+AL14 -> 0 | BC14: =I14+S14+AC14+AM14 -> 0 | BD14: 22 | BE14: 18 | BF14: =SUM(BD14:BE14) -> 40 | BG14: 7 | BH14: 3 | BI14: =SUM(BG14:BH14) -> 10 | BJ14: =SUM(BD14+BG14) -> 29 | BK14: =SUM(BE14+BH14) -> 21 | BL14: =SUM(BJ14:BK14) -> 50 | BS14: =SUM(BQ14:BR14) -> 0 | BT14: =SUM(BN14+BQ14) -> 0 | BU14: =SUM(BO14+BR14) -> 0 | BV14: =SUM(BT14:BU14) -> 0 | BX14: =BN14+BD14+AI14+Y14+O14+E14 -> 22 | BY14: =BO14+BE14+AJ14+Z14+P14+F14 -> 18 | BZ14: =BQ14+BG14+AL14+AB14+R14+H14 -> 7 | CA14: =BR14+BH14+AM14+AC14+S14+I14 -> 3 | CB14: =BX14+BY14+BZ14+CA14 -> 50 | CH14: =SUM(CF14:CG14) -> 0 | CI14: =SUM(CC14+CF14) -> 0 | CJ14: =SUM(CD14+CG14) -> 0 | CK14: =SUM(CI14:CJ14) -> 0 | CR14: =SUM(CP14:CQ14) -> 0 | CS14: =SUM(CM14+CP14) -> 0 | CT14: =SUM(CN14+CQ14) -> 0 | CU14: =SUM(CS14:CT14) -> 0 | CW14: =SUM(CS14+CI14+BT14+BJ14) -> 29 | CX14: =SUM(CT14+CJ14+BU14+BK14) -> 21 | CY14: =SUM(CU14+CK14+BV14+BL14) -> 50 | CZ14: =SUM(CR14+CH14+BS14+BI14) -> 10 | DB14: =SUM(CW14:CX14) -> 50 | DC14: =DB14/DA14 -> #DIV/0! | DD14: =BD14+BN14+CC14+CM14 -> 22 | DE14: =BE14+BO14+CD14+CN14 -> 18 | DF14: =BG14+BQ14+CF14+CP14 -> 7 | DG14: =BH14+BR14+CG14+CQ14 -> 3 | DH14: =DB14+AX14 -> 50 | DN14: =SUM(DL14:DM14) -> 0 | DO14: =SUM(DI14+DL14) -> 0 | DP14: =SUM(DJ14+DM14) -> 0 | DQ14: =SUM(DO14:DP14) -> 0 | DU14: =SUM(DS14:DT14) -> 0 | DX14: =SUM(DV14:DW14) -> 0 | DY14: =SUM(DS14+DV14) -> 0 | DZ14: =SUM(DT14+DW14) -> 0 | EA14: =SUM(DY14:DZ14) -> 0 | EH14: =SUM(EF14:EG14) -> 0 | EI14: =SUM(EC14+EF14) -> 0 | EJ14: =SUM(ED14+EG14) -> 0 | EK14: =SUM(EI14:EJ14) -> 0 | ER14: =SUM(EP14:EQ14) -> 0 | ES14: =SUM(EM14+EP14) -> 0 | ET14: =SUM(EN14+EQ14) -> 0 | EU14: =SUM(ES14:ET14) -> 0 | EW14: =SUM(ES14+EI14+DY14+DO14) -> 0 | EX14: =SUM(ET14+EJ14+DZ14+DP14) -> 0 | EY14: =SUM(EO14+EE14+DU14+DK14) -> 0 | EZ14: =SUM(ER14+EH14+DX14+DN14) -> 0 | FB14: =SUM(EW14:EX14) -> 0 | FC14: =FB14/FA14 -> #DIV/0! | FD14: =DI14+DS14+EC14+EM14+CM14+CC14 -> 0 | FE14: =DJ14+DT14+ED14+EN14+CD14+CN14 -> 0 | FF14: =DL14+DV14+EF14+EP14+CP14+CF14 -> 0 | FG14: =DM14+DW14+EG14+EQ14+CG14+CQ14 -> 0 | FH14: =FD14+FF14 -> 0 | FI14: =FE14+FG14 -> 0 | FJ14: =FH14+FI14 -> 0 | FK14: =EW14+CW14+AS14 -> 29 | FL14: =EX14+CX14+AT14 -> 21 | FM14: =FK14+FL14 -> 50 | FS14: =SUM(FQ14:FR14) -> 0 | FT14: =SUM(FN14+FQ14) -> 0 | FU14: =SUM(FO14+FR14) -> 0 | FV14: =SUM(FT14:FU14) -> 0 | GC14: =SUM(GA14:GB14) -> 0 | GD14: =FX14+GA14 -> 0 | GE14: =FY14+GB14 -> 0 | GF14: =GD14+GE14 -> 0 | GM14: =SUM(GK14:GL14) -> 0 | GN14: =GH14+GK14 -> 0 | GO14: =GI14+GL14 -> 0 | GP14: =GN14+GO14 -> 0 | GR14: =GN14+GD14+FT14+ES14+EI14+DY14+DO14+CS14+CI14+BT14+BJ14 -> 29 | GS14: =GO14+GE14+FU14+ET14+EJ14+DZ14+DP14+CT14+CJ14+BU14+BK14 -> 21 | GT14: =GH14+FX14+FN14+EM14+EC14+DS14+DI14+CM14+CC14+BN14+BD14 -> 22 | GU14: =GI14+FY14+FO14+EN14+ED14+DT14+DJ14+CN14+CD14+BO14+BE14 -> 18 | GV14: =GK14+GA14+FQ14+EP14+EF14+DV14+DL14+CP14+CF14+BQ14+BG14 -> 7 | GW14: =GL14+GB14+FR14+EQ14+EG14+DW14+DM14+CQ14+CG14+BR14+BH14 -> 3 | GZ14: =GX14+GY14 -> 0 | HC14: =HA14+HB14 -> 0 | HD14: =GX14+HA14 -> 0 | HE14: =GY14+HB14 -> 0 | HF14: =HD14+HE14 -> 0 | HH14: =HD14+GN14+GD14+FT14 -> 0 | HI14: =GO14+GE14+FU14+HE14 -> 0 | HJ14: =GX14+GH14+FX14+FN14 -> 0 | HK14: =GI14+FY14+GY14+FO14 -> 0 | HL14: =GK14+GA14+FQ14+HA14 -> 0 | HM14: =GL14+HB14+GB14+FR14 -> 0 | HO14: =HF14+GP14+GF14+FV14 -> 0 | HP14: =HO14/HN14 -> #DIV/0! | HQ14: =FN14+FX14+GH14+GX14 -> 0 | HR14: =FO14+FY14+GI14+GY14 -> 0 | HS14: =FQ14+GA14+GK14+HA14 -> 0 | HT14: =FR14+GB14+GL14+HB14 -> 0 | HW14: =HU14+HV14 -> 0 | HZ14: =HX14+HY14 -> 0 | IA14: =HU14+HX14 -> 0 | IB14: =HV14+HY14 -> 0 | IC14: =IA14+IB14 -> 0 | IJ14: =SUM(IH14:II14) -> 0 | IK14: =SUM(IE14+IH14) -> 0 | IL14: =SUM(IF14+II14) -> 0 | IM14: =SUM(IK14:IL14) -> 0 | IT14: =SUM(IR14:IS14) -> 0 | IU14: =SUM(IO14+IR14) -> 0 | IV14: =SUM(IP14+IS14) -> 0 | IW14: =SUM(IU14:IV14) -> 0 | JD14: =SUM(JB14:JC14) -> 0 | JE14: =SUM(IY14+JB14) -> 0 | JF14: =SUM(IZ14+JC14) -> 0 | JG14: =SUM(JE14:JF14) -> 0 | JN14: =JG14+IW14+IM14+IC14 -> 0 | JO14: =JN14/JM14 -> #DIV/0! | JU14: =SUM(JS14:JT14) -> 0 | JV14: =SUM(JP14+JS14) -> 0 | JW14: =SUM(JQ14+JT14) -> 0 | JX14: =SUM(JV14:JW14) -> 0 | JZ14: =JX14+JN14+HO14+FB14 -> 0 | KA14: =SUM(JV14+JE14+IU14+IK14+IA14+HD14+GN14+GD14+FT14+ES14+EI14+DY14+DO14+CS14+CI14+BT14+BJ14+AO14+AE14+U14+K14) -> 29 | KB14: =SUM(JW14+JF14+IV14+IL14+IB14+HE14+GO14+GE14+FU14+ET14+EJ14+DZ14+DP14+CT14+CJ14+BU14+BK14+AP14+AF14+V14+L14) -> 21 | KC14: =SUM(JP14+IY14+IO14+IE14+HU14+GX14+GH14+FX14+FN14+EM14+EC14+DS14+DI14+CM14+CC14+BN14+BD14+AI14+Y14+O14+E14) -> 22 | KD14: =SUM(JQ14+IZ14+IP14+IF14+HV14+GY14+GI14+FY14+FO14+EN14+ED14+DT14+DJ14+CN14+CD14+BO14+BE14+AJ14+Z14+P14+F14) -> 18 | KE14: =SUM(JS14+JB14+IR14+IH14+HX14+HA14+GK14+GA14+FQ14+EP14+EF14+DV14+DL14+CP14+CF14+BQ14+BG14+AL14+AB14+R14+H14) -> 7 | KF14: =SUM(JT14+JC14+IS14+II14+HY14+HB14+GL14+GB14+FR14+EQ14+EG14+DW14+DM14+CQ14+CG14+BR14+BH14+AM14+AC14+S14+I14) -> 3 | KG14: =SUM(KA14:KB14) -> 50 | KH14: 50 | KI14: =KH14-KG14 -> 0 | KJ14: =KG14/KH14 -> 1
B15: GBV Information counseling | C15: Nakivale | D15: 200 | BX15: =BN15+BD15+AI15+Y15+O15+E15 -> 0 | BY15: =BO15+BE15+AJ15+Z15+P15+F15 -> 0 | BZ15: =BQ15+BG15+AL15+AB15+R15+H15 -> 0 | CA15: =BR15+BH15+AM15+AC15+S15+I15 -> 0 | CB15: =BX15+BY15+BZ15+CA15 -> 0 | DH15: =DB15+AX15 -> 0 | FD15: =DI15+DS15+EC15+EM15+CM15+CC15 -> 0 | FE15: =DJ15+DT15+ED15+EN15+CD15+CN15 -> 0 | FF15: =DL15+DV15+EF15+EP15+CP15+CF15 -> 0 | FG15: =DM15+DW15+EG15+EQ15+CG15+CQ15 -> 0 | FH15: =FD15+FF15 -> 0 | FI15: =FE15+FG15 -> 0 | FJ15: =FH15+FI15 -> 0 | FK15: =EW15+CW15+AS15 -> 0 | FL15: =EX15+CX15+AT15 -> 0 | FM15: =FK15+FL15 -> 0 | FX15: 73 | FY15: 0 | FZ15: =FX15+FY15 -> 73 | GA15: 0 | GB15: 0 | GC15: =SUM(GA15:GB15) -> 0 | GD15: =FX15+GA15 -> 73 | GE15: =FY15+GB15 -> 0 | GF15: =GD15+GE15 -> 73 | GH15: 103 | GI15: 0 | GJ15: =GH15+GI15 -> 103 | GK15: 0 | GL15: 0 | GM15: =GK15+GL15 -> 0 | GN15: =GH15+GK15 -> 103 | GO15: =GI15+GL15 -> 0 | GP15: =GN15+GO15 -> 103 | GR15: =GN15+GD15+FT15+ES15+EI15+DY15+DO15+CS15+CI15+BT15+BJ15 -> 176 | GS15: =GO15+GE15+FU15+ET15+EJ15+DZ15+DP15+CT15+CJ15+BU15+BK15 -> 0 | GT15: =GH15+FX15+FN15+EM15+EC15+DS15+DI15+CM15+CC15+BN15+BD15 -> 176 | GU15: =GI15+FY15+FO15+EN15+ED15+DT15+DJ15+CN15+CD15+BO15+BE15 -> 0 | GV15: =GK15+GA15+FQ15+EP15+EF15+DV15+DL15+CP15+CF15+BQ15+BG15 -> 0 | GW15: =GL15+GB15+FR15+EQ15+EG15+DW15+DM15+CQ15+CG15+BR15+BH15 -> 0 | GZ15: =GX15+GY15 -> 0 | HC15: =HA15+HB15 -> 0 | HD15: =GX15+HA15 -> 0 | HE15: =GY15+HB15 -> 0 | HF15: =HD15+HE15 -> 0 | HH15: =HD15+GN15+GD15+FT15 -> 176 | HI15: =GO15+GE15+FU15+HE15 -> 0 | HJ15: =GX15+GH15+FX15+FN15 -> 176 | HK15: =GI15+FY15+GY15+FO15 -> 0 | HL15: =GK15+GA15+FQ15+HA15 -> 0 | HM15: =GL15+HB15+GB15+FR15 -> 0 | HO15: =HF15+GP15+GF15+FV15 -> 176 | HQ15: =FN15+FX15+GH15+GX15 -> 176 | HR15: =FO15+FY15+GI15+GY15 -> 0 | HS15: =FQ15+GA15+GK15+HA15 -> 0 | HT15: =FR15+GB15+GL15+HB15 -> 0 | HU15: 136 | HV15: 0 | HW15: =HU15+HV15 -> 136 | HX15: 0 | HY15: 0 | HZ15: =HX15+HY15 -> 0 | IA15: =HU15+HX15 -> 136 | IB15: =HV15+HY15 -> 0 | IC15: =IA15+IB15 -> 136 | IJ15: =SUM(IH15:II15) -> 0 | IK15: =SUM(IE15+IH15) -> 0 | IL15: =SUM(IF15+II15) -> 0 | IM15: =SUM(IK15:IL15) -> 0 | IT15: =SUM(IR15:IS15) -> 0 | IU15: =SUM(IO15+IR15) -> 0 | IV15: =SUM(IP15+IS15) -> 0 | IW15: =SUM(IU15:IV15) -> 0 | JD15: =SUM(JB15:JC15) -> 0 | JE15: =SUM(IY15+JB15) -> 0 | JF15: =SUM(IZ15+JC15) -> 0 | JG15: =SUM(JE15:JF15) -> 0 | JN15: =JG15+IW15+IM15+IC15 -> 136 | JO15: =JN15/JM15 -> #DIV/0! | JU15: =SUM(JS15:JT15) -> 0 | JV15: =SUM(JP15+JS15) -> 0 | JW15: =SUM(JQ15+JT15) -> 0 | JX15: =SUM(JV15:JW15) -> 0 | JZ15: =JX15+JN15+HO15+FB15 -> 312 | KA15: =SUM(JV15+JE15+IU15+IK15+IA15+HD15+GN15+GD15+FT15+ES15+EI15+DY15+DO15+CS15+CI15+BT15+BJ15+AO15+AE15+U15+K15) -> 312 | KB15: =SUM(JW15+JF15+IV15+IL15+IB15+HE15+GO15+GE15+FU15+ET15+EJ15+DZ15+DP15+CT15+CJ15+BU15+BK15+AP15+AF15+V15+L15) -> 0 | KC15: =SUM(JP15+IY15+IO15+IE15+HU15+GX15+GH15+FX15+FN15+EM15+EC15+DS15+DI15+CM15+CC15+BN15+BD15+AI15+Y15+O15+E15) -> 312 | KD15: =SUM(JQ15+IZ15+IP15+IF15+HV15+GY15+GI15+FY15+FO15+EN15+ED15+DT15+DJ15+CN15+CD15+BO15+BE15+AJ15+Z15+P15+F15) -> 0 | KE15: =SUM(JS15+JB15+IR15+IH15+HX15+HA15+GK15+GA15+FQ15+EP15+EF15+DV15+DL15+CP15+CF15+BQ15+BG15+AL15+AB15+R15+H15) -> 0 | KF15: =SUM(JT15+JC15+IS15+II15+HY15+HB15+GL15+GB15+FR15+EQ15+EG15+DW15+DM15+CQ15+CG15+BR15+BH15+AM15+AC15+S15+I15) -> 0 | KG15: =SUM(KA15:KB15) -> 312 | KH15: 200 | KI15: =KH15-KG15 -> -112 | KJ15: =KG15/KH15 -> 1.56
B16: Referrals made from Women and Girls Safe Spaces | C16: Nakivale | D16: 450 | AS16: =AO16+AE16+U16+K16 -> 0 | AT16: =AP16+AF16+V16+L16 -> 0 | AU16: =AK16+AA16+Q16+G16 -> 0 | AV16: =AN16 -> 0 | AX16: =SUM(AQ16+AG16+W16+M16) -> 0 | AZ16: =SUM(E16+O16+Y16+AI16) -> 0 | BA16: =F16+P16+Z16+AJ16 -> 0 | BB16: =H16+R16+AB16+AL16 -> 0 | BC16: =I16+S16+AC16+AM16 -> 0 | BX16: =BN16+BD16+AI16+Y16+O16+E16 -> 0 | BY16: =BO16+BE16+AJ16+Z16+P16+F16 -> 0 | BZ16: =BQ16+BG16+AL16+AB16+R16+H16 -> 0 | CA16: =BR16+BH16+AM16+AC16+S16+I16 -> 0 | CB16: =BX16+BY16+BZ16+CA16 -> 0 | CW16: =SUM(CS16+CI16+BT16+BJ16) -> 0 | CX16: =SUM(CT16+CJ16+BU16+BK16) -> 0 | CY16: =SUM(CU16+CK16+BV16+BL16) -> 0 | CZ16: =SUM(CR16+CH16+BS16+BI16) -> 0 | DB16: =SUM(CW16:CX16) -> 0 | DD16: =BD16+BN16+CC16+CM16 -> 0 | DE16: =BE16+BO16+CD16+CN16 -> 0 | DF16: =BG16+BQ16+CF16+CP16 -> 0 | DG16: =BH16+BR16+CG16+CQ16 -> 0 | DH16: =DB16+AX16 -> 0 | DU16: =SUM(DS16:DT16) -> 0 | DX16: =SUM(DV16:DW16) -> 0 | DY16: =SUM(DS16+DV16) -> 0 | DZ16: =SUM(DT16+DW16) -> 0 | EA16: =SUM(DY16:DZ16) -> 0 | EI16: =SUM(EC16+EF16) -> 0 | EJ16: =SUM(ED16+EG16) -> 0 | EK16: =SUM(EI16:EJ16) -> 0 | EW16: =SUM(ES16+EI16+DY16+DO16) -> 0 | EX16: =SUM(ET16+EJ16+DZ16+DP16) -> 0 | EY16: =SUM(EO16+EE16+DU16+DK16) -> 0 | EZ16: =SUM(ER16+EH16+DX16+DN16) -> 0 | FB16: =SUM(EW16:EX16) -> 0 | FD16: =DI16+DS16+EC16+EM16+CM16+CC16 -> 0 | FE16: =DJ16+DT16+ED16+EN16+CD16+CN16 -> 0 | FF16: =DL16+DV16+EF16+EP16+CP16+CF16 -> 0 | FG16: =DM16+DW16+EG16+EQ16+CG16+CQ16 -> 0 | FH16: =FD16+FF16 -> 0 | FI16: =FE16+FG16 -> 0 | FJ16: =FH16+FI16 -> 0 | FK16: =EW16+CW16+AS16 -> 0 | FL16: =EX16+CX16+AT16 -> 0 | FM16: =FK16+FL16 -> 0 | FN16: 22 | FO16: 0 | FP16: =SUM(FN16:FO16) -> 22 | FQ16: 0 | FR16: 0 | FS16: =SUM(FQ16:FR16) -> 0 | FT16: =SUM(FN16+FQ16) -> 22 | FU16: =SUM(FO16+FR16) -> 0 | FV16: =SUM(FT16:FU16) -> 22 | GD16: =FX16+GA16 -> 0 | GE16: =FY16+GB16 -> 0 | GF16: =GD16+GE16 -> 0 | GN16: =GH16+GK16 -> 0 | GO16: =GI16+GL16 -> 0 | GP16: =GN16+GO16 -> 0 | GR16: =GN16+GD16+FT16+ES16+EI16+DY16+DO16+CS16+CI16+BT16+BJ16 -> 22 | GS16: =GO16+GE16+FU16+ET16+EJ16+DZ16+DP16+CT16+CJ16+BU16+BK16 -> 0 | GT16: =GH16+FX16+FN16+EM16+EC16+DS16+DI16+CM16+CC16+BN16+BD16 -> 22 | GU16: =GI16+FY16+FO16+EN16+ED16+DT16+DJ16+CN16+CD16+BO16+BE16 -> 0 | GV16: =GK16+GA16+FQ16+EP16+EF16+DV16+DL16+CP16+CF16+BQ16+BG16 -> 0 | GW16: =GL16+GB16+FR16+EQ16+EG16+DW16+DM16+CQ16+CG16+BR16+BH16 -> 0 | GZ16: =GX16+GY16 -> 0 | HC16: =HA16+HB16 -> 0 | HD16: =GX16+HA16 -> 0 | HE16: =GY16+HB16 -> 0 | HF16: =HD16+HE16 -> 0 | HH16: =HD16+GN16+GD16+FT16 -> 22 | HI16: =GO16+GE16+FU16+HE16 -> 0 | HJ16: =GX16+GH16+FX16+FN16 -> 22 | HK16: =GI16+FY16+GY16+FO16 -> 0 | HL16: =GK16+GA16+FQ16+HA16 -> 0 | HM16: =GL16+HB16+GB16+FR16 -> 0 | HO16: =HF16+GP16+GF16+FV16 -> 22 | HQ16: =FN16+FX16+GH16+GX16 -> 22 | HR16: =FO16+FY16+GI16+GY16 -> 0 | HS16: =FQ16+GA16+GK16+HA16 -> 0 | HT16: =FR16+GB16+GL16+HB16 -> 0 | HW16: =HU16+HV16 -> 0 | HZ16: =HX16+HY16 -> 0 | IA16: =HU16+HX16 -> 0 | IB16: =HV16+HY16 -> 0 | IC16: =IA16+IB16 -> 0 | JN16: =JG16+IW16+IM16+IC16 -> 0 | JZ16: =JX16+JN16+HO16+FB16 -> 22 | KA16: =SUM(JV16+JE16+IU16+IK16+IA16+HD16+GN16+GD16+FT16+ES16+EI16+DY16+DO16+CS16+CI16+BT16+BJ16+AO16+AE16+U16+K16) -> 22 | KB16: =SUM(JW16+JF16+IV16+IL16+IB16+HE16+GO16+GE16+FU16+ET16+EJ16+DZ16+DP16+CT16+CJ16+BU16+BK16+AP16+AF16+V16+L16) -> 0 | KC16: =SUM(JP16+IY16+IO16+IE16+HU16+GX16+GH16+FX16+FN16+EM16+EC16+DS16+DI16+CM16+CC16+BN16+BD16+AI16+Y16+O16+E16) -> 22 | KD16: =SUM(JQ16+IZ16+IP16+IF16+HV16+GY16+GI16+FY16+FO16+EN16+ED16+DT16+DJ16+CN16+CD16+BO16+BE16+AJ16+Z16+P16+F16) -> 0 | KE16: =SUM(JS16+JB16+IR16+IH16+HX16+HA16+GK16+GA16+FQ16+EP16+EF16+DV16+DL16+CP16+CF16+BQ16+BG16+AL16+AB16+R16+H16) -> 0 | KF16: =SUM(JT16+JC16+IS16+II16+HY16+HB16+GL16+GB16+FR16+EQ16+EG16+DW16+DM16+CQ16+CG16+BR16+BH16+AM16+AC16+S16+I16) -> 0 | KG16: =SUM(KA16:KB16) -> 22 | KH16: 450 | KI16: =KH16-KG16 -> 428 | KJ16: =KG16/KH16 -> 0.048888889 | KK16: =SUM(#REF!+44+60) -> #REF!
B17: Skilling to girls | C17: Nakivale | D17: 225 | AS17: =AO17+AE17+U17+K17 -> 0 | AT17: =AP17+AF17+V17+L17 -> 0 | AU17: =AK17+AA17+Q17+G17 -> 0 | AV17: =AN17 -> 0 | AX17: =SUM(AQ17+AG17+W17+M17) -> 0 | AY17: =AX17/AW17 -> #DIV/0! | AZ17: =SUM(E17+O17+Y17+AI17) -> 0 | BA17: =F17+P17+Z17+AJ17 -> 0 | BB17: =H17+R17+AB17+AL17 -> 0 | BC17: =I17+S17+AC17+AM17 -> 0 | BX17: =BN17+BD17+AI17+Y17+O17+E17 -> 0 | BY17: =BO17+BE17+AJ17+Z17+P17+F17 -> 0 | BZ17: =BQ17+BG17+AL17+AB17+R17+H17 -> 0 | CA17: =BR17+BH17+AM17+AC17+S17+I17 -> 0 | CB17: =BX17+BY17+BZ17+CA17 -> 0 | CW17: =SUM(CS17+CI17+BT17+BJ17) -> 0 | CX17: =SUM(CT17+CJ17+BU17+BK17) -> 0 | CY17: =SUM(CU17+CK17+BV17+BL17) -> 0 | CZ17: =SUM(CR17+CH17+BS17+BI17) -> 0 | DB17: =SUM(CW17:CX17) -> 0 | DD17: =BD17+BN17+CC17+CM17 -> 0 | DE17: =BE17+BO17+CD17+CN17 -> 0 | DF17: =BG17+BQ17+CF17+CP17 -> 0 | DG17: =BH17+BR17+CG17+CQ17 -> 0 | DH17: =DB17+AX17 -> 0 | DU17: =SUM(DS17:DT17) -> 0 | DX17: =SUM(DV17:DW17) -> 0 | DY17: =SUM(DS17+DV17) -> 0 | DZ17: =SUM(DT17+DW17) -> 0 | EA17: =SUM(DY17:DZ17) -> 0 | EW17: =SUM(ES17+EI17+DY17+DO17) -> 0 | EX17: =SUM(ET17+EJ17+DZ17+DP17) -> 0 | EY17: =SUM(EO17+EE17+DU17+DK17) -> 0 | EZ17: =SUM(ER17+EH17+DX17+DN17) -> 0 | FB17: =SUM(EW17:EX17) -> 0 | FD17: =DI17+DS17+EC17+EM17+CM17+CC17 -> 0 | FE17: =DJ17+DT17+ED17+EN17+CD17+CN17 -> 0 | FF17: =DL17+DV17+EF17+EP17+CP17+CF17 -> 0 | FG17: =DM17+DW17+EG17+EQ17+CG17+CQ17 -> 0 | FH17: =FD17+FF17 -> 0 | FI17: =FE17+FG17 -> 0 | FJ17: =FH17+FI17 -> 0 | FK17: =EW17+CW17+AS17 -> 0 | FL17: =EX17+CX17+AT17 -> 0 | FM17: =FK17+FL17 -> 0 | GD17: =FX17+GA17 -> 0 | GE17: =FY17+GB17 -> 0 | GF17: =GD17+GE17 -> 0 | GN17: =GH17+GK17 -> 0 | GO17: =GI17+GL17 -> 0 | GP17: =GN17+GO17 -> 0 | GR17: =GN17+GD17+FT17+ES17+EI17+DY17+DO17+CS17+CI17+BT17+BJ17 -> 0 | GS17: =GO17+GE17+FU17+ET17+EJ17+DZ17+DP17+CT17+CJ17+BU17+BK17 -> 0 | GT17: =GH17+FX17+FN17+EM17+EC17+DS17+DI17+CM17+CC17+BN17+BD17 -> 0 | GU17: =GI17+FY17+FO17+EN17+ED17+DT17+DJ17+CN17+CD17+BO17+BE17 -> 0 | GV17: =GK17+GA17+FQ17+EP17+EF17+DV17+DL17+CP17+CF17+BQ17+BG17 -> 0 | GW17: =GL17+GB17+FR17+EQ17+EG17+DW17+DM17+CQ17+CG17+BR17+BH17 -> 0 | GZ17: =GX17+GY17 -> 0 | HC17: =HA17+HB17 -> 0 | HD17: =GX17+HA17 -> 0 | HE17: =GY17+HB17 -> 0 | HF17: =HD17+HE17 -> 0 | HH17: =HD17+GN17+GD17+FT17 -> 0 | HI17: =GO17+GE17+FU17+HE17 -> 0 | HJ17: =GX17+GH17+FX17+FN17 -> 0 | HK17: =GI17+FY17+GY17+FO17 -> 0 | HL17: =GK17+GA17+FQ17+HA17 -> 0 | HM17: =GL17+HB17+GB17+FR17 -> 0 | HO17: =HF17+GP17+GF17+FV17 -> 0 | HQ17: =FN17+FX17+GH17+GX17 -> 0 | HR17: =FO17+FY17+GI17+GY17 -> 0 | HS17: =FQ17+GA17+GK17+HA17 -> 0 | HT17: =FR17+GB17+GL17+HB17 -> 0 | HW17: =HU17+HV17 -> 0 | HZ17: =HX17+HY17 -> 0 | IA17: =HU17+HX17 -> 0 | IB17: =HV17+HY17 -> 0 | IC17: =IA17+IB17 -> 0 | JN17: =JG17+IW17+IM17+IC17 -> 0 | JZ17: =JX17+JN17+HO17+FB17 -> 0 | KA17: =SUM(JV17+JE17+IU17+IK17+IA17+HD17+GN17+GD17+FT17+ES17+EI17+DY17+DO17+CS17+CI17+BT17+BJ17+AO17+AE17+U17+K17) -> 0 | KB17: =SUM(JW17+JF17+IV17+IL17+IB17+HE17+GO17+GE17+FU17+ET17+EJ17+DZ17+DP17+CT17+CJ17+BU17+BK17+AP17+AF17+V17+L17) -> 0 | KC17: =SUM(JP17+IY17+IO17+IE17+HU17+GX17+GH17+FX17+FN17+EM17+EC17+DS17+DI17+CM17+CC17+BN17+BD17+AI17+Y17+O17+E17) -> 0 | KD17: =SUM(JQ17+IZ17+IP17+IF17+HV17+GY17+GI17+FY17+FO17+EN17+ED17+DT17+DJ17+CN17+CD17+BO17+BE17+AJ17+Z17+P17+F17) -> 0 | KE17: =SUM(JS17+JB17+IR17+IH17+HX17+HA17+GK17+GA17+FQ17+EP17+EF17+DV17+DL17+CP17+CF17+BQ17+BG17+AL17+AB17+R17+H17) -> 0 | KF17: =SUM(JT17+JC17+IS17+II17+HY17+HB17+GL17+GB17+FR17+EQ17+EG17+DW17+DM17+CQ17+CG17+BR17+BH17+AM17+AC17+S17+I17) -> 0 | KG17: =SUM(KA17:KB17) -> 0 | KH17: 225 | KI17: =KH17-KG17 -> 225 | KJ17: =KG17/KH17 -> 0
B18: Total for Indicator | C18: Nakivale | AS18: =SUM(AS10:AS17) -> 23 | AT18: =SUM(AT10:AT17) -> 22 | AU18: =SUM(AU10:AU17) -> 33 | AV18: =SUM(AV10:AV17) -> 0 | AW18: =SUM(AW10:AW17) -> 0 | AX18: =SUM(AX10:AX17) -> 45 | AY18: =SUM(AY10:AY17) -> #DIV/0! | AZ18: =SUM(AZ10:AZ17) -> 16 | ... BC18: =SUM(BC10:BC17) -> 5 | CW18: =SUM(CW10:CW17) -> 49 | CX18: =SUM(CX10:CX17) -> 41 | CY18: =SUM(CY10:CY17) -> 90 | CZ18: =SUM(CZ10:CZ17) -> 10 | DA18: =SUM(DA10:DA17) -> 0 | DB18: =SUM(DB10:DB17) -> 90 | DC18: =SUM(DC10:DC17) -> #DIV/0! | DD18: =SUM(DD10:DD17) -> 42 | ... DG18: =SUM(DG10:DG17) -> 3 | DH18: =DH10+DH11+#REF!+DH12+DH14+DH15+#REF!+#REF!+DH17 -> #REF! | EW18: =SUM(EW10:EW17) -> 27 | EX18: =SUM(EX10:EX17) -> 0 | EY18: =SUM(EY10:EY17) -> 26 | EZ18: =SUM(EZ10:EZ17) -> 1 | FA18: =SUM(FA10:FA17) -> 0 | FB18: =SUM(FB10:FB17) -> 27 | FC18: =SUM(FC10:FC17) -> #DIV/0! | FD18: =SUM(FD10:FD17) -> 26 | ... FG18: =SUM(FG10:FG17) -> 0 | GZ18: =GX18+GY18 -> 0 | HC18: =HA18+HB18 -> 0 | HD18: =GX18+HA18 -> 0 | HE18: =GY18+HB18 -> 0 | HF18: =HD18+HE18 -> 0 | HH18: =SUM(HH10:HH17) -> 203 | HI18: =SUM(HI10:HI17) -> 7 | HJ18: =SUM(HJ10:HJ17) -> 203 | HK18: =SUM(HK10:HK17) -> 7 | HL18: =SUM(HL10:HL17) -> 0 | HM18: =SUM(HM10:HM17) -> 0 | HN18: =SUM(HN10:HN17) -> 0 | HO18: =SUM(HO10:HO17) -> 210 | ... HT18: =SUM(HT10:HT17) -> 0 | HU18: 0 | HV18: 0 | HW18: =HU18+HV18 -> 0 | HX18: 0 | HY18: 0 | HZ18: =HX18+HY18 -> 0 | IA18: =HU18+HX18 -> 0 | IB18: =HV18+HY18 -> 0 | IC18: =IA18+IB18 -> 0 | KG18: =KG10+KG11+#REF!+KG12+KG14+KG15+#REF!+#REF!+KG17 -> #REF!
A19: Indicator 3 Number of persons effectively referred to other specialised service or assistance providers | B19: GBV Referrals | C19: Nakivale | D19: 550 | O19: 12 | P19: 3 | Q19: =SUM(O19:P19) -> 15 | R19: 0 | S19: 0 | T19: =SUM(R19:S19) -> 0 | U19: =SUM(O19+R19) -> 12 | V19: =SUM(P19+S19) -> 3 | W19: =SUM(U19:V19) -> 15 | Y19: 12 | Z19: 1 | AA19: =SUM(Y19:Z19) -> 13 | AB19: 0 | AC19: 0 | AD19: =SUM(AB19:AC19) -> 0 | AE19: =SUM(Y19+AB19) -> 12 | AF19: =SUM(Z19+AC19) -> 1 | AG19: =SUM(AE19:AF19) -> 13 | AI19: 15 | AJ19: 0 | AK19: =SUM(AI19:AJ19) -> 15 | AL19: 0 | AM19: 0 | AN19: =SUM(AL19:AM19) -> 0 | AO19: =SUM(AI19+AL19) -> 15 | AP19: =SUM(AJ19+AM19) -> 0 | AQ19: =SUM(AO19:AP19) -> 15 | AS19: =AO19+AE19+U19+K19 -> 39 | AT19: =AP19+AF19+V19+L19 -> 4 | AU19: =AK19+AA19+Q19+G19 -> 43 | AV19: =AN19 -> 0 | AW19: 200 | AX19: =SUM(AQ19+AG19+W19+M19) -> 43 | AY19: =AX19/AW19 -> 0.215 | AZ19: =SUM(E19+O19+Y19+AI19) -> 39 | BA19: =F19+P19+Z19+AJ19 -> 4 | BB19: =H19+R19+AB19+AL19 -> 0 | BC19: =I19+S19+AC19+AM19 -> 0 | BD19: 8 | BE19: 0 | BF19: =SUM(BD19:BE19) -> 8 | BG19: 0 | BH19: 0 | BI19: =SUM(BG19:BH19) -> 0 | BJ19: =(BD19+BG19) -> 8 | BK19: =SUM(BE19+BH19) -> 0 | BL19: =SUM(BJ19:BK19) -> 8 | BN19: 20 | BO19: 0 | BP19: =SUM(BN19:BO19) -> 20 | BS19: =SUM(BQ19:BR19) -> 0 | BT19: =SUM(BN19+BQ19) -> 20 | BU19: =SUM(BO19+BR19) -> 0 | BV19: =SUM(BT19:BU19) -> 20 | BX19: =BN19+BD19+AI19+Y19+O19+E19 -> 67 | BY19: =BO19+BE19+AJ19+Z19+P19+F19 -> 4 | BZ19: =BQ19+BG19+AL19+AB19+R19+H19 -> 0 | CA19: =BR19+BH19+AM19+AC19+S19+I19 -> 0 | CB19: =BX19+BY19+BZ19+CA19 -> 71 | CC19: 20 | CD19: 0 | CE19: =SUM(CC19:CD19) -> 20 | CF19: 0 | CG19: 0 | CH19: =SUM(CF19:CG19) -> 0 | CI19: =SUM(CC19+CF19) -> 20 | CJ19: =SUM(CD19+CG19) -> 0 | CK19: =SUM(CI19:CJ19) -> 20 | CM19: 18 | CN19: 0 | CO19: =SUM(CM19:CN19) -> 18 | CP19: 0 | CQ19: 0 | CR19: =SUM(CP19:CQ19) -> 0 | CS19: 63 | CT19: =SUM(CN19+CQ19) -> 0 | CU19: =SUM(CS19:CT19) -> 63 | CW19: =SUM(CS19+CI19+BT19+BJ19) -> 111 | CX19: =SUM(CT19+CJ19+BU19+BK19) -> 0 | CY19: =SUM(CU19+CK19+BV19+BL19) -> 111 | CZ19: =SUM(CR19+CH19+BS19+BI19) -> 0 | DB19: =SUM(CW19:CX19) -> 111 | DC19: =DB19/DA19 -> #DIV/0! | DD19: =BD19+BN19+CC19+CM19 -> 66 | DE19: =BE19+BO19+CD19+CN19 -> 0 | DF19: =BG19+BQ19+CF19+CP19 -> 0 | DG19: =BH19+BR19+CG19+CQ19 -> 0 | DH19: =DB19+AX19 -> 154 | DI19: 33 | DJ19: 0 | DK19: =SUM(DI19:DJ19) -> 33 | DL19: 0 | DM19: 0 | DN19: =SUM(DL19:DM19) -> 0 | DO19: =DI19+DL19 -> 33 | DP19: =DJ19+DM19 -> 0 | DQ19: =SUM(DO19:DP19) -> 33 | DS19: 61 | DT19: 0 | DU19: =SUM(DS19:DT19) -> 61 | DV19: 0 | DW19: 0 | DX19: =SUM(DV19:DW19) -> 0 | DY19: =SUM(DS19+DV19) -> 61 | DZ19: =SUM(DT19+DW19) -> 0 | EA19: =SUM(DY19:DZ19) -> 61 | EC19: 18 | ED19: 0 | EE19: =SUM(EC19:ED19) -> 18 | EF19: 0 | EG19: 0 | EH19: =SUM(EF19:EG19) -> 0 | EI19: =EC19+EF19 -> 18 | EJ19: =ED19+EG19 -> 0 | EM19: 18 | EN19: 0 | EO19: =SUM(EM19:EN19) -> 18 | EP19: 0 | EQ19: 0 | ER19: =SUM(EP19:EQ19) -> 0 | ES19: =SUM(EM19+EP19) -> 18 | ET19: =SUM(EN19+EQ19) -> 0 | EU19: =SUM(ES19:ET19) -> 18 | EW19: =DS19+EC19+EM19+DI19 -> 130 | EX19: =SUM(ET19+EJ19+DZ19+DP19) -> 0 | EY19: =SUM(EO19+EE19+DU19+DK19) -> 130 | EZ19: =SUM(ER19+EH19+DX19+DN19) -> 0 | FB19: =SUM(EW19:EX19) -> 130 | FC19: =FB19/FA19 -> #DIV/0! | FD19: =DI19+DS19+EC19+EM19+CM19+CC19 -> 168 | FE19: =DJ19+DT19+ED19+EN19+CD19+CN19 -> 0 | FF19: =DL19+DV19+EF19+EP19+CP19+CF19 -> 0 | FG19: =DM19+DW19+EG19+EQ19+CG19+CQ19 -> 0 | FH19: =FD19+FF19 -> 168 | FI19: =FE19+FG19 -> 0 | FJ19: =FH19+FI19 -> 168 | FK19: =EW19+CW19+AS19 -> 280 | FL19: =EX19+CX19+AT19 -> 4 | FM19: =FK19+FL19 -> 284 | FN19: 70 | FO19: 0 | FP19: =SUM(FN19:FO19) -> 70 | FQ19: 0 | FR19: 0 | FS19: =SUM(FQ19:FR19) -> 0 | FT19: =SUM(FN19+FQ19) -> 70 | FU19: =SUM(FO19+FR19) -> 0 | FV19: =SUM(FT19:FU19) -> 70 | FX19: 227 | FY19: 0 | FZ19: =SUM(FX19:FY19) -> 227 | GA19: 0 | GB19: 0 | GC19: =SUM(GA19:GB19) -> 0 | GD19: =FX19+GA19 -> 227 | GE19: =FY19+GB19 -> 0 | GF19: =GD19+GE19 -> 227 | GH19: 90 | GI19: 0 | GJ19: =SUM(GH19:GI19) -> 90 | GK19: 0 | GL19: 0 | GM19: =SUM(GK19:GL19) -> 0 | GN19: =GH19+GK19 -> 90 | GO19: =GI19+GL19 -> 0 | GP19: =GN19+GO19 -> 90 | GR19: =GN19+GD19+FT19+ES19+EI19+DY19+DO19+CS19+CI19+BT19+BJ19 -> 628 | GS19: =GO19+GE19+FU19+ET19+EJ19+DZ19+DP19+CT19+CJ19+BU19+BK19 -> 0 | GT19: =GH19+FX19+FN19+EM19+EC19+DS19+DI19+CM19+CC19+BN19+BD19 -> 583 | GU19: =GI19+FY19+FO19+EN19+ED19+DT19+DJ19+CN19+CD19+BO19+BE19 -> 0 | GV19: =GK19+GA19+FQ19+EP19+EF19+DV19+DL19+CP19+CF19+BQ19+BG19 -> 0 | GW19: =GL19+GB19+FR19+EQ19+EG19+DW19+DM19+CQ19+CG19+BR19+BH19 -> 0 | GX19: 60 | GY19: 0 | GZ19: =GX19+GY19 -> 60 | HA19: 0 | HB19: 0 | HC19: =HA19+HB19 -> 0 | HD19: =GX19+HA19 -> 60 | HE19: =GY19+HB19 -> 0 | HF19: =HD19+HE19 -> 60 | HH19: =HD19+GN19+GD19+FT19 -> 447 | HI19: =GO19+GE19+FU19+HE19 -> 0 | HJ19: =GX19+GH19+FX19+FN19 -> 447 | HK19: =GI19+FY19+GY19+FO19 -> 0 | HL19: =GK19+GA19+FQ19+HA19 -> 0 | HM19: =GL19+HB19+GB19+FR19 -> 0 | HO19: =HF19+GP19+GF19+FV19 -> 447 | HP19: =HO19/HN19 -> #DIV/0! | HQ19: =FN19+FX19+GH19+GX19 -> 447 | HR19: =FO19+FY19+GI19+GY19 -> 0 | HS19: =FQ19+GA19+GK19+HA19 -> 0 | HT19: =FR19+GB19+GL19+HB19 -> 0 | HU19: 96 | HV19: 0 | HW19: =HU19+HV19 -> 96 | HX19: 0 | HY19: 0 | HZ19: =HX19+HY19 -> 0 | IA19: =HU19+HX19 -> 96 | IB19: =HV19+HY19 -> 0 | IC19: =IA19+IB19 -> 96 | JN19: =JG19+IW19+IM19+IC19 -> 96 | JO19: =JN19/JM19 -> #DIV/0! | JZ19: =JX19+JN19+HO19+FB19 -> 673 | KA19: =SUM(JV19+JE19+IU19+IK19+IA19+HD19+GN19+GD19+FT19+ES19+EI19+DY19+DO19+CS19+CI19+BT19+BJ19+AO19+AE19+U19+K19) -> 823 | KB19: =SUM(JW19+JF19+IV19+IL19+IB19+HE19+GO19+GE19+FU19+ET19+EJ19+DZ19+DP19+CT19+CJ19+BU19+BK19+AP19+AF19+V19+L19) -> 4 | KC19: =SUM(JP19+IY19+IO19+IE19+HU19+GX19+GH19+FX19+FN19+EM19+EC19+DS19+DI19+CM19+CC19+BN19+BD19+AI19+Y19+O19+E19) -> 778 | KD19: =SUM(JQ19+IZ19+IP19+IF19+HV19+GY19+GI19+FY19+FO19+EN19+ED19+DT19+DJ19+CN19+CD19+BO19+BE19+AJ19+Z19+P19+F19) -> 4 | KE19: =SUM(JS19+JB19+IR19+IH19+HX19+HA19+GK19+GA19+FQ19+EP19+EF19+DV19+DL19+CP19+CF19+BQ19+BG19+AL19+AB19+R19+H19) -> 0 | KF19: =SUM(JT19+JC19+IS19+II19+HY19+HB19+GL19+GB19+FR19+EQ19+EG19+DW19+DM19+CQ19+CG19+BR19+BH19+AM19+AC19+S19+I19) -> 0 | KG19: =SUM(KA19:KB19) -> 827 | KH19: 550 | KI19: =KH19-KG19 -> -277 | KJ19: =KG19/KH19 -> 1.5036364 | KK19: =KG19+KG20 -> 1113
B20: GBV Referrals | C20: Nyakabande | AS20: =AO20+AE20+U20+K20 -> 0 | AT20: =AP20+AF20+V20+L20 -> 0 | AU20: =AK20+AA20+Q20+G20 -> 0 | AV20: =AN20 -> 0 | AX20: =SUM(AQ20+AG20+W20+M20) -> 0 | AZ20: =SUM(E20+O20+Y20+AI20) -> 0 | BA20: =F20+P20+Z20+AJ20 -> 0 | BB20: =H20+R20+AB20+AL20 -> 0 | BC20: =I20+S20+AC20+AM20 -> 0 | BX20: =BN20+BD20+AI20+Y20+O20+E20 -> 0 | BY20: =BO20+BE20+AJ20+Z20+P20+F20 -> 0 | BZ20: =BQ20+BG20+AL20+AB20+R20+H20 -> 0 | CA20: =BR20+BH20+AM20+AC20+S20+I20 -> 0 | CB20: =BX20+BY20+BZ20+CA20 -> 0 | CM20: 20 | CN20: 0 | CO20: =SUM(CM20:CN20) -> 20 | CP20: 0 | CQ20: 0 | CR20: =SUM(CP20) -> 0 | CS20: =CM20+CP20 -> 20 | CT20: =CN20+CQ20 -> 0 | CU20: =SUM(CS20:CT20) -> 20 | CW20: =SUM(CS20+CI20+BT20+BJ20) -> 20 | CX20: =SUM(CT20+CJ20+BU20+BK20) -> 0 | CY20: =SUM(CU20+CK20+BV20+BL20) -> 20 | CZ20: =SUM(CR20+CH20+BS20+BI20) -> 0 | DB20: =CU20 -> 20 | DD20: =BD20+BN20+CC20+CM20 -> 20 | DE20: =BE20+BO20+CD20+CN20 -> 0 | DF20: =BG20+BQ20+CF20+CP20 -> 0 | DG20: =BH20+BR20+CG20+CQ20 -> 0 | DH20: =DB20+AX20 -> 20 | DI20: 63 | DJ20: 0 | DK20: =SUM(DI20:DJ20) -> 63 | DL20: 0 | DM20: 0 | DN20: =SUM(DL20:DM20) -> 0 | DO20: =DI20+DL20 -> 63 | DP20: =DJ20+DM20 -> 0 | DQ20: =SUM(DO20:DP20) -> 63 | DS20: 44 | DT20: 0 | DU20: =SUM(DS20:DT20) -> 44 | DV20: 0 | DW20: 0 | DX20: =SUM(DV20:DW20) -> 0 | DY20: =SUM(DS20+DV20) -> 44 | DZ20: =SUM(DT20+DW20) -> 0 | EA20: =SUM(DY20:DZ20) -> 44 | EC20: 72 | ED20: 0 | EE20: =SUM(EC20:ED20) -> 72 | EF20: 0 | EG20: 0 | EH20: =SUM(EF20:EG20) -> 0 | EI20: =EC20+EF20 -> 72 | EJ20: =ED20+EG20 -> 0 | EM20: 34 | EN20: 0 | EO20: =SUM(EM20:EN20) -> 34 | EP20: 0 | EQ20: 0 | ER20: =SUM(EP20:EQ20) -> 0 | ES20: =SUM(EM20+EP20) -> 34 | ET20: =SUM(EN20+EQ20) -> 0 | EU20: =SUM(ES20:ET20) -> 34 | EW20: =EM20+EC20+DS20+DI20 -> 213 | EX20: =SUM(ET20+EJ20+DZ20+DP20) -> 0 | EY20: =SUM(EO20+EE20+DU20+DK20) -> 213 | EZ20: =SUM(ER20+EH20+DX20+DN20) -> 0 | FB20: =SUM(EW20:EX20) -> 213 | FD20: =DI20+DS20+EC20+EM20+CM20+CC20 -> 233 | FE20: =DJ20+DT20+ED20+EN20+CD20+CN20 -> 0 | FF20: =DL20+DV20+EF20+EP20+CP20+CF20 -> 0 | FG20: =DM20+DW20+EG20+EQ20+CG20+CQ20 -> 0 | FH20: =FD20+FF20 -> 233 | FI20: =FE20+FG20 -> 0 | FJ20: =FH20+FI20 -> 233 | FK20: =EW20+CW20+AS20 -> 233 | FL20: =EX20+CX20+AT20 -> 0 | FM20: =FK20+FL20 -> 233 | FN20: 27 | FO20: 0 | FP20: =SUM(FN20:FO20) -> 27 | FQ20: 0 | FR20: 0 | FS20: =SUM(FQ20:FR20) -> 0 | FT20: =SUM(FN20+FQ20) -> 27 | FU20: =SUM(FO20+FR20) -> 0 | FV20: =SUM(FT20:FU20) -> 27 | FX20: 14 | FY20: 0 | FZ20: =SUM(FX20:FY20) -> 14 | GA20: 0 | GB20: 0 | GC20: =SUM(GA20:GB20) -> 0 | GD20: =FX20+GA20 -> 14 | GE20: =FY20+GB20 -> 0 | GF20: =GD20+GE20 -> 14 | GH20: 12 | GI20: 0 | GJ20: =SUM(GH20:GI20) -> 12 | GK20: 0 | GL20: 0 | GM20: =SUM(GK20:GL20) -> 0 | GN20: =GH20+GK20 -> 12 | GO20: =GI20+GL20 -> 0 | GP20: =GN20+GO20 -> 12 | GR20: =GN20+GD20+FT20+ES20+EI20+DY20+DO20+CS20+CI20+BT20+BJ20 -> 286 | GS20: =GO20+GE20+FU20+ET20+EJ20+DZ20+DP20+CT20+CJ20+BU20+BK20 -> 0 | GT20: =GH20+FX20+FN20+EM20+EC20+DS20+DI20+CM20+CC20+BN20+BD20 -> 286 | GU20: =GI20+FY20+FO20+EN20+ED20+DT20+DJ20+CN20+CD20+BO20+BE20 -> 0 | GV20: =GK20+GA20+FQ20+EP20+EF20+DV20+DL20+CP20+CF20+BQ20+BG20 -> 0 | GW20: =GL20+GB20+FR20+EQ20+EG20+DW20+DM20+CQ20+CG20+BR20+BH20 -> 0 | GZ20: =GX20+GY20 -> 0 | HC20: =HA20+HB20 -> 0 | HD20: =GX20+HA20 -> 0 | HE20: =GY20+HB20 -> 0 | HF20: =HD20+HE20 -> 0 | HH20: =HD20+GN20+GD20+FT20 -> 53 | HI20: =GO20+GE20+FU20+HE20 -> 0 | HJ20: =GX20+GH20+FX20+FN20 -> 53 | HK20: =GI20+FY20+GY20+FO20 -> 0 | HL20: =GK20+GA20+FQ20+HA20 -> 0 | HM20: =GL20+HB20+GB20+FR20 -> 0 | HO20: =HF20+GP20+GF20+FV20 -> 53 | HQ20: =FN20+FX20+GH20+GX20 -> 53 | HR20: =FO20+FY20+GI20+GY20 -> 0 | HS20: =FQ20+GA20+GK20+HA20 -> 0 | HT20: =FR20+GB20+GL20+HB20 -> 0 | HW20: =HU20+HV20 -> 0 | HZ20: =HX20+HY20 -> 0 | IA20: =HU20+HX20 -> 0 | IB20: =HV20+HY20 -> 0 | IC20: =IA20+IB20 -> 0 | JN20: =JG20+IW20+IM20+IC20 -> 0 | JZ20: =JX20+JN20+HO20+FB20 -> 266 | KA20: =SUM(JV20+JE20+IU20+IK20+IA20+HD20+GN20+GD20+FT20+ES20+EI20+DY20+DO20+CS20+CI20+BT20+BJ20+AO20+AE20+U20+K20) -> 286 | KB20: =SUM(JW20+JF20+IV20+IL20+IB20+HE20+GO20+GE20+FU20+ET20+EJ20+DZ20+DP20+CT20+CJ20+BU20+BK20+AP20+AF20+V20+L20) -> 0 | KC20: =SUM(JP20+IY20+IO20+IE20+HU20+GX20+GH20+FX20+FN20+EM20+EC20+DS20+DI20+CM20+CC20+BN20+BD20+AI20+Y20+O20+E20) -> 286 | KD20: =SUM(JQ20+IZ20+IP20+IF20+HV20+GY20+GI20+FY20+FO20+EN20+ED20+DT20+DJ20+CN20+CD20+BO20+BE20+AJ20+Z20+P20+F20) -> 0 | KE20: =SUM(JS20+JB20+IR20+IH20+HX20+HA20+GK20+GA20+FQ20+EP20+EF20+DV20+DL20+CP20+CF20+BQ20+BG20+AL20+AB20+R20+H20) -> 0 | KF20: =SUM(JT20+JC20+IS20+II20+HY20+HB20+GL20+GB20+FR20+EQ20+EG20+DW20+DM20+CQ20+CG20+BR20+BH20+AM20+AC20+S20+I20) -> 0 | KG20: =SUM(KA20:KB20) -> 286 | KK20: =KA19+KA20 -> 1109
AZ21: =AZ19+AZ20 -> 39 | BA21: =BA19+BA20 -> 4 | BB21: =BB19+BB20 -> 0 | BC21: =BC19+BC20 -> 0 | BX21: =BN21+BD21+AI21+Y21+O21+E21 -> 0 | BY21: =BO21+BE21+AJ21+Z21+P21+F21 -> 0 | BZ21: =BQ21+BG21+AL21+AB21+R21+H21 -> 0 | CA21: =BR21+BH21+AM21+AC21+S21+I21 -> 0 | CB21: =BX21+BY21+BZ21+CA21 -> 0 | DH21: =DB21+AX21 -> 0 | FD21: =DI21+DS21+EC21+EM21+CM21+CC21 -> 0 | FE21: =DJ21+DT21+ED21+EN21+CD21+CN21 -> 0 | FF21: =DL21+DV21+EF21+EP21+CP21+CF21 -> 0 | FG21: =DM21+DW21+EG21+EQ21+CG21+CQ21 -> 0 | FH21: =FD21+FF21 -> 0 | FI21: =FE21+FG21 -> 0 | FJ21: =FH21+FI21 -> 0 | FK21: =EW21+CW21+AS21 -> 0 | FL21: =EX21+CX21+AT21 -> 0 | FM21: =FK21+FL21 -> 0 | GD21: =FX21+GA21 -> 0 | GE21: =FY21+GB21 -> 0 | GF21: =GD21+GE21 -> 0 | GN21: =GH21+GK21 -> 0 | GO21: =GI21+GL21 -> 0 | GP21: =GN21+GO21 -> 0 | GR21: =GN21+GD21+FT21+ES21+EI21+DY21+DO21+CS21+CI21+BT21+BJ21 -> 0 | GS21: =GO21+GE21+FU21+ET21+EJ21+DZ21+DP21+CT21+CJ21+BU21+BK21 -> 0 | GT21: =GH21+FX21+FN21+EM21+EC21+DS21+DI21+CM21+CC21+BN21+BD21 -> 0 | GU21: =GI21+FY21+FO21+EN21+ED21+DT21+DJ21+CN21+CD21+BO21+BE21 -> 0 | GV21: =GK21+GA21+FQ21+EP21+EF21+DV21+DL21+CP21+CF21+BQ21+BG21 -> 0 | GW21: =GL21+GB21+FR21+EQ21+EG21+DW21+DM21+CQ21+CG21+BR21+BH21 -> 0 | GZ21: =GX21+GY21 -> 0 | HC21: =HA21+HB21 -> 0 | HD21: =GX21+HA21 -> 0 | HE21: =GY21+HB21 -> 0 | HF21: =HD21+HE21 -> 0 | HH21: =HH19+HH20 -> 500 | HI21: =GO21+GE21+FU21+HE21 -> 0 | HJ21: =GX21+GH21+FX21+FN21 -> 0 | HK21: =GI21+FY21+GY21+FO21 -> 0 | HL21: =GK21+GA21+FQ21+HA21 -> 0 | HM21: =GL21+HB21+GB21+FR21 -> 0 | HO21: =HF21+GP21+GF21+FV21 -> 0 | HW21: =HU21+HV21 -> 0 | HZ21: =HX21+HY21 -> 0 | IA21: =HU21+HX21 -> 0 | IB21: =HV21+HY21 -> 0 | IC21: =IA21+IB21 -> 0 | JN21: =JG21+IW21+IM21+IC21 -> 0 | JZ21: =JX21+JN21+HO21+FB21 -> 0
A22: Indicator 4 Number of persons with increased/appropriate information on relevant rights and/or entitlements | B22: Sensitization dialogues & Awareness Sessions | C22: Nakivale | O22: 93 | P22: 40 | Q22: =SUM(O22:P22) -> 133 | R22: 41 | S22: 0 | T22: =SUM(R22:S22) -> 41 | U22: =SUM(O22+R22) -> 134 | V22: =SUM(P22+S22) -> 40 | W22: =SUM(U22:V22) -> 174 | X22: 2 | Y22: 69 | Z22: 0 | AA22: =SUM(Y22:Z22) -> 69 | AB22: 0 | AC22: 0 | AD22: =SUM(AB22:AC22) -> 0 | AE22: =SUM(Y22+AB22) -> 69 | AF22: =SUM(Z22+AC22) -> 0 | AG22: =SUM(AE22:AF22) -> 69 | AI22: 26 | AJ22: 21 | AK22: =SUM(AI22:AJ22) -> 47 | AL22: 38 | AM22: 9 | AN22: =SUM(AL22:AM22) -> 47 | AO22: =SUM(AI22+AL22) -> 64 | AP22: =SUM(AJ22+AM22) -> 30 | AQ22: =SUM(AO22:AP22) -> 94 | AS22: =AO22+AE22+U22+K22 -> 267 | AT22: =AP22+AF22+V22+L22 -> 70 | AU22: =AK22+AA22+Q22+G22 -> 249 | AV22: =AN22 -> 47 | AX22: =SUM(AQ22+AG22+W22+M22) -> 337 | AY22: =AX22/AW22 -> #DIV/0! | AZ22: =SUM(E22+O22+Y22+AI22) -> 188 | BA22: =F22+P22+Z22+AJ22 -> 61 | BB22: =H22+R22+AB22+AL22 -> 79 | BC22: =I22+S22+AC22+AM22 -> 9 | BE22: 0 | BF22: =SUM(BD22:BE22) -> 0 | BH22: 0 | BI22: =SUM(BG22:BH22) -> 0 | BJ22: =SUM(BG22+BD22) -> 0 | BK22: =SUM(BE22+BH22) -> 0 | BL22: =SUM(BJ22:BK22) -> 0 | BN22: 180 | BO22: 0 | BP22: =SUM(BN22:BO22) -> 180 | BQ22: 0 | BR22: 0 | BS22: 0 | BT22: =SUM(BN22+BQ22) -> 180 | BU22: =SUM(BO22+BR22) -> 0 | BV22: =SUM(BT22:BU22) -> 180 | BX22: =BN22+BD22+AI22+Y22+O22+E22 -> 368 | BY22: =BO22+BE22+AJ22+Z22+P22+F22 -> 61 | BZ22: =BQ22+BG22+AL22+AB22+R22+H22 -> 79 | CA22: =BR22+BH22+AM22+AC22+S22+I22 -> 9 | CB22: =BX22+BY22+BZ22+CA22 -> 517 | CC22: 0 | CD22: 0 | CE22: =SUM(CC22:CD22) -> 0 | CF22: 0 | CG22: 0 | CH22: =SUM(CF22:CG22) -> 0 | CI22: =SUM(CC22+CF22) -> 0 | CJ22: =SUM(CD22+CG22) -> 0 | CK22: =SUM(CI22:CJ22) -> 0 | CM22: 348 | CN22: 321 | CO22: =SUM(CM22:CN22) -> 669 | CP22: 0 | CQ22: 0 | CR22: =SUM(CP22:CQ22) -> 0 | CS22: =SUM(CM22+CP22) -> 348 | CT22: =SUM(CN22+CQ22) -> 321 | CU22: =SUM(CS22:CT22) -> 669 | CW22: =SUM(CS22+CI22+BT22+BJ22) -> 528 | CX22: =SUM(CT22+CJ22+BU22+BK22) -> 321 | CY22: =SUM(CU22+CK22+BV22+BL22) -> 849 | CZ22: =SUM(CR22+CH22+BS22+BI22) -> 0 | DB22: =SUM(CW22:CX22) -> 849 | DC22: =DB22/DA22 -> #DIV/0! | DD22: =BD22+BN22+CC22+CM22 -> 528 | DE22: =BE22+BO22+CD22+CN22 -> 321 | DF22: =BG22+BQ22+CF22+CP22 -> 0 | DG22: =BH22+BR22+CG22+CQ22 -> 0 | DH22: =DB22+AX22 -> 1186 | DI22: 1080 | DJ22: 1111 | DK22: =SUM(DI22:DJ22) -> 2191 | DN22: =SUM(DL22:DM22) -> 0 | DO22: =SUM(DI22+DL22) -> 1080 | DP22: =SUM(DJ22+DM22) -> 1111 | DQ22: =SUM(DO22:DP22) -> 2191 | DU22: =SUM(DS22:DT22) -> 0 | DX22: =SUM(DV22:DW22) -> 0 | DY22: =SUM(DS22+DV22) -> 0 | DZ22: =SUM(DT22+DW22) -> 0 | EA22: =SUM(DY22:DZ22) -> 0 | EC22: 60 | ED22: 0 | EE22: =SUM(EC22:ED22) -> 60 | EF22: 0 | EG22: 0 | EH22: =SUM(EF22:EG22) -> 0 | EI22: =SUM(EC22+EF22) -> 60 | EJ22: =SUM(ED22+EG22) -> 0 | EK22: =SUM(EI22:EJ22) -> 60 | EO22: =SUM(EM22:EN22) -> 0 | ER22: =SUM(EP22:EQ22) -> 0 | ES22: =SUM(EM22+EP22) -> 0 | ET22: =SUM(EN22+EQ22) -> 0 | EU22: =SUM(ES22:ET22) -> 0 | EW22: =SUM(ES22+EI22+DY22+DO22) -> 1140 | EX22: =SUM(ET22+EJ22+DZ22+DP22) -> 1111 | EY22: =SUM(EO22+EE22+DU22+DK22) -> 2251 | EZ22: =SUM(ER22+EH22+DX22+DN22) -> 0 | FB22: =SUM(EW22:EX22) -> 2251 | FC22: =FB22/FA22 -> #DIV/0! | FD22: =DI22+DS22+EC22+EM22+CM22+CC22 -> 1488 | FE22: =DJ22+DT22+ED22+EN22+CD22+CN22 -> 1432 | FF22: =DL22+DV22+EF22+EP22+CP22+CF22 -> 0 | FG22: =DM22+DW22+EG22+EQ22+CG22+CQ22 -> 0 | FH22: =FD22+FF22 -> 1488 | FI22: =FE22+FG22 -> 1432 | FJ22: =FH22+FI22 -> 2920 | FK22: =EW22+CW22+AS22 -> 1935 | FL22: =EX22+CX22+AT22 -> 1502 | FM22: =FK22+FL22 -> 3437 | FP22: =SUM(FN22:FO22) -> 0 | FS22: =SUM(FQ22:FR22) -> 0 | FT22: =SUM(FN22+FQ22) -> 0 | FU22: =SUM(FO22+FR22) -> 0 | FV22: =SUM(FT22:FU22) -> 0 | FZ22: =SUM(FX22:FY22) -> 0 | GC22: =SUM(GA22:GB22) -> 0 | GD22: =FX22+GA22 -> 0 | GE22: =FY22+GB22 -> 0 | GF22: =GD22+GE22 -> 0 | GH22: 383 | GI22: 0 | GJ22: =SUM(GH22:GI22) -> 383 | GK22: 140 | GL22: 0 | GM22: =SUM(GK22:GL22) -> 140 | GN22: =GH22+GK22 -> 523 | GO22: =GI22+GL22 -> 0 | GP22: =GN22+GO22 -> 523 | GR22: =GN22+GD22+FT22+ES22+EI22+DY22+DO22+CS22+CI22+BT22+BJ22 -> 2191 | GS22: =GO22+GE22+FU22+ET22+EJ22+DZ22+DP22+CT22+CJ22+BU22+BK22 -> 1432 | GT22: =GH22+FX22+FN22+EM22+EC22+DS22+DI22+CM22+CC22+BN22+BD22 -> 2051 | GU22: =GI22+FY22+FO22+EN22+ED22+DT22+DJ22+CN22+CD22+BO22+BE22 -> 1432 | GV22: =GK22+GA22+FQ22+EP22+EF22+DV22+DL22+CP22+CF22+BQ22+BG22 -> 140 | GW22: =GL22+GB22+FR22+EQ22+EG22+DW22+DM22+CQ22+CG22+BR22+BH22 -> 0 | GZ22: =GX22+GY22 -> 0 | HC22: =HA22+HB22 -> 0 | HD22: =GX22+HA22 -> 0 | HE22: =GY22+HB22 -> 0 | HF22: =HD22+HE22 -> 0 | HH22: =HD22+GN22+GD22+FT22 -> 523 | HI22: =GO22+GE22+FU22+HE22 -> 0 | HJ22: =GX22+GH22+FX22+FN22 -> 383 | HK22: =GI22+FY22+GY22+FO22 -> 0 | HL22: =GK22+GA22+FQ22+HA22 -> 140 | HM22: =GL22+HB22+GB22+FR22 -> 0 | HO22: =HF22+GP22+GF22+FV22 -> 523 | HP22: =HO22/HN22 -> #DIV/0! | HQ22: =FN22+FX22+GH22+GX22 -> 383 | HR22: =FO22+FY22+GI22+GY22 -> 0 | HS22: =FQ22+GA22+GK22+HA22 -> 140 | HT22: =FR22+GB22+GL22+HB22 -> 0 | HW22: =HU22+HV22 -> 0 | HZ22: =HX22+HY22 -> 0 | IA22: =HU22+HX22 -> 0 | IB22: =HV22+HY22 -> 0 | IC22: =IA22+IB22 -> 0 | IG22: =SUM(IE22:IF22) -> 0 | IJ22: =SUM(IH22:II22) -> 0 | IK22: =SUM(IE22+IH22) -> 0 | IL22: =SUM(IF22+II22) -> 0 | IM22: =SUM(IK22:IL22) -> 0 | IQ22: =SUM(IO22:IP22) -> 0 | IT22: =SUM(IR22:IS22) -> 0 | IU22: =SUM(IO22+IR22) -> 0 | IV22: =SUM(IP22+IS22) -> 0 | IW22: =SUM(IU22:IV22) -> 0 | JD22: =SUM(JB22:JC22) -> 0 | JE22: =SUM(IY22+JB22) -> 0 | JF22: =SUM(IZ22+JC22) -> 0 | JG22: =SUM(JE22:JF22) -> 0 | JN22: =JG22+IW22+IM22+IC22 -> 0 | JO22: =JN22/JM22 -> #DIV/0! | JQ22: 0 | JR22: =SUM(JP22:JQ22) -> 0 | JT22: 0 | JU22: =SUM(JS22:JT22) -> 0 | JV22: =SUM(JP22+JS22) -> 0 | JW22: =SUM(JQ22+JT22) -> 0 | JX22: =SUM(JV22:JW22) -> 0 | JZ22: =JX22+JN22+HO22+FB22 -> 2774 | KA22: =SUM(JV22+JE22+IU22+IK22+IA22+HD22+GN22+GD22+FT22+ES22+EI22+DY22+DO22+CS22+CI22+BT22+BJ22+AO22+AE22+U22+K22) -> 2458 | KB22: =SUM(JW22+JF22+IV22+IL22+IB22+HE22+GO22+GE22+FU22+ET22+EJ22+DZ22+DP22+CT22+CJ22+BU22+BK22+AP22+AF22+V22+L22) -> 1502 | KC22: =SUM(JP22+IY22+IO22+IE22+HU22+GX22+GH22+FX22+FN22+EM22+EC22+DS22+DI22+CM22+CC22+BN22+BD22+AI22+Y22+O22+E22) -> 2239 | KD22: =SUM(JQ22+IZ22+IP22+IF22+HV22+GY22+GI22+FY22+FO22+EN22+ED22+DT22+DJ22+CN22+CD22+BO22+BE22+AJ22+Z22+P22+F22) -> 1493 | KE22: =SUM(JS22+JB22+IR22+IH22+HX22+HA22+GK22+GA22+FQ22+EP22+EF22+DV22+DL22+CP22+CF22+BQ22+BG22+AL22+AB22+R22+H22) -> 219 | KF22: =SUM(JT22+JC22+IS22+II22+HY22+HB22+GL22+GB22+FR22+EQ22+EG22+DW22+DM22+CQ22+CG22+BR22+BH22+AM22+AC22+S22+I22) -> 9 | KG22: =SUM(KA22:KB22) -> 3960 | KJ22: =KG22/KH22 -> #DIV/0! | KK22: =KG22+KG23 -> 13037
B23: Sensitization dialogues & Awareness Sessions | C23: Nyakabande | AZ23: =SUM(E23+O23+Y23+AI23) -> 0 | BA23: =F23+P23+Z23+AJ23 -> 0 | BB23: =H23+R23+AB23+AL23 -> 0 | BC23: =I23+S23+AC23+AM23 -> 0 | BX23: =BN23+BD23+AI23+Y23+O23+E23 -> 0 | BY23: =BO23+BE23+AJ23+Z23+P23+F23 -> 0 | BZ23: =BQ23+BG23+AL23+AB23+R23+H23 -> 0 | CA23: =BR23+BH23+AM23+AC23+S23+I23 -> 0 | CB23: =BX23+BY23+BZ23+CA23 -> 0 | CC23: 342 | CD23: 322 | CE23: =SUM(CC23:CD23) -> 664 | CF23: 0 | CG23: 0 | CH23: =SUM(CF23:CG23) -> 0 | CI23: =SUM(CC23+CF23) -> 342 | CJ23: =SUM(CD23+CG23) -> 322 | CK23: =SUM(CI23:CJ23) -> 664 | CM23: 626 | CN23: 501 | CO23: =CM23+CN23 -> 1127 | CP23: 0 | CQ23: 0 | CR23: =CP23+CQ23 -> 0 | CS23: =SUM(CM23+CP23) -> 626 | CT23: =SUM(CN23+CQ23) -> 501 | CU23: =SUM(CS23:CT23) -> 1127 | CW23: =SUM(CS23+CI23+BT23+BJ23) -> 968 | CX23: =SUM(CT23+CJ23+BU23+BK23) -> 823 | CY23: =SUM(CU23+CK23+BV23+BL23) -> 1791 | CZ23: =SUM(CR23+CH23+BS23+BI23) -> 0 | DB23: =SUM(CW23:CX23) -> 1791 | DD23: =BD23+BN23+CC23+CM23 -> 968 | DE23: =BE23+BO23+CD23+CN23 -> 823 | DF23: =BG23+BQ23+CF23+CP23 -> 0 | DG23: =BH23+BR23+CG23+CQ23 -> 0 | DH23: =DB23+AX23 -> 1791 | DS23: 0 | DT23: 0 | DU23: =SUM(DS23:DT23) -> 0 | DV23: 0 | DW23: 0 | DX23: =SUM(DV23:DW23) -> 0 | DY23: =DS23+DV23 -> 0 | DZ23: =DT23+DW23 -> 0 | EA23: =SUM(DY23:DZ23) -> 0 | EC23: 1534 | ED23: 1733 | EE23: =SUM(EC23:ED23) -> 3267 | EF23: 0 | EG23: 0 | EH23: =SUM(EF23:EG23) -> 0 | EI23: =SUM(EC23+EF23) -> 1534 | EJ23: =SUM(ED23+EG23) -> 1733 | EK23: =SUM(EI23:EJ23) -> 3267 | EM23: 0 | EN23: 0 | EO23: =SUM(EM23:EN23) -> 0 | EP23: 0 | EQ23: 0 | ER23: =SUM(EP23:EQ23) -> 0 | ES23: =SUM(EM23+EP23) -> 0 | ET23: =SUM(EN23+EQ23) -> 0 | EU23: =SUM(ES23:ET23) -> 0 | EW23: =SUM(ES23+EI23+DY23+DO23) -> 1534 | EX23: =SUM(ET23+EJ23+DZ23+DP23) -> 1733 | EY23: =SUM(EO23+EE23+DU23+DK23) -> 3267 | EZ23: =SUM(ER23+EH23+DX23+DN23) -> 0 | FB23: =SUM(EW23:EX23) -> 3267 | FC23: =FB23/FA23 -> #DIV/0! | FD23: =DI23+DS23+EC23+EM23+CM23+CC23 -> 2502 | FE23: =DJ23+DT23+ED23+EN23+CD23+CN23 -> 2556 | FF23: =DL23+DV23+EF23+EP23+CP23+CF23 -> 0 | FG23: =DM23+DW23+EG23+EQ23+CG23+CQ23 -> 0 | FH23: =FD23+FF23 -> 2502 | FI23: =FE23+FG23 -> 2556 | FJ23: =FH23+FI23 -> 5058 | FK23: =EW23+CW23+AS23 -> 2502 | FL23: =EX23+CX23+AT23 -> 2556 | FM23: =FK23+FL23 -> 5058 | FN23: 450 | FO23: 366 | FP23: =SUM(FN23:FO23) -> 816 | FQ23: 0 | FR23: 0 | FS23: =SUM(FQ23:FR23) -> 0 | FT23: =SUM(FN23+FQ23) -> 450 | FU23: =SUM(FO23+FR23) -> 366 | FV23: =SUM(FT23:FU23) -> 816 | FX23: 522 | FY23: 597 | FZ23: =SUM(FX23:FY23) -> 1119 | GA23: 0 | GB23: 0 | GC23: =SUM(GA23:GB23) -> 0 | GD23: =FX23+GA23 -> 522 | GE23: =FY23+GB23 -> 597 | GF23: =GD23+GE23 -> 1119 | GH23: 676 | GI23: 597 | GJ23: =SUM(GH23:GI23) -> 1273 | GK23: 0 | GL23: 0 | GM23: =SUM(GK23:GL23) -> 0 | GN23: =GH23+GK23 -> 676 | GO23: =GI23+GL23 -> 597 | GP23: =GN23+GO23 -> 1273 | GR23: =GN23+GD23+FT23+ES23+EI23+DY23+DO23+CS23+CI23+BT23+BJ23 -> 4150 | GS23: =GO23+GE23+FU23+ET23+EJ23+DZ23+DP23+CT23+CJ23+BU23+BK23 -> 4116 | GT23: =GH23+FX23+FN23+EM23+EC23+DS23+DI23+CM23+CC23+BN23+BD23 -> 4150 | GU23: =GI23+FY23+FO23+EN23+ED23+DT23+DJ23+CN23+CD23+BO23+BE23 -> 4116 | GV23: =GK23+GA23+FQ23+EP23+EF23+DV23+DL23+CP23+CF23+BQ23+BG23 -> 0 | GW23: =GL23+GB23+FR23+EQ23+EG23+DW23+DM23+CQ23+CG23+BR23+BH23 -> 0 | GZ23: =GX23+GY23 -> 0 | HC23: =HA23+HB23 -> 0 | HD23: =GX23+HA23 -> 0 | HE23: =GY23+HB23 -> 0 | HF23: =HD23+HE23 -> 0 | HH23: =HD23+GN23+GD23+FT23 -> 1648 | HI23: =GO23+GE23+FU23+HE23 -> 1560 | HJ23: =GX23+GH23+FX23+FN23 -> 1648 | HK23: =GI23+FY23+GY23+FO23 -> 1560 | HL23: =GK23+GA23+FQ23+HA23 -> 0 | HM23: =GL23+HB23+GB23+FR23 -> 0 | HO23: =HF23+GP23+GF23+FV23 -> 3208 | HQ23: =FN23+FX23+GH23+GX23 -> 1648 | HR23: =FO23+FY23+GI23+GY23 -> 1560 | HS23: =FQ23+GA23+GK23+HA23 -> 0 | HT23: =FR23+GB23+GL23+HB23 -> 0 | HU23: 352 | HV23: 459 | HW23: =HU23+HV23 -> 811 | HX23: 0 | HY23: 0 | HZ23: =HX23+HY23 -> 0 | IA23: =HU23+HX23 -> 352 | IB23: =HV23+HY23 -> 459 | IC23: =IA23+IB23 -> 811 | JN23: =JG23+IW23+IM23+IC23 -> 811 | JZ23: =JX23+JN23+HO23+FB23 -> 7286 | KA23: =SUM(JV23+JE23+IU23+IK23+IA23+HD23+GN23+GD23+FT23+ES23+EI23+DY23+DO23+CS23+CI23+BT23+BJ23+AO23+AE23+U23+K23) -> 4502 | KB23: =SUM(JW23+JF23+IV23+IL23+IB23+HE23+GO23+GE23+FU23+ET23+EJ23+DZ23+DP23+CT23+CJ23+BU23+BK23+AP23+AF23+V23+L23) -> 4575 | KC23: =SUM(JP23+IY23+IO23+IE23+HU23+GX23+GH23+FX23+FN23+EM23+EC23+DS23+DI23+CM23+CC23+BN23+BD23+AI23+Y23+O23+E23) -> 4502 | KD23: =SUM(JQ23+IZ23+IP23+IF23+HV23+GY23+GI23+FY23+FO23+EN23+ED23+DT23+DJ23+CN23+CD23+BO23+BE23+AJ23+Z23+P23+F23) -> 4575 | KE23: =SUM(JS23+JB23+IR23+IH23+HX23+HA23+GK23+GA23+FQ23+EP23+EF23+DV23+DL23+CP23+CF23+BQ23+BG23+AL23+AB23+R23+H23) -> 0 | KF23: =SUM(JT23+JC23+IS23+II23+HY23+HB23+GL23+GB23+FR23+EQ23+EG23+DW23+DM23+CQ23+CG23+BR23+BH23+AM23+AC23+S23+I23) -> 0 | KG23: =SUM(KA23:KB23) -> 9077 | KJ23: =KG23/KH23 -> #DIV/0! | KK23: =KA22+KA23 -> 6960 | KL23: =KB22+KB23 -> 6077
B24: Sensitization dialogues & Awareness Sessions | C24: Matanda | AZ24: =SUM(E24+O24+Y24+AI24) -> 0 | BA24: =F24+P24+Z24+AJ24 -> 0 | BB24: =H24+R24+AB24+AL24 -> 0 | BC24: =I24+S24+AC24+AM24 -> 0 | BX24: =BN24+BD24+AI24+Y24+O24+E24 -> 0 | BY24: =BO24+BE24+AJ24+Z24+P24+F24 -> 0 | BZ24: =BQ24+BG24+AL24+AB24+R24+H24 -> 0 | CA24: =BR24+BH24+AM24+AC24+S24+I24 -> 0 | CB24: =BX24+BY24+BZ24+CA24 -> 0 | CC24: 280 | CD24: 233 | CE24: =SUM(CC24:CD24) -> 513 | CF24: 0 | CG24: 0 | CH24: =SUM(CF24:CG24) -> 0 | CI24: =SUM(CC24+CF24) -> 280 | CJ24: =SUM(CD24+CG24) -> 233 | CK24: =SUM(CI24:CJ24) -> 513 | CW24: =SUM(CS24+CI24+BT24+BJ24) -> 280 | CX24: =SUM(CT24+CJ24+BU24+BK24) -> 233 | CY24: =SUM(CU24+CK24+BV24+BL24) -> 513 | CZ24: =SUM(CR24+CH24+BS24+BI24) -> 0 | DB24: =SUM(CW24:CX24) -> 513 | DD24: =BD24+BN24+CC24+CM24 -> 280 | DE24: =BE24+BO24+CD24+CN24 -> 233 | DF24: =BG24+BQ24+CF24+CP24 -> 0 | DG24: =BH24+BR24+CG24+CQ24 -> 0 | DH24: =DB24+AX24 -> 513 | EY24: =SUM(EO24+EE24+DU24+DK24) -> 0 | FD24: =DI24+DS24+EC24+EM24+CM24+CC24 -> 280 | FE24: =DJ24+DT24+ED24+EN24+CD24+CN24 -> 233 | FF24: =DL24+DV24+EF24+EP24+CP24+CF24 -> 0 | FG24: =DM24+DW24+EG24+EQ24+CG24+CQ24 -> 0 | FH24: =FD24+FF24 -> 280 | FI24: =FE24+FG24 -> 233 | FJ24: =FH24+FI24 -> 513 | FK24: =EW24+CW24+AS24 -> 280 | FL24: =EX24+CX24+AT24 -> 233 | FM24: =FK24+FL24 -> 513 | FN24: 0 | FO24: 0 | FP24: =SUM(FN24:FO24) -> 0 | FQ24: 0 | FR24: 0 | FS24: =SUM(FQ24:FR24) -> 0 | FT24: =SUM(FN24+FQ24) -> 0 | FU24: =SUM(FO24+FR24) -> 0 | FV24: =SUM(FT24:FU24) -> 0 | FZ24: =SUM(FX24:FY24) -> 0 | GC24: =SUM(GA24:GB24) -> 0 | GD24: =FX24+GA24 -> 0 | GE24: =FY24+GB24 -> 0 | GF24: =GD24+GE24 -> 0 | GJ24: =SUM(GH24:GI24) -> 0 | GM24: =SUM(GK24:GL24) -> 0 | GN24: =GH24+GK24 -> 0 | GO24: =GI24+GL24 -> 0 | GP24: =GN24+GO24 -> 0 | GR24: =GN24+GD24+FT24+ES24+EI24+DY24+DO24+CS24+CI24+BT24+BJ24 -> 280 | GS24: =GO24+GE24+FU24+ET24+EJ24+DZ24+DP24+CT24+CJ24+BU24+BK24 -> 233 | GT24: =GH24+FX24+FN24+EM24+EC24+DS24+DI24+CM24+CC24+BN24+BD24 -> 280 | GU24: =GI24+FY24+FO24+EN24+ED24+DT24+DJ24+CN24+CD24+BO24+BE24 -> 233 | GV24: =GK24+GA24+FQ24+EP24+EF24+DV24+DL24+CP24+CF24+BQ24+BG24 -> 0 | GW24: =GL24+GB24+FR24+EQ24+EG24+DW24+DM24+CQ24+CG24+BR24+BH24 -> 0 | GZ24: =GX24+GY24 -> 0 | HC24: =HA24+HB24 -> 0 | HD24: =GX24+HA24 -> 0 | HE24: =GY24+HB24 -> 0 | HF24: =HD24+HE24 -> 0 | HH24: =HD24+GN24+GD24+FT24 -> 0 | HI24: =GO24+GE24+FU24+HE24 -> 0 | HJ24: =GX24+GH24+FX24+FN24 -> 0 | HK24: =GI24+FY24+GY24+FO24 -> 0 | HL24: =GK24+GA24+FQ24+HA24 -> 0 | HM24: =GL24+HB24+GB24+FR24 -> 0 | HO24: =HF24+GP24+GF24+FV24 -> 0 | HQ24: =FN24+FX24+GH24+GX24 -> 0 | HR24: =FO24+FY24+GI24+GY24 -> 0 | HS24: =FQ24+GA24+GK24+HA24 -> 0 | HT24: =FR24+GB24+GL24+HB24 -> 0 | HW24: =HU24+HV24 -> 0 | HZ24: =HX24+HY24 -> 0 | IA24: =HU24+HX24 -> 0 | IB24: =HV24+HY24 -> 0 | IC24: =IA24+IB24 -> 0 | JN24: =JG24+IW24+IM24+IC24 -> 0 | JZ24: =JX24+JN24+HO24+FB24 -> 0 | KA24: =SUM(JV24+JE24+IU24+IK24+IA24+HD24+GN24+GD24+FT24+ES24+EI24+DY24+DO24+CS24+CI24+BT24+BJ24+AO24+AE24+U24+K24) -> 280 | KB24: =SUM(JW24+JF24+IV24+IL24+IB24+HE24+GO24+GE24+FU24+ET24+EJ24+DZ24+DP24+CT24+CJ24+BU24+BK24+AP24+AF24+V24+L24) -> 233 | KC24: =SUM(JP24+IY24+IO24+IE24+HU24+GX24+GH24+FX24+FN24+EM24+EC24+DS24+DI24+CM24+CC24+BN24+BD24+AI24+Y24+O24+E24) -> 280 | KD24: =SUM(JQ24+IZ24+IP24+IF24+HV24+GY24+GI24+FY24+FO24+EN24+ED24+DT24+DJ24+CN24+CD24+BO24+BE24+AJ24+Z24+P24+F24) -> 233 | KE24: =SUM(JS24+JB24+IR24+IH24+HX24+HA24+GK24+GA24+FQ24+EP24+EF24+DV24+DL24+CP24+CF24+BQ24+BG24+AL24+AB24+R24+H24) -> 0 | KF24: =SUM(JT24+JC24+IS24+II24+HY24+HB24+GL24+GB24+FR24+EQ24+EG24+DW24+DM24+CQ24+CG24+BR24+BH24+AM24+AC24+S24+I24) -> 0 | KG24: =SUM(KA24:KB24) -> 513 | KJ24: =KG24/KH24 -> #DIV/0!
B25: Provide integrated services to women and girls at the safe spaces | C25: Nakivale | D25: 4500 | O25: 37 | P25: 0 | Q25: =SUM(O25:P25) -> 37 | R25: 0 | S25: 0 | T25: =SUM(R25:S25) -> 0 | U25: =SUM(O25+R25) -> 37 | V25: =SUM(P25+S25) -> 0 | W25: =SUM(U25:V25) -> 37 | X25: 2 | Y25: 16 | Z25: 0 | AA25: =SUM(Y25:Z25) -> 16 | AB25: 0 | AC25: 0 | AD25: =SUM(AB25:AC25) -> 0 | AE25: =SUM(Y25+AB25) -> 16 | AF25: =SUM(Z25+AC25) -> 0 | AG25: =SUM(AE25:AF25) -> 16 | AI25: 95 | AJ25: 0 | AK25: =SUM(AI25:AJ25) -> 95 | AL25: 0 | AM25: 0 | AN25: =SUM(AL25:AM25) -> 0 | AO25: =SUM(AI25+AL25) -> 95 | AP25: =SUM(AJ25+AM25) -> 0 | AQ25: =SUM(AO25:AP25) -> 95 | AS25: =AO25+AE25+U25+K25 -> 148 | AT25: =AP25+AF25+V25+L25 -> 0 | AU25: =AK25+AA25+Q25+G25 -> 148 | AV25: =AN25 -> 0 | AX25: =SUM(AQ25+AG25+W25+M25) -> 148 | AY25: =AX25/AW25 -> #DIV/0! | AZ25: =SUM(E25+O25+Y25+AI25) -> 148 | BA25: =F25+P25+Z25+AJ25 -> 0 | BB25: =H25+R25+AB25+AL25 -> 0 | BC25: =I25+S25+AC25+AM25 -> 0 | BD25: 505 | BE25: 0 | BF25: =SUM(BD25:BE25) -> 505 | BG25: 1 | BI25: =SUM(BG25:BH25) -> 1 | BJ25: =SUM(BD25+BG25) -> 506 | BK25: =SUM(BE25+BH25) -> 0 | BL25: =SUM(BJ25:BK25) -> 506 | BN25: 241 | BO25: 0 | BP25: =SUM(BN25:BO25) -> 241 | BQ25: 0 | BR25: 0 | BS25: =SUM(BQ25:BR25) -> 0 | BT25: =SUM(BN25+BQ25) -> 241 | BU25: =SUM(BO25+BR25) -> 0 | BV25: =SUM(BT25:BU25) -> 241 | BX25: =BN25+BD25+AI25+Y25+O25+E25 -> 894 | BY25: =BO25+BE25+AJ25+Z25+P25+F25 -> 0 | BZ25: =BQ25+BG25+AL25+AB25+R25+H25 -> 1 | CA25: =BR25+BH25+AM25+AC25+S25+I25 -> 0 | CB25: =BX25+BY25+BZ25+CA25 -> 895 | CC25: 111 | CD25: 0 | CE25: =SUM(CC25:CD25) -> 111 | CF25: 0 | CG25: 0 | CH25: 0 | CI25: =SUM(CC25+CF25) -> 111 | CJ25: =SUM(CD25+CG25) -> 0 | CK25: =SUM(CI25:CJ25) -> 111 | CM25: 459 | CN25: 0 | CO25: =SUM(CM25:CN25) -> 459 | CP25: 0 | CQ25: 0 | CR25: =SUM(CP25:CQ25) -> 0 | CS25: =SUM(CM25+CP25) -> 459 | CT25: =SUM(CN25+CQ25) -> 0 | CU25: =SUM(CS25:CT25) -> 459 | CW25: =SUM(CS25+CI25+BT25+BJ25) -> 1317 | CX25: =SUM(CT25+CJ25+BU25+BK25) -> 0 | CY25: =SUM(CU25+CK25+BV25+BL25) -> 1317 | CZ25: =SUM(CR25+CH25+BS25+BI25) -> 1 | DB25: =SUM(CW25:CX25) -> 1317 | DD25: =BD25+BN25+CC25+CM25 -> 1316 | DE25: =BE25+BO25+CD25+CN25 -> 0 | DF25: =BG25+BQ25+CF25+CP25 -> 1 | DG25: =BH25+BR25+CG25+CQ25 -> 0 | DH25: =DB25+AX25 -> 1465 | DI25: 240 | DJ25: 0 | DK25: =SUM(DI25:DJ25) -> 240 | DL25: 0 | DM25: 0 | DN25: =SUM(DL25:DM25) -> 0 | DO25: =DI25+DL25 -> 240 | DP25: =DJ25+DM25 -> 0 | DQ25: =DK25 -> 240 | DR25: =DN25 -> 0 | DS25: 256 | DT25: 0 | DU25: =SUM(DS25:DT25) -> 256 | DV25: 0 | DW25: 0 | DX25: =SUM(DV25:DW25) -> 0 | DY25: =SUM(DS25+DV25) -> 256 | DZ25: =SUM(DT25+DW25) -> 0 | EA25: =SUM(DY25:DZ25) -> 256 | EC25: 298 | ED25: 0 | EE25: =SUM(EC25:ED25) -> 298 | EF25: 0 | EG25: 0 | EH25: =SUM(EF25:EG25) -> 0 | EI25: =SUM(EC25+EF25) -> 298 | EJ25: =SUM(ED25+EG25) -> 0 | EK25: =SUM(EI25:EJ25) -> 298 | EM25: 192 | EN25: 0 | EO25: =SUM(EM25:EN25) -> 192 | EP25: 0 | EQ25: 0 | ER25: =SUM(EP25:EQ25) -> 0 | ES25: =SUM(EM25+EP25) -> 192 | ET25: =SUM(EN25+EQ25) -> 0 | EU25: =SUM(ES25:ET25) -> 192 | EW25: =SUM(ES25+EI25+DY25+DO25) -> 986 | EX25: =SUM(ET25+EJ25+DZ25+DP25) -> 0 | EY25: =SUM(EO25+EE25+DU25+DK25) -> 986 | EZ25: =SUM(ER25+EH25+DX25+DN25) -> 0 | FA25: =D25/12 -> 375 | FB25: =SUM(EW25:EX25) -> 986 | FC25: =FB25/FA25 -> 2.6293333 | FD25: =DI25+DS25+EC25+EM25+CM25+CC25 -> 1556 | FE25: =DJ25+DT25+ED25+EN25+CD25+CN25 -> 0 | FF25: =DL25+DV25+EF25+EP25+CP25+CF25 -> 0 | FG25: =DM25+DW25+EG25+EQ25+CG25+CQ25 -> 0 | FH25: =FD25+FF25 -> 1556 | FI25: =FE25+FG25 -> 0 | FJ25: =FH25+FI25 -> 1556 | FK25: =EW25+CW25+AS25 -> 2451 | FL25: =EX25+CX25+AT25 -> 0 | FM25: =FK25+FL25 -> 2451 | FN25: 418 | FO25: 0 | FP25: =SUM(FN25:FO25) -> 418 | FQ25: 0 | FR25: 0 | FS25: =SUM(FQ25:FR25) -> 0 | FT25: =SUM(FN25+FQ25) -> 418 | FU25: =SUM(FO25+FR25) -> 0 | FV25: =SUM(FT25:FU25) -> 418 | FX25: 383 | FY25: 0 | FZ25: =FX25+FY25 -> 383 | GA25: 140 | GB25: 0 | GC25: =SUM(GA25:GB25) -> 140 | GD25: 537 | GE25: =FY25+GB25 -> 0 | GF25: =GD25+GE25 -> 537 | GH25: 277 | GI25: 0 | GJ25: =SUM(GH25:GI25) -> 277 | GK25: 0 | GL25: 0 | GM25: =GK25+GL25 -> 0 | GN25: =GH25+GK25 -> 277 | GO25: =GI25+GL25 -> 0 | GP25: =GN25+GO25 -> 277 | GR25: =GN25+GD25+FT25+ES25+EI25+DY25+DO25+CS25+CI25+BT25+BJ25 -> 3535 | GS25: =GO25+GE25+FU25+ET25+EJ25+DZ25+DP25+CT25+CJ25+BU25+BK25 -> 0 | GT25: =GH25+FX25+FN25+EM25+EC25+DS25+DI25+CM25+CC25+BN25+BD25 -> 3380 | GU25: =GI25+FY25+FO25+EN25+ED25+DT25+DJ25+CN25+CD25+BO25+BE25 -> 0 | GV25: =GK25+GA25+FQ25+EP25+EF25+DV25+DL25+CP25+CF25+BQ25+BG25 -> 141 | GW25: =GL25+GB25+FR25+EQ25+EG25+DW25+DM25+CQ25+CG25+BR25+BH25 -> 0 | GX25: 260 | GY25: 0 | GZ25: =GX25+GY25 -> 260 | HA25: 0 | HB25: 0 | HC25: =HA25+HB25 -> 0 | HD25: =GX25+HA25 -> 260 | HE25: =GY25+HB25 -> 0 | HF25: =HD25+HE25 -> 260 | HH25: =HD25+GN25+GD25+FT25 -> 1492 | HI25: =GO25+GE25+FU25+HE25 -> 0 | HJ25: =GX25+GH25+FX25+FN25 -> 1338 | HK25: =GI25+FY25+GY25+FO25 -> 0 | HL25: =GK25+GA25+FQ25+HA25 -> 140 | HM25: =GL25+HB25+GB25+FR25 -> 0 | HO25: =HF25+GP25+GF25+FV25 -> 1492 | HQ25: =FN25+FX25+GH25+GX25 -> 1338 | HR25: =FO25+FY25+GI25+GY25 -> 0 | HS25: =FQ25+GA25+GK25+HA25 -> 140 | HT25: =FR25+GB25+GL25+HB25 -> 0 | HU25: 210 | HV25: 0 | HW25: =HU25+HV25 -> 210 | HX25: 0 | HY25: 0 | HZ25: =HX25+HY25 -> 0 | IA25: =HU25+HX25 -> 210 | IB25: =HV25+HY25 -> 0 | IC25: =IA25+IB25 -> 210 | JN25: =JG25+IW25+IM25+IC25 -> 210 | JZ25: =JX25+JN25+HO25+FB25 -> 2688 | KA25: =SUM(JV25+JE25+IU25+IK25+IA25+HD25+GN25+GD25+FT25+ES25+EI25+DY25+DO25+CS25+CI25+BT25+BJ25+AO25+AE25+U25+K25) -> 4153 | KB25: =SUM(JW25+JF25+IV25+IL25+IB25+HE25+GO25+GE25+FU25+ET25+EJ25+DZ25+DP25+CT25+CJ25+BU25+BK25+AP25+AF25+V25+L25) -> 0 | KC25: =SUM(JP25+IY25+IO25+IE25+HU25+GX25+GH25+FX25+FN25+EM25+EC25+DS25+DI25+CM25+CC25+BN25+BD25+AI25+Y25+O25+E25) -> 3998 | KD25: =SUM(JQ25+IZ25+IP25+IF25+HV25+GY25+GI25+FY25+FO25+EN25+ED25+DT25+DJ25+CN25+CD25+BO25+BE25+AJ25+Z25+P25+F25) -> 0 | KE25: =SUM(JS25+JB25+IR25+IH25+HX25+HA25+GK25+GA25+FQ25+EP25+EF25+DV25+DL25+CP25+CF25+BQ25+BG25+AL25+AB25+R25+H25) -> 141 | KF25: =SUM(JT25+JC25+IS25+II25+HY25+HB25+GL25+GB25+FR25+EQ25+EG25+DW25+DM25+CQ25+CG25+BR25+BH25+AM25+AC25+S25+I25) -> 0 | KG25: =KA25 -> 4153 | KH25: 4500 | KI25: =KH25-KG25 -> 347 | KJ25: =KG25/KH25 -> 0.92288889 | KK25: =KG25+KG26 -> 4461
B26: Provide integrated services to women and girls at the safe spaces | C26: Nyakabande | BX26: =BN26+BD26+AI26+Y26+O26+E26 -> 0 | BY26: =BO26+BE26+AJ26+Z26+P26+F26 -> 0 | BZ26: =BQ26+BG26+AL26+AB26+R26+H26 -> 0 | CA26: =BR26+BH26+AM26+AC26+S26+I26 -> 0 | CB26: =BX26+BY26+BZ26+CA26 -> 0 | DH26: =DB26+AX26 -> 0 | EI26: =SUM(EC26+EF26) -> 0 | EJ26: =SUM(ED26+EG26) -> 0 | EK26: =SUM(EI26:EJ26) -> 0 | FD26: =DI26+DS26+EC26+EM26+CM26+CC26 -> 0 | FE26: =DJ26+DT26+ED26+EN26+CD26+CN26 -> 0 | FF26: =DL26+DV26+EF26+EP26+CP26+CF26 -> 0 | FG26: =DM26+DW26+EG26+EQ26+CG26+CQ26 -> 0 | FH26: =FD26+FF26 -> 0 | FI26: =FE26+FG26 -> 0 | FJ26: =FH26+FI26 -> 0 | FK26: =EW26+CW26+AS26 -> 0 | FL26: =EX26+CX26+AT26 -> 0 | FM26: =FK26+FL26 -> 0 | FN26: 22 | FO26: 0 | FP26: =SUM(FN26:FO26) -> 22 | FQ26: 0 | FR26: 0 | FS26: =SUM(FQ26:FR26) -> 0 | FT26: =SUM(FN26+FQ26) -> 22 | FU26: =SUM(FO26+FR26) -> 0 | FV26: =SUM(FT26:FU26) -> 22 | FX26: 154 | FY26: 0 | FZ26: =FX26+FY26 -> 154 | GA26: 0 | GB26: 0 | GC26: =SUM(GA26:GB26) -> 0 | GD26: =FX26+GA26 -> 154 | GE26: =FY26+GB26 -> 0 | GF26: =GD26+GE26 -> 154 | GH26: 36 | GJ26: =GH26+GI26 -> 36 | GK26: 0 | GL26: 0 | GM26: =GK26+GL26 -> 0 | GN26: =GH26+GK26 -> 36 | GO26: =GI26+GL26 -> 0 | GP26: =GN26+GO26 -> 36 | GR26: =GN26+GD26+FT26+ES26+EI26+DY26+DO26+CS26+CI26+BT26+BJ26 -> 212 | GS26: =GO26+GE26+FU26+ET26+EJ26+DZ26+DP26+CT26+CJ26+BU26+BK26 -> 0 | GT26: =GH26+FX26+FN26+EM26+EC26+DS26+DI26+CM26+CC26+BN26+BD26 -> 212 | GU26: =GI26+FY26+FO26+EN26+ED26+DT26+DJ26+CN26+CD26+BO26+BE26 -> 0 | GV26: =GK26+GA26+FQ26+EP26+EF26+DV26+DL26+CP26+CF26+BQ26+BG26 -> 0 | GW26: =GL26+GB26+FR26+EQ26+EG26+DW26+DM26+CQ26+CG26+BR26+BH26 -> 0 | GX26: 0 | GY26: 0 | GZ26: =GX26+GY26 -> 0 | HA26: 0 | HB26: 0 | HC26: =HA26+HB26 -> 0 | HD26: =GX26+HA26 -> 0 | HE26: =GY26+HB26 -> 0 | HF26: =HD26+HE26 -> 0 | HH26: =HD26+GN26+GD26+FT26 -> 212 | HI26: =GO26+GE26+FU26+HE26 -> 0 | HJ26: =GX26+GH26+FX26+FN26 -> 212 | HK26: =GI26+FY26+GY26+FO26 -> 0 | HL26: =GK26+GA26+FQ26+HA26 -> 0 | HM26: =GL26+HB26+GB26+FR26 -> 0 | HO26: =HF26+GP26+GF26+FV26 -> 212 | HQ26: =FN26+FX26+GH26+GX26 -> 212 | HR26: =FO26+FY26+GI26+GY26 -> 0 | HS26: =FQ26+GA26+GK26+HA26 -> 0 | HT26: =FR26+GB26+GL26+HB26 -> 0 | HU26: 96 | HV26: 0 | HW26: =HU26+HV26 -> 96 | HX26: 0 | HY26: 0 | HZ26: =HX26+HY26 -> 0 | IA26: =HU26+HX26 -> 96 | IB26: =HV26+HY26 -> 0 | IC26: =IA26+IB26 -> 96 | JN26: =JG26+IW26+IM26+IC26 -> 96 | JZ26: =JX26+JN26+HO26+FB26 -> 308 | KA26: =SUM(JV26+JE26+IU26+IK26+IA26+HD26+GN26+GD26+FT26+ES26+EI26+DY26+DO26+CS26+CI26+BT26+BJ26+AO26+AE26+U26+K26) -> 308 | KB26: =SUM(JW26+JF26+IV26+IL26+IB26+HE26+GO26+GE26+FU26+ET26+EJ26+DZ26+DP26+CT26+CJ26+BU26+BK26+AP26+AF26+V26+L26) -> 0 | KC26: =SUM(JP26+IY26+IO26+IE26+HU26+GX26+GH26+FX26+FN26+EM26+EC26+DS26+DI26+CM26+CC26+BN26+BD26+AI26+Y26+O26+E26) -> 308 | KD26: =SUM(JQ26+IZ26+IP26+IF26+HV26+GY26+GI26+FY26+FO26+EN26+ED26+DT26+DJ26+CN26+CD26+BO26+BE26+AJ26+Z26+P26+F26) -> 0 | KE26: =SUM(JS26+JB26+IR26+IH26+HX26+HA26+GK26+GA26+FQ26+EP26+EF26+DV26+DL26+CP26+CF26+BQ26+BG26+AL26+AB26+R26+H26) -> 0 | KF26: =SUM(JT26+JC26+IS26+II26+HY26+HB26+GL26+GB26+FR26+EQ26+EG26+DW26+DM26+CQ26+CG26+BR26+BH26+AM26+AC26+S26+I26) -> 0 | KG26: =SUM(KA26:KB26) -> 308 | KH26: 0 | KI26: =KH26-KG26 -> -308 | KJ26: =KG26/KH26 -> #DIV/0! | KK26: =KK25=KA25+KA26 -> TRUE | KL26: =KG25+KG26 -> 4461
B27: Establish or Maintain Girl's Safe Spaces | C27: Nakivale | D27: 3 | AS27: =AO27+AE27+U27+K27 -> 0 | AT27: =AP27+AF27+V27+L27 -> 0 | AU27: =AK27+AA27+Q27+G27 -> 0 | AV27: =AN27 -> 0 | AX27: =SUM(AQ27+AG27+W27+M27) -> 0 | AY27: =AX27/AW27 -> #DIV/0! | AZ27: =SUM(E27+O27+Y27+AI27) -> 0 | BA27: =F27+P27+Z27+AJ27 -> 0 | BB27: =H27+R27+AB27+AL27 -> 0 | BC27: =I27+S27+AC27+AM27 -> 0 | BX27: =BN27+BD27+AI27+Y27+O27+E27 -> 0 | BY27: =BO27+BE27+AJ27+Z27+P27+F27 -> 0 | BZ27: =BQ27+BG27+AL27+AB27+R27+H27 -> 0 | CA27: =BR27+BH27+AM27+AC27+S27+I27 -> 0 | CB27: =BX27+BY27+BZ27+CA27 -> 0 | CW27: =SUM(CS27+CI27+BT27+BJ27) -> 0 | CX27: =SUM(CT27+CJ27+BU27+BK27) -> 0 | CY27: =SUM(CU27+CK27+BV27+BL27) -> 0 | CZ27: =SUM(CR27+CH27+BS27+BI27) -> 0 | DB27: =SUM(CW27:CX27) -> 0 | DD27: =BD27+BN27+CC27+CM27 -> 0 | DE27: =BE27+BO27+CD27+CN27 -> 0 | DF27: =BG27+BQ27+CF27+CP27 -> 0 | DG27: =BH27+BR27+CG27+CQ27 -> 0 | DH27: =DB27+AX27 -> 0 | DU27: =SUM(DS27:DT27) -> 0 | DX27: =SUM(DV27:DW27) -> 0 | DY27: =SUM(DS27+DV27) -> 0 | DZ27: =SUM(DT27+DW27) -> 0 | EA27: =SUM(DY27:DZ27) -> 0 | EI27: =SUM(EC27+EF27) -> 0 | EJ27: =SUM(ED27+EG27) -> 0 | EK27: =SUM(EI27:EJ27) -> 0 | EW27: =SUM(ES27+EI27+DY27+DO27) -> 0 | EX27: =SUM(ET27+EJ27+DZ27+DP27) -> 0 | EY27: =SUM(EO27+EE27+DU27+DK27) -> 0 | EZ27: =SUM(ER27+EH27+DX27+DN27) -> 0 | FB27: =SUM(EW27:EX27) -> 0 | FD27: =DI27+DS27+EC27+EM27+CM27+CC27 -> 0 | FE27: =DJ27+DT27+ED27+EN27+CD27+CN27 -> 0 | FF27: =DL27+DV27+EF27+EP27+CP27+CF27 -> 0 | FG27: =DM27+DW27+EG27+EQ27+CG27+CQ27 -> 0 | FH27: =FD27+FF27 -> 0 | FI27: =FE27+FG27 -> 0 | FJ27: =FH27+FI27 -> 0 | FK27: =EW27+CW27+AS27 -> 0 | FL27: =EX27+CX27+AT27 -> 0 | FM27: =FK27+FL27 -> 0 | FN27: 0 | FO27: 0 | FP27: =SUM(FN27:FO27) -> 0 | FQ27: 0 | FR27: 0 | FS27: =SUM(FQ27:FR27) -> 0 | FT27: =SUM(FN27+FQ27) -> 0 | FU27: =SUM(FO27+FR27) -> 0 | FV27: =SUM(FT27:FU27) -> 0 | FY27: 0 | GD27: =FX27+GA27 -> 0 | GE27: =FY27+GB27 -> 0 | GF27: =GD27+GE27 -> 0 | GN27: =GH27+GK27 -> 0 | GO27: =GI27+GL27 -> 0 | GP27: =GN27+GO27 -> 0 | GR27: =GN27+GD27+FT27+ES27+EI27+DY27+DO27+CS27+CI27+BT27+BJ27 -> 0 | GS27: =GO27+GE27+FU27+ET27+EJ27+DZ27+DP27+CT27+CJ27+BU27+BK27 -> 0 | GT27: =GH27+FX27+FN27+EM27+EC27+DS27+DI27+CM27+CC27+BN27+BD27 -> 0 | GU27: =GI27+FY27+FO27+EN27+ED27+DT27+DJ27+CN27+CD27+BO27+BE27 -> 0 | GV27: =GK27+GA27+FQ27+EP27+EF27+DV27+DL27+CP27+CF27+BQ27+BG27 -> 0 | GW27: =GL27+GB27+FR27+EQ27+EG27+DW27+DM27+CQ27+CG27+BR27+BH27 -> 0 | GZ27: =GX27+GY27 -> 0 | HC27: =HA27+HB27 -> 0 | HD27: =GX27+HA27 -> 0 | HE27: =GY27+HB27 -> 0 | HF27: =HD27+HE27 -> 0 | HH27: =HD27+GN27+GD27+FT27 -> 0 | HI27: =GO27+GE27+FU27+HE27 -> 0 | HJ27: =GX27+GH27+FX27+FN27 -> 0 | HK27: =GI27+FY27+GY27+FO27 -> 0 | HL27: =GK27+GA27+FQ27+HA27 -> 0 | HM27: =GL27+HB27+GB27+FR27 -> 0 | HO27: =HF27+GP27+GF27+FV27 -> 0 | HQ27: =FN27+FX27+GH27+GX27 -> 0 | HR27: =FO27+FY27+GI27+GY27 -> 0 | HS27: =FQ27+GA27+GK27+HA27 -> 0 | HT27: =FR27+GB27+GL27+HB27 -> 0 | HW27: =HU27+HV27 -> 0 | HZ27: =HX27+HY27 -> 0 | IA27: =HU27+HX27 -> 0 | IB27: =HV27+HY27 -> 0 | IC27: =IA27+IB27 -> 0 | JN27: =JG27+IW27+IM27+IC27 -> 0 | JZ27: =JX27+JN27+HO27+FB27 -> 0 | KA27: =SUM(JV27+JE27+IU27+IK27+IA27+HD27+GN27+GD27+FT27+ES27+EI27+DY27+DO27+CS27+CI27+BT27+BJ27+AO27+AE27+U27+K27) -> 0 | KB27: =SUM(JW27+JF27+IV27+IL27+IB27+HE27+GO27+GE27+FU27+ET27+EJ27+DZ27+DP27+CT27+CJ27+BU27+BK27+AP27+AF27+V27+L27) -> 0 | KC27: =SUM(JP27+IY27+IO27+IE27+HU27+GX27+GH27+FX27+FN27+EM27+EC27+DS27+DI27+CM27+CC27+BN27+BD27+AI27+Y27+O27+E27) -> 0 | KD27: =SUM(JQ27+IZ27+IP27+IF27+HV27+GY27+GI27+FY27+FO27+EN27+ED27+DT27+DJ27+CN27+CD27+BO27+BE27+AJ27+Z27+P27+F27) -> 0 | KE27: =SUM(JS27+JB27+IR27+IH27+HX27+HA27+GK27+GA27+FQ27+EP27+EF27+DV27+DL27+CP27+CF27+BQ27+BG27+AL27+AB27+R27+H27) -> 0 | KF27: =SUM(JT27+JC27+IS27+II27+HY27+HB27+GL27+GB27+FR27+EQ27+EG27+DW27+DM27+CQ27+CG27+BR27+BH27+AM27+AC27+S27+I27) -> 0 | KG27: =SUM(KA27:KB27) -> 0 | KH27: 3 | KI27: =KH27-KG27 -> 3 | KJ27: =KG27/KH27 -> 0
B28: Community members reached with GBV prevention messages by stregthened GBV community structures | C28: Nakivale | D28: 3700 | AS28: =AO28+AE28+U28+K28 -> 0 | AT28: =AP28+AF28+V28+L28 -> 0 | AU28: =AK28+AA28+Q28+G28 -> 0 | AV28: =AN28 -> 0 | AX28: =SUM(AQ28+AG28+W28+M28) -> 0 | AZ28: =SUM(E28+O28+Y28+AI28) -> 0 | BA28: =F28+P28+Z28+AJ28 -> 0 | BB28: =H28+R28+AB28+AL28 -> 0 | BC28: =I28+S28+AC28+AM28 -> 0 | BX28: =BN28+BD28+AI28+Y28+O28+E28 -> 0 | BY28: =BO28+BE28+AJ28+Z28+P28+F28 -> 0 | BZ28: =BQ28+BG28+AL28+AB28+R28+H28 -> 0 | CA28: =BR28+BH28+AM28+AC28+S28+I28 -> 0 | CB28: =BX28+BY28+BZ28+CA28 -> 0 | CM28: 324 | CN28: 227 | CO28: =SUM(CM28:CN28) -> 551 | CP28: 0 | CQ28: 0 | CR28: =SUM(CP28:CQ28) -> 0 | CS28: =SUM(CM28+CP28) -> 324 | CT28: =SUM(CN28+CQ28) -> 227 | CU28: =SUM(CT28) -> 227 | CW28: =SUM(CS28+CI28+BT28+BJ28) -> 324 | CX28: =SUM(CT28+CJ28+BU28+BK28) -> 227 | CY28: =SUM(CU28+CK28+BV28+BL28) -> 227 | CZ28: =SUM(CR28+CH28+BS28+BI28) -> 0 | DB28: =SUM(CW28:CX28) -> 551 | DD28: =BD28+BN28+CC28+CM28 -> 324 | DE28: =BE28+BO28+CD28+CN28 -> 227 | DF28: =BG28+BQ28+CF28+CP28 -> 0 | DG28: =BH28+BR28+CG28+CQ28 -> 0 | DH28: =DB28+AX28 -> 551 | DI28: 0 | DJ28: 0 | DK28: =SUM(DI28:DJ28) -> 0 | DL28: 0 | DM28: 0 | DN28: =SUM(DL28:DM28) -> 0 | DO28: =SUM(DI28+DL28) -> 0 | DP28: =SUM(DJ28+DM28) -> 0 | DU28: =SUM(DS28:DT28) -> 0 | DX28: =SUM(DV28:DW28) -> 0 | DY28: =SUM(DS28+DV28) -> 0 | DZ28: =SUM(DT28+DW28) -> 0 | EA28: =SUM(DY28:DZ28) -> 0 | EW28: =SUM(ES28+EI28+DY28+DO28) -> 0 | EX28: =SUM(ET28+EJ28+DZ28+DP28) -> 0 | EY28: =SUM(EO28+EE28+DU28+DK28) -> 0 | EZ28: =SUM(ER28+EH28+DX28+DN28) -> 0 | FB28: =SUM(EW28:EX28) -> 0 | FD28: =DI28+DS28+EC28+EM28+CM28+CC28 -> 324 | FE28: =DJ28+DT28+ED28+EN28+CD28+CN28 -> 227 | FF28: =DL28+DV28+EF28+EP28+CP28+CF28 -> 0 | FG28: =DM28+DW28+EG28+EQ28+CG28+CQ28 -> 0 | FH28: =FD28+FF28 -> 324 | FI28: =FE28+FG28 -> 227 | FJ28: =FH28+FI28 -> 551 | FK28: =EW28+CW28+AS28 -> 324 | FL28: =EX28+CX28+AT28 -> 227 | FM28: =FK28+FL28 -> 551 | FN28: 65 | FO28: 33 | FP28: =SUM(FN28:FO28) -> 98 | FQ28: 0 | FR28: 0 | FS28: =SUM(FQ28:FR28) -> 0 | FT28: =FN28+FQ28 -> 65 | FU28: =FO28+FR28 -> 33 | FV28: =SUM(FT28:FU28) -> 98 | FX28: 375 | FY28: 226 | FZ28: =SUM(FX28:FY28) -> 601 | GA28: 0 | GB28: 0 | GC28: =SUM(GA28:GB28) -> 0 | GD28: =FX28+GA28 -> 375 | GE28: =FY28+GB28 -> 226 | GF28: =GD28+GE28 -> 601 | GH28: 371 | GI28: 172 | GJ28: =GH28+GI28 -> 543 | GK28: 0 | GL28: 0 | GM28: =GK28+GL28 -> 0 | GN28: =GH28+GK28 -> 371 | GO28: =GI28+GL28 -> 172 | GP28: =GN28+GO28 -> 543 | GR28: =GN28+GD28+FT28+ES28+EI28+DY28+DO28+CS28+CI28+BT28+BJ28 -> 1135 | GS28: =GO28+GE28+FU28+ET28+EJ28+DZ28+DP28+CT28+CJ28+BU28+BK28 -> 658 | GT28: =GH28+FX28+FN28+EM28+EC28+DS28+DI28+CM28+CC28+BN28+BD28 -> 1135 | GU28: =GI28+FY28+FO28+EN28+ED28+DT28+DJ28+CN28+CD28+BO28+BE28 -> 658 | GV28: =GK28+GA28+FQ28+EP28+EF28+DV28+DL28+CP28+CF28+BQ28+BG28 -> 0 | GW28: =GL28+GB28+FR28+EQ28+EG28+DW28+DM28+CQ28+CG28+BR28+BH28 -> 0 | GX28: 267 | GY28: 108 | GZ28: =GX28+GY28 -> 375 | HA28: 0 | HB28: 0 | HC28: =HA28+HB28 -> 0 | HD28: =GX28+HA28 -> 267 | HE28: =GY28+HB28 -> 108 | HF28: =HD28+HE28 -> 375 | HH28: =HD28+GN28+GD28+FT28 -> 1078 | HI28: =GO28+GE28+FU28+HE28 -> 539 | HJ28: =GX28+GH28+FX28+FN28 -> 1078 | HK28: =GI28+FY28+GY28+FO28 -> 539 | HL28: =GK28+GA28+FQ28+HA28 -> 0 | HM28: =GL28+HB28+GB28+FR28 -> 0 | HO28: =HF28+GP28+GF28+FV28 -> 1617 | HQ28: =FN28+FX28+GH28+GX28 -> 1078 | HR28: =FO28+FY28+GI28+GY28 -> 539 | HS28: =FQ28+GA28+GK28+HA28 -> 0 | HT28: =FR28+GB28+GL28+HB28 -> 0 | HU28: 247 | HV28: 125 | HW28: =HU28+HV28 -> 372 | HX28: 0 | HY28: 0 | HZ28: =HX28+HY28 -> 0 | IA28: =HU28+HX28 -> 247 | IB28: =HV28+HY28 -> 125 | IC28: =IA28+IB28 -> 372 | JN28: =JG28+IW28+IM28+IC28 -> 372 | JZ28: =JX28+JN28+HO28+FB28 -> 1989 | KA28: =SUM(JV28+JE28+IU28+IK28+IA28+HD28+GN28+GD28+FT28+ES28+EI28+DY28+DO28+CS28+CI28+BT28+BJ28+AO28+AE28+U28+K28) -> 1649 | KB28: =SUM(JW28+JF28+IV28+IL28+IB28+HE28+GO28+GE28+FU28+ET28+EJ28+DZ28+DP28+CT28+CJ28+BU28+BK28+AP28+AF28+V28+L28) -> 891 | KC28: =SUM(JP28+IY28+IO28+IE28+HU28+GX28+GH28+FX28+FN28+EM28+EC28+DS28+DI28+CM28+CC28+BN28+BD28+AI28+Y28+O28+E28) -> 1649 | KD28: =SUM(JQ28+IZ28+IP28+IF28+HV28+GY28+GI28+FY28+FO28+EN28+ED28+DT28+DJ28+CN28+CD28+BO28+BE28+AJ28+Z28+P28+F28) -> 891 | KE28: =SUM(JS28+JB28+IR28+IH28+HX28+HA28+GK28+GA28+FQ28+EP28+EF28+DV28+DL28+CP28+CF28+BQ28+BG28+AL28+AB28+R28+H28) -> 0 | KF28: =SUM(JT28+JC28+IS28+II28+HY28+HB28+GL28+GB28+FR28+EQ28+EG28+DW28+DM28+CQ28+CG28+BR28+BH28+AM28+AC28+S28+I28) -> 0 | KG28: =SUM(KA28:KB28) -> 2540 | KH28: 3700 | KJ28: =KG28/KH28 -> 0.68648649 | KK28: =KJ26 -> #DIV/0!
B29: Comic Books Sessions Deliver Community Engagement Interventions on protection, prevention of GBV/CP and other forms of violence through Comic Book Sessions | C29: Nakivale | D29: 450 | AS29: =AO29+AE29+U29+K29 -> 0 | AT29: =AP29+AF29+V29+L29 -> 0 | AU29: =AK29+AA29+Q29+G29 -> 0 | AV29: =AN29 -> 0 | AX29: =SUM(AQ29+AG29+W29+M29) -> 0 | AZ29: =SUM(E29+O29+Y29+AI29) -> 0 | BA29: =F29+P29+Z29+AJ29 -> 0 | BB29: =H29+R29+AB29+AL29 -> 0 | BC29: =I29+S29+AC29+AM29 -> 0 | BX29: =BN29+BD29+AI29+Y29+O29+E29 -> 0 | BY29: =BO29+BE29+AJ29+Z29+P29+F29 -> 0 | BZ29: =BQ29+BG29+AL29+AB29+R29+H29 -> 0 | CA29: =BR29+BH29+AM29+AC29+S29+I29 -> 0 | CB29: =BX29+BY29+BZ29+CA29 -> 0 | CM29: 44 | CN29: 16 | CO29: =SUM(CM29:CN29) -> 60 | CP29: 0 | CQ29: 0 | CR29: =SUM(CP29:CQ29) -> 0 | CS29: =SUM(CM29+CP29) -> 44 | CT29: =SUM(CN29+CQ29) -> 16 | CU29: =SUM(CS29:CT29) -> 60 | CW29: =SUM(CS29+CI29+BT29+BJ29) -> 44 | CX29: =SUM(CT29+CJ29+BU29+BK29) -> 16 | CY29: =SUM(CU29+CK29+BV29+BL29) -> 60 | CZ29: =SUM(CR29+CH29+BS29+BI29) -> 0 | DB29: =SUM(CW29:CX29) -> 60 | DD29: =BD29+BN29+CC29+CM29 -> 44 | DE29: =BE29+BO29+CD29+CN29 -> 16 | DF29: =BG29+BQ29+CF29+CP29 -> 0 | DG29: =BH29+BR29+CG29+CQ29 -> 0 | DH29: =DB29+AX29 -> 60 | DI29: 17 | DJ29: 14 | DK29: =SUM(DI29:DJ29) -> 31 | DL29: 0 | DM29: 0 | DN29: =SUM(DL29:DM29) -> 0 | DO29: =DI29+DL29 -> 17 | DP29: =DJ29+DM29 -> 14 | DQ29: =SUM(DO29:DP29) -> 31 | DS29: 17 | DT29: 3 | DU29: =SUM(DS29:DT29) -> 20 | DV29: 0 | DW29: 0 | DX29: =SUM(DV29:DW29) -> 0 | DY29: =SUM(DS29+DV29) -> 17 | DZ29: =SUM(DT29+DW29) -> 3 | EA29: =SUM(DY29:DZ29) -> 20 | EC29: 44 | ED29: 0 | EE29: =SUM(EC29:ED29) -> 44 | EF29: 0 | EG29: 0 | EH29: =SUM(EF29:EG29) -> 0 | EI29: =SUM(EC29+EF29) -> 44 | EJ29: =SUM(ED29+EG29) -> 0 | EK29: =SUM(EI29:EJ29) -> 44 | EM29: 69 | EN29: 0 | EO29: =SUM(EM29:EN29) -> 69 | EP29: 0 | EQ29: 0 | ER29: =SUM(EP29:EQ29) -> 0 | ES29: =SUM(EM29+EP29) -> 69 | ET29: =SUM(EN29+EQ29) -> 0 | EU29: =SUM(ES29:ET29) -> 69 | EW29: =SUM(ES29+EI29+DY29+DO29) -> 147 | EX29: =SUM(ET29+EJ29+DZ29+DP29) -> 17 | EY29: =SUM(EO29+EE29+DU29+DK29) -> 164 | EZ29: =SUM(ER29+EH29+DX29+DN29) -> 0 | FA29: 38 | FB29: =EU29+EK29+EA29+DQ29 -> 164 | FC29: =FB29/FA29 -> 4.3157895 | FD29: =DI29+DS29+EC29+EM29+CM29+CC29 -> 191 | FE29: =DJ29+DT29+ED29+EN29+CD29+CN29 -> 33 | FF29: =DL29+DV29+EF29+EP29+CP29+CF29 -> 0 | FG29: =DM29+DW29+EG29+EQ29+CG29+CQ29 -> 0 | FH29: =FD29+FF29 -> 191 | FI29: =FE29+FG29 -> 33 | FJ29: =FH29+FI29 -> 224 | FK29: =EW29+CW29+AS29 -> 191 | FL29: =EX29+CX29+AT29 -> 33 | FM29: =FK29+FL29 -> 224 | FN29: 131 | FO29: 0 | FP29: =SUM(FN29:FO29) -> 131 | FQ29: 0 | FR29: 0 | FS29: =SUM(FQ29:FR29) -> 0 | FT29: =SUM(FN29+FQ29) -> 131 | FU29: =SUM(FO29+FR29) -> 0 | FV29: =SUM(FT29:FU29) -> 131 | FX29: 98 | FY29: 0 | FZ29: =SUM(FX29:FY29) -> 98 | GA29: 0 | GB29: 0 | GC29: =SUM(GA29:GB29) -> 0 | GD29: =FX29+GA29 -> 98 | GE29: =FY29+GB29 -> 0 | GF29: =GD29+GE29 -> 98 | GH29: 74 | GI29: 0 | GJ29: =GH29+GI29 -> 74 | GK29: 0 | GL29: 0 | GM29: =GK29+GL29 -> 0 | GN29: =GH29+GK29 -> 74 | GO29: =GI29+GL29 -> 0 | GP29: =GN29+GO29 -> 74 | GR29: =GN29+GD29+FT29+ES29+EI29+DY29+DO29+CS29+CI29+BT29+BJ29 -> 494 | GS29: =GO29+GE29+FU29+ET29+EJ29+DZ29+DP29+CT29+CJ29+BU29+BK29 -> 33 | GT29: =GH29+FX29+FN29+EM29+EC29+DS29+DI29+CM29+CC29+BN29+BD29 -> 494 | GU29: =GI29+FY29+FO29+EN29+ED29+DT29+DJ29+CN29+CD29+BO29+BE29 -> 33 | GV29: =GK29+GA29+FQ29+EP29+EF29+DV29+DL29+CP29+CF29+BQ29+BG29 -> 0 | GW29: =GL29+GB29+FR29+EQ29+EG29+DW29+DM29+CQ29+CG29+BR29+BH29 -> 0 | GX29: 51 | GY29: 0 | GZ29: =GX29+GY29 -> 51 | HA29: 0 | HB29: 0 | HC29: =HA29+HB29 -> 0 | HD29: =GX29+HA29 -> 51 | HE29: =GY29+HB29 -> 0 | HF29: =HD29+HE29 -> 51 | HH29: =HD29+GN29+GD29+FT29 -> 354 | HI29: =GO29+GE29+FU29+HE29 -> 0 | HJ29: =GX29+GH29+FX29+FN29 -> 354 | HK29: =GI29+FY29+GY29+FO29 -> 0 | HL29: =GK29+GA29+FQ29+HA29 -> 0 | HM29: =GL29+HB29+GB29+FR29 -> 0 | HO29: =HF29+GP29+GF29+FV29 -> 354 | HQ29: =FN29+FX29+GH29+GX29 -> 354 | HR29: =FO29+FY29+GI29+GY29 -> 0 | HS29: =FQ29+GA29+GK29+HA29 -> 0 | HT29: =FR29+GB29+GL29+HB29 -> 0 | HW29: =HU29+HV29 -> 0 | HZ29: =HX29+HY29 -> 0 | IA29: =HU29+HX29 -> 0 | IB29: =HV29+HY29 -> 0 | IC29: =IA29+IB29 -> 0 | JN29: =JG29+IW29+IM29+IC29 -> 0 | JZ29: =JX29+JN29+HO29+FB29 -> 518 | KA29: =SUM(JV29+JE29+IU29+IK29+IA29+HD29+GN29+GD29+FT29+ES29+EI29+DY29+DO29+CS29+CI29+BT29+BJ29+AO29+AE29+U29+K29) -> 545 | KB29: =SUM(JW29+JF29+IV29+IL29+IB29+HE29+GO29+GE29+FU29+ET29+EJ29+DZ29+DP29+CT29+CJ29+BU29+BK29+AP29+AF29+V29+L29) -> 33 | KC29: =SUM(JP29+IY29+IO29+IE29+HU29+GX29+GH29+FX29+FN29+EM29+EC29+DS29+DI29+CM29+CC29+BN29+BD29+AI29+Y29+O29+E29) -> 545 | KD29: =SUM(JQ29+IZ29+IP29+IF29+HV29+GY29+GI29+FY29+FO29+EN29+ED29+DT29+DJ29+CN29+CD29+BO29+BE29+AJ29+Z29+P29+F29) -> 33 | KE29: =SUM(JS29+JB29+IR29+IH29+HX29+HA29+GK29+GA29+FQ29+EP29+EF29+DV29+DL29+CP29+CF29+BQ29+BG29+AL29+AB29+R29+H29) -> 0 | KF29: =SUM(JT29+JC29+IS29+II29+HY29+HB29+GL29+GB29+FR29+EQ29+EG29+DW29+DM29+CQ29+CG29+BR29+BH29+AM29+AC29+S29+I29) -> 0 | KG29: =SUM(KA29:KB29) -> 578 | KH29: 450 | KI29: =KH29-KG29 -> -128 | KJ29: =KG29/KH29 -> 1.2844444 | KK29: =#REF!-KG29+#REF! -> #REF!
B30: Nakivale Total | AS30: =AS22+AS25+AS28+AS29 -> 415 | AT30: =AT22+AT25+AT28+AT29 -> 70 | AU30: =AU22+AU25+AU28+AU29 -> 397 | AV30: =AV22+AV25+AV28+AV29 -> 47 | AW30: =AW22+AW25+AW28+AW29 -> 0 | AX30: =AX22+AX25+AX28+AX29 -> 485 | AY30: =AY22+AY25+AY28+AY29 -> #DIV/0! | AZ30: =AZ22+AZ25+AZ28+AZ29 -> 336 | ... BC30: =BC22+BC25+BC28+BC29 -> 9 | CW30: =CW22+CW25+CW28+CW29 -> 2213 | CX30: =CX22+CX25+CX28+CX29 -> 564 | CY30: =CY22+CY25+CY28+CY29 -> 2453 | CZ30: =CZ22+CZ25+CZ28+CZ29 -> 1 | DA30: =DA22+DA25+DA28+DA29 -> 0 | DB30: =DB22+DB25+DB28+DB29 -> 2777 | DC30: =DC22+DC25+DC28+DC29 -> #DIV/0! | DD30: =DD22+DD25+DD28+DD29 -> 2212 | ... DH30: =DH22+DH25+DH28+DH29 -> 3262 | EW30: =EW22+EW25+EW28+EW29 -> 2273 | EX30: =EX22+EX25+EX28+EX29 -> 1128 | EY30: =EY22+EY25+EY28+EY29 -> 3401 | EZ30: =EZ22+EZ25+EZ28+EZ29 -> 0 | FA30: =FA22+FA25+FA28+FA29 -> 413 | FB30: =FB22+FB25+FB28+FB29 -> 3401 | FC30: =FC22+FC25+FC28+FC29 -> #DIV/0! | FD30: =FD22+FD25+FD28+FD29 -> 3559 | ... FG30: =FG22+FG25+FG28+FG29 -> 0 | GZ30: =GX30+GY30 -> 0 | HC30: =HA30+HB30 -> 0 | HD30: =GX30+HA30 -> 0 | HE30: =GY30+HB30 -> 0 | HF30: =HD30+HE30 -> 0 | HH30: =HH22+HH25+HH28+HH29 -> 3447 | HI30: =HI22+HI25+HI28+HI29 -> 539 | HJ30: =HJ22+HJ25+HJ28+HJ29 -> 3153 | HK30: =HK22+HK25+HK28+HK29 -> 539 | HL30: =HL22+HL25+HL28+HL29 -> 280 | HM30: =HM22+HM25+HM28+HM29 -> 0 | HN30: =HN22+HN25+HN28+HN29 -> 0 | HO30: =HO22+HO25+HO28+HO29 -> 3986 | ... HT30: =HT22+HT25+HT28+HT29 -> 0 | HW30: =HU30+HV30 -> 0 | HZ30: =HX30+HY30 -> 0 | IA30: =HU30+HX30 -> 0 | IB30: =HV30+HY30 -> 0 | IC30: =IA30+IB30 -> 0 | KA30: =SUM(JV30+JE30+IU30+IK30+IA30+HD30+GN30+GD30+FT30+ES30+EI30+DY30+DO30+CS30+CI30+BT30+BJ30+AO30+AE30+U30+K30) -> 0 | KB30: =SUM(JW30+JF30+IV30+IL30+IB30+HE30+GO30+GE30+FU30+ET30+EJ30+DZ30+DP30+CT30+CJ30+BU30+BK30+AP30+AF30+V30+L30) -> 0 | KC30: =SUM(JP30+IY30+IO30+IE30+HU30+GX30+GH30+FX30+FN30+EM30+EC30+DS30+DI30+CM30+CC30+BN30+BD30+AI30+Y30+O30+E30) -> 0 | KD30: =SUM(JQ30+IZ30+IP30+IF30+HV30+GY30+GI30+FY30+FO30+EN30+ED30+DT30+DJ30+CN30+CD30+BO30+BE30+AJ30+Z30+P30+F30) -> 0 | KE30: =SUM(JS30+JB30+IR30+IH30+HX30+HA30+GK30+GA30+FQ30+EP30+EF30+DV30+DL30+CP30+CF30+BQ30+BG30+AL30+AB30+R30+H30) -> 0 | KF30: =SUM(JT30+JC30+IS30+II30+HY30+HB30+GL30+GB30+FR30+EQ30+EG30+DW30+DM30+CQ30+CG30+BR30+BH30+AM30+AC30+S30+I30) -> 0
B31: Nyakabande Total | AS31: =AS23+AS24+AS26 -> 0 | AT31: =AT23+AT24+AT26 -> 0 | AU31: =AU23+AU24+AU26 -> 0 | AV31: =AV23+AV24+AV26 -> 0 | AW31: =AW23+AW24+AW26 -> 0 | AX31: =AX23+AX24+AX26 -> 0 | AY31: =AY23+AY24+AY26 -> 0 | AZ31: =AZ23+AZ24+AZ26 -> 0 | ... BC31: =BC23+BC24+BC26 -> 0 | CW31: =CW23+CW24+CW26 -> 1248 | CX31: =CX23+CX24+CX26 -> 1056 | CY31: =CY23+CY24+CY26 -> 2304 | CZ31: =CZ23+CZ24+CZ26 -> 0 | DD31: =DD23+DD24+DD26 -> 1248 | DE31: =DE23+DE24+DE26 -> 1056 | DF31: =DF23+DF24+DF26 -> 0 | DG31: =DG23+DG24+DG26 -> 0 | EW31: =EW23+EW24+EW26 -> 1534 | EX31: =EX23+EX24+EX26 -> 1733 | EY31: =EY23+EY24+EY26 -> 3267 | EZ31: =EZ23+EZ24+EZ26 -> 0 | FD31: =FD23+FD24+FD26 -> 2782 | FE31: =FE23+FE24+FE26 -> 2789 | FF31: =FF23+FF24+FF26 -> 0 | FG31: =FG23+FG24+FG26 -> 0 | GZ31: =GX31+GY31 -> 0 | HC31: =HA31+HB31 -> 0 | HD31: =GX31+HA31 -> 0 | HE31: =GY31+HB31 -> 0 | HF31: =HD31+HE31 -> 0 | HH31: =HH23+HH24+HH26 -> 1860 | HI31: =HI23+HI24+HI26 -> 1560 | HJ31: =HJ23+HJ24+HJ26 -> 1860 | HK31: =HK23+HK24+HK26 -> 1560 | HQ31: =HQ23+HQ24+HQ26 -> 1860 | HR31: =HR23+HR24+HR26 -> 1560 | HS31: =HS23+HS24+HS26 -> 0 | HT31: =HT23+HT24+HT26 -> 0 | HW31: =HU31+HV31 -> 0 | HZ31: =HX31+HY31 -> 0 | IA31: =HU31+HX31 -> 0 | IB31: =HV31+HY31 -> 0 | IC31: =IA31+IB31 -> 0 | KA31: =SUM(JV31+JE31+IU31+IK31+IA31+HD31+GN31+GD31+FT31+ES31+EI31+DY31+DO31+CS31+CI31+BT31+BJ31+AO31+AE31+U31+K31) -> 0 | KB31: =SUM(JW31+JF31+IV31+IL31+IB31+HE31+GO31+GE31+FU31+ET31+EJ31+DZ31+DP31+CT31+CJ31+BU31+BK31+AP31+AF31+V31+L31) -> 0 | KC31: =SUM(JP31+IY31+IO31+IE31+HU31+GX31+GH31+FX31+FN31+EM31+EC31+DS31+DI31+CM31+CC31+BN31+BD31+AI31+Y31+O31+E31) -> 0 | KD31: =SUM(JQ31+IZ31+IP31+IF31+HV31+GY31+GI31+FY31+FO31+EN31+ED31+DT31+DJ31+CN31+CD31+BO31+BE31+AJ31+Z31+P31+F31) -> 0 | KE31: =SUM(JS31+JB31+IR31+IH31+HX31+HA31+GK31+GA31+FQ31+EP31+EF31+DV31+DL31+CP31+CF31+BQ31+BG31+AL31+AB31+R31+H31) -> 0 | KF31: =SUM(JT31+JC31+IS31+II31+HY31+HB31+GL31+GB31+FR31+EQ31+EG31+DW31+DM31+CQ31+CG31+BR31+BH31+AM31+AC31+S31+I31) -> 0
A32: 2.5: Percentage of women and girls with specific protection needs (e.g., survivors of gender-based violence, persons with disabilities, | BX32: =BN32+BD32+AI32+Y32+O32+E32 -> 0 | BY32: =BO32+BE32+AJ32+Z32+P32+F32 -> 0 | BZ32: =BQ32+BG32+AL32+AB32+R32+H32 -> 0 | CA32: =BR32+BH32+AM32+AC32+S32+I32 -> 0 | CB32: =BX32+BY32+BZ32+CA32 -> 0 | DH32: =DB32+AX32 -> 0 | FD32: =DI32+DS32+EC32+EM32+CM32+CC32 -> 0 | FE32: =DJ32+DT32+ED32+EN32+CD32+CN32 -> 0 | FF32: =DL32+DV32+EF32+EP32+CP32+CF32 -> 0 | FG32: =DM32+DW32+EG32+EQ32+CG32+CQ32 -> 0 | FH32: =FD32+FF32 -> 0 | FI32: =FE32+FG32 -> 0 | FJ32: =FH32+FI32 -> 0 | FK32: =EW32+CW32+AS32 -> 0 | FL32: =EX32+CX32+AT32 -> 0 | FM32: =FK32+FL32 -> 0 | GD32: =FX32+GA32 -> 0 | GE32: =FY32+GB32 -> 0 | GF32: =GD32+GE32 -> 0 | GN32: =GH32+GK32 -> 0 | GO32: =GI32+GL32 -> 0 | GP32: =GN32+GO32 -> 0 | GR32: =GN32+GD32+FT32+ES32+EI32+DY32+DO32+CS32+CI32+BT32+BJ32 -> 0 | GS32: =GO32+GE32+FU32+ET32+EJ32+DZ32+DP32+CT32+CJ32+BU32+BK32 -> 0 | GT32: =GH32+FX32+FN32+EM32+EC32+DS32+DI32+CM32+CC32+BN32+BD32 -> 0 | GU32: =GI32+FY32+FO32+EN32+ED32+DT32+DJ32+CN32+CD32+BO32+BE32 -> 0 | GV32: =GK32+GA32+FQ32+EP32+EF32+DV32+DL32+CP32+CF32+BQ32+BG32 -> 0 | GW32: =GL32+GB32+FR32+EQ32+EG32+DW32+DM32+CQ32+CG32+BR32+BH32 -> 0 | GZ32: =GX32+GY32 -> 0 | HC32: =HA32+HB32 -> 0 | HD32: =GX32+HA32 -> 0 | HE32: =GY32+HB32 -> 0 | HF32: =HD32+HE32 -> 0 | HH32: =HD32+GN32+GD32+FT32 -> 0 | HI32: =GO32+GE32+FU32+HE32 -> 0 | HJ32: =GX32+GH32+FX32+FN32 -> 0 | HK32: =GI32+FY32+GY32+FO32 -> 0 | HL32: =GK32+GA32+FQ32+HA32 -> 0 | HM32: =GL32+HB32+GB32+FR32 -> 0 | HO32: =HF32+GP32+GF32+FV32 -> 0 | HW32: =HU32+HV32 -> 0 | HZ32: =HX32+HY32 -> 0 | IA32: =HU32+HX32 -> 0 | IB32: =HV32+HY32 -> 0 | IC32: =IA32+IB32 -> 0 | JN32: =JG32+IW32+IM32+IC32 -> 0 | JZ32: =JX32+JN32+HO32+FB32 -> 0 | KA32: =SUM(JV32+JE32+IU32+IK32+IA32+HD32+GN32+GD32+FT32+ES32+EI32+DY32+DO32+CS32+CI32+BT32+BJ32+AO32+AE32+U32+K32) -> 0 | KB32: =SUM(JW32+JF32+IV32+IL32+IB32+HE32+GO32+GE32+FU32+ET32+EJ32+DZ32+DP32+CT32+CJ32+BU32+BK32+AP32+AF32+V32+L32) -> 0 | KC32: =SUM(JP32+IY32+IO32+IE32+HU32+GX32+GH32+FX32+FN32+EM32+EC32+DS32+DI32+CM32+CC32+BN32+BD32+AI32+Y32+O32+E32) -> 0 | KD32: =SUM(JQ32+IZ32+IP32+IF32+HV32+GY32+GI32+FY32+FO32+EN32+ED32+DT32+DJ32+CN32+CD32+BO32+BE32+AJ32+Z32+P32+F32) -> 0 | KE32: =SUM(JS32+JB32+IR32+IH32+HX32+HA32+GK32+GA32+FQ32+EP32+EF32+DV32+DL32+CP32+CF32+BQ32+BG32+AL32+AB32+R32+H32) -> 0 | KF32: =SUM(JT32+JC32+IS32+II32+HY32+HB32+GL32+GB32+FR32+EQ32+EG32+DW32+DM32+CQ32+CG32+BR32+BH32+AM32+AC32+S32+I32) -> 0
A33: RESULT 3:Local partners effectively respond to Child Protection risks among new arrivals appropriate to their age, gender, and disability | AS33: =AO33+AE33+U33+K33 -> 0 | AT33: =AP33+AF33+V33+L33 -> 0 | AU33: =AK33+AA33+Q33+G33 -> 0 | AV33: =AN33 -> 0 | AX33: =SUM(AQ33+AG33+W33+M33) -> 0 | AZ33: =SUM(E33+O33+Y33+AI33) -> 0 | BA33: =F33+P33+Z33+AJ33 -> 0 | BB33: =H33+R33+AB33+AL33 -> 0 | BC33: =I33+S33+AC33+AM33 -> 0 | CW33: =SUM(CS33+CI33+BT33+BJ33) -> 0 | CX33: =SUM(CT33+CJ33+BU33+BK33) -> 0 | CY33: =SUM(CU33+CK33+BV33+BL33) -> 0 | CZ33: =SUM(CR33+CH33+BS33+BI33) -> 0 | DD33: =BD33+BN33+CC33+CM33 -> 0 | DE33: =BE33+BO33+CD33+CN33 -> 0 | DF33: =BG33+BQ33+CF33+CP33 -> 0 | DG33: =BH33+BR33+CG33+CQ33 -> 0 | DH33: =DB33+AX33 -> 0 | DY33: =SUM(DS33+DV33) -> 0 | DZ33: =SUM(DT33+DW33) -> 0 | EA33: =SUM(DY33:DZ33) -> 0 | EW33: =SUM(ES33+EI33+DY33+DO33) -> 0 | EX33: =SUM(ET33+EJ33+DZ33+DP33) -> 0 | EY33: =SUM(EO33+EE33+DU33+DK33) -> 0 | EZ33: =SUM(ER33+EH33+DX33+DN33) -> 0 | FB33: =SUM(EW33:EX33) -> 0 | FJ33: =FH33+FI33 -> 0 | FK33: =EW33+CW33+AS33 -> 0 | FL33: =EX33+CX33+AT33 -> 0 | FM33: =FK33+FL33 -> 0 | GD33: =FX33+GA33 -> 0 | GE33: =FY33+GB33 -> 0 | GF33: =GD33+GE33 -> 0 | GN33: =GH33+GK33 -> 0 | GO33: =GI33+GL33 -> 0 | GP33: =GN33+GO33 -> 0 | GR33: =GN33+GD33+FT33+ES33+EI33+DY33+DO33+CS33+CI33+BT33+BJ33 -> 0 | GS33: =GO33+GE33+FU33+ET33+EJ33+DZ33+DP33+CT33+CJ33+BU33+BK33 -> 0 | GT33: =GH33+FX33+FN33+EM33+EC33+DS33+DI33+CM33+CC33+BN33+BD33 -> #VALUE! | GU33: =GI33+FY33+FO33+EN33+ED33+DT33+DJ33+CN33+CD33+BO33+BE33 -> 0 | GV33: =GK33+GA33+FQ33+EP33+EF33+DV33+DL33+CP33+CF33+BQ33+BG33 -> 0 | GW33: =GL33+GB33+FR33+EQ33+EG33+DW33+DM33+CQ33+CG33+BR33+BH33 -> 0 | HH33: =HD33+GN33+GD33+FT33 -> 0 | HI33: =GO33+GE33+FU33+HE33 -> 0 | HJ33: =GX33+GH33+FX33+FN33 -> 0 | HK33: =GI33+FY33+GY33+FO33 -> 0 | HL33: =GK33+GA33+FQ33+HA33 -> 0 | HM33: =GL33+HB33+GB33+FR33 -> 0 | HO33: =HF33+GP33+GF33+FV33 -> 0 | HQ33: =FN33+FX33+GH33+GX33 -> 0 | HR33: =FO33+FY33+GI33+GY33 -> 0 | HS33: =FQ33+GA33+GK33+HA33 -> 0 | HT33: =FR33+GB33+GL33+HB33 -> 0 | HW33: =HU33+HV33 -> 0 | HZ33: =HX33+HY33 -> 0 | IA33: =HU33+HX33 -> 0 | IB33: =HV33+HY33 -> 0 | IC33: =IA33+IB33 -> 0 | JN33: =JG33+IW33+IM33+IC33 -> 0 | JZ33: =JX33+JN33+HO33+FB33 -> 0 | KA33: =SUM(JV33+JE33+IU33+IK33+IA33+HD33+GN33+GD33+FT33+ES33+EI33+DY33+DO33+CS33+CI33+BT33+BJ33+AO33+AE33+U33+K33) -> 0 | KB33: =SUM(JW33+JF33+IV33+IL33+IB33+HE33+GO33+GE33+FU33+ET33+EJ33+DZ33+DP33+CT33+CJ33+BU33+BK33+AP33+AF33+V33+L33) -> 0 | KC33: =SUM(JP33+IY33+IO33+IE33+HU33+GX33+GH33+FX33+FN33+EM33+EC33+DS33+DI33+CM33+CC33+BN33+BD33+AI33+Y33+O33+E33) -> #VALUE! | KD33: =SUM(JQ33+IZ33+IP33+IF33+HV33+GY33+GI33+FY33+FO33+EN33+ED33+DT33+DJ33+CN33+CD33+BO33+BE33+AJ33+Z33+P33+F33) -> 0 | KE33: =SUM(JS33+JB33+IR33+IH33+HX33+HA33+GK33+GA33+FQ33+EP33+EF33+DV33+DL33+CP33+CF33+BQ33+BG33+AL33+AB33+R33+H33) -> 0 | KF33: =SUM(JT33+JC33+IS33+II33+HY33+HB33+GL33+GB33+FR33+EQ33+EG33+DW33+DM33+CQ33+CG33+BR33+BH33+AM33+AC33+S33+I33) -> 0 | KK33: =KG34+KG35 -> 704 | KL33: =SUM(KI34:KI35) -> 2496
A34: Indicator 1: Number of persons who receive an appropriate response | B34: Case Management Provide appropriate case management support through documentation and reporting of cases (Nakivale 1350) | C34: Nakivale | D34: 1350 | O34: 3 | P34: 1 | Q34: =SUM(O34:P34) -> 4 | R34: 0 | S34: 0 | T34: =SUM(R34:S34) -> 0 | U34: =SUM(O34+R34) -> 3 | V34: =SUM(P34+S34) -> 1 | W34: =SUM(U34:V34) -> 4 | Y34: 4 | Z34: 0 | AA34: =SUM(Y34:Z34) -> 4 | AB34: 0 | AC34: 0 | AD34: =SUM(AB34:AC34) -> 0 | AE34: =SUM(Y34+AB34) -> 4 | AF34: =SUM(Z34+AC34) -> 0 | AG34: =SUM(AE34:AF34) -> 4 | AI34: 9 | AJ34: 3 | AK34: =SUM(AI34:AJ34) -> 12 | AL34: 0 | AM34: 0 | AN34: =SUM(AL34:AN34) -> 0 | AO34: =SUM(AI34+AL34) -> 9 | AP34: =SUM(AJ34+AM34) -> 3 | AQ34: =SUM(AO34:AP34) -> 12 | AS34: =AI34+Y34+O34+E34 -> 16 | AT34: =AJ34+Z34+P34+F34 -> 4 | AU34: =AK34+AA34+Q34+G34 -> 20 | AV34: =AN34 -> 0 | AX34: =SUM(AQ34+AG34+W34+M34) -> 20 | AY34: =AX34/AW34 -> #DIV/0! | AZ34: =SUM(E34+O34+Y34+AI34) -> 16 | BA34: =F34+P34+Z34+AJ34 -> 4 | BB34: =H34+R34+AB34+AL34 -> 0 | BC34: =I34+S34+AC34+AM34 -> 0 | BD34: 11 | BE34: 10 | BF34: =SUM(BD34:BE34) -> 21 | BG34: 0 | BH34: 0 | BI34: =SUM(BG34:BH34) -> 0 | BJ34: =SUM(BD34+BG34) -> 11 | BK34: =SUM(BE34+BH34) -> 10 | BL34: =SUM(BJ34:BK34) -> 21 | BN34: 17 | BO34: 18 | BP34: =SUM(BN34:BO34) -> 35 | BQ34: 0 | BR34: 0 | BT34: =SUM(BN34+BQ34) -> 17 | BU34: =SUM(BO34+BR34) -> 18 | BV34: =SUM(BT34:BU34) -> 35 | BX34: =BN34+BD34+AI34+Y34+O34+E34 -> 44 | BY34: =BO34+BE34+AJ34+Z34+P34+F34 -> 32 | BZ34: =BQ34+BG34+AL34+AB34+R34+H34 -> 0 | CA34: =BR34+BH34+AM34+AC34+S34+I34 -> 0 | CB34: =BX34+BY34+BZ34+CA34 -> 76 | CC34: 10 | CD34: 8 | CE34: =SUM(CC34:CD34) -> 18 | CF34: 0 | CG34: 0 | CH34: =SUM(CF34:CG34) -> 0 | CI34: =SUM(CC34+CF34) -> 10 | CJ34: =SUM(CD34+CG34) -> 8 | CK34: =SUM(CI34:CJ34) -> 18 | CM34: 26 | CN34: 44 | CO34: =SUM(CM34:CN34) -> 70 | CP34: 0 | CQ34: 0 | CR34: =SUM(CP34:CQ34) -> 0 | CS34: =SUM(CM34+CP34) -> 26 | CT34: =SUM(CN34+CQ34) -> 44 | CU34: =SUM(CS34:CT34) -> 70 | CV34: 0 | CW34: =BD34+BN34+CC34+CM34 -> 64 | CX34: =BO34+CD34+CN34+BE34 -> 80 | CY34: =SUM(CU34+CK34+BV34+BL34) -> 144 | CZ34: =SUM(CR34+CH34+BS34+BI34) -> 0 | DB34: =SUM(CW34:CX34) -> 144 | DD34: =BD34+BN34+CC34+CM34 -> 64 | DE34: =BE34+BO34+CD34+CN34 -> 80 | DF34: =BG34+BQ34+CF34+CP34 -> 0 | DG34: =BH34+BR34+CG34+CQ34 -> 0 | DH34: =DB34+AX34 -> 164 | DI34: 2 | DJ34: 4 | DK34: =SUM(DI34:DJ34) -> 6 | DL34: 0 | DM34: 0 | DN34: =SUM(DL34:DM34) -> 0 | DO34: =DI34+DL34 -> 2 | DP34: =DJ34+DM34 -> 4 | DQ34: =SUM(DO34+DP34) -> 6 | DR34: 0 | DS34: 2 | DT34: 4 | DU34: =SUM(DS34:DT34) -> 6 | DV34: 0 | DW34: 0 | DX34: =SUM(DV34:DW34) -> 0 | DY34: =SUM(DS34+DV34) -> 2 | DZ34: =SUM(DT34+DW34) -> 4 | EA34: =SUM(DY34:DZ34) -> 6 | EC34: 2 | ED34: 2 | EE34: =SUM(EC34:ED34) -> 4 | EF34: 0 | EG34: 0 | EH34: =SUM(EF34:EG34) -> 0 | EI34: =SUM(EC34+EF34) -> 2 | EJ34: =ED34+EG34 -> 2 | EK34: =SUM(EI34:EJ34) -> 4 | EM34: 19 | EN34: 8 | EO34: =SUM(EM34:EN34) -> 27 | EP34: 0 | EQ34: 0 | ER34: =SUM(EP34:EQ34) -> 0 | ES34: =SUM(EM34+EP34) -> 19 | ET34: =SUM(EN34+EQ34) -> 8 | EU34: =SUM(ES34:ET34) -> 27 | EW34: =EM34+EC34+DS34+DI34 -> 25 | EX34: =EN34+ED34+DT34+DJ34 -> 18 | EY34: =SUM(EO34+EE34+DU34+DK34) -> 43 | EZ34: =SUM(ER34+EH34+DX34+DN34) -> 0 | FA34: 100 | FB34: =SUM(EW34:EX34) -> 43 | FC34: =FB34/FA34 -> 0.43 | FD34: =DI34+DS34+EC34+EM34+CM34+CC34 -> 61 | FE34: =DJ34+DT34+ED34+EN34+CD34+CN34 -> 70 | FF34: =DL34+DV34+EF34+EP34+CP34+CF34 -> 0 | FG34: =DM34+DW34+EG34+EQ34+CG34+CQ34 -> 0 | FH34: =FD34+FF34 -> 61 | FI34: =FE34+FG34 -> 70 | FJ34: =FH34+FI34 -> 131 | FK34: =EW34+CW34+AS34 -> 105 | FL34: =EX34+CX34+AT34 -> 102 | FM34: =FK34+FL34 -> 207 | FN34: 2 | FO34: 2 | FP34: =SUM(FN34:FO34) -> 4 | FQ34: 0 | FR34: 0 | FS34: =SUM(FQ34:FR34) -> 0 | FT34: =SUM(FN34+FQ34) -> 2 | FU34: =SUM(FO34+FR34) -> 2 | FV34: =SUM(FT34:FU34) -> 4 | FX34: 0 | FY34: 2 | FZ34: =SUM(FX34:FY34) -> 2 | GA34: 0 | GB34: 0 | GC34: =SUM(GA34:GB34) -> 0 | GD34: =FX34+GA34 -> 0 | GE34: =FY34+GB34 -> 2 | GF34: =GD34+GE34 -> 2 | GH34: 78 | GI34: 71 | GJ34: =SUM(GH34:GI34) -> 149 | GK34: 0 | GL34: 0 | GM34: =GK34+GL34 -> 0 | GN34: =GH34+GK34 -> 78 | GO34: =GI34+GL34 -> 71 | GP34: =GN34+GO34 -> 149 | GR34: =GN34+GD34+FT34+ES34+EI34+DY34+DO34+CS34+CI34+BT34+BJ34 -> 169 | GS34: =GO34+GE34+FU34+ET34+EJ34+DZ34+DP34+CT34+CJ34+BU34+BK34 -> 173 | GT34: =GH34+FX34+FN34+EM34+EC34+DS34+DI34+CM34+CC34+BN34+BD34 -> 169 | GU34: =GI34+FY34+FO34+EN34+ED34+DT34+DJ34+CN34+CD34+BO34+BE34 -> 173 | GV34: =GK34+GA34+FQ34+EP34+EF34+DV34+DL34+CP34+CF34+BQ34+BG34 -> 0 | GW34: =GL34+GB34+FR34+EQ34+EG34+DW34+DM34+CQ34+CG34+BR34+BH34 -> 0 | GX34: 2 | GY34: 12 | GZ34: =GX34+GY34 -> 14 | HA34: 0 | HB34: 0 | HC34: =HA34+HB34 -> 0 | HD34: =GX34+HA34 -> 2 | HE34: =GY34+HB34 -> 12 | HF34: =HD34+HE34 -> 14 | HH34: =HD34+GN34+GD34+FT34 -> 82 | HI34: =GO34+GE34+FU34+HE34 -> 87 | HJ34: =GX34+GH34+FX34+FN34 -> 82 | HK34: =GI34+FY34+GY34+FO34 -> 87 | HL34: =GK34+GA34+FQ34+HA34 -> 0 | HM34: =GL34+HB34+GB34+FR34 -> 0 | HO34: =HF34+GP34+GF34+FV34 -> 169 | HQ34: =FN34+FX34+GH34+GX34 -> 82 | HR34: =FO34+FY34+GI34+GY34 -> 87 | HS34: =FQ34+GA34+GK34+HA34 -> 0 | HT34: =FR34+GB34+GL34+HB34 -> 0 | HU34: 25 | HV34: 28 | HW34: =HU34+HV34 -> 53 | HX34: 0 | HY34: 0 | HZ34: =HX34+HY34 -> 0 | IA34: =HU34+HX34 -> 25 | IB34: =HV34+HY34 -> 28 | IC34: =IA34+IB34 -> 53 | JN34: =JG34+IW34+IM34+IC34 -> 53 | JZ34: =JX34+JN34+HO34+FB34 -> 265 | KA34: =SUM(JV34+JE34+IU34+IK34+IA34+HD34+GN34+GD34+FT34+ES34+EI34+DY34+DO34+CS34+CI34+BT34+BJ34+AO34+AE34+U34+K34) -> 212 | KB34: =SUM(JW34+JF34+IV34+IL34+IB34+HE34+GO34+GE34+FU34+ET34+EJ34+DZ34+DP34+CT34+CJ34+BU34+BK34+AP34+AF34+V34+L34) -> 217 | KC34: =SUM(JP34+IY34+IO34+IE34+HU34+GX34+GH34+FX34+FN34+EM34+EC34+DS34+DI34+CM34+CC34+BN34+BD34+AI34+Y34+O34+E34) -> 212 | KD34: =SUM(JQ34+IZ34+IP34+IF34+HV34+GY34+GI34+FY34+FO34+EN34+ED34+DT34+DJ34+CN34+CD34+BO34+BE34+AJ34+Z34+P34+F34) -> 217 | KE34: =SUM(JS34+JB34+IR34+IH34+HX34+HA34+GK34+GA34+FQ34+EP34+EF34+DV34+DL34+CP34+CF34+BQ34+BG34+AL34+AB34+R34+H34) -> 0 | KF34: =SUM(JT34+JC34+IS34+II34+HY34+HB34+GL34+GB34+FR34+EQ34+EG34+DW34+DM34+CQ34+CG34+BR34+BH34+AM34+AC34+S34+I34) -> 0 | KG34: =SUM(KA34:KB34) -> 429 | KH34: 1200 | KI34: =KH34-KG34 -> 771 | KJ34: =KG34/KH34 -> 0.3575 | KK34: =KA34+KA35 -> 314 | KL34: =KC34+KC35 -> 314 | KM34: =SUM(KA34:KA35) -> 314
B35: Case Management Provide appropriate case management support through documentation and reporting of cases (Nyakabande 2000) | C35: Nyakabande | D35: 2000 | AS35: =AO35+AE35+U35+K35 -> 0 | AT35: =AP35+AF35+V35+L35 -> 0 | AU35: =AK35+AA35+Q35+G35 -> 0 | AV35: =AN35 -> 0 | AX35: =SUM(AQ35+AG35+W35+M35) -> 0 | AZ35: =SUM(E35+O35+Y35+AI35) -> 0 | BA35: =F35+P35+Z35+AJ35 -> 0 | BB35: =H35+R35+AB35+AL35 -> 0 | BC35: =I35+S35+AC35+AM35 -> 0 | BX35: =BN35+BD35+AI35+Y35+O35+E35 -> 0 | BY35: =BO35+BE35+AJ35+Z35+P35+F35 -> 0 | BZ35: =BQ35+BG35+AL35+AB35+R35+H35 -> 0 | CA35: =BR35+BH35+AM35+AC35+S35+I35 -> 0 | CB35: =BX35+BY35+BZ35+CA35 -> 0 | CM35: 8 | CN35: 18 | CO35: =SUM(CM35+CN35) -> 26 | CP35: 0 | CQ35: 0 | CR35: =SUM(CP35:CQ35) -> 0 | CS35: =SUM(CM35+CP35) -> 8 | CT35: =SUM(CN35+CQ35) -> 18 | CU35: =SUM(CS35:CT35) -> 26 | CW35: =BD35+BN35+CC35+CM35 -> 8 | CX35: =BO35+CD35+CN35+BE35 -> 18 | CY35: =SUM(CU35+CK35+BV35+BL35) -> 26 | CZ35: =SUM(CR35+CH35+BS35+BI35) -> 0 | DB35: =SUM(CW35:CX35) -> 26 | DD35: =BD35+BN35+CC35+CM35 -> 8 | DE35: =BE35+BO35+CD35+CN35 -> 18 | DF35: =BG35+BQ35+CF35+CP35 -> 0 | DG35: =BH35+BR35+CG35+CQ35 -> 0 | DH35: =DB35+AX35 -> 26 | DI35: 17 | DJ35: 33 | DK35: =SUM(DI35:DJ35) -> 50 | DL35: 0 | DM35: 0 | DN35: =SUM(DL35:DM35) -> 0 | DO35: =SUM(DI35+DL35) -> 17 | DP35: =SUM(DJ35+DM35) -> 33 | DQ35: =DO35+DP35 -> 50 | DS35: 17 | DT35: 33 | DU35: =SUM(DS35:DT35) -> 50 | DV35: 0 | DW35: 0 | DX35: =SUM(DV35:DW35) -> 0 | DY35: =SUM(DS35+DV35) -> 17 | DZ35: =SUM(DT35+DW35) -> 33 | EA35: =SUM(DY35:DZ35) -> 50 | EC35: 17 | ED35: 34 | EE35: =SUM(EC35:ED35) -> 51 | EF35: 0 | EG35: 0 | EH35: =SUM(EF35:EG35) -> 0 | EI35: =SUM(EC35+EF35) -> 17 | EJ35: =SUM(ED35+EG35) -> 34 | EK35: =SUM(EI35:EJ35) -> 51 | EM35: 9 | EN35: 14 | EO35: =SUM(EM35:EN35) -> 23 | EP35: 0 | EQ35: 0 | ER35: =SUM(EP35:EQ35) -> 0 | ES35: =SUM(EM35+EP35) -> 9 | ET35: =SUM(EN35+EQ35) -> 14 | EU35: =SUM(ES35:ET35) -> 23 | EW35: =EM35+EC35+DS35+DI35 -> 60 | EX35: =EN35+ED35+DT35+DJ35 -> 114 | EY35: =SUM(EO35+EE35+DU35+DK35) -> 174 | EZ35: =SUM(ER35+EH35+DX35+DN35) -> 0 | FB35: =SUM(EW35:EX35) -> 174 | FD35: =DI35+DS35+EC35+EM35+CM35+CC35 -> 68 | FE35: =DJ35+DT35+ED35+EN35+CD35+CN35 -> 132 | FF35: =DL35+DV35+EF35+EP35+CP35+CF35 -> 0 | FG35: =DM35+DW35+EG35+EQ35+CG35+CQ35 -> 0 | FH35: =FD35+FF35 -> 68 | FI35: =FE35+FG35 -> 132 | FJ35: =FH35+FI35 -> 200 | FK35: =EW35+CW35+AS35 -> 68 | FL35: =EX35+CX35+AT35 -> 132 | FM35: =FK35+FL35 -> 200 | FN35: 2 | FO35: 6 | FP35: =SUM(FN35:FO35) -> 8 | FQ35: 0 | FR35: 0 | FS35: =SUM(FQ35:FR35) -> 0 | FT35: =SUM(FN35+FQ35) -> 2 | FU35: =SUM(FO35+FR35) -> 6 | FV35: =SUM(FT35:FU35) -> 8 | FX35: 17 | FY35: 17 | FZ35: =SUM(FX35:FY35) -> 34 | GA35: 0 | GB35: 0 | GC35: =SUM(GA35:GB35) -> 0 | GD35: =FX35+GA35 -> 17 | GE35: =FY35+GB35 -> 17 | GF35: =GD35+GE35 -> 34 | GH35: 0 | GI35: 2 | GJ35: =SUM(GH35:GI35) -> 2 | GK35: 0 | GL35: 0 | GM35: =GK35+GL35 -> 0 | GN35: =GH35+GK35 -> 0 | GO35: =GI35+GL35 -> 2 | GP35: =GN35+GO35 -> 2 | GR35: =GN35+GD35+FT35+ES35+EI35+DY35+DO35+CS35+CI35+BT35+BJ35 -> 87 | GS35: =GO35+GE35+FU35+ET35+EJ35+DZ35+DP35+CT35+CJ35+BU35+BK35 -> 157 | GT35: =GH35+FX35+FN35+EM35+EC35+DS35+DI35+CM35+CC35+BN35+BD35 -> 87 | GU35: =GI35+FY35+FO35+EN35+ED35+DT35+DJ35+CN35+CD35+BO35+BE35 -> 157 | GV35: =GK35+GA35+FQ35+EP35+EF35+DV35+DL35+CP35+CF35+BQ35+BG35 -> 0 | GW35: =GL35+GB35+FR35+EQ35+EG35+DW35+DM35+CQ35+CG35+BR35+BH35 -> 0 | GX35: 8 | GY35: 10 | GZ35: =GX35+GY35 -> 18 | HA35: 0 | HB35: 0 | HC35: =HA35+HB35 -> 0 | HD35: =GX35+HA35 -> 8 | HE35: =GY35+HB35 -> 10 | HF35: =HD35+HE35 -> 18 | HH35: =HD35+GN35+GD35+FT35 -> 27 | HI35: =GO35+GE35+FU35+HE35 -> 35 | HJ35: =GX35+GH35+FX35+FN35 -> 27 | HK35: =GI35+FY35+GY35+FO35 -> 35 | HL35: =GK35+GA35+FQ35+HA35 -> 0 | HM35: =GL35+HB35+GB35+FR35 -> 0 | HO35: =HF35+GP35+GF35+FV35 -> 62 | HQ35: =FN35+FX35+GH35+GX35 -> 27 | HR35: =FO35+FY35+GI35+GY35 -> 35 | HS35: =FQ35+GA35+GK35+HA35 -> 0 | HT35: =FR35+GB35+GL35+HB35 -> 0 | HU35: 7 | HV35: 6 | HW35: =HU35+HV35 -> 13 | HX35: 0 | HY35: 0 | HZ35: =HX35+HY35 -> 0 | IA35: =HU35+HX35 -> 7 | IB35: =HV35+HY35 -> 6 | IC35: =IA35+IB35 -> 13 | JN35: =JG35+IW35+IM35+IC35 -> 13 | JZ35: =JX35+JN35+HO35+FB35 -> 249 | KA35: =SUM(JV35+JE35+IU35+IK35+IA35+HD35+GN35+GD35+FT35+ES35+EI35+DY35+DO35+CS35+CI35+BT35+BJ35+AO35+AE35+U35+K35) -> 102 | KB35: =SUM(JW35+JF35+IV35+IL35+IB35+HE35+GO35+GE35+FU35+ET35+EJ35+DZ35+DP35+CT35+CJ35+BU35+BK35+AP35+AF35+V35+L35) -> 173 | KC35: =SUM(JP35+IY35+IO35+IE35+HU35+GX35+GH35+FX35+FN35+EM35+EC35+DS35+DI35+CM35+CC35+BN35+BD35+AI35+Y35+O35+E35) -> 102 | KD35: =SUM(JQ35+IZ35+IP35+IF35+HV35+GY35+GI35+FY35+FO35+EN35+ED35+DT35+DJ35+CN35+CD35+BO35+BE35+AJ35+Z35+P35+F35) -> 173 | KE35: =SUM(JS35+JB35+IR35+IH35+HX35+HA35+GK35+GA35+FQ35+EP35+EF35+DV35+DL35+CP35+CF35+BQ35+BG35+AL35+AB35+R35+H35) -> 0 | KF35: =SUM(JT35+JC35+IS35+II35+HY35+HB35+GL35+GB35+FR35+EQ35+EG35+DW35+DM35+CQ35+CG35+BR35+BH35+AM35+AC35+S35+I35) -> 0 | KG35: =SUM(KA35:KB35) -> 275 | KH35: 2000 | KI35: =KH35-KG35 -> 1725 | KJ35: =KG35/KH35 -> 0.1375 | KK35: =KB34+KB35 -> 390 | KL35: =KB34+KB35 -> 390 | KM35: =SUM(KL34:KM34) -> 628
B36: Referrals zCase Management & referrals to service providers - Provide Individual Protection Assistance to children like blankets, sleeping mats, clothes.etc | C36: Nakivale | D36: 600 | O36: 3 | P36: 1 | Q36: =SUM(O36:P36) -> 4 | R36: 0 | S36: 0 | T36: =SUM(R36:S36) -> 0 | U36: =SUM(O36+R36) -> 3 | V36: =SUM(P36+S36) -> 1 | W36: =SUM(U36:V36) -> 4 | Y36: 4 | Z36: 0 | AA36: =SUM(Y36:Z36) -> 4 | AB36: 0 | AC36: 0 | AD36: =SUM(AB36:AC36) -> 0 | AE36: =SUM(Y36+AB36) -> 4 | AF36: =SUM(Z36+AC36) -> 0 | AG36: =SUM(AE36:AF36) -> 4 | AI36: 9 | AJ36: 3 | AK36: =SUM(AI36:AJ36) -> 12 | AL36: 0 | AM36: 0 | AN36: =SUM(AL36:AM36) -> 0 | AO36: =SUM(AI36+AL36) -> 9 | AP36: =SUM(AJ36+AM36) -> 3 | AQ36: =SUM(AO36:AP36) -> 12 | AS36: =AO36+AE36+U36+K36 -> 16 | AT36: =AP36+AF36+V36+L36 -> 4 | AU36: =AK36+AA36+Q36+G36 -> 20 | AV36: =AN36 -> 0 | AX36: =SUM(AQ36+AG36+W36+M36) -> 20 | AY36: =AX36/AW36 -> #DIV/0! | AZ36: =SUM(E36+O36+Y36+AI36) -> 16 | BA36: =F36+P36+Z36+AJ36 -> 4 | BB36: =H36+R36+AB36+AL36 -> 0 | BC36: =I36+S36+AC36+AM36 -> 0 | BD36: 11 | BE36: 10 | BF36: =SUM(BD36:BE36) -> 21 | BG36: 0 | BH36: 0 | BI36: =SUM(BG36:BH36) -> 0 | BJ36: =SUM(BD36+BG36) -> 11 | BK36: =SUM(BE36+BH36) -> 10 | BL36: =SUM(BJ36:BK36) -> 21 | BN36: 17 | BO36: 18 | BP36: =SUM(BN36:BO36) -> 35 | BQ36: 0 | BR36: 0 | BT36: =SUM(BN36+BQ36) -> 17 | BU36: =SUM(BO36+BR36) -> 18 | BV36: =SUM(BT36:BU36) -> 35 | BX36: =BN36+BD36+AI36+Y36+O36+E36 -> 44 | BY36: =BO36+BE36+AJ36+Z36+P36+F36 -> 32 | BZ36: =BQ36+BG36+AL36+AB36+R36+H36 -> 0 | CA36: =BR36+BH36+AM36+AC36+S36+I36 -> 0 | CB36: =BX36+BY36+BZ36+CA36 -> 76 | CC36: 10 | CD36: 8 | CE36: =SUM(CC36:CD36) -> 18 | CF36: 0 | CG36: 0 | CH36: =SUM(CF36:CG36) -> 0 | CI36: =SUM(CC36+CF36) -> 10 | CJ36: =SUM(CD36+CG36) -> 8 | CK36: =SUM(CI36:CJ36) -> 18 | CM36: 58 | CN36: 69 | CO36: =SUM(CM36:CN36) -> 127 | CP36: 0 | CQ36: 0 | CR36: =SUM(CP36:CQ36) -> 0 | CS36: =SUM(CM36+CP36) -> 58 | CT36: =SUM(CN36+CQ36) -> 69 | CU36: =SUM(CS36:CT36) -> 127 | CW36: =SUM(CS36+CI36+BT36+BJ36) -> 96 | CX36: =SUM(CT36+CJ36+BU36+BK36) -> 105 | CY36: =SUM(CU36+CK36+BV36+BL36) -> 201 | CZ36: =SUM(CR36+CH36+BS36+BI36) -> 0 | DB36: =SUM(CW36:CX36) -> 201 | DD36: =BD36+BN36+CC36+CM36 -> 96 | DE36: =BE36+BO36+CD36+CN36 -> 105 | DF36: =BG36+BQ36+CF36+CP36 -> 0 | DG36: =BH36+BR36+CG36+CQ36 -> 0 | DH36: =DB36+AX36 -> 221 | DI36: 6 | DJ36: 5 | DK36: =SUM(DI36:DJ36) -> 11 | DL36: 0 | DM36: 0 | DN36: =SUM(DL36:DM36) -> 0 | DO36: =DI36 -> 6 | DP36: =DJ36 -> 5 | DQ36: =SUM(DO36:DP36) -> 11 | DR36: =DN36 -> 0 | DS36: 5 | DT36: 9 | DU36: =SUM(DS36:DT36) -> 14 | DV36: 0 | DW36: 0 | DX36: =SUM(DV36:DW36) -> 0 | DY36: =SUM(DS36+DV36) -> 5 | DZ36: =SUM(DT36+DW36) -> 9 | EA36: =SUM(DY36:DZ36) -> 14 | EC36: 2 | ED36: 0 | EE36: =SUM(EC36:ED36) -> 2 | EF36: 0 | EG36: 0 | EH36: =SUM(EF36:EG36) -> 0 | EI36: =SUM(EC36+EF36) -> 2 | EJ36: =SUM(ED36+EG36) -> 0 | EK36: =SUM(EI36:EJ36) -> 2 | EM36: 14 | EN36: 27 | EO36: =SUM(EM36:EN36) -> 41 | EP36: 0 | EQ36: 0 | ER36: =SUM(EP36:EQ36) -> 0 | ES36: =SUM(EM36+EP36) -> 14 | ET36: =SUM(EN36+EQ36) -> 27 | EU36: =SUM(ES36:ET36) -> 41 | EW36: =SUM(ES36+EI36+DY36+DO36) -> 27 | EX36: =SUM(ET36+EJ36+DZ36+DP36) -> 41 | EY36: =SUM(EO36+EE36+DU36+DK36) -> 68 | EZ36: =SUM(ER36+EH36+DX36+DN36) -> 0 | FB36: =SUM(EW36:EX36) -> 68 | FD36: =DI36+DS36+EC36+EM36+CM36+CC36 -> 95 | FE36: =DJ36+DT36+ED36+EN36+CD36+CN36 -> 118 | FF36: =DL36+DV36+EF36+EP36+CP36+CF36 -> 0 | FG36: =DM36+DW36+EG36+EQ36+CG36+CQ36 -> 0 | FH36: =FD36+FF36 -> 95 | FI36: =FE36+FG36 -> 118 | FJ36: =FH36+FI36 -> 213 | FK36: =EW36+CW36+AS36 -> 139 | FL36: =EX36+CX36+AT36 -> 150 | FM36: =FK36+FL36 -> 289 | FN36: 51 | FO36: 64 | FP36: =SUM(FN36:FO36) -> 115 | FQ36: 0 | FR36: 0 | FS36: =SUM(FQ36:FR36) -> 0 | FT36: =SUM(FN36+FQ36) -> 51 | FU36: =SUM(FO36+FR36) -> 64 | FV36: =SUM(FT36:FU36) -> 115 | FX36: 37 | FY36: 16 | FZ36: =SUM(FX36:FY36) -> 53 | GA36: 0 | GB36: 0 | GC36: =SUM(GA36:GB36) -> 0 | GD36: =FX36+GA36 -> 37 | GE36: =FY36+GB36 -> 16 | GF36: =GD36+GE36 -> 53 | GH36: 155 | GI36: 160 | GJ36: =SUM(GH36:GI36) -> 315 | GK36: 0 | GL36: 0 | GM36: =GK36+GL36 -> 0 | GN36: =GH36+GK36 -> 155 | GO36: =GI36+GL36 -> 160 | GP36: =GN36+GO36 -> 315 | GR36: =GN36+GD36+FT36+ES36+EI36+DY36+DO36+CS36+CI36+BT36+BJ36 -> 366 | GS36: =GO36+GE36+FU36+ET36+EJ36+DZ36+DP36+CT36+CJ36+BU36+BK36 -> 386 | GT36: =GH36+FX36+FN36+EM36+EC36+DS36+DI36+CM36+CC36+BN36+BD36 -> 366 | GU36: =GI36+FY36+FO36+EN36+ED36+DT36+DJ36+CN36+CD36+BO36+BE36 -> 386 | GV36: =GK36+GA36+FQ36+EP36+EF36+DV36+DL36+CP36+CF36+BQ36+BG36 -> 0 | GW36: =GL36+GB36+FR36+EQ36+EG36+DW36+DM36+CQ36+CG36+BR36+BH36 -> 0 | GZ36: =GX36+GY36 -> 0 | HC36: =HA36+HB36 -> 0 | HD36: =GX36+HA36 -> 0 | HE36: =GY36+HB36 -> 0 | HF36: =HD36+HE36 -> 0 | HH36: =HD36+GN36+GD36+FT36 -> 243 | HI36: =GO36+GE36+FU36+HE36 -> 240 | HJ36: =GX36+GH36+FX36+FN36 -> 243 | HK36: =GI36+FY36+GY36+FO36 -> 240 | HL36: =GK36+GA36+FQ36+HA36 -> 0 | HM36: =GL36+HB36+GB36+FR36 -> 0 | HO36: =HF36+GP36+GF36+FV36 -> 483 | HQ36: =FN36+FX36+GH36+GX36 -> 243 | HR36: =FO36+FY36+GI36+GY36 -> 240 | HS36: =FQ36+GA36+GK36+HA36 -> 0 | HT36: =FR36+GB36+GL36+HB36 -> 0 | HU36: 117 | HV36: 111 | HW36: =HU36+HV36 -> 228 | HX36: 0 | HY36: 0 | HZ36: =HX36+HY36 -> 0 | IA36: =HU36+HX36 -> 117 | IB36: =HV36+HY36 -> 111 | IC36: =IA36+IB36 -> 228 | JN36: =JG36+IW36+IM36+IC36 -> 228 | JZ36: =JX36+JN36+HO36+FB36 -> 779 | KA36: =SUM(JV36+JE36+IU36+IK36+IA36+HD36+GN36+GD36+FT36+ES36+EI36+DY36+DO36+CS36+CI36+BT36+BJ36+AO36+AE36+U36+K36) -> 499 | KB36: =SUM(JW36+JF36+IV36+IL36+IB36+HE36+GO36+GE36+FU36+ET36+EJ36+DZ36+DP36+CT36+CJ36+BU36+BK36+AP36+AF36+V36+L36) -> 501 | KC36: =SUM(JP36+IY36+IO36+IE36+HU36+GX36+GH36+FX36+FN36+EM36+EC36+DS36+DI36+CM36+CC36+BN36+BD36+AI36+Y36+O36+E36) -> 499 | KD36: =SUM(JQ36+IZ36+IP36+IF36+HV36+GY36+GI36+FY36+FO36+EN36+ED36+DT36+DJ36+CN36+CD36+BO36+BE36+AJ36+Z36+P36+F36) -> 501 | KE36: =SUM(JS36+JB36+IR36+IH36+HX36+HA36+GK36+GA36+FQ36+EP36+EF36+DV36+DL36+CP36+CF36+BQ36+BG36+AL36+AB36+R36+H36) -> 0 | KF36: =SUM(JT36+JC36+IS36+II36+HY36+HB36+GL36+GB36+FR36+EQ36+EG36+DW36+DM36+CQ36+CG36+BR36+BH36+AM36+AC36+S36+I36) -> 0 | KG36: =SUM(KA36:KB36) -> 1000 | KH36: 600 | KI36: =KH36-KG36 -> -400 | KJ36: =KG36/KH36 -> 1.6666667 | KK36: =KA36+KA37 -> 555 | KL36: =SUM(EX36+CX36+AT36)+10 -> 160 | KM36: =SUM(KI34:KI35) -> 2496
B37: Referrals Case Management & referrals to service providers - Provide Individual Protection Assistance to children like blankets, sleeping mats, clothes.etc | C37: Nyakabande | D37: 600 | AS37: =AO37+AE37+U37+K37 -> 0 | AT37: =AP37+AF37+V37+L37 -> 0 | AU37: =AK37+AA37+Q37+G37 -> 0 | AV37: =AN37 -> 0 | AX37: =SUM(AQ37+AG37+W37+M37) -> 0 | AZ37: =SUM(E37+O37+Y37+AI37) -> 0 | BA37: =F37+P37+Z37+AJ37 -> 0 | BB37: =H37+R37+AB37+AL37 -> 0 | BC37: =I37+S37+AC37+AM37 -> 0 | BX37: =BN37+BD37+AI37+Y37+O37+E37 -> 0 | BY37: =BO37+BE37+AJ37+Z37+P37+F37 -> 0 | BZ37: =BQ37+BG37+AL37+AB37+R37+H37 -> 0 | CA37: =BR37+BH37+AM37+AC37+S37+I37 -> 0 | CB37: =BX37+BY37+BZ37+CA37 -> 0 | CC37: =BT34+BJ34+AO34+AE34+U34 -> 44 | CM37: 1 | CN37: 10 | CO37: =SUM(CM37:CN37) -> 11 | CP37: 0 | CQ37: 0 | CR37: =SUM(CP37:CQ37) -> 0 | CW37: =SUM(CS37+CI37+BT37+BJ37) -> 0 | CX37: =SUM(CT37+CJ37+BU37+BK37) -> 0 | CY37: =SUM(CU37+CK37+BV37+BL37) -> 0 | CZ37: =SUM(CR37+CH37+BS37+BI37) -> 0 | DD37: =BD37+BN37+CC37+CM37 -> 45 | DE37: =BE37+BO37+CD37+CN37 -> 10 | DF37: =BG37+BQ37+CF37+CP37 -> 0 | DG37: =BH37+BR37+CG37+CQ37 -> 0 | DH37: =DB37+AX37 -> 0 | DK37: =SUM(DI37:DJ37) -> 0 | DL37: 0 | DM37: 0 | DN37: =SUM(DL37:DM37) -> 0 | DO37: =SUM(DI37+DL37) -> 0 | DP37: =SUM(DJ37+DM37) -> 0 | DQ37: =SUM(DO37:DP37) -> 0 | DS37: 19 | DT37: 29 | DU37: =SUM(DS37:DT37) -> 48 | DV37: 0 | DW37: 0 | DX37: =SUM(DV37:DW37) -> 0 | DY37: =SUM(DS37+DV37) -> 19 | DZ37: =SUM(DT37+DW37) -> 29 | EA37: =SUM(DY37:DZ37) -> 48 | EC37: 6 | ED37: 9 | EE37: =SUM(EC37:ED37) -> 15 | EF37: 0 | EG37: 0 | EH37: =SUM(EF37:EG37) -> 0 | EI37: =SUM(EC37+EF37) -> 6 | EJ37: =SUM(ED37+EG37) -> 9 | EK37: =SUM(EI37:EJ37) -> 15 | EM37: 27 | EN37: 26 | EO37: =SUM(EM37:EN37) -> 53 | EP37: 0 | EQ37: 0 | ER37: =SUM(EP37:EQ37) -> 0 | ES37: =SUM(EM37+EP37) -> 27 | ET37: =SUM(EN37+EQ37) -> 26 | EU37: =SUM(ES37:ET37) -> 53 | EW37: =SUM(ES37+EI37+DY37+DO37) -> 52 | EX37: =SUM(ET37+EJ37+DZ37+DP37) -> 64 | EY37: =SUM(EO37+EE37+DU37+DK37) -> 116 | EZ37: =SUM(ER37+EH37+DX37+DN37) -> 0 | FB37: =SUM(EW37:EX37) -> 116 | FD37: =DI37+DS37+EC37+EM37+CM37+CC37 -> 97 | FE37: =DJ37+DT37+ED37+EN37+CD37+CN37 -> 74 | FF37: =DL37+DV37+EF37+EP37+CP37+CF37 -> 0 | FG37: =DM37+DW37+EG37+EQ37+CG37+CQ37 -> 0 | FH37: =FD37+FF37 -> 97 | FI37: =FE37+FG37 -> 74 | FJ37: =FH37+FI37 -> 171 | FK37: =EW37+CW37+AS37 -> 52 | FL37: =EX37+CX37+AT37 -> 64 | FM37: =FK37+FL37 -> 116 | FN37: 1 | FO37: 8 | FP37: =SUM(FN37:FO37) -> 9 | FQ37: 0 | FR37: 0 | FS37: =SUM(FQ37:FR37) -> 0 | FT37: =SUM(FN37+FQ37) -> 1 | FU37: =SUM(FO37+FR37) -> 8 | FV37: =SUM(FT37:FU37) -> 9 | FX37: 1 | FY37: 0 | FZ37: =SUM(FX37:FY37) -> 1 | GA37: 0 | GB37: 0 | GC37: =SUM(GA37:GB37) -> 0 | GD37: =FX37+GA37 -> 1 | GE37: =FY37+GB37 -> 0 | GF37: =GD37+GE37 -> 1 | GH37: 2 | GI37: 6 | GJ37: =SUM(GH37:GI37) -> 8 | GK37: 0 | GL37: 0 | GM37: =GK37+GL37 -> 0 | GN37: =GH37+GK37 -> 2 | GO37: =GI37+GL37 -> 6 | GP37: =GN37+GO37 -> 8 | GR37: =GN37+GD37+FT37+ES37+EI37+DY37+DO37+CS37+CI37+BT37+BJ37 -> 56 | GS37: =GO37+GE37+FU37+ET37+EJ37+DZ37+DP37+CT37+CJ37+BU37+BK37 -> 78 | GT37: =GH37+FX37+FN37+EM37+EC37+DS37+DI37+CM37+CC37+BN37+BD37 -> 101 | GU37: =GI37+FY37+FO37+EN37+ED37+DT37+DJ37+CN37+CD37+BO37+BE37 -> 88 | GV37: =GK37+GA37+FQ37+EP37+EF37+DV37+DL37+CP37+CF37+BQ37+BG37 -> 0 | GW37: =GL37+GB37+FR37+EQ37+EG37+DW37+DM37+CQ37+CG37+BR37+BH37 -> 0 | GZ37: =GX37+GY37 -> 0 | HC37: =HA37+HB37 -> 0 | HD37: =GX37+HA37 -> 0 | HE37: =GY37+HB37 -> 0 | HF37: =HD37+HE37 -> 0 | HH37: =HD37+GN37+GD37+FT37 -> 4 | HI37: =GO37+GE37+FU37+HE37 -> 14 | HJ37: =GX37+GH37+FX37+FN37 -> 4 | HK37: =GI37+FY37+GY37+FO37 -> 14 | HL37: =GK37+GA37+FQ37+HA37 -> 0 | HM37: =GL37+HB37+GB37+FR37 -> 0 | HO37: =HF37+GP37+GF37+FV37 -> 18 | HQ37: =FN37+FX37+GH37+GX37 -> 4 | HR37: =FO37+FY37+GI37+GY37 -> 14 | HS37: =FQ37+GA37+GK37+HA37 -> 0 | HT37: =FR37+GB37+GL37+HB37 -> 0 | HW37: =HU37+HV37 -> 0 | HZ37: =HX37+HY37 -> 0 | IA37: =HU37+HX37 -> 0 | IB37: =HV37+HY37 -> 0 | IC37: =IA37+IB37 -> 0 | JN37: =JG37+IW37+IM37+IC37 -> 0 | JZ37: =JX37+JN37+HO37+FB37 -> 134 | KA37: =SUM(JV37+JE37+IU37+IK37+IA37+HD37+GN37+GD37+FT37+ES37+EI37+DY37+DO37+CS37+CI37+BT37+BJ37+AO37+AE37+U37+K37) -> 56 | KB37: =SUM(JW37+JF37+IV37+IL37+IB37+HE37+GO37+GE37+FU37+ET37+EJ37+DZ37+DP37+CT37+CJ37+BU37+BK37+AP37+AF37+V37+L37) -> 78 | KC37: =SUM(JP37+IY37+IO37+IE37+HU37+GX37+GH37+FX37+FN37+EM37+EC37+DS37+DI37+CM37+CC37+BN37+BD37+AI37+Y37+O37+E37) -> 101 | KD37: =SUM(JQ37+IZ37+IP37+IF37+HV37+GY37+GI37+FY37+FO37+EN37+ED37+DT37+DJ37+CN37+CD37+BO37+BE37+AJ37+Z37+P37+F37) -> 88 | KE37: =SUM(JS37+JB37+IR37+IH37+HX37+HA37+GK37+GA37+FQ37+EP37+EF37+DV37+DL37+CP37+CF37+BQ37+BG37+AL37+AB37+R37+H37) -> 0 | KF37: =SUM(JT37+JC37+IS37+II37+HY37+HB37+GL37+GB37+FR37+EQ37+EG37+DW37+DM37+CQ37+CG37+BR37+BH37+AM37+AC37+S37+I37) -> 0 | KG37: =SUM(KA37:KB37) -> 134 | KH37: 600 | KI37: =KH37-KG37 -> 466 | KJ37: =KG37/KH37 -> 0.22333333 | KK37: =KB36+KB37 -> 579 | KM37: =SVT9 -> 0
B38: Case Conferencing | C38: Nakivale | D38: 8 | AS38: =AO38+AE38+U38+K38 -> 0 | AT38: =AP38+AF38+V38+L38 -> 0 | AU38: =AK38+AA38+Q38+G38 -> 0 | AV38: =AN38 -> 0 | AX38: =SUM(AQ38+AG38+W38+M38) -> 0 | AY38: =AX38/AW38 -> #DIV/0! | AZ38: =SUM(E38+O38+Y38+AI38) -> 0 | BA38: =F38+P38+Z38+AJ38 -> 0 | BB38: =H38+R38+AB38+AL38 -> 0 | BC38: =I38+S38+AC38+AM38 -> 0 | BX38: =BN38+BD38+AI38+Y38+O38+E38 -> 0 | BY38: =BO38+BE38+AJ38+Z38+P38+F38 -> 0 | BZ38: =BQ38+BG38+AL38+AB38+R38+H38 -> 0 | CA38: =BR38+BH38+AM38+AC38+S38+I38 -> 0 | CB38: =BX38+BY38+BZ38+CA38 -> 0 | CW38: =SUM(CS38+CI38+BT38+BJ38) -> 0 | CX38: =SUM(CT38+CJ38+BU38+BK38) -> 0 | CY38: =SUM(CU38+CK38+BV38+BL38) -> 0 | CZ38: =SUM(CR38+CH38+BS38+BI38) -> 0 | DB38: =SUM(CW38:CX38) -> 0 | DD38: =BD38+BN38+CC38+CM38 -> 0 | DE38: =BE38+BO38+CD38+CN38 -> 0 | DF38: =BG38+BQ38+CF38+CP38 -> 0 | DG38: =BH38+BR38+CG38+CQ38 -> 0 | DH38: =DB38+AX38 -> 0 | DU38: =SUM(DS38:DT38) -> 0 | DX38: =SUM(DV38:DW38) -> 0 | DY38: =SUM(DS38+DV38) -> 0 | DZ38: 1 | EA38: =SUM(DY38:DZ38) -> 1 | EJ38: 5 | EK38: 0 | EW38: =SUM(ES38+EI38+DY38+DO38) -> 0 | EX38: =SUM(ET38+EJ38+DZ38+DP38) -> 6 | EY38: =SUM(EO38+EE38+DU38+DK38) -> 0 | EZ38: =SUM(ER38+EH38+DX38+DN38) -> 0 | FB38: =SUM(EW38:EX38) -> 6 | FD38: =DI38+DS38+EC38+EM38+CM38+CC38 -> 0 | FE38: =DJ38+DT38+ED38+EN38+CD38+CN38 -> 0 | FF38: =DL38+DV38+EF38+EP38+CP38+CF38 -> 0 | FG38: =DM38+DW38+EG38+EQ38+CG38+CQ38 -> 0 | FH38: =FD38+FF38 -> 0 | FI38: =FE38+FG38 -> 0 | FJ38: =FH38+FI38 -> 0 | FK38: =EW38+CW38+AS38 -> 0 | FL38: =EX38+CX38+AT38 -> 6 | FM38: =FK38+FL38 -> 6 | FP38: 2 | FT38: =SUM(FN38+FQ38) -> 0 | FU38: =SUM(FO38+FR38) -> 0 | FV38: =SUM(FT38:FU38) -> 0 | FZ38: 2 | GD38: =FX38+GA38 -> 0 | GE38: =FY38+GB38 -> 0 | GF38: =GD38+GE38 -> 0 | GN38: =GH38+GK38 -> 0 | GO38: =GI38+GL38 -> 0 | GP38: =GN38+GO38 -> 0 | GR38: =GN38+GD38+FT38+ES38+EI38+DY38+DO38+CS38+CI38+BT38+BJ38 -> 0 | GS38: =GO38+GE38+FU38+ET38+EJ38+DZ38+DP38+CT38+CJ38+BU38+BK38 -> 6 | GT38: =GH38+FX38+FN38+EM38+EC38+DS38+DI38+CM38+CC38+BN38+BD38 -> 0 | GU38: =GI38+FY38+FO38+EN38+ED38+DT38+DJ38+CN38+CD38+BO38+BE38 -> 0 | GV38: =GK38+GA38+FQ38+EP38+EF38+DV38+DL38+CP38+CF38+BQ38+BG38 -> 0 | GW38: =GL38+GB38+FR38+EQ38+EG38+DW38+DM38+CQ38+CG38+BR38+BH38 -> 0 | GZ38: =GX38+GY38 -> 0 | HC38: =HA38+HB38 -> 0 | HD38: =GX38+HA38 -> 0 | HE38: =GY38+HB38 -> 0 | HF38: =HD38+HE38 -> 0 | HH38: =HD38+GN38+GD38+FT38 -> 0 | HI38: =GO38+GE38+FU38+HE38 -> 0 | HJ38: =GX38+GH38+FX38+FN38 -> 0 | HK38: =GI38+FY38+GY38+FO38 -> 0 | HL38: =GK38+GA38+FQ38+HA38 -> 0 | HM38: =GL38+HB38+GB38+FR38 -> 0 | HO38: =HF38+GP38+GF38+FV38 -> 0 | HQ38: =FN38+FX38+GH38+GX38 -> 0 | HR38: =FO38+FY38+GI38+GY38 -> 0 | HS38: =FQ38+GA38+GK38+HA38 -> 0 | HT38: =FR38+GB38+GL38+HB38 -> 0 | HW38: =HU38+HV38 -> 0 | HZ38: =HX38+HY38 -> 0 | IA38: =HU38+HX38 -> 0 | IB38: =HV38+HY38 -> 0 | IC38: =IA38+IB38 -> 0 | JN38: =JG38+IW38+IM38+IC38 -> 0 | JZ38: =JX38+JN38+HO38+FB38 -> 6 | KA38: =SUM(JV38+JE38+IU38+IK38+IA38+HD38+GN38+GD38+FT38+ES38+EI38+DY38+DO38+CS38+CI38+BT38+BJ38+AO38+AE38+U38+K38) -> 0 | KB38: =SUM(JW38+JF38+IV38+IL38+IB38+HE38+GO38+GE38+FU38+ET38+EJ38+DZ38+DP38+CT38+CJ38+BU38+BK38+AP38+AF38+V38+L38) -> 6 | KC38: =SUM(JP38+IY38+IO38+IE38+HU38+GX38+GH38+FX38+FN38+EM38+EC38+DS38+DI38+CM38+CC38+BN38+BD38+AI38+Y38+O38+E38) -> 0 | KD38: =SUM(JQ38+IZ38+IP38+IF38+HV38+GY38+GI38+FY38+FO38+EN38+ED38+DT38+DJ38+CN38+CD38+BO38+BE38+AJ38+Z38+P38+F38) -> 0 | KE38: =SUM(JS38+JB38+IR38+IH38+HX38+HA38+GK38+GA38+FQ38+EP38+EF38+DV38+DL38+CP38+CF38+BQ38+BG38+AL38+AB38+R38+H38) -> 0 | KF38: =SUM(JT38+JC38+IS38+II38+HY38+HB38+GL38+GB38+FR38+EQ38+EG38+DW38+DM38+CQ38+CG38+BR38+BH38+AM38+AC38+S38+I38) -> 0 | KG38: =SUM(KA38:KB38) -> 6 | KH38: 8 | KI38: =KH38-KG38 -> 2 | KJ38: =KG38/KH38 -> 0.75 | KK38: =KI38/10 -> 0.2 | KL38: =SUM(KL34:KL37) -> 864
B39: Team UP | C39: Nakivale | D39: 240 | Y39: 133 | Z39: 107 | AA39: =SUM('Activity Tracking Table'!Y39:Z39) -> 240 | AB39: 0 | AC39: 0 | AD39: =SUM(AB39:AC39) -> 0 | AE39: =SUM(Y39+AB39) -> 133 | AF39: =SUM(Z39+AC39) -> 107 | AG39: =SUM(AE39:AF39) -> 240 | AH39: 7 | AR39: 8 | AS39: =AO39+AE39+U39+K39 -> 133 | AT39: =AP39+AF39+V39+L39 -> 107 | AU39: =AK39+AA39+Q39+G39 -> 240 | AV39: =AN39 -> 0 | AX39: =SUM(AQ39+AG39+W39+M39) -> 240 | AY39: =AX39/AW39 -> #DIV/0! | AZ39: =SUM(E39+O39+Y39+AI39) -> 133 | BA39: =F39+P39+Z39+AJ39 -> 107 | BB39: =H39+R39+AB39+AL39 -> 0 | BC39: =I39+S39+AC39+AM39 -> 0 | BX39: =BN39+BD39+AI39+Y39+O39+E39 -> 133 | BY39: =BO39+BE39+AJ39+Z39+P39+F39 -> 107 | BZ39: =BQ39+BG39+AL39+AB39+R39+H39 -> 0 | CA39: =BR39+BH39+AM39+AC39+S39+I39 -> 0 | CB39: =BX39+BY39+BZ39+CA39 -> 240 | CC39: 0 | CD39: 0 | CE39: =SUM(CC39:CD39) -> 0 | CF39: 0 | CG39: 0 | CH39: =SUM(CF39:CG39) -> 0 | CL39: 7 | CV39: 24 | CW39: =SUM(CS39+CI39+BT39+BJ39) -> 0 | CX39: =SUM(CT39+CJ39+BU39+BK39) -> 0 | CY39: =SUM(CU39+CK39+BV39+BL39) -> 0 | CZ39: =SUM(CR39+CH39+BS39+BI39) -> 0 | DB39: =SUM(CW39:CX39) -> 0 | DD39: =BD39+BN39+CC39+CM39 -> 0 | DE39: =BE39+BO39+CD39+CN39 -> 0 | DF39: =BG39+BQ39+CF39+CP39 -> 0 | DG39: =BH39+BR39+CG39+CQ39 -> 0 | DH39: =DB39+AX39 -> 240 | DU39: =SUM(DS39:DT39) -> 0 | DX39: =SUM(DV39:DW39) -> 0 | DY39: =SUM(DS39+DV39) -> 0 | DZ39: =SUM(DT39+DW39) -> 0 | EA39: =SUM(DY39:DZ39) -> 0 | EW39: =SUM(ES39+EI39+DY39+DO39) -> 0 | EX39: =SUM(ET39+EJ39+DZ39+DP39) -> 0 | EY39: =SUM(EO39+EE39+DU39+DK39) -> 0 | EZ39: =SUM(ER39+EH39+DX39+DN39) -> 0 | FB39: =SUM(EW39:EX39) -> 0 | FD39: =DI39+DS39+EC39+EM39+CM39+CC39 -> 0 | FE39: =DJ39+DT39+ED39+EN39+CD39+CN39 -> 0 | FF39: =DL39+DV39+EF39+EP39+CP39+CF39 -> 0 | FG39: =DM39+DW39+EG39+EQ39+CG39+CQ39 -> 0 | FH39: =FD39+FF39 -> 0 | FI39: =FE39+FG39 -> 0 | FJ39: =FH39+FI39 -> 0 | FK39: =EW39+CW39+AS39 -> 133 | FL39: =EX39+CX39+AT39 -> 107 | FM39: =FK39+FL39 -> 240 | FT39: =SUM(FN39+FQ39) -> 0 | FU39: =SUM(FO39+FR39) -> 0 | FV39: =SUM(FT39:FU39) -> 0 | GD39: =FX39+GA39 -> 0 | GE39: =FY39+GB39 -> 0 | GF39: =GD39+GE39 -> 0 | GN39: =GH39+GK39 -> 0 | GO39: =GI39+GL39 -> 0 | GP39: =GN39+GO39 -> 0 | GR39: =GN39+GD39+FT39+ES39+EI39+DY39+DO39+CS39+CI39+BT39+BJ39 -> 0 | GS39: =GO39+GE39+FU39+ET39+EJ39+DZ39+DP39+CT39+CJ39+BU39+BK39 -> 0 | GT39: =GH39+FX39+FN39+EM39+EC39+DS39+DI39+CM39+CC39+BN39+BD39 -> 0 | GU39: =GI39+FY39+FO39+EN39+ED39+DT39+DJ39+CN39+CD39+BO39+BE39 -> 0 | GV39: =GK39+GA39+FQ39+EP39+EF39+DV39+DL39+CP39+CF39+BQ39+BG39 -> 0 | GW39: =GL39+GB39+FR39+EQ39+EG39+DW39+DM39+CQ39+CG39+BR39+BH39 -> 0 | GZ39: =GX39+GY39 -> 0 | HC39: =HA39+HB39 -> 0 | HD39: =GX39+HA39 -> 0 | HE39: =GY39+HB39 -> 0 | HF39: =HD39+HE39 -> 0 | HH39: =HD39+GN39+GD39+FT39 -> 0 | HI39: =GO39+GE39+FU39+HE39 -> 0 | HJ39: =GX39+GH39+FX39+FN39 -> 0 | HK39: =GI39+FY39+GY39+FO39 -> 0 | HL39: =GK39+GA39+FQ39+HA39 -> 0 | HM39: =GL39+HB39+GB39+FR39 -> 0 | HO39: =HF39+GP39+GF39+FV39 -> 0 | HQ39: =FN39+FX39+GH39+GX39 -> 0 | HR39: =FO39+FY39+GI39+GY39 -> 0 | HS39: =FQ39+GA39+GK39+HA39 -> 0 | HT39: =FR39+GB39+GL39+HB39 -> 0 | HW39: =HU39+HV39 -> 0 | HZ39: =HX39+HY39 -> 0 | IA39: =HU39+HX39 -> 0 | IB39: =HV39+HY39 -> 0 | IC39: =IA39+IB39 -> 0 | JN39: =JG39+IW39+IM39+IC39 -> 0 | JZ39: =JX39+JN39+HO39+FB39 -> 0 | KA39: =SUM(JV39+JE39+IU39+IK39+IA39+HD39+GN39+GD39+FT39+ES39+EI39+DY39+DO39+CS39+CI39+BT39+BJ39+AO39+AE39+U39+K39) -> 133 | KB39: =SUM(JW39+JF39+IV39+IL39+IB39+HE39+GO39+GE39+FU39+ET39+EJ39+DZ39+DP39+CT39+CJ39+BU39+BK39+AP39+AF39+V39+L39) -> 107 | KC39: =SUM(JP39+IY39+IO39+IE39+HU39+GX39+GH39+FX39+FN39+EM39+EC39+DS39+DI39+CM39+CC39+BN39+BD39+AI39+Y39+O39+E39) -> 133 | KD39: =SUM(JQ39+IZ39+IP39+IF39+HV39+GY39+GI39+FY39+FO39+EN39+ED39+DT39+DJ39+CN39+CD39+BO39+BE39+AJ39+Z39+P39+F39) -> 107 | KE39: =SUM(JS39+JB39+IR39+IH39+HX39+HA39+GK39+GA39+FQ39+EP39+EF39+DV39+DL39+CP39+CF39+BQ39+BG39+AL39+AB39+R39+H39) -> 0 | KF39: =SUM(JT39+JC39+IS39+II39+HY39+HB39+GL39+GB39+FR39+EQ39+EG39+DW39+DM39+CQ39+CG39+BR39+BH39+AM39+AC39+S39+I39) -> 0 | KG39: =SUM(KA39:KB39) -> 240 | KH39: 240 | KI39: =KH39-KG39 -> 0 | KJ39: =KG39/KH39 -> 1 | KK39: =KI39/10 -> 0
B40: Facilitate CFS Facilitators to support activities at the CFS centers | C40: Nakivale | D40: 6 | AS40: =AO40+AE40+U40+K40 -> 0 | AT40: =AP40+AF40+V40+L40 -> 0 | AU40: =AK40+AA40+Q40+G40 -> 0 | AV40: =AN40 -> 0 | AX40: =SUM(AQ40+AG40+W40+M40) -> 0 | AY40: =AX40/AW40 -> #DIV/0! | AZ40: =SUM(E40+O40+Y40+AI40) -> 0 | BA40: =F40+P40+Z40+AJ40 -> 0 | BB40: =H40+R40+AB40+AL40 -> 0 | BC40: =I40+S40+AC40+AM40 -> 0 | BX40: =BN40+BD40+AI40+Y40+O40+E40 -> 0 | BY40: =BO40+BE40+AJ40+Z40+P40+F40 -> 0 | BZ40: =BQ40+BG40+AL40+AB40+R40+H40 -> 0 | CA40: =BR40+BH40+AM40+AC40+S40+I40 -> 0 | CB40: =BX40+BY40+BZ40+CA40 -> 0 | CW40: =SUM(CS40+CI40+BT40+BJ40) -> 0 | CX40: =SUM(CT40+CJ40+BU40+BK40) -> 0 | CY40: =SUM(CU40+CK40+BV40+BL40) -> 0 | CZ40: =SUM(CR40+CH40+BS40+BI40) -> 0 | DB40: =SUM(CW40:CX40) -> 0 | DD40: =BD40+BN40+CC40+CM40 -> 0 | DE40: =BE40+BO40+CD40+CN40 -> 0 | DF40: =BG40+BQ40+CF40+CP40 -> 0 | DG40: =BH40+BR40+CG40+CQ40 -> 0 | DH40: =DB40+AX40 -> 0 | DU40: =SUM(DS40:DT40) -> 0 | DX40: =SUM(DV40:DW40) -> 0 | DY40: =SUM(DS40+DV40) -> 0 | DZ40: =SUM(DT40+DW40) -> 0 | EA40: =SUM(DY40:DZ40) -> 0 | EW40: =SUM(ES40+EI40+DY40+DO40) -> 0 | EX40: =SUM(ET40+EJ40+DZ40+DP40) -> 0 | EY40: =SUM(EO40+EE40+DU40+DK40) -> 0 | EZ40: =SUM(ER40+EH40+DX40+DN40) -> 0 | FB40: =SUM(EW40:EX40) -> 0 | FD40: =DI40+DS40+EC40+EM40+CM40+CC40 -> 0 | FE40: =DJ40+DT40+ED40+EN40+CD40+CN40 -> 0 | FF40: =DL40+DV40+EF40+EP40+CP40+CF40 -> 0 | FG40: =DM40+DW40+EG40+EQ40+CG40+CQ40 -> 0 | FH40: =FD40+FF40 -> 0 | FI40: =FE40+FG40 -> 0 | FJ40: =FH40+FI40 -> 0 | FK40: =EW40+CW40+AS40 -> 0 | FL40: =EX40+CX40+AT40 -> 0 | FM40: =FK40+FL40 -> 0 | FT40: =SUM(FN40+FQ40) -> 0 | FU40: =SUM(FO40+FR40) -> 0 | FV40: =SUM(FT40:FU40) -> 0 | GD40: =FX40+GA40 -> 0 | GE40: =FY40+GB40 -> 0 | GF40: =GD40+GE40 -> 0 | GN40: =GH40+GK40 -> 0 | GO40: =GI40+GL40 -> 0 | GP40: =GN40+GO40 -> 0 | GR40: =GN40+GD40+FT40+ES40+EI40+DY40+DO40+CS40+CI40+BT40+BJ40 -> 0 | GS40: =GO40+GE40+FU40+ET40+EJ40+DZ40+DP40+CT40+CJ40+BU40+BK40 -> 0 | GT40: =GH40+FX40+FN40+EM40+EC40+DS40+DI40+CM40+CC40+BN40+BD40 -> 0 | GU40: =GI40+FY40+FO40+EN40+ED40+DT40+DJ40+CN40+CD40+BO40+BE40 -> 0 | GV40: =GK40+GA40+FQ40+EP40+EF40+DV40+DL40+CP40+CF40+BQ40+BG40 -> 0 | GW40: =GL40+GB40+FR40+EQ40+EG40+DW40+DM40+CQ40+CG40+BR40+BH40 -> 0 | GZ40: =GX40+GY40 -> 0 | HC40: =HA40+HB40 -> 0 | HD40: =GX40+HA40 -> 0 | HE40: =GY40+HB40 -> 0 | HF40: =HD40+HE40 -> 0 | HH40: =HD40+GN40+GD40+FT40 -> 0 | HI40: =GO40+GE40+FU40+HE40 -> 0 | HJ40: =GX40+GH40+FX40+FN40 -> 0 | HK40: =GI40+FY40+GY40+FO40 -> 0 | HL40: =GK40+GA40+FQ40+HA40 -> 0 | HM40: =GL40+HB40+GB40+FR40 -> 0 | HO40: =HF40+GP40+GF40+FV40 -> 0 | HQ40: =FN40+FX40+GH40+GX40 -> 0 | HR40: =FO40+FY40+GI40+GY40 -> 0 | HS40: =FQ40+GA40+GK40+HA40 -> 0 | HT40: =FR40+GB40+GL40+HB40 -> 0 | HW40: =HU40+HV40 -> 0 | HZ40: =HX40+HY40 -> 0 | IA40: =HU40+HX40 -> 0 | IB40: =HV40+HY40 -> 0 | IC40: =IA40+IB40 -> 0 | JN40: =JG40+IW40+IM40+IC40 -> 0 | JZ40: =JX40+JN40+HO40+FB40 -> 0 | KA40: =SUM(JV40+JE40+IU40+IK40+IA40+HD40+GN40+GD40+FT40+ES40+EI40+DY40+DO40+CS40+CI40+BT40+BJ40+AO40+AE40+U40+K40) -> 0 | KB40: =SUM(JW40+JF40+IV40+IL40+IB40+HE40+GO40+GE40+FU40+ET40+EJ40+DZ40+DP40+CT40+CJ40+BU40+BK40+AP40+AF40+V40+L40) -> 0 | KC40: =SUM(JP40+IY40+IO40+IE40+HU40+GX40+GH40+FX40+FN40+EM40+EC40+DS40+DI40+CM40+CC40+BN40+BD40+AI40+Y40+O40+E40) -> 0 | KD40: =SUM(JQ40+IZ40+IP40+IF40+HV40+GY40+GI40+FY40+FO40+EN40+ED40+DT40+DJ40+CN40+CD40+BO40+BE40+AJ40+Z40+P40+F40) -> 0 | KE40: =SUM(JS40+JB40+IR40+IH40+HX40+HA40+GK40+GA40+FQ40+EP40+EF40+DV40+DL40+CP40+CF40+BQ40+BG40+AL40+AB40+R40+H40) -> 0 | KF40: =SUM(JT40+JC40+IS40+II40+HY40+HB40+GL40+GB40+FR40+EQ40+EG40+DW40+DM40+CQ40+CG40+BR40+BH40+AM40+AC40+S40+I40) -> 0 | KG40: =SUM(KA40:KB40) -> 0 | KH40: 6 | KI40: =KH40-KG40 -> 6 | KJ40: =KG40/KH40 -> 0 | KK40: =KI40/10 -> 0.6
B41: Provide material support to foster parents and care givers | C41: Nakivale | D41: 50 | AS41: =AO41+AE41+U41+K41 -> 0 | AT41: =AP41+AF41+V41+L41 -> 0 | AU41: =AK41+AA41+Q41+G41 -> 0 | AV41: =AN41 -> 0 | AX41: =SUM(AQ41+AG41+W41+M41) -> 0 | AY41: =AX41/AW41 -> #DIV/0! | AZ41: =SUM(E41+O41+Y41+AI41) -> 0 | BA41: =F41+P41+Z41+AJ41 -> 0 | BB41: =H41+R41+AB41+AL41 -> 0 | BC41: =I41+S41+AC41+AM41 -> 0 | BX41: =BN41+BD41+AI41+Y41+O41+E41 -> 0 | BY41: =BO41+BE41+AJ41+Z41+P41+F41 -> 0 | BZ41: =BQ41+BG41+AL41+AB41+R41+H41 -> 0 | CA41: =BR41+BH41+AM41+AC41+S41+I41 -> 0 | CB41: =BX41+BY41+BZ41+CA41 -> 0 | CW41: =SUM(CS41+CI41+BT41+BJ41) -> 0 | CX41: =SUM(CT41+CJ41+BU41+BK41) -> 0 | CY41: =SUM(CU41+CK41+BV41+BL41) -> 0 | CZ41: =SUM(CR41+CH41+BS41+BI41) -> 0 | DB41: =SUM(CW41:CX41) -> 0 | DD41: =BD41+BN41+CC41+CM41 -> 0 | DE41: =BE41+BO41+CD41+CN41 -> 0 | DF41: =BG41+BQ41+CF41+CP41 -> 0 | DG41: =BH41+BR41+CG41+CQ41 -> 0 | DH41: =DB41+AX41 -> 0 | DU41: =SUM(DS41:DT41) -> 0 | DX41: =SUM(DV41:DW41) -> 0 | DY41: =SUM(DS41+DV41) -> 0 | DZ41: =SUM(DT41+DW41) -> 0 | EA41: =SUM(DY41:DZ41) -> 0 | EC41: 0 | ED41: 0 | EE41: =SUM(EC41:ED41) -> 0 | EF41: 0 | EG41: 0 | EH41: =SUM(EF41:EG41) -> 0 | EI41: =SUM(EC41+EF41) -> 0 | EJ41: =SUM(ED41+EG41) -> 0 | EK41: =SUM(EI41:EJ41) -> 0 | EM41: 36 | EN41: 14 | EO41: =SUM(EM41:EN41) -> 50 | EP41: 0 | EQ41: 0 | ER41: 0 | ES41: =SUM(EM41+EP41) -> 36 | ET41: =SUM(EN41+EQ41) -> 14 | EU41: =SUM(ES41:ET41) -> 50 | EW41: =SUM(ES41+EI41+DY41+DO41) -> 36 | EX41: =SUM(ET41+EJ41+DZ41+DP41) -> 14 | EY41: =SUM(EO41+EE41+DU41+DK41) -> 50 | EZ41: =SUM(ER41+EH41+DX41+DN41) -> 0 | FB41: =SUM(EW41:EX41) -> 50 | FD41: =DI41+DS41+EC41+EM41+CM41+CC41 -> 36 | FE41: =DJ41+DT41+ED41+EN41+CD41+CN41 -> 14 | FF41: =DL41+DV41+EF41+EP41+CP41+CF41 -> 0 | FG41: =DM41+DW41+EG41+EQ41+CG41+CQ41 -> 0 | FH41: =FD41+FF41 -> 36 | FI41: =FE41+FG41 -> 14 | FJ41: =FH41+FI41 -> 50 | FK41: =EW41+CW41+AS41 -> 36 | FL41: =EX41+CX41+AT41 -> 14 | FM41: =FK41+FL41 -> 50 | FT41: =SUM(FN41+FQ41) -> 0 | FU41: =SUM(FO41+FR41) -> 0 | FV41: =SUM(FT41:FU41) -> 0 | GD41: =FX41+GA41 -> 0 | GE41: =FY41+GB41 -> 0 | GF41: =GD41+GE41 -> 0 | GN41: =GH41+GK41 -> 0 | GO41: =GI41+GL41 -> 0 | GP41: =GN41+GO41 -> 0 | GR41: =GN41+GD41+FT41+ES41+EI41+DY41+DO41+CS41+CI41+BT41+BJ41 -> 36 | GS41: =GO41+GE41+FU41+ET41+EJ41+DZ41+DP41+CT41+CJ41+BU41+BK41 -> 14 | GT41: =GH41+FX41+FN41+EM41+EC41+DS41+DI41+CM41+CC41+BN41+BD41 -> 36 | GU41: =GI41+FY41+FO41+EN41+ED41+DT41+DJ41+CN41+CD41+BO41+BE41 -> 14 | GV41: =GK41+GA41+FQ41+EP41+EF41+DV41+DL41+CP41+CF41+BQ41+BG41 -> 0 | GW41: =GL41+GB41+FR41+EQ41+EG41+DW41+DM41+CQ41+CG41+BR41+BH41 -> 0 | GX41: 2 | GY41: 17 | GZ41: =GX41+GY41 -> 19 | HA41: 0 | HB41: 0 | HC41: =HA41+HB41 -> 0 | HD41: =GX41+HA41 -> 2 | HE41: =GY41+HB41 -> 17 | HF41: =HD41+HE41 -> 19 | HH41: =HD41+GN41+GD41+FT41 -> 2 | HI41: =GO41+GE41+FU41+HE41 -> 17 | HJ41: =GX41+GH41+FX41+FN41 -> 2 | HK41: =GI41+FY41+GY41+FO41 -> 17 | HL41: =GK41+GA41+FQ41+HA41 -> 0 | HM41: =GL41+HB41+GB41+FR41 -> 0 | HO41: =HF41+GP41+GF41+FV41 -> 19 | HQ41: =FN41+FX41+GH41+GX41 -> 2 | HR41: =FO41+FY41+GI41+GY41 -> 17 | HS41: =FQ41+GA41+GK41+HA41 -> 0 | HT41: =FR41+GB41+GL41+HB41 -> 0 | HW41: =HU41+HV41 -> 0 | HZ41: =HX41+HY41 -> 0 | IA41: =HU41+HX41 -> 0 | IB41: =HV41+HY41 -> 0 | IC41: =IA41+IB41 -> 0 | JN41: =JG41+IW41+IM41+IC41 -> 0 | JZ41: =JX41+JN41+HO41+FB41 -> 69 | KA41: =SUM(JV41+JE41+IU41+IK41+IA41+HD41+GN41+GD41+FT41+ES41+EI41+DY41+DO41+CS41+CI41+BT41+BJ41+AO41+AE41+U41+K41) -> 38 | KB41: =SUM(JW41+JF41+IV41+IL41+IB41+HE41+GO41+GE41+FU41+ET41+EJ41+DZ41+DP41+CT41+CJ41+BU41+BK41+AP41+AF41+V41+L41) -> 31 | KC41: =SUM(JP41+IY41+IO41+IE41+HU41+GX41+GH41+FX41+FN41+EM41+EC41+DS41+DI41+CM41+CC41+BN41+BD41+AI41+Y41+O41+E41) -> 38 | KD41: =SUM(JQ41+IZ41+IP41+IF41+HV41+GY41+GI41+FY41+FO41+EN41+ED41+DT41+DJ41+CN41+CD41+BO41+BE41+AJ41+Z41+P41+F41) -> 31 | KE41: =SUM(JS41+JB41+IR41+IH41+HX41+HA41+GK41+GA41+FQ41+EP41+EF41+DV41+DL41+CP41+CF41+BQ41+BG41+AL41+AB41+R41+H41) -> 0 | KF41: =SUM(JT41+JC41+IS41+II41+HY41+HB41+GL41+GB41+FR41+EQ41+EG41+DW41+DM41+CQ41+CG41+BR41+BH41+AM41+AC41+S41+I41) -> 0 | KG41: =SUM(KA41:KB41) -> 69 | KH41: 50 | KI41: =KH41-KG41 -> -19 | KJ41: =KG41/KH41 -> 1.38 | KK41: =KI41/10 -> -1.9
B42: Support to lactating mothers | C42: Nakivale | D42: 50 | AS42: =AO42+AE42+U42+K42 -> 0 | AT42: =AP42+AF42+V42+L42 -> 0 | AU42: =AK42+AA42+Q42+G42 -> 0 | AV42: =AN42 -> 0 | AX42: =SUM(AQ42+AG42+W42+M42) -> 0 | AY42: =AX42/AW42 -> #DIV/0! | AZ42: =SUM(E42+O42+Y42+AI42) -> 0 | BA42: =F42+P42+Z42+AJ42 -> 0 | BB42: =H42+R42+AB42+AL42 -> 0 | BC42: =I42+S42+AC42+AM42 -> 0 | BX42: =BN42+BD42+AI42+Y42+O42+E42 -> 0 | BY42: =BO42+BE42+AJ42+Z42+P42+F42 -> 0 | BZ42: =BQ42+BG42+AL42+AB42+R42+H42 -> 0 | CA42: =BR42+BH42+AM42+AC42+S42+I42 -> 0 | CB42: =BX42+BY42+BZ42+CA42 -> 0 | CW42: =SUM(CS42+CI42+BT42+BJ42) -> 0 | CX42: =SUM(CT42+CJ42+BU42+BK42) -> 0 | CY42: =SUM(CU42+CK42+BV42+BL42) -> 0 | CZ42: =SUM(CR42+CH42+BS42+BI42) -> 0 | DB42: =SUM(CW42:CX42) -> 0 | DD42: =BD42+BN42+CC42+CM42 -> 0 | DE42: =BE42+BO42+CD42+CN42 -> 0 | DF42: =BG42+BQ42+CF42+CP42 -> 0 | DG42: =BH42+BR42+CG42+CQ42 -> 0 | DH42: =DB42+AX42 -> 0 | DU42: =SUM(DS42:DT42) -> 0 | DX42: =SUM(DV42:DW42) -> 0 | DY42: =SUM(DS42+DV42) -> 0 | DZ42: =SUM(DT42+DW42) -> 0 | EA42: =SUM(DY42:DZ42) -> 0 | EC42: 23 | ED42: 0 | EE42: =SUM(EC42:ED42) -> 23 | EF42: 0 | EG42: 0 | EH42: =SUM(EF42:EG42) -> 0 | EI42: =SUM(EC42+EF42) -> 23 | EJ42: =SUM(ED42+EG42) -> 0 | EK42: =SUM(EI42:EJ42) -> 23 | EM42: 77 | EN42: 0 | EO42: =SUM(EM42:EN42) -> 77 | EP42: 0 | EQ42: 0 | ER42: =SUM(EP42:EQ42) -> 0 | ES42: =SUM(EM42+EP42) -> 77 | ET42: =SUM(EN42+EQ42) -> 0 | EU42: =SUM(ES42:ET42) -> 77 | EW42: =SUM(ES42+EI42+DY42+DO42) -> 100 | EX42: =SUM(ET42+EJ42+DZ42+DP42) -> 0 | EY42: =SUM(EO42+EE42+DU42+DK42) -> 100 | EZ42: =SUM(ER42+EH42+DX42+DN42) -> 0 | FB42: =SUM(EW42:EX42) -> 100 | FD42: =DI42+DS42+EC42+EM42+CM42+CC42 -> 100 | FE42: =DJ42+DT42+ED42+EN42+CD42+CN42 -> 0 | FF42: =DL42+DV42+EF42+EP42+CP42+CF42 -> 0 | FG42: =DM42+DW42+EG42+EQ42+CG42+CQ42 -> 0 | FH42: =FD42+FF42 -> 100 | FI42: =FE42+FG42 -> 0 | FJ42: =FH42+FI42 -> 100 | FK42: =EW42+CW42+AS42 -> 100 | FL42: =EX42+CX42+AT42 -> 0 | FM42: =FK42+FL42 -> 100 | FT42: =SUM(FN42+FQ42) -> 0 | FU42: =SUM(FO42+FR42) -> 0 | FV42: =SUM(FT42:FU42) -> 0 | GD42: =FX42+GA42 -> 0 | GE42: =FY42+GB42 -> 0 | GF42: =GD42+GE42 -> 0 | GN42: =GH42+GK42 -> 0 | GO42: =GI42+GL42 -> 0 | GP42: =GN42+GO42 -> 0 | GR42: =GN42+GD42+FT42+ES42+EI42+DY42+DO42+CS42+CI42+BT42+BJ42 -> 100 | GS42: =GO42+GE42+FU42+ET42+EJ42+DZ42+DP42+CT42+CJ42+BU42+BK42 -> 0 | GT42: =GH42+FX42+FN42+EM42+EC42+DS42+DI42+CM42+CC42+BN42+BD42 -> 100 | GU42: =GI42+FY42+FO42+EN42+ED42+DT42+DJ42+CN42+CD42+BO42+BE42 -> 0 | GV42: =GK42+GA42+FQ42+EP42+EF42+DV42+DL42+CP42+CF42+BQ42+BG42 -> 0 | GW42: =GL42+GB42+FR42+EQ42+EG42+DW42+DM42+CQ42+CG42+BR42+BH42 -> 0 | GZ42: =GX42+GY42 -> 0 | HC42: =HA42+HB42 -> 0 | HD42: =GX42+HA42 -> 0 | HE42: =GY42+HB42 -> 0 | HF42: =HD42+HE42 -> 0 | HH42: =HD42+GN42+GD42+FT42 -> 0 | HI42: =GO42+GE42+FU42+HE42 -> 0 | HJ42: =GX42+GH42+FX42+FN42 -> 0 | HK42: =GI42+FY42+GY42+FO42 -> 0 | HL42: =GK42+GA42+FQ42+HA42 -> 0 | HM42: =GL42+HB42+GB42+FR42 -> 0 | HO42: =HF42+GP42+GF42+FV42 -> 0 | HQ42: =FN42+FX42+GH42+GX42 -> 0 | HR42: =FO42+FY42+GI42+GY42 -> 0 | HS42: =FQ42+GA42+GK42+HA42 -> 0 | HT42: =FR42+GB42+GL42+HB42 -> 0 | HW42: =HU42+HV42 -> 0 | HZ42: =HX42+HY42 -> 0 | IA42: =HU42+HX42 -> 0 | IB42: =HV42+HY42 -> 0 | IC42: =IA42+IB42 -> 0 | JN42: =JG42+IW42+IM42+IC42 -> 0 | JZ42: =JX42+JN42+HO42+FB42 -> 100 | KA42: =SUM(JV42+JE42+IU42+IK42+IA42+HD42+GN42+GD42+FT42+ES42+EI42+DY42+DO42+CS42+CI42+BT42+BJ42+AO42+AE42+U42+K42) -> 100 | KB42: =SUM(JW42+JF42+IV42+IL42+IB42+HE42+GO42+GE42+FU42+ET42+EJ42+DZ42+DP42+CT42+CJ42+BU42+BK42+AP42+AF42+V42+L42) -> 0 | KC42: =SUM(JP42+IY42+IO42+IE42+HU42+GX42+GH42+FX42+FN42+EM42+EC42+DS42+DI42+CM42+CC42+BN42+BD42+AI42+Y42+O42+E42) -> 100 | KD42: =SUM(JQ42+IZ42+IP42+IF42+HV42+GY42+GI42+FY42+FO42+EN42+ED42+DT42+DJ42+CN42+CD42+BO42+BE42+AJ42+Z42+P42+F42) -> 0 | KE42: =SUM(JS42+JB42+IR42+IH42+HX42+HA42+GK42+GA42+FQ42+EP42+EF42+DV42+DL42+CP42+CF42+BQ42+BG42+AL42+AB42+R42+H42) -> 0 | KF42: =SUM(JT42+JC42+IS42+II42+HY42+HB42+GL42+GB42+FR42+EQ42+EG42+DW42+DM42+CQ42+CG42+BR42+BH42+AM42+AC42+S42+I42) -> 0 | KG42: =SUM(KA42:KB42) -> 100 | KH42: 50 | KI42: =KH42-KG42 -> -50 | KJ42: =KG42/KH42 -> 2 | KK42: =KI42/10 -> -5
B43: Provide Individual Protection Assistance to children like blankets, sleeping mats, clothes.etc | C43: Nakivale | D43: 600 | AS43: =AO43+AE43+U43+K43 -> 0 | AT43: =AP43+AF43+V43+L43 -> 0 | AU43: =AK43+AA43+Q43+G43 -> 0 | AV43: =AN43 -> 0 | AX43: =SUM(AQ43+AG43+W43+M43) -> 0 | AY43: =AX43/AW43 -> #DIV/0! | AZ43: =SUM(E43+O43+Y43+AI43) -> 0 | BA43: =F43+P43+Z43+AJ43 -> 0 | BB43: =H43+R43+AB43+AL43 -> 0 | BC43: =I43+S43+AC43+AM43 -> 0 | BX43: =BN43+BD43+AI43+Y43+O43+E43 -> 0 | BY43: =BO43+BE43+AJ43+Z43+P43+F43 -> 0 | BZ43: =BQ43+BG43+AL43+AB43+R43+H43 -> 0 | CA43: =BR43+BH43+AM43+AC43+S43+I43 -> 0 | CB43: =BX43+BY43+BZ43+CA43 -> 0 | CW43: =SUM(CS43+CI43+BT43+BJ43) -> 0 | CX43: =SUM(CT43+CJ43+BU43+BK43) -> 0 | CY43: =SUM(CU43+CK43+BV43+BL43) -> 0 | CZ43: =SUM(CR43+CH43+BS43+BI43) -> 0 | DB43: =SUM(CW43:CX43) -> 0 | DD43: =BD43+BN43+CC43+CM43 -> 0 | DE43: =BE43+BO43+CD43+CN43 -> 0 | DF43: =BG43+BQ43+CF43+CP43 -> 0 | DG43: =BH43+BR43+CG43+CQ43 -> 0 | DH43: =DB43+AX43 -> 0 | DU43: =SUM(DS43:DT43) -> 0 | DX43: =SUM(DV43:DW43) -> 0 | DY43: =SUM(DS43+DV43) -> 0 | DZ43: =SUM(DT43+DW43) -> 0 | EA43: =SUM(DY43:DZ43) -> 0 | EC43: 140 | ED43: 160 | EE43: =SUM(EC43:ED43) -> 300 | EF43: 0 | EG43: 0 | EH43: =SUM(EF43:EG43) -> 0 | EI43: =SUM(EC43+EF43) -> 140 | EJ43: =SUM(ED43+EG43) -> 160 | EK43: =SUM(EI43:EJ43) -> 300 | EW43: =SUM(ES43+EI43+DY43+DO43) -> 140 | EX43: =SUM(ET43+EJ43+DZ43+DP43) -> 160 | EY43: =SUM(EO43+EE43+DU43+DK43) -> 300 | EZ43: =SUM(ER43+EH43+DX43+DN43) -> 0 | FB43: =SUM(EW43:EX43) -> 300 | FD43: =DI43+DS43+EC43+EM43+CM43+CC43 -> 140 | FE43: =DJ43+DT43+ED43+EN43+CD43+CN43 -> 160 | FF43: =DL43+DV43+EF43+EP43+CP43+CF43 -> 0 | FG43: =DM43+DW43+EG43+EQ43+CG43+CQ43 -> 0 | FH43: =FD43+FF43 -> 140 | FI43: =FE43+FG43 -> 160 | FJ43: =FH43+FI43 -> 300 | FK43: =EW43+CW43+AS43 -> 140 | FL43: =EX43+CX43+AT43 -> 160 | FM43: =FK43+FL43 -> 300 | FT43: =SUM(FN43+FQ43) -> 0 | FU43: =SUM(FO43+FR43) -> 0 | FV43: =SUM(FT43:FU43) -> 0 | GD43: =FX43+GA43 -> 0 | GE43: =FY43+GB43 -> 0 | GF43: =GD43+GE43 -> 0 | GH43: 144 | GI43: 156 | GJ43: =GH43+GI43 -> 300 | GK43: 0 | GL43: 0 | GM43: =GK43=GL43 -> TRUE | GN43: =GH43+GK43 -> 144 | GO43: =GI43+GL43 -> 156 | GP43: =GN43+GO43 -> 300 | GR43: =GN43+GD43+FT43+ES43+EI43+DY43+DO43+CS43+CI43+BT43+BJ43 -> 284 | GS43: =GO43+GE43+FU43+ET43+EJ43+DZ43+DP43+CT43+CJ43+BU43+BK43 -> 316 | GT43: =GH43+FX43+FN43+EM43+EC43+DS43+DI43+CM43+CC43+BN43+BD43 -> 284 | GU43: =GI43+FY43+FO43+EN43+ED43+DT43+DJ43+CN43+CD43+BO43+BE43 -> 316 | GV43: =GK43+GA43+FQ43+EP43+EF43+DV43+DL43+CP43+CF43+BQ43+BG43 -> 0 | GW43: =GL43+GB43+FR43+EQ43+EG43+DW43+DM43+CQ43+CG43+BR43+BH43 -> 0 | GZ43: =GX43+GY43 -> 0 | HC43: =HA43+HB43 -> 0 | HD43: =GX43+HA43 -> 0 | HE43: =GY43+HB43 -> 0 | HF43: =HD43+HE43 -> 0 | HH43: =HD43+GN43+GD43+FT43 -> 144 | HI43: =GO43+GE43+FU43+HE43 -> 156 | HJ43: =GX43+GH43+FX43+FN43 -> 144 | HK43: =GI43+FY43+GY43+FO43 -> 156 | HL43: =GK43+GA43+FQ43+HA43 -> 0 | HM43: =GL43+HB43+GB43+FR43 -> 0 | HO43: =HF43+GP43+GF43+FV43 -> 300 | HQ43: =FN43+FX43+GH43+GX43 -> 144 | HR43: =FO43+FY43+GI43+GY43 -> 156 | HS43: =FQ43+GA43+GK43+HA43 -> 0 | HT43: =FR43+GB43+GL43+HB43 -> 0 | HW43: =HU43+HV43 -> 0 | HZ43: =HX43+HY43 -> 0 | IA43: =HU43+HX43 -> 0 | IB43: =HV43+HY43 -> 0 | IC43: =IA43+IB43 -> 0 | JN43: =JG43+IW43+IM43+IC43 -> 0 | JZ43: =JX43+JN43+HO43+FB43 -> 600 | KA43: =SUM(JV43+JE43+IU43+IK43+IA43+HD43+GN43+GD43+FT43+ES43+EI43+DY43+DO43+CS43+CI43+BT43+BJ43+AO43+AE43+U43+K43) -> 284 | KB43: =SUM(JW43+JF43+IV43+IL43+IB43+HE43+GO43+GE43+FU43+ET43+EJ43+DZ43+DP43+CT43+CJ43+BU43+BK43+AP43+AF43+V43+L43) -> 316 | KC43: =SUM(JP43+IY43+IO43+IE43+HU43+GX43+GH43+FX43+FN43+EM43+EC43+DS43+DI43+CM43+CC43+BN43+BD43+AI43+Y43+O43+E43) -> 284 | KD43: =SUM(JQ43+IZ43+IP43+IF43+HV43+GY43+GI43+FY43+FO43+EN43+ED43+DT43+DJ43+CN43+CD43+BO43+BE43+AJ43+Z43+P43+F43) -> 316 | KE43: =SUM(JS43+JB43+IR43+IH43+HX43+HA43+GK43+GA43+FQ43+EP43+EF43+DV43+DL43+CP43+CF43+BQ43+BG43+AL43+AB43+R43+H43) -> 0 | KF43: =SUM(JT43+JC43+IS43+II43+HY43+HB43+GL43+GB43+FR43+EQ43+EG43+DW43+DM43+CQ43+CG43+BR43+BH43+AM43+AC43+S43+I43) -> 0 | KG43: =SUM(KA43:KB43) -> 600 | KH43: 600 | KI43: =KH43-KG43 -> 0 | KJ43: =KG43/KH43 -> 1 | KK43: =KI43/10 -> 0
B44: IPA support through referrals | HU44: 101 | HV44: 99 | HW44: =HU44+HV44 -> 200 | HX44: 0 | HY44: 0 | HZ44: =HX44+HY44 -> 0
B45: Closed Cases | AZ45: =SUM(E45+O45+Y45+AI45) -> 0 | BA45: =F45+P45+Z45+AJ45 -> 0 | BB45: =H45+R45+AB45+AL45 -> 0 | BC45: =I45+S45+AC45+AM45 -> 0 | BX45: =BN45+BD45+AI45+Y45+O45+E45 -> 0 | BY45: =BO45+BE45+AJ45+Z45+P45+F45 -> 0 | BZ45: =BQ45+BG45+AL45+AB45+R45+H45 -> 0 | CA45: =BR45+BH45+AM45+AC45+S45+I45 -> 0 | CB45: =BX45+BY45+BZ45+CA45 -> 0 | DD45: =BD45+BN45+CC45+CM45 -> 0 | DE45: =BE45+BO45+CD45+CN45 -> 0 | DF45: =BG45+BQ45+CF45+CP45 -> 0 | DG45: =BH45+BR45+CG45+CQ45 -> 0 | DH45: =DB45+AX45 -> 0 | EC45: 1 | ED45: 2 | EE45: =SUM(EC45:ED45) -> 3 | EF45: 0 | EG45: 0 | EH45: =SUM(EF45:EG45) -> 0 | EI45: =SUM(EC45+EF45) -> 1 | EJ45: =SUM(ED45+EG45) -> 2 | EK45: =SUM(EI45:EJ45) -> 3 | FD45: =DI45+DS45+EC45+EM45+CM45+CC45 -> 1 | FE45: =DJ45+DT45+ED45+EN45+CD45+CN45 -> 2 | FF45: =DL45+DV45+EF45+EP45+CP45+CF45 -> 0 | FG45: =DM45+DW45+EG45+EQ45+CG45+CQ45 -> 0 | FH45: =FD45+FF45 -> 1 | FI45: =FE45+FG45 -> 2 | FJ45: =FH45+FI45 -> 3 | FK45: =EW45+CW45+AS45 -> 0 | FL45: =EX45+CX45+AT45 -> 0 | FM45: =FK45+FL45 -> 0 | FT45: =SUM(FN45+FQ45) -> 0 | FU45: =SUM(FO45+FR45) -> 0 | FV45: =SUM(FT45:FU45) -> 0 | GD45: =FX45+GA45 -> 0 | GE45: =FY45+GB45 -> 0 | GF45: =GD45+GE45 -> 0 | GN45: =GH45+GK45 -> 0 | GO45: =GI45+GL45 -> 0 | GP45: =GN45+GO45 -> 0 | GR45: =GN45+GD45+FT45+ES45+EI45+DY45+DO45+CS45+CI45+BT45+BJ45 -> 1 | GS45: =GO45+GE45+FU45+ET45+EJ45+DZ45+DP45+CT45+CJ45+BU45+BK45 -> 2 | GT45: =GH45+FX45+FN45+EM45+EC45+DS45+DI45+CM45+CC45+BN45+BD45 -> 1 | GU45: =GI45+FY45+FO45+EN45+ED45+DT45+DJ45+CN45+CD45+BO45+BE45 -> 2 | GV45: =GK45+GA45+FQ45+EP45+EF45+DV45+DL45+CP45+CF45+BQ45+BG45 -> 0 | GW45: =GL45+GB45+FR45+EQ45+EG45+DW45+DM45+CQ45+CG45+BR45+BH45 -> 0 | GZ45: =GX45+GY45 -> 0 | HC45: =HA45+HB45 -> 0 | HD45: =GX45+HA45 -> 0 | HE45: =GY45+HB45 -> 0 | HF45: =HD45+HE45 -> 0 | HH45: =HD45+GN45+GD45+FT45 -> 0 | HI45: =GO45+GE45+FU45+HE45 -> 0 | HJ45: =GX45+GH45+FX45+FN45 -> 0 | HK45: =GI45+FY45+GY45+FO45 -> 0 | HL45: =GK45+GA45+FQ45+HA45 -> 0 | HM45: =GL45+HB45+GB45+FR45 -> 0 | HO45: =HF45+GP45+GF45+FV45 -> 0 | HQ45: =FN45+FX45+GH45+GX45 -> 0 | HR45: =FO45+FY45+GI45+GY45 -> 0 | HS45: =FQ45+GA45+GK45+HA45 -> 0 | HT45: =FR45+GB45+GL45+HB45 -> 0 | HW45: =HU45+HV45 -> 0 | HZ45: =HX45+HY45 -> 0 | IA45: =HU45+HX45 -> 0 | IB45: =HV45+HY45 -> 0 | IC45: =IA45+IB45 -> 0 | JN45: =JG45+IW45+IM45+IC45 -> 0 | JZ45: =JX45+JN45+HO45+FB45 -> 0
AS46: 0 | AZ46: =AZ39+AZ34 -> 149 | BA46: =BA39+BA34 -> 111 | BX46: =BN46+BD46+AI46+Y46+O46+E46 -> 0 | BY46: =BO46+BE46+AJ46+Z46+P46+F46 -> 0 | BZ46: =BQ46+BG46+AL46+AB46+R46+H46 -> 0 | CA46: =BR46+BH46+AM46+AC46+S46+I46 -> 0 | CB46: =BX46+BY46+BZ46+CA46 -> 0 | DD46: 0 | DE46: 0 | DF46: 0 | DG46: 0 | DH46: =DB46+AX46 -> 0 | FC46: Nakivale | FD46: =DI46+DS46+EC46+EM46+CM46+CC46 -> 0 | FE46: =DJ46+DT46+ED46+EN46+CD46+CN46 -> 0 | FF46: =DL46+DV46+EF46+EP46+CP46+CF46 -> 0 | FG46: =DM46+DW46+EG46+EQ46+CG46+CQ46 -> 0 | FH46: =FD46+FF46 -> 0 | FI46: =FE46+FG46 -> 0 | FJ46: =FH46+FI46 -> 0 | FK46: =EW46+CW46+AS46 -> 0 | FL46: =EX46+CX46+AT46 -> 0 | FM46: =FK46+FL46 -> 0 | FT46: =SUM(FN46+FQ46) -> 0 | FU46: =SUM(FO46+FR46) -> 0 | FV46: =SUM(FT46:FU46) -> 0 | GD46: =FX46+GA46 -> 0 | GE46: =FY46+GB46 -> 0 | GF46: =GD46+GE46 -> 0 | GN46: =GH46+GK46 -> 0 | GO46: =GI46+GL46 -> 0 | GP46: =GN46+GO46 -> 0 | GR46: =GN46+GD46+FT46+ES46+EI46+DY46+DO46+CS46+CI46+BT46+BJ46 -> 0 | GS46: =GO46+GE46+FU46+ET46+EJ46+DZ46+DP46+CT46+CJ46+BU46+BK46 -> 0 | GT46: =GH46+FX46+FN46+EM46+EC46+DS46+DI46+CM46+CC46+BN46+BD46 -> 0 | GU46: =GI46+FY46+FO46+EN46+ED46+DT46+DJ46+CN46+CD46+BO46+BE46 -> 0 | GV46: =GK46+GA46+FQ46+EP46+EF46+DV46+DL46+CP46+CF46+BQ46+BG46 -> 0 | GW46: =GL46+GB46+FR46+EQ46+EG46+DW46+DM46+CQ46+CG46+BR46+BH46 -> 0 | GZ46: =GX46+GY46 -> 0 | HC46: =HA46+HB46 -> 0 | HD46: =GX46+HA46 -> 0 | HE46: =GY46+HB46 -> 0 | HF46: =HD46+HE46 -> 0 | HH46: =HD46+GN46+GD46+FT46 -> 0 | HI46: =GO46+GE46+FU46+HE46 -> 0 | HJ46: =GX46+GH46+FX46+FN46 -> 0 | HK46: =GI46+FY46+GY46+FO46 -> 0 | HL46: =GK46+GA46+FQ46+HA46 -> 0 | HM46: =GL46+HB46+GB46+FR46 -> 0 | HO46: =HF46+GP46+GF46+FV46 -> 0 | HQ46: =HQ43+HQ42+HQ41+HQ34 -> 228 | HR46: =HR43+HR42+HR41+HR34 -> 260 | HS46: =HS43+HS42+HS41+HS34 -> 0 | HT46: =HT43+HT42+HT41+HT34 -> 0 | HW46: =HU46+HV46 -> 0 | HZ46: =HX46+HY46 -> 0 | IA46: =HU46+HX46 -> 0 | IB46: =HV46+HY46 -> 0 | IC46: =IA46+IB46 -> 0 | JN46: =JG46+IW46+IM46+IC46 -> 0 | JZ46: =JX46+JN46+HO46+FB46 -> 0
A47: Indicator 2: Number of unaccompanied and/or separated children who are reunited with their caregivers OR in appropriate protective arrangements based on BIA | B47: Conduct child family tracing and reunification | C47: Nakivale | D47: 10 | AS47: =AO47+AE47+U47+K47 -> 0 | AT47: =AP47+AF47+V47+L47 -> 0 | AU47: =AK47+AA47+Q47+G47 -> 0 | AV47: =AN47 -> 0 | AX47: =SUM(AQ47+AG47+W47+M47) -> 0 | AY47: =AX47/AW47 -> #DIV/0! | AZ47: =SUM(E47+O47+Y47+AI47) -> 0 | BA47: =F47+P47+Z47+AJ47 -> 0 | BB47: =H47+R47+AB47+AL47 -> 0 | BC47: =I47+S47+AC47+AM47 -> 0 | BX47: =BN47+BD47+AI47+Y47+O47+E47 -> 0 | BY47: =BO47+BE47+AJ47+Z47+P47+F47 -> 0 | BZ47: =BQ47+BG47+AL47+AB47+R47+H47 -> 0 | CA47: =BR47+BH47+AM47+AC47+S47+I47 -> 0 | CB47: =BX47+BY47+BZ47+CA47 -> 0 | CC47: 0 | CD47: 0 | CE47: =SUM(CC47:CD47) -> 0 | CF47: 0 | CG47: 0 | CH47: =SUM(CF47:CG47) -> 0 | CI47: =SUM(CC47+CF47) -> 0 | CJ47: =SUM(CD47+CG47) -> 0 | CK47: =SUM(CI47:CJ47) -> 0 | CW47: =SUM(CS47+CI47+BT47+BJ47) -> 0 | CX47: =SUM(CT47+CJ47+BU47+BK47) -> 0 | CY47: =SUM(CU47+CK47+BV47+BL47) -> 0 | CZ47: =SUM(CR47+CH47+BS47+BI47) -> 0 | DB47: =SUM(CW47:CX47) -> 0 | DD47: =BD47+BN47+CC47+CM47 -> 0 | DE47: =BE47+BO47+CD47+CN47 -> 0 | DF47: =BG47+BQ47+CF47+CP47 -> 0 | DG47: =BH47+BR47+CG47+CQ47 -> 0 | DH47: =DB47+AX47 -> 0 | DI47: 7 | DK47: =SUM(DI47:DJ47) -> 7 | DL47: 0 | DM47: 0 | DN47: =SUM(DL47:DM47) -> 0 | DO47: =SUM(DI47+DL47) -> 7 | DP47: =SUM(DJ47+DM47) -> 0 | DQ47: =SUM(DO47:DP47) -> 7 | DS47: 8 | DU47: =SUM(DS47:DT47) -> 8 | DX47: =SUM(DV47:DW47) -> 0 | DY47: =SUM(DS47+DV47) -> 8 | DZ47: =SUM(DT47+DW47) -> 0 | EA47: =SUM(DY47:DZ47) -> 8 | EC47: 2 | ED47: 3 | EE47: =SUM(EC47:ED47) -> 5 | EF47: 0 | EG47: 0 | EH47: =SUM(EF47:EG47) -> 0 | EI47: =SUM(EC47+EF47) -> 2 | EJ47: =SUM(ED47+EG47) -> 3 | EK47: =SUM(EI47:EJ47) -> 5 | EM47: 9 | EN47: 5 | EO47: =SUM(EM47:EN47) -> 14 | EP47: 0 | EQ47: 0 | ER47: 0 | ES47: =SUM(EM47+EP47) -> 9 | ET47: =SUM(EN47+EQ47) -> 5 | EU47: =SUM(ES47:ET47) -> 14 | EW47: =SUM(ES47+EI47+DY47+DO47) -> 26 | EX47: =SUM(ET47+EJ47+DZ47+DP47) -> 8 | EY47: =SUM(EO47+EE47+DU47+DK47) -> 34 | EZ47: =SUM(ER47+EH47+DX47+DN47) -> 0 | FB47: =SUM(EW47:EX47) -> 34 | FD47: =DI47+DS47+EC47+EM47+CM47+CC47 -> 26 | FE47: =DJ47+DT47+ED47+EN47+CD47+CN47 -> 8 | FF47: =DL47+DV47+EF47+EP47+CP47+CF47 -> 0 | FG47: =DM47+DW47+EG47+EQ47+CG47+CQ47 -> 0 | FH47: =FD47+FF47 -> 26 | FI47: =FE47+FG47 -> 8 | FJ47: =FH47+FI47 -> 34 | FK47: =EW47+CW47+AS47 -> 26 | FL47: =EX47+CX47+AT47 -> 8 | FM47: =FK47+FL47 -> 34 | FN47: 0 | FO47: 0 | FP47: =FN47+FO47 -> 0 | FQ47: 0 | FR47: 0 | FS47: =FQ47+FR47 -> 0 | FT47: =SUM(FN47+FQ47) -> 0 | FU47: =SUM(FO47+FR47) -> 0 | FV47: =SUM(FT47:FU47) -> 0 | FX47: 2 | FY47: 0 | FZ47: =FX47+FY47 -> 2 | GA47: 0 | GB47: 0 | GC47: =GA47+GB47 -> 0 | GD47: =FX47+GA47 -> 2 | GE47: =FY47+GB47 -> 0 | GF47: =GD47+GE47 -> 2 | GH47: 0 | GI47: 4 | GJ47: =GH47+GI47 -> 4 | GK47: 0 | GL47: 0 | GM47: =GK47+GL47 -> 0 | GN47: =GH47+GK47 -> 0 | GO47: =GI47+GL47 -> 4 | GP47: =GN47+GO47 -> 4 | GR47: =GN47+GD47+FT47+ES47+EI47+DY47+DO47+CS47+CI47+BT47+BJ47 -> 28 | GS47: =GO47+GE47+FU47+ET47+EJ47+DZ47+DP47+CT47+CJ47+BU47+BK47 -> 12 | GT47: =GH47+FX47+FN47+EM47+EC47+DS47+DI47+CM47+CC47+BN47+BD47 -> 28 | GU47: =GI47+FY47+FO47+EN47+ED47+DT47+DJ47+CN47+CD47+BO47+BE47 -> 12 | GV47: =GK47+GA47+FQ47+EP47+EF47+DV47+DL47+CP47+CF47+BQ47+BG47 -> 0 | GW47: =GL47+GB47+FR47+EQ47+EG47+DW47+DM47+CQ47+CG47+BR47+BH47 -> 0 | GX47: 1 | GY47: 2 | GZ47: =GX47+GY47 -> 3 | HA47: 0 | HB47: 0 | HC47: =HA47+HB47 -> 0 | HD47: =GX47+HA47 -> 1 | HE47: =GY47+HB47 -> 2 | HF47: =HD47+HE47 -> 3 | HH47: =HD47+GN47+GD47+FT47 -> 3 | HI47: =GO47+GE47+FU47+HE47 -> 6 | HJ47: =GX47+GH47+FX47+FN47 -> 3 | HK47: =GI47+FY47+GY47+FO47 -> 6 | HL47: =GK47+GA47+FQ47+HA47 -> 0 | HM47: =GL47+HB47+GB47+FR47 -> 0 | HO47: =HF47+GP47+GF47+FV47 -> 9 | HQ47: =FN47+FX47+GH47+GX47 -> 3 | HR47: =FO47+FY47+GI47+GY47 -> 6 | HS47: =FQ47+GA47+GK47+HA47 -> 0 | HT47: =FR47+GB47+GL47+HB47 -> 0 | HU47: 3 | HV47: 6 | HW47: =HU47+HV47 -> 9 | HX47: 9 | HY47: 9 | HZ47: =HX47+HY47 -> 18 | IA47: =HU47+HX47 -> 12 | IB47: =HV47+HY47 -> 15 | IC47: =IA47+IB47 -> 27 | JN47: =JG47+IW47+IM47+IC47 -> 27 | JZ47: =JX47+JN47+HO47+FB47 -> 70 | KA47: =SUM(JV47+JE47+IU47+IK47+IA47+HD47+GN47+GD47+FT47+ES47+EI47+DY47+DO47+CS47+CI47+BT47+BJ47+AO47+AE47+U47+K47) -> 41 | KB47: =SUM(JW47+JF47+IV47+IL47+IB47+HE47+GO47+GE47+FU47+ET47+EJ47+DZ47+DP47+CT47+CJ47+BU47+BK47+AP47+AF47+V47+L47) -> 29 | KC47: =SUM(JP47+IY47+IO47+IE47+HU47+GX47+GH47+FX47+FN47+EM47+EC47+DS47+DI47+CM47+CC47+BN47+BD47+AI47+Y47+O47+E47) -> 32 | KD47: =SUM(JQ47+IZ47+IP47+IF47+HV47+GY47+GI47+FY47+FO47+EN47+ED47+DT47+DJ47+CN47+CD47+BO47+BE47+AJ47+Z47+P47+F47) -> 20 | KE47: =SUM(JS47+JB47+IR47+IH47+HX47+HA47+GK47+GA47+FQ47+EP47+EF47+DV47+DL47+CP47+CF47+BQ47+BG47+AL47+AB47+R47+H47) -> 9 | KF47: =SUM(JT47+JC47+IS47+II47+HY47+HB47+GL47+GB47+FR47+EQ47+EG47+DW47+DM47+CQ47+CG47+BR47+BH47+AM47+AC47+S47+I47) -> 9 | KG47: =SUM(KA47:KB47) -> 70 | KH47: 10 | KI47: =KH47-KG47 -> -60 | KJ47: =KG47/KH47 -> 7 | KK47: =KI47/10 -> -6
