Workbook

Sheet a. Problem Tree Documentation.
A1: Instructions: The easiest way to insert a final draft of the Problem Tree analysis into the Project Design Workbook is to use the “Snipping Tool” which is a Microsoft tool found in the Start Menu: All Programs – Accessories – Snipping Tool. Select and copy the whole graphic and paste it into the Project Design Workbook in the Problem Analysis Documentation tab. The Snipping Tool can be used to copy and paste from any electronic medium, including websites, Microsoft Office applications, etc.
A2: KEY: Any method or program can be used to document the results of the Problem Analysis in the Project Design Workbook, including a photo of the document the group uses to work through this analysis. What is important is that the results are documented and can be clearly read.
A3: Below is an example of a Word template pasted in the tab using the Snipping Tool. Simply delete this example and paste your finalized Problem Analysis results when it is completed.
G4: LWR PROBLEM TREE SAMPLE MODEL
C6: Effect 1: Food Insecurity | F6: Effect 2: Poor Household income | I6: Effect 3: Poor Nutrition | L6: Effect 4: Poor Health
C8: Problem Statement:Low income, self reliance and and livelihood opportunities for South Sudan refugees and their host communities in and around palabek settlement.
E10: Cause 1: There is poor productivity and low income from agriculture for South Sudanese refugees and host communities | H10: Cause 2: South Sudan vulnerable refugees have poor living conditions
E13: Cause 1.a: South Sudan refugees and host communities have poor access to agricultural extension services | H13: Cause 2.a: South Sudan vulnerable refugees have limited access to resources.
E16: Cause 1.b: South Sudan and host communities have limited access to agricultural inputs | H16: Cause 2.b: South Sudan refugee children have limited access to material resources.
E19: Cause 1.c: South Sudan refugees and host communities have poor knowledge on recommended agronomic practices.

Sheet b. Problems to Objectives
A1: Explanation | B1: The PROBLEM/CAUSE column: Enter the problems and causes from the Problem Analysis. Remember, the problems and causes are the reality currently experienced in the target area. These are therefore expressed as the negative condition. For example, "Poor agricultural productivity in the priority action zone." | C1: The EVIDENCE FOR PROBLEM/CAUSE W/CITATION column is a way to document the source of the evidence for each problem or cause. It helps ensure that the problems and causes identified in the project design are based on actual or observed situations. It is a way to document what is found in the Needs Assessment but can also come from peer agency needs assessments, government reports, agency reports or another published document. The document or source of the evidence for each problem/cause should be written in parenthesis after the evidence. For example, if the Problem is "poor agricultural productivity in the priority action zone," then the evidence with citation could be “Agricultural output in the PAZ has decreased by 25% from 2011-2013 (Needs assessment section 2.1).” The citation helps document key information and can also assist in setting indicators or beneficiary targets. | E1: The OBJECTIVE STATEMENT column is where the project's objectives are documented. Having this column on the same page as the PROBLEM/CAUSE helps ensure that the proposed objective responds to the problems/causes identified during the assessment stage. The objectives statements are the opposite of negative condition identified in the Problem Analysis. They are written as the positive condition and as if the result has already been achieved. The Objective Analysis Tool Summary, as well as the guidance in the sections related to the objective analysis in the IFRC Project Planning Guidance, can assist in selecting the most appropriate objectives for the context of the project. The Results Framework can then be used to verify the logic between the selected Goal, Outcomes and Outputs.
A2: Project Title: | B2: REselience SUpport Leading To Sustainable Livelihoods for South Sudanese Refugees (RESULTS Livelihoods) Project
A3: # | B3: PROBLEM/CAUSE | C3: EVIDENCE FOR PROBLEM-CAUSE W/ CITATION | D3: # | E3: OBJECTIVE STATEMENT
A4: Problem 1 | B4: Targeted South Sudan refugees and their host communities do not optimise income and livelihood opportunities | D4: GOAL: | E4: Targeted South Sudan refugees and their host communities optimize income, self reliance and livelihood opportunities
A5: Cause 1 | B5: Targeted South Sudan refugees and their host communities have poor productivity and low income from agriculture | D5: Outcome 1 | E5: Targeted South Sudan refugees and their host communities have improved productivity and increased income generated from agriculture
A6: Cause 1.1 | B6: Targeted South Sudan refugees and their host communities have poor access to agricultural extension services | D6: Output 1.1 | E6: Targeted South Sudan Refugees and their host communities have access to agricultural extension services
A7: Cause 1.2 | B7: Targeted South Sudan refugees and their host communities have limited access to agricultural inputs | D7: Output 1.2 | E7: Targeted South Sudan Refugees and their host communities have access to agricultural inputs
A8: Cause 1.3 | B8: Targeted South Sudan refugees and their host communities have poor knowledge on recommended agronomic practices | D8: Output 1.3 | E8: Targeted South Sudan Refugees and their host communities practice climate smart agriculture
A9: Cause 2 | B9: Targeted South Sudn vulnerable refugees have poor living conditions | D9: Outcome 2 | E9: Targeted South Sudan vulnerable refugees have improved living conditions
A10: Cause 2.1 | B10: Targeted South Sudan vulverable refugees have limited access to resources | D10: Output 2.1 | E10: Targeted South Sudan vulnerable refugees have access to resources (mission quilts and personal care kits)
A11: Cause 2.2 | B11: Targeted South Sudan refugees children have limited access to material resources | D11: Output 2.2 | E11: Targeted South Sudan refugee children have access to material resources (baby care kits)
A12: Cause 3 | D12: Outcome 3
A13: Cause 3.1 | D13: Output 3.1
A14: Cause 4 | D14: Outcome 4
A15: Cause 4.1 | D15: Output 4.1
A16: Cause 5 | D16: Outcome 5
A17: Cause 5.1 | D17: Output 5.1

Sheet c. Results Framework
A1: The following 3 templates (Results Framework, Logframe, Work Plan) are designed to be used together and some cells are linked. When you enter information into the Results Framework, it automatically fills in details in the Logical Framework and Work Plan. This ensures that the objectives statements are consistent throughout the document. If edits are made to the objective statements, only make changes in the Results Framework. Because the Results Framework, LogFrame and WorkPlan are linked, it is very important to NOT modify the formulas in the objective statement columns of the Evidence for Cause, Logframe and Work Plan tabs. If you have any questions about modifying these templates, please contact the M&E Unit for technical support.
A2: Project Title | B2: ='b. Problems to Objectives'!B2:E2 -> REselience SUpport Leading To Sustainable Livelihoods for South Sudanese Refugees (RESULTS Livelihoods) Project
A4: GOAL: | B4: ='b. Problems to Objectives'!E4 -> Targeted South Sudan refugees and their host communities optimize income, self reliance and livelihood opportunities
A6: Outcome | C6: =A6 -> Outcome | E6: =C6 -> Outcome | G6: =E6 -> Outcome | I6: =G6 -> Outcome
A7: 1 | C7: =A7+1 -> 2 | E7: =C7+1 -> 3 | G7: =E7+1 -> 4 | I7: =G7+1 -> 5
A8: ='b. Problems to Objectives'!E5 -> Targeted South Sudan refugees and their host communities have improved productivity and increased income generated from agriculture | C8: ='b. Problems to Objectives'!E9 -> Targeted South Sudan vulnerable refugees have improved living conditions | E8: ='b. Problems to Objectives'!E12 -> 0 | G8: ='b. Problems to Objectives'!E14 -> 0
B9: Output | D9: =B9 -> Output | F9: =D9 -> Output | H9: =F9 -> Output | J9: =H9 -> Output
B10: =A7+0.1 -> 1.1 | D10: =C7+0.1 -> 2.1 | F10: =E7+0.1 -> 3.1 | H10: =G7+0.1 -> 4.1 | J10: =I7+0.1 -> 5.1
B11: ='b. Problems to Objectives'!E6 -> Targeted South Sudan Refugees and their host communities have access to agricultural extension services | D11: ='b. Problems to Objectives'!E10 -> Targeted South Sudan vulnerable refugees have access to resources (mission quilts and personal care kits) | F11: ='b. Problems to Objectives'!E13 -> 0 | H11: ='b. Problems to Objectives'!E15 -> 0 | J11: ='b. Problems to Objectives'!E17 -> 0
B12: =B10+0.1 -> 1.2 | D12: =D10+0.1 -> 2.2 | F12: =F10+0.1 -> 3.2 | H12: =H10+0.1 -> 4.2 | J12: =J10+0.1 -> 5.2
B13: ='b. Problems to Objectives'!E7 -> Targeted South Sudan Refugees and their host communities have access to agricultural inputs | D13: ='b. Problems to Objectives'!E11 -> Targeted South Sudan refugee children have access to material resources (baby care kits)
B14: =B12+0.1 -> 1.3 | D14: =D12+0.1 -> 2.3 | H14: =H12+0.1 -> 4.3 | J14: =J12+0.1 -> 5.3
B15: ='b. Problems to Objectives'!E8 -> Targeted South Sudan Refugees and their host communities practice climate smart agriculture
B16: =B14+0.1 -> 1.4 | D16: =D14+0.1 -> 2.4 | F16: =F14+0.1 -> 0.1 | H16: =H14+0.1 -> 4.4 | J16: =J14+0.1 -> 5.4
B18: =B16+0.1 -> 1.5 | D18: =D16+0.1 -> 2.5 | H18: =H16+0.1 -> 4.5 | J18: =J16+0.1 -> 5.5

Sheet d. LogFrame
A1: ='c. Results Framework'!A2 -> Project Title | E1: ='c. Results Framework'!B2 -> REselience SUpport Leading To Sustainable Livelihoods for South Sudanese Refugees (RESULTS Livelihoods) Project
C2: PROBLEM/CAUSE | D2: EVIDENCE OF PROBLEM-CAUSE WITH CITATION | E2: OBJECTIVE STATEMENT | F2: OBJECTIVELY VERIFIABLE INDICATOR | G2: MEANS OF VERIFICATION | H2: RISK AND ASSUMPTION
A3: ='c. Results Framework'!A4 -> GOAL: | C3: ='b. Problems to Objectives'!B4 -> Targeted South Sudan refugees and their host communities do not optimise income and livelihood opportunities | D3: ='b. Problems to Objectives'!C4 -> 0 | E3: ='c. Results Framework'!B4 -> Targeted South Sudan refugees and their host communities optimize income, self reliance and livelihood opportunities
A4: ='c. Results Framework'!A6 -> Outcome | B4: ='c. Results Framework'!A7 -> 1 | C4: ='b. Problems to Objectives'!B5 -> Targeted South Sudan refugees and their host communities have poor productivity and low income from agriculture | D4: ='b. Problems to Objectives'!C5 -> 0 | E4: ='c. Results Framework'!A8 -> Targeted South Sudan refugees and their host communities have improved productivity and increased income generated from agriculture | F4: 1a 80% of Refugee and host communities HHs report increased food production by Sept 2018 | G4: Presence of backyard gardens in target refugee house holds | H4: Refugees and host communities embrace the services provided by the project
A5: ='c. Results Framework'!B9 -> Output | B5: ='c. Results Framework'!B10 -> 1.1 | C5: ='b. Problems to Objectives'!B6 -> Targeted South Sudan refugees and their host communities have poor access to agricultural extension services | D5: ='b. Problems to Objectives'!C6 -> 0 | E5: ='c. Results Framework'!B11 -> Targeted South Sudan Refugees and their host communities have access to agricultural extension services | F5: 1.1a 40 women refugee volunteers are identified and selected to support extension service provision 1.1b 1800 refugees are receiving extension services from refugee volunteer farmers | G5: Presence of Volunteer Refugee farmers that have been trained in good agronomic practices | H5: Refugees and host communities are interested in getting extension support
A6: Activity | B6: 1.1.A. | E6: Identify volunteer youth farmers from Refugee households and host community
A7: Activity | B7: 1.1.B. | E7: Conduct a TOT for the Refugee Women Volunteers in Good agronomic practices
A8: Activity | B8: 1.1.C. | E8: Conduct regular field visits to host community farmers and Refugees HHs
A9: =A5 -> Output | B9: ='c. Results Framework'!B12 -> 1.2 | C9: ='b. Problems to Objectives'!B7 -> Targeted South Sudan refugees and their host communities have limited access to agricultural inputs | D9: ='b. Problems to Objectives'!C7 -> 0 | E9: ='c. Results Framework'!B13 -> Targeted South Sudan Refugees and their host communities have access to agricultural inputs | F9: 1.2.a 64 farmer groups of both refugees and host communities are formed 1.2b 1920 refugees and host community HHs receive agricultural seeds (OLSP, beans and amaranth) | G9: Presence of distribution records | H9: Presence of quality seed inputs and suppliers
A10: Activity | B10: 1.2.A. | E10: Formation of farmer groups at refugee and host community levels
A11: Activity | B11: 1.2.B. | E11: Provide Agricultural seeds to identified Refugee and host community HHs
A12: Activity | B12: 1.2.C. | E12: Conduct quarterly review meetings to review project progress
A13: =A9 -> Output | B13: ='c. Results Framework'!B14 -> 1.3 | C13: ='b. Problems to Objectives'!B8 -> Targeted South Sudan refugees and their host communities have poor knowledge on recommended agronomic practices | D13: ='b. Problems to Objectives'!C8 -> 0 | E13: ='c. Results Framework'!B15 -> Targeted South Sudan Refugees and their host communities practice climate smart agriculture | F13: 1.3.a 1920 refugee households are applying good agronomic practices in their gardens | G13: Presence of backyard gardens at target refugee and host community house holds | H13: Refugges and host communites are willing to learn
A14: Activity | B14: 1.3.A. | E14: Setup RHHs and host community backyard gardens
A15: Activity | B15: 1.3.B. | E15: Provide technical backstoping to model farmers
A16: Activity | B16: 1.3.C.
A17: =A4 -> Outcome | B17: ='c. Results Framework'!C7 -> 2 | C17: ='b. Problems to Objectives'!B9 -> Targeted South Sudn vulnerable refugees have poor living conditions | D17: ='b. Problems to Objectives'!C9 -> 0 | E17: ='c. Results Framework'!C8 -> Targeted South Sudan vulnerable refugees have improved living conditions | F17: 2a 100% of vulnerable refugee women and children are properly selected and documented | G17: Presence of records of distribution lists for both the mothers and babies | H17: Refugees and host communities are interested to learn how to use the items provided
A18: ='c. Results Framework'!D9 -> Output | B18: ='c. Results Framework'!D10 -> 2.1 | C18: ='b. Problems to Objectives'!B10 -> Targeted South Sudan vulverable refugees have limited access to resources | D18: ='b. Problems to Objectives'!C10 -> 0 | E18: ='c. Results Framework'!D11 -> Targeted South Sudan vulnerable refugees have access to resources (mission quilts and personal care kits) | F18: 2.1.a 3000 vulnerable refugee women receive material resouces of mission quilts and personal care kits | G18: Presence of records of distribution lists for mission quilts and personal care kits | H18: Refugees and host communities are interested to learn how to use the items provided
A19: Activity | B19: 2.1.A. | E19: Selection and documetnation of the most in need refugees
A20: Activity | B20: 2.1.B. | E20: Distribution of Quilts and personal Care kits
A21: Activity | B21: 2.1.C.
A22: =A18 -> Output | B22: ='c. Results Framework'!D12 -> 2.2 | C22: ='b. Problems to Objectives'!B11 -> Targeted South Sudan refugees children have limited access to material resources | D22: ='b. Problems to Objectives'!C11 -> 0 | E22: ='c. Results Framework'!D13 -> Targeted South Sudan refugee children have access to material resources (baby care kits) | F22: 2.2.a 2,682 babies receive material resources of baby care kits | G22: Presence of records of distribution lists for baby care kits | H22: Refugees and host communities are interested to learn how to use the items provided
A23: Activity | B23: 2.2.A. | E23: Selection and documetnation refugee Women with new borns
A24: Activity | B24: 2.2.B. | E24: Distribution of baby care Kits to 2,682 babies
A25: Activity | B25: 2.2.C.
A26: =A17 -> Outcome | B26: ='c. Results Framework'!E7 -> 3 | C26: ='b. Problems to Objectives'!B12 -> 0 | D26: ='b. Problems to Objectives'!C12 -> 0 | E26: ='c. Results Framework'!E8 -> 0
A27: ='c. Results Framework'!F9 -> Output | B27: ='c. Results Framework'!F10 -> 3.1 | C27: ='b. Problems to Objectives'!B13 -> 0 | D27: ='b. Problems to Objectives'!C13 -> 0 | E27: ='c. Results Framework'!F11 -> 0
A28: Activity | B28: 3.1.A.
A29: Activity | B29: 3.1.B.
A30: =A26 -> Outcome | B30: ='c. Results Framework'!G7 -> 4 | C30: ='b. Problems to Objectives'!B14 -> 0 | D30: ='b. Problems to Objectives'!C14 -> 0 | E30: ='c. Results Framework'!G8 -> 0
A31: ='c. Results Framework'!H9 -> Output | B31: ='c. Results Framework'!H10 -> 4.1 | C31: ='b. Problems to Objectives'!B15 -> 0 | D31: ='b. Problems to Objectives'!C15 -> 0 | E31: ='c. Results Framework'!H11 -> 0
A32: Activity | B32: 4.1.A.
A33: Activity | B33: 4.1.B.
A34: =A30 -> Outcome | B34: ='c. Results Framework'!I7 -> 5 | C34: ='b. Problems to Objectives'!B16 -> 0 | D34: ='b. Problems to Objectives'!C16 -> 0 | E34: ='c. Results Framework'!I8 -> 0
A35: ='c. Results Framework'!J9 -> Output | B35: ='c. Results Framework'!J10 -> 5.1 | C35: ='b. Problems to Objectives'!B17 -> 0 | D35: ='b. Problems to Objectives'!C17 -> 0 | E35: ='c. Results Framework'!J11 -> 0
A36: Activity | B36: 5.1.A.
A37: Activity | B37: 5.1.B.

Sheet Detail M&E Plan Instructions
A1: LWR Detailed M&E Plan Instructions
A2: 1. Complete the M&E Matrix: It can be developed within the tab or within a Word document and transferred to the M&E Matrix tab.
A3: a. For detailed instructions on completing the content of the M&E Matrix, please refer to tab c. M&E Matrix Cheat Sheet.
A4: b. Enter the objective statements and indicators ONLY in the M&E Matrix. They are automatically linked to the Indicator Tracking Table (ITT) and the Activity Tracking Table (ATT).
A5: 2. Baseline Table:
A6: a. Fill in the Baseline Table after or as the baseline data is collected either by a consultant or the project team.
A7: 3. Complete the Indicator Tracking Table: See tab i. for further instructions on using the ITT.
A8: a. Fill in the Project Name and the Project Year (PY) for the ITT. The blank version of this workbook contains linked ITT and ATT tables for up to a three year project.
A9: b. Fill in the baseline values for each indicator including the date it was collected and the unit of measurement. If the baseline values do not come from a consolidated baseline survey, note in the status column where the values are archived (the document, file, government database, etc). The baseline values are automatically populated in the Year 2 and Year 3 ITTs in the blank workbook.
A10: 4. Set indicator targets:
A11: a. Indicator targets should be set for each indicator based upon the details outlined in the project proposal taking into consideration timelines, number of staff, and budget. Start with Life of Project (LOP) targets, then annual targets, then quarterly targets. Targets should be based on the project’s work plan/detailed implementation plan.
A12: i. All targets and actuals should be cumulative. This means that targets and actuals recorded for each quarter reflect what has been targeted or achieved to date. If a given indicator cannot be recorded in a cumulative manner for some reason, include a note in the status column.
... A27: d. For each reporting period, update the status of the activity in column W. It should be updated with "Not yet started," In progress," or "Completed." If it is completed, list the date completed.

Sheet M&E Matrix Description
A1: TOOL SUMMARY: M&E MATRIX INSTRUCTIONS
A2: Purpose | B2: The purpose of this tool is to guide staff to complete each column of the M&E Matrix.
B3: · The M&E Matrix is a critical tool for planning and managing data collection, analysis, and use. It expands on the Logframe to identify key information requirements for each indicator and summarizes the key M&E tasks for the project.
B4: o It helps staff determine if a proposed indicator can effectively measure the result to which it is linked.
B5: o It helps staff determine if the proposed indicators can feasibly be collected given time and resource constraints.
A6: Information Sources | B6: Information the project team should have before starting the M&E Matrix:
B7: · Logframe
B8: · Project Proposal (Initial M&E Plan)
B9: Guidance for M&E Matrix:
B10: · CRS SMILER Guide
A11: Who | B11: This tool is a reference that can be used as a reference for by any staff working to complete the M&E Matrix
A12: When | B12: Given that the M&E Matrix helps define the scope (cost, time) of the project’s monitoring system, it is recommended that the Indicator Definition, Frequency/Schedule, and Responsible Person columns be completed before finalizing the project proposal.
B13: The remaining columns of the M&E Matrix should be filled out as the information becomes available, but must be finalized within the following timeframes:
B14: · Projects 1 year or less: complete a detailed M&E plan within 60 days of the project approval
B15: · Projects with a duration of 1-3 years: complete a detailed M&E plan within 90 days of the project approval
B16: · Projects with a duration of 3-5 years: complete a detailed M&E plan within 120 days of project approval
A17: Requirements | B17: REQUIREMENTS:
B18: · This M&E Matrix should be used for all LWR projects.
B19: · The M&E Matrix is a living document and should be updated based upon relevant project adjustments
B20: o If the M&E Matrix is changed report the changes, the reason, and how it affects other aspects of the M&E and project implementation plan
B21: o If changes are made to the plan, ensure that HQ, the country office, and the partner have the updated version
B22: RECOMMENDATIONS:
B23: · Ideally, the M&E Matrix will be finalized during a joint project planning meeting (project kick-off meeting) with participation from both key partner and LWR staff.
B24: SMART Criteria:
B25: · SMART criteria are: Specific, Measurable, Attainable, Relevant, and Timebound.
B26: · It is recommended that objective statements in the Logframe are NOT written using SMART criteria.
B27: o Nevertheless, SMART objective statements can sometimes be used effectively within project proposals to show all the details of the expected result in one statement.
B28: · SMART criteria should be applied to indicators, not objective statements. (reference p. 37 of IFRC Project Planning Guidance Manual for further information on SMART criteria).
B29: · Follow the instructions and examples for writing indicators found in the Logframe Cheat Sheet.
B30: · As presented in the Logframe, each indicator may not meet all the SMART criteria, but once the M&E Matrix is fully developed the indicators should be SMART.
A31: Tips | B31: · The M&E Matrix should be completed by those who will be using it. This allows the project team to crosscheck the Logframe and indicators before project implementation (ensuring they are sensitive to field realities and team capacities). Team involvement is essential because the M&E Matrix requires their detailed knowledge of the project context, and their involvement reinforces their understanding of what data they are to collect and how they will collect them.
B32: · Keep the M&E Matrix plan appropriate for the scale and timeframe of the project. Remember, it should be ‘good enough’.
B33: · Double check that your indicators can be measured in a realistic manner. Balance qualitative and quantitative data to measure indicators.
B34: · Make sure to be clear who within the project team is responsible for “owning the M&E Matrix.” This includes ensuring it is thoroughly completed, that all relevant project stakeholders understand it and have copies of it, that any changes made are fully incorporated and shared, and to regularly monitor and manage that all outlined tasks are being completed. The same person should also be responsible for managing the Indicator Tracking Table and the Activity Tracking Table.
B35: · The M&E Matrix is nearly identical to USAID’s Performance Monitoring Plan. The instructions for the M&E Matrix can be applied to complete USAID’s PMP.
A36: How to Address Gender Issues | B36: · Sex-disaggregate data of all indicators for which people are the unit of measure.
B37: · Include qualitative and quantitative indicators .

Sheet M&E Matrix Cheat Sheet
A1: M&E Matrix Cheat Sheet [1]
A2: PERFORMANCE INDICATORS | D2: DATA GATHERING | H2: ANALYSIS, USE, REPORTING
A3: Indicator | B3: Indicator Definition | C3: Unit of Measurement | D3: Method | E3: Means of Verification (Data Source/Tools) | F3: Frequency & Schedule | G3: Responsible Person | H3: Data Analysis | I3: Information Use/Audience | J3: Reporting
A4: - Indicators are taken from the logframe. When transferring them, check to ensure they are SMART (specific, measureable, achievable, relevant, and time-bound). - Often, the indicator may need to be revised according to field realities. If this is the case, be sure any revisions are approved by LWR and/or the donor. - If indicators are updated here, ensure the logframe is also updated. | B4: - Each indicator needs a detailed definition of its key terms, including an explanation of specific aspects that will be measured (such as who, what, and where the indicator applies). - Define subjective words as necessary, such as “appropriate,” “successful,” “sustainable,” “sufficient,” “capacity,” etc. - The definition should explain precisely how the indicator will be calculated, such as the numerator and denominator of a percent measure. - This column should also note if the indicator is to be disaggregated by sex, age, ethnicity, or some other variable. | C4: -Each indicator must have a clear unit of measure. | D4: -This column can be used to outline if the indicator will be collected during the baseline, during monitoring, and/or at the end of the project. Each of these require specific methods by which data will be collected during that period. These can include approaches such as use of secondary data, regular monitoring, baseline or endline surveys, PRA, focus group discussions, etc. -The method should match the Means of Verification. For example, if the method is ‘regular monitoring,’ the means of verification should be some type of report regularly produced by project staff. | E4: - This column identifies sources of information. - If multiple sources are listed, it must be clear how the information in the various sources will come together to make one aggregated data point for the indicator that can be entered into the ITT. - This column should also indicate whether data collection tools (questionnaires, checklists) are pre-existing or will need to be developed. - The logframe column on “Means of Verification” may list only one source (field agent report). The M&E plan requires much more detail, since the M&E system much include all responsbilities and related data collection templates and timeframes. | F4: - This column states the frequency for each indicator (monthly, quarterly, annually) as well as the scheduled (day/month/year). - The frequency and schedule listed must match the targets set in the Indicator Tracking Table. - When planning for data collection timing, it is important to consider factors such as planting and harvest periods, seasonal variations, school schedules, holidays, and religious observances (i.e. Ramadan). | G4: - This column lists the people responsible and accountable for the data collection and analysis, i.e., community volunteers, field staff, project managers, local partner/s, and external consultants. - In addition to specific people’s names, use the position title to ensure clarity in case of personnel changes. - This column is useful to budget for M&E staff and planning for their capacity building. | H4: -This column should be used by the project team for whatever reminders or support are deemed practical. It describes the process for compiling and analyzing the data. This process gauges if the indicator has been met. - For example, survey data usually requires statistical analysis, while qualitative data may be reviewed by research staff or community members. - Include any questions that the project team may want to ask to better understand the data once it is compiled. | I4: - This column identifies the intended audience and use of the information. - For example, the findings could be used for monitoring project implementation, evaluating the interventions, planning future project work, or reporting to policy makers or donors. - Defining how you will use the information helps eliminate unnecessary indicators or analysis. The data should be linked clearly to decision making and/or accountability. - Reduce the quantity and frequency of data collection if the tabulation and analysis cannot be done in time for decision-making or communications and reporting. | J4: - It is important to identify in which reports each indicator data will appear. Communication and reporting mapping will assist in identifying where each indicator is reported. - This column should also state ways that the findings will be formatted (tables, graphs, maps, histograms, narrative reports). This will help to ensure that only the most relevant data and information is reported to each stakeholder, and will increase the likelihood of feedback on reported information.
A6: [1] M&E Plan Matrix template was derived from IFRC’s M&E Plan Template (April 6, 2011): http://ifrc.org/en/who-we-are/performance-and-accountability/monitoring-and-evaluation/, and CRS’ ProPak. The content for the instructions were borrowed primarily from IFRC’s M&E Plan Template (April 6, 2011) with additional content borrowed from CRS’ M&E in Emergencies, DESIGN: How to develop an M&E plan in an emergency project M&E Plan Template, Appendix 3, p. 54.

Sheet M&E Matrix Example 
A1: Project Name: | D1: Project Location: | H1: Project Year:
A2: Identifier | D2: Partner: | H2: Project Start Date:
A3: Project Sector(s): | H3: Project End Date:
A4: PERFORMANCE INDICATORS | D4: DATA GATHERING | H4: ANALYSIS, USE, REPORTING
A5: Indicator | B5: Indicator Definition | C5: Unit of Measurement | D5: Method | E5: Means of Verification | F5: Frequency and Schedule | G5: Reponsible person/ team | H5: Data Analysis | I5: Information Use/Audience | J5: Reporting
A6: GOAL: Communities living along Nepal- India boarder have a better quality of life as a result of being more resilient to flooding
A8: OUTCOME 1: Households living along the Nepal-India border have more robust livelihoods
A9: Indicator 1.a: % increase in household savings. | B9: % increase calculation: ((new period savings value - prior period savings value)/prior period savings value))*100 HH calculation: (savings increase of men + savings increase of women)/# members in HH with savings ITT Calculation: sum of all HH savings increase/total # HH Disaggregated by savings held by men and women within the household. | C9: Unit (s): Men and Women (in HH with savings) Household | D9: Baseline: 1. Household survey Monitoring: 2. Census Endline: N/A | E9: 1. Consultant database/Baseline Report 2.1. ITT 2.2. Director database 2.3. Consolidated savings group records 2.4 Savings group records | F9: 1. Beginning of project (Oct. 31, 2016) 2.1 Annually (Jan. 30) 2.2 Annually (Jan. 15) 2.3. Annually (Jan. 2) 2.4. Ongoing | G9: 1. Consultant 2.1. Project Director 2.2. Data entry officer 2.3. Field officer 2.4. Savings group record keeper | H9: Are men and women's savings rate different? If so, why? How much of the household savings is being used for livelihood activities? What is the minimum rate of savings that creates a robust livelihood? | I9: Project management team to determine if savings rates are increasing sufficiently to create more robust livelihoods. Savings group leaders to determine which members are more successful than others and how they can improve savings rates overall. | J9: Quarterly LWR progress reports.
A10: OUTPUT 1.1: Target communities have improved access to financial services
A11: Indicator 1.1.a: # of saving and credit groups/cooperatives formed and strengthened | B11: Calculation: Count number of formal/informal gropus involved in saving and Credits, Savings and Credit Group/Cooperative: Regulating fund mobilization at the community level Formed: created Strengthened: trained on purpose, norms | C11: Unit: Number of Saving and Credits groups | D11: Ongoing monitoring; Cooperative/self-help group meetings Partner responsible for Baseline data | E11: 1. ITT 2. Project Coordinator database 3. Social Mobilizer report | F11: 1. Quarterly 2. Quarterly 3. Monthly | G11: 1. Program Manager 2. Project Coordinator 3. Social Mobilizer | H11: Is the number of groups increasing over time? Are the groups getting stronger and/or improving their ability to provide service? | I11: Partners | J11: Quarterly

Sheet M&E Matrix
A1: “REAP PROJECT” M&E Matrix
A2: Project Name: | B2: RESULTS Livelihoods | D2: Project Location: | E2: Lamwo District | G2: Project Year: | I2: January 2018 -September 2018
A3: Identifier: | B3: 18-2210-1 | D3: Partner: | E3: African Women and Youth Action for Development | H3: Project Start Date: | I3: 1.01.2018
A4: Project Sector(s): | B4: Agriculture | H4: Project End Date: | I4: 30.09.2018
A5: PERFORMANCE INDICATORS | D5: DATA GATHERING | H5: ANALYSIS, USE, REPORTING
A6: Indicator | B6: Indicator Definition | C6: Unit of Measurement | D6: Method | E6: Mean of Verification | F6: Frequency and Schedule | G6: Reponsible person/ team | H6: Data Analysis | I6: Information Use/Audience | J6: Reporting Deadline
A7: GOAL: Increased household self-reliance and resilience among refugees and host community members in Palabek and Kyaka II refugee settlements.
A9: Outcome 1. Increased household food security and incomes among refugees and host communities
A10: Indicator 1.A. 1200 refugees and host communities achieve atleast 30% increase in household food production. | B10: 30% increase in food production calculation: ((new period amount of food produced - prior period amount of food produced)/prior period amount of food produced))*100 ITT Calculation: Count all refugees and host communities who achieved 30% + food production a year. | C10: Unit (s): Men and Women (engaged in own food production) Household | D10: Baseline: 1. Household survey Monitoring: 2. Census Endline: 3. Household survey | E10: 1. Consultant database/Endline Report 2.1. ITT 2.2. Consolidated group production records 2.3. Household group records | F10: 1. Beginning of year 2 (Oct. 31, 2018) 2. End of qourter 1 (31st December) 2. End of Quarter 2 (March 31st) 3. End of Quarter 3 (June 30th) 4. End of year (Sept 30th) 5. Endline Survey 6. Ongoing | G10: 1. Consultant 2.1. Project Manager 2.2. Project Ext officer 2.3. Field officer 2.4. Household record keeper | H10: Is own food production reducing dependence on food aid? If not, why? Is own food production contributing to increase in consumption diversity? Between male and female headed households, which are more food secure? | I10: 1. United Nations High Commission for Refugees (UNHCR) 2. Office of the Prime Minister (OPM) 3. Lamwo & Kyegegwa District Local Governments. 4. LWR Country Office & HQ. | J10: Quarterly LWR progress reports.
A11: Indicator 1.B. 800 refugees and host communities acquire atleast one productive household asset and one non-productive asset. | B11: ITT Calculation: 1. Count number of women who bought a productive asset within project period. 2. Count number of women who bought a productive asset within project period. 3. Add the number of women and men who bought a productive asset within project period. A productive asset may include: Farm tools, business equipment, livestock, bodaboda, truck, land, house, etc. | C11: Unit (s): Men and Women (in HH with Assets) Household | D11: Baseline: 1. Household survey Monitoring: 2. Census Endline: 3. Household survey | E11: 1. Consultant database/Endline Report 2.1. ITT 2.3.Household asset purchase records | F11: 1. Beginning of year 2 (Oct. 31, 2018) 2. End of qourter 1 (31st December) 2. End of Quarter 2 (March 31st) 3. End of Quarter 3 (June 30th) 4. End of year (Sept 30th) 5. Endline Survey 6. Ongoing | G11: 1. Consultant 2.1. Project Manager 2.2. Project Ext officer 2.3. Field officer 2.4. Household record keeper | H11: Are men and women to accumulating assets? If not, why? Howare the assets being used for generating better livelihoods? What are the key assets a household should have to promote resilient livelihoods? | I11: 1. United Nations High Commission for Refugees (UNHCR) 2. Office of the Prime Minister (OPM) 3. Lamwo & Kyegegwa District Local Governments. 4. LWR Country Office & HQ. | J11: Quarterly LWR progress reports.
A12: Indicator 1.C: 800 refugees and host community members increase their savings by atleast 50% | B12: % increase calculation: ((new period savings value - prior period savings value)/prior period savings value))*100 ITT Calculation: Count all refugees and host community members who increased their savings by 50% + during the project period. Disaggregated by savings held by men and women within the household. | C12: Unit (s): Men and Women (in HH with savings) Household | D12: Baseline: 1. Household survey Monitoring: 2. Census Endline: 3. Household survey | E12: 1. Consultant database/Endline Report 2.1. ITT 2.2. Consolidated savings group records 2.3. Savings group records | F12: 1. Beginning of year 2 (Oct. 31, 2018) 2. End of qourter 1 (31st December) 2. End of Quarter 2 (March 31st) 3. End of Quarter 3 (June 30th) 4. End of year (Sept 30th) 5. Endline Survey 6. Ongoing | G12: 1. Consultant 2.1. Project Director 2.2. Data entry officer 2.3. Field officer 2.4. Savings group record keeper | H12: Are men and women's savings rate different? If so, why? How much of the household savings is being used for livelihood activities? What is the minimum rate of savings that creates a robust livelihood? | I12: 1. United Nations High Commission for Refugees (UNHCR) 2. Office of the Prime Minister (OPM) 3. Lamwo & Kyegegwa District Local Governments. 4. LWR Country Office & HQ. | J12: Quarterly LWR progress reports.
A13: OUTPUT 1.1: Targeted Refugees and their host communities have access to communty extension services
A14: Indicator 1.1.a: 10 training modules (agronomy, PHH and eco-system mgt) conducted for lead/modal farmers | B14: Lead/Model Farmer - A refugee or host farmer is a member of the refugee/host farmer group selected by group as their peer leader/trainer. Farmer-to-Farmer Extension services - Refers to knowledge & skills provided by the lead/model farmers to at group level or household level during monitoring visit. ITT Calculation: Count the number of lead farmers who receieved atleast 10 training modules in Agronomy, PHH and eco-system management. | C14: Lead Farmers | D14: Baseline: 1. Household survey Monitoring: 2. Census Endline: 3. Household survey | E14: 1. Consultant database/Endline Report 2.1. ITT 2.2. Consolidated savings group records 2.3. Savings group records | F14: 1. Beginning of year 2 (Oct. 31, 2018) 2. End of qourter 1 (31st December) 2. End of Quarter 2 (March 31st) 3. End of Quarter 3 (June 30th) 4. End of year (Sept 30th) 5. Endline Survey 6. Ongoing | G14: 1. Consultant 2.1. Project Director 2.2. Data entry officer 2.3. Field officer | H14: Disaggregate by gender (women & men) | I14: 1. United Nations High Commission for Refugees (UNHCR) 2. Office of the Prime Minister (OPM) 3. Lamwo & Kyegegwa District Local Governments. 4. LWR Country Office & HQ. | J14: Quarterly LWR progress reports.
A15: Indicator 1.1.b: 1600 refugees & host communities receive extension services from lead/model farmers. | B15: Refugee = South Sudanese nationals who have been forced to leave their country to seek asylum in Uganda(Palabek refugee settlement) Host communities = Ugandan nationals living in and around Palabek refugee settlement. ITT Calculation Count the number of refugee and host community farmers who recieved advice/knowledge/skills from the lead farmers. | C15: Refugee and host community farmers | D15: Baseline: 1. Household survey Monitoring: 2. Census/ongoing Endline: 3. Household survey | E15: 1. Consultant database/Endline Report 2.1. ITT 2.2. Consolidated savings group records 2.3. Savings group records | F15: 1. Beginning of year 2 (Oct. 31, 2018) 2. End of qourter 1 (31st December) 2. End of Quarter 2 (March 31st) 3. End of Quarter 3 (June 30th) 4. End of year (Sept 30th) 5. Endline Survey 6. Ongoing | G15: 1. Consultant 2.1. Project Director 2.2. Data entry officer 2.3. Field officer 2.4. Savings group record keeper | H15: Disaggregate by gender (women & men) | I15: 1. United Nations High Commission for Refugees (UNHCR) 2. Office of the Prime Minister (OPM) 3. Lamwo & Kyegegwa District Local Governments. 4. LWR Country Office & HQ. | J15: Quarterly LWR progress reports.
A16: OUTPUT 1.2: Targeted refugees and host community members have access to improved high yielding seeds.
A17: Indicator 1.2.a: 1200 refugees and host community HHs receive high yeilding seeds | B17: Agricultural seeds = high yielding varieties of OSLP, cassava, okra, spinanch, onion, egg plant, and amaranth Host communities = Ugandan nationals living in and around Palabek refugee settlement. ITT Calculation: Count the number of refugees and Host communities who receive the one of the the following seeds: cassava, okra, OSP. | C17: Households | D17: Baseline: 1. Household survey Monitoring: 2. Census/ongoing Endline: 3. Household survey | E17: 1. Consultant database/Endline Report 2.1. ITT 2.2. Consolidated savings group records 2.3. Savings group records | F17: 1. Beginning of year 2 (Oct. 31, 2018) 2. End of qourter 1 (31st December) 2. End of Quarter 2 (March 31st) 3. End of Quarter 3 (June 30th) 4. End of year (Sept 30th) 5. Endline Survey 6. Ongoing | G17: 1. Consultant 2.1. Project Director 2.2. Data entry officer 2.3. Field officer | H17: Disaggregate by gender (women & men) | I17: 1. United Nations High Commission for Refugees (UNHCR) 2. Office of the Prime Minister (OPM) 3. Lamwo & Kyegegwa District Local Governments. 4. LWR Country Office & HQ. | J17: Quarterly LWR progress reports.
A18: OUTPUT 1.3: Targeted refugees engage in off-farm income generating activities.
A19: Indicator 1.3. a. 200 refugees supported to establish small scale businesses. | B19: Small-scale business - a business that has low capital investments and does not have a high volume of sales. ITT Calculation: Count the number of refugees who acquired a loan from the VSLA cash grants provided by LWR. | C19: Men and women operating businesses | D19: Baseline: 1. Household survey Monitoring: 2. Census/ ongoing Endline: 3. Household survey | E19: 1. Consultant database/Endline Report 2.1. ITT 2.2. Consolidated group production records 2.3. Business records | F19: 1. Beginning of year 2 (Oct. 31, 2018) 2. End of qourter 1 (31st December) 2. End of Quarter 2 (March 31st) 3. End of Quarter 3 (June 30th) 4. End of year (Sept 30th) 5. Endline Survey 6. Ongoing | G19: 1. Consultant 2.1. Project Manager 2.2. Project Ext officer 2.3. Field officer 2.4. Household record keeper | H19: Disaggregate by gender (women & men) | I19: 1. United Nations High Commission for Refugees (UNHCR) 2. Office of the Prime Minister (OPM) 3. Lamwo & Kyegegwa District Local Governments. 4. LWR Country Office & HQ. | J19: Quarterly LWR progress reports.
A20: Indicator 1.3.b. 50 refugee and host communities generating income from honey production and Marketing. | B20: Honey = A product of bees got from bee hives. Honey Production: Process of getting honey from bee hives. Honey Marketing: A process of selling honey. ITT Calculation: Count the number of refugee and host community members producing and selling honey. | C20: Men and women engaged in honey production and selling. | D20: Baseline: 1. Household survey Monitoring: 2. Census/ongoing Endline: 3. Household survey | E20: 1. Consultant database/Endline Report 2.1. ITT 2.2. Consolidated group production records 2.3. Household group records | F20: 1. Beginning of year 2 (Oct. 31, 2018) 2. End of qourter 1 (31st December) 2. End of Quarter 2 (March 31st) 3. End of Quarter 3 (June 30th) 4. End of year (Sept 30th) 5. Endline Survey 6. Ongoing | G20: 1. Consultant 2.1. Project Manager 2.2. Project Ext officer 2.3. Field officer 2.4. Group record keeper | H20: Disaggregate by gender (women & men) | I20: 1. United Nations High Commission for Refugees (UNHCR) 2. Office of the Prime Minister (OPM) 3. Lamwo & Kyegegwa District Local Governments. 4. LWR Country Office & HQ. | J20: Quarterly LWR progress reports.
A21: OUTPUT 1.4: Targeted refugees and host community members in engage in VSLA.
A22: Indicator 1.4.a: 30 Village Savings and Lending Associations (groups) formed and strengthened | B22: ITT Calculation: Count number of farmer gropus involved in VSLA. Savings and Credit Group/Cooperative: Regulating fund mobilization at the community level Formed: created Strengthened: trained on purpose, norms | C22: Unit: Number of Saving and Credits groups | D22: Ongoing monitoring; Cooperative/self-help group meetings Partner responsible for Baseline data | E22: 1. ITT 2. Project Coordinator database 3. Social Mobilizer report | F22: 1. Beginning of year 2 (Oct. 31, 2018) 2. End of qourter 1 (31st December) 2. End of Quarter 2 (March 31st) 3. End of Quarter 3 (June 30th) 4. End of year (Sept 30th) 5. Endline Survey 6. Ongoing | G22: 1. Program Manager 2. Project Coordinator 3. Project Officer | H22: Is the number of groups increasing over time? Are the groups getting stronger and/or improving their ability to provide service? | I22: Partners | J22: Quarterly
A23: Indicator 1.4 b. 600 refugee and host community members engaged in VSLA activities (saving and borrowing). | B23: ITT Calculation: Count number of refugees and host communities involved in saving money into the VSLA and involved in taking loans from the group. Savings: Individual VSLA group member takes a stipulated amount of money to VSLA group for keeping/using on his behalf for a stipulated amount of time. Borrowing: Involves a member taking a loan from the VSLA group with a purpose of using the money and later returning it with interest. | C23: Unit: people (men and women) | D23: Baseline: 1. Household survey Monitoring: 2. Census/ongoing Endline: 3. Household survey | E23: 1. Consultant database/Endline Report 2.1. ITT 2.2. Consolidated savings group records 2.3. Savings group records & members pass books | F23: 1. Beginning of year 2 (Oct. 31, 2018) 2. End of qourter 1 (31st December) 2. End of Quarter 2 (March 31st) 3. End of Quarter 3 (June 30th) 4. End of year (Sept 30th) 5. Endline Survey 6. Ongoing | G23: 1. Consultant 2.1. Project Director 2.2. Data entry officer 2.3. Field officer | H23: Disaggregate by gender (women & men) | I23: 1. United Nations High Commission for Refugees (UNHCR) 2. Office of the Prime Minister (OPM) 3. Lamwo & Kyegegwa District Local Governments. 4. LWR Country Office & HQ. | J23: Quarterly LWR progress reports.
A24: Output 1.5: Targeted refugees and host community members engage in eco-system activities that enhance agriculture productivity.
A25: Indicator 1.5.a: 1000 refugee and host community members who established woodlots. | B25: Woodlots: Number of trees planted. ITT Calculation: Count the number of refugees and host communities who planted trees provided by the project. Endline: 3. Household survey | C25: Refugee and host community farmers | D25: Baseline: 1. Household survey Monitoring: 2. Census/ongoing Endline: 3. Household survey | E25: 1. Consultant database/Endline Report 2.1. ITT 2.2. Group records | F25: 1. Beginning of year 2 (Oct. 31, 2018) 2. End of qourter 1 (31st December) 2. End of Quarter 2 (March 31st) 3. End of Quarter 3 (June 30th) 4. End of year (Sept 30th) 5. Endline Survey 6. Ongoing | G25: 1. Consultant 2.1. Project Director 2.2. Data entry officer 2.3. Field officer | H25: Disaggregate by gender (women & men) | I25: 1. United Nations High Commission for Refugees (UNHCR) 2. Office of the Prime Minister (OPM) 3. Lamwo & Kyegegwa District Local Governments. 4. LWR Country Office & HQ. | J25: Quarterly LWR progress reports.
A26: Indicator 1.5.b: 1000 of refugee and host community members who adopt use of organic manure and pesticides. | B26: Organic Manure: Fermented/rotten waste materials prepared by farmers from natural plant materials and animal wastes. Organic Pesticide: Fermented liquid made from natural plant materials, herbs and pepper. ITT Calculation: Count number of refugee and host community members who adopt use of organic manure and pesticides. | C26: Refugee and host community farmers | D26: Baseline: 1. Household survey Monitoring: 2. Census/ongoing Endline: 3. Household survey | E26: 1. Consultant database/Endline Report 2.1. ITT 2.2. Consolidated savings group records 2.3. Savings group records | F26: 1. Beginning of year 2 (Oct. 31, 2018) 2. End of qourter 1 (31st December) 2. End of Quarter 2 (March 31st) 3. End of Quarter 3 (June 30th) 4. End of year (Sept 30th) 5. Endline Survey 6. Ongoing | G26: 1. Consultant 2.1. Project Director 2.2. Data entry officer 2.3. Field officer | H26: Disaggregate by gender (women & men) | I26: 1. United Nations High Commission for Refugees (UNHCR) 2. Office of the Prime Minister (OPM) 3. Lamwo & Kyegegwa District Local Governments. 4. LWR Country Office & HQ. | J26: Quarterly LWR progress reports.
A28: OUTCOME 2: Increased community action towards reduction of SGBV risks, promotion of protection, safety, dignity and fundamental human rights of vulnerable refugees and host communities.
A29: Indicator 2.A: 1000 refugees and host community members taking positive actions towards reduction of protection and SGBV risks as well as promotion of fundamental human rights of vulnerable refugees and host communities. | B29: Positive Actions include: Creating awarenss, advocacy, identifying risks, human rights violations and reporting geared towards prevention & response to SGBV and protection concerns of vulnerable persons in the community. Protection & SGBV Risks include: Sexual assualt, sexual harrasment, Rape, Defilement, Domestic violence, Child marriage, Child sacrifice, Child labour, Human traficking and forced marriage. Fundalmental human rights include: the right to life with dignity, the right to receive humanitarian assistance and the right to protection and security. ITT Calculation: Count the number of community members who took atleast one positive action towards reduction of protection and SGBV risks as well as promotion of fundamental human rights of vulnerable refugees and host communities. | C29: Men, Women, boys and girls. | D29: Baseline: 1. Household survey Monitoring: 2. Census/ongoing Endline: 3. Household survey | E29: 1. Consultant database/Endline Report 2.1. ITT 2.2. Consolidated savings group records 2.3. Savings group records | F29: 1. Beginning of year 2 (Oct. 31, 2018) 2. End of qourter 1 (31st December) 2. End of Quarter 2 (March 31st) 3. End of Quarter 3 (June 30th) 4. End of year (Sept 30th) 5. Endline Survey 6. Ongoing | G29: 1. Consultant 2.1. Project Director 2.2. Data entry officer 2.3. Field officer | H29: Are men and women's involvement in taking action towards reduction of protection and SGBV risks as well as promotion of fundamental human rights of vulnerable refugees and host communities, the same? If not why? If not what actions must be taken to ensure that both men and women are equally involved? How are the local leaders involved? | I29: 1. United Nations High Commission for Refugees (UNHCR) 2. Office of the Prime Minister (OPM) 3. Lamwo & Kyegegwa District Local Governments. 4. LWR Country Office & HQ. | J29: Quarterly LWR progress reports.
A30: OUTPUT 2.1: Protection of all refugees are strengthened through meaningful engagement with communities, with particular attention to at-risk group
A31: Indicator 2.1.a. 820 of women in leadership structures and community groups for community self-management and empowerment | B31: Leadership Structures: Include RWCs, Protection Committees, etc. Community groups include livelihood groups and women groups/women own fora. ITT Calculation: 1. Count the number of women in leadership structures 2. Count the number of women in community groups 3. Add the numbers in 1 & 2. | C31: women | D31: Baseline: 1. Household survey Monitoring: 2. Census/ongoing Endline: 3. Household survey | E31: 1. Consultant database/Endline Report 2.1. ITT 2.2. Consolidated savings group records 2.3. Savings group records | F31: 1. Beginning of year 2 (Oct. 31, 2018) 2. End of qourter 1 (31st December) 2. End of Quarter 2 (March 31st) 3. End of Quarter 3 (June 30th) 4. End of year (Sept 30th) 5. Endline Survey Report 6. Ongoing | G31: 1. Consultant 2.1. Project Director 2.2. Data entry officer 2.3. Field officer | H31: Disaggregate by gender (women & men) | I31: 1. United Nations High Commission for Refugees (UNHCR) 2. Office of the Prime Minister (OPM) 3. Lamwo & Kyegegwa District Local Governments. 4. LWR Country Office & HQ. | J31: Quarterly LWR progress reports.
A32: Indicator 2.1.b. 2000 of complaints addressed through effective feedback mechanisms | B32: Complaits: Any issue of concern to the refugee or host community member that needs to be addressed. Feedback Mechanism: Refers to the complaits desks, and Protection committees. ITT Calculation Count all received and addressed complaits that have been documented in complaits records at the complaits desks. | C32: Complaits | D32: Baseline: 1. Household survey Monitoring: 2. Census/ongoing Endline: 3. Household survey | E32: 1. Consultant database/Endline Report 2.1. ITT 2.2. Consolidated savings group records 2.3. Savings group records | F32: 1. Beginning of year 2 (Oct. 31, 2018) 2. End of qourter 1 (31st December) 2. End of Quarter 2 (March 31st) 3. End of Quarter 3 (June 30th) 4. End of year (Sept 30th) 5. Endline Survey Report 6. Ongoing | G32: 1. Consultant 2.1. Project Director 2.2. Data entry officer 2.3. Field officer | H32: Disaggregate by gender (women & men) | I32: 1. United Nations High Commission for Refugees (UNHCR) 2. Office of the Prime Minister (OPM) 3. Lamwo & Kyegegwa District Local Governments. 4. LWR Country Office & HQ. | J32: Quarterly LWR progress reports.
A33: Indicator 2.1.C. 10,000 of persons with specific needs provided with targeted support | B33: Pesrsons with Specific Needs (PSNS): include: People with disability, elderly, child headed households, terminally ill, SGBV survivors, poor pregnant mothers, poor breast feeding mothers, single mothers, school girls. Trageted support: Includes any support that is given to address PSNs specific vulnerability. This support may include provision of RUMPs, Cash grants, clothing, beddings, baby kits, personal care kits, misson quilts, etc. Endline: 3. Household survey | C33: PSNs | D33: Baseline: 1. Household survey Monitoring: 2. Census/ongoing Endline: 3. Household survey | E33: 1. Consultant database/Endline Report 2.1. ITT 2.2. Consolidated savings group records 2.3. Savings group records | F33: 1. Beginning of year 2 (Oct. 31, 2018) 2. End of qourter 1 (31st December) 2. End of Quarter 2 (March 31st) 3. End of Quarter 3 (June 30th) 4. End of year (Sept 30th) 5. Endline Survey Report 6. Ongoing | G33: 1. Consultant 2.1. Project Director 2.2. Data entry officer 2.3. Field officer | H33: Disaggregate by gender (women & men) | I33: 1. United Nations High Commission for Refugees (UNHCR) 2. Office of the Prime Minister (OPM) 3. Lamwo & Kyegegwa District Local Governments. 4. LWR Country Office & HQ. | J33: Quarterly LWR progress reports.
A34: OUTPUT 2.2: Social cohesion and Peaceful co-existence among refugees and host communities strengthened
A35: Indicator 2.2.a. 40 incidents of conflict within refugee communities as well as between host communities and refugees documented and reported. | B35: Conflicts: Missunderstandings between two parties. ITT Calculation Count the number of conflicts that have been recorded. | C35: conflicts | D35: Baseline: 1. Household survey Monitoring: 2. Census Endline: 3. Household survey | E35: 1. Consultant database/Endline Report 2.1. ITT 2.2. Consolidated savings group records 2.3. Savings group records | F35: 1. Beginning of year 2 (Oct. 31, 2018) 2. End of qourter 1 (31st December) 2. End of Quarter 2 (March 31st) 3. End of Quarter 3 (June 30th) 4. End of year (Sept 30th) 5. Endline Survey 6. Ongoing | G35: 1. Consultant 2.1. Project Director 2.2. Data entry officer 2.3. Field officer | H35: Disaggregate by gender (women & men) | I35: 1. United Nations High Commission for Refugees (UNHCR) 2. Office of the Prime Minister (OPM) 3. Lamwo & Kyegegwa District Local Governments. 4. LWR Country Office & HQ. | J35: Quarterly LWR progress reports.
A36: Indicator 2.2.b. 24 dialogues conducted to resolve conflicts and promote peaceful co-existence. | B36: Dialogues: Discussion between two parties to resolve pending missunderstandings between the two parties. ITT Calculation Count the number of dialogues that have been conducted based on the reports. | C36: dialogues | D36: Baseline: 1. Household survey Monitoring: 2. Census/ongoing Endline: 3. Household survey | E36: 1. Consultant database/Endline Report 2.1. ITT 2.2. Consolidated savings group records 2.3. Savings group records | F36: 1. Beginning of year 2 (Oct. 31, 2018) 2. End of qourter 1 (31st December) 2. End of Quarter 2 (March 31st) 3. End of Quarter 3 (June 30th) 4. End of year (Sept 30th) 5. Endline Survey Report 6. Ongoing | G36: 1. Consultant 2.1. Project Director 2.2. Data entry officer 2.3. Field officer | H36: Disaggregate by gender (women & men) | I36: 1. United Nations High Commission for Refugees (UNHCR) 2. Office of the Prime Minister (OPM) 3. Lamwo & Kyegegwa District Local Governments. 4. LWR Country Office & HQ. | J36: Quarterly LWR progress reports.
A37: Indicator 2.2.C. 2000 refugees and host community engaged in social cohesion activities. | B37: Social Cohesion Activities: Include community dialogues, sports activities and Music, dance and drama activities. ITT Calculation Count the number of dialogues that have been conducted based on the reports. | C37: Men, Women, boys and girls. | D37: Baseline: 1. Household survey Monitoring: 2. Census/ongoing Endline: 3. Household survey | E37: 1. Consultant database/Endline Report 2.1. ITT 2.2. Consolidated savings group records 2.3. Savings group records | F37: 1. Beginning of year 2 (Oct. 31, 2018) 2. End of qourter 1 (31st December) 2. End of Quarter 2 (March 31st) 3. End of Quarter 3 (June 30th) 4. End of year (Sept 30th) 5. Endline Survey Report 6. Ongoing | G37: 1. Consultant 2.1. Project Director 2.2. Data entry officer 2.3. Field officer | H37: Disaggregate by gender (women & men) | I37: 1. United Nations High Commission for Refugees (UNHCR) 2. Office of the Prime Minister (OPM) 3. Lamwo & Kyegegwa District Local Governments. 4. LWR Country Office & HQ. | J37: Quarterly LWR progress reports.
A38: OUTPUT 2.3: Protection systems and mechanisms SGBV prevention and response strengthened
A39: Indicator 2.3. a. 4000 refugees and host community members participate in SGBV information dissemination activities. | B39: SGBV information dissemination activities include: awareness campaigns, FGDs, conversations, IEC, trainings, media ttalk shows. ITT Calculation: Count the number of refugees and host community members who participate in atleast 1 SGBV information dissemination activity. | C39: Men, Women, boys and girls. | D39: Baseline: 1. Household survey Monitoring: 2. Census Endline: 3. Household survey | E39: 1. Consultant database/Endline Report 2.1. ITT 2.2. Consolidated savings group records 2.3. Savings group records | F39: 1. Beginning of year 2 (Oct. 31, 2018) 2. End of qourter 1 (31st December) 2. End of Quarter 2 (March 31st) 3. End of Quarter 3 (June 30th) 4. End of year (Sept 30th) 5. Endline Survey 6. Ongoing | G39: 1. Consultant 2.1. Project Director 2.2. Data entry officer 2.3. Field officer | H39: Disaggregate by gender (women & men) | I39: 1. United Nations High Commission for Refugees (UNHCR) 2. Office of the Prime Minister (OPM) 3. Lamwo & Kyegegwa District Local Governments. 4. LWR Country Office & HQ. | J39: Quarterly LWR progress reports.
A40: Indicator 2.3.b. 200 SGBV survivors identified and referred to receiving appropriate multi-sectoral support. | B40: SGBV Survivors: Women, girls, boys and men who have suffered from SGBV. Multi-sectoral Support: Protection support, legal, health, psycho-social and livelihoods support given to SGBV survivor. ITT Calculation: Count the number of SGBV survivors who have received at least one of the multi-sectoral support listed above. | C40: SGBV Survivors | D40: Baseline: 1. Household survey Monitoring: 2. Census/ongoing Endline: 3. Household survey | E40: 1. Consultant database/Endline Report 2.1. ITT 2.2. Consolidated savings group records 2.3. Savings group records | F40: 1. Beginning of year 2 (Oct. 31, 2018) 2. End of qourter 1 (31st December) 2. End of Quarter 2 (March 31st) 3. End of Quarter 3 (June 30th) 4. End of year (Sept 30th) 5. Endline Survey Report 6. Ongoing | G40: 1. Consultant 2.1. Project Director 2.2. Data entry officer 2.3. Field officer | H40: Disaggregate by gender (women & men) | I40: 1. United Nations High Commission for Refugees (UNHCR) 2. Office of the Prime Minister (OPM) 3. Lamwo & Kyegegwa District Local Governments. 4. LWR Country Office & HQ. | J40: Quarterly LWR progress reports.
A41: 12 functional community structures (protection committees, women own fora and men own fora) trained and able to support survivors. | B41: ITT Calculation: Count the number of functional community structures (protection committees, women own fora and men own fora) trained and supporting SGBV survivors. | C41: Structures | D41: Baseline: 1. Household survey Monitoring: 2. Census/ongoing Endline: 3. Household survey | E41: 1. Consultant database/Endline Report 2.1. ITT 2.2. Consolidated savings group records 2.3. Savings group records | F41: 1. Beginning of year 2 (Oct. 31, 2018) 2. End of qourter 1 (31st December) 2. End of Quarter 2 (March 31st) 3. End of Quarter 3 (June 30th) 4. End of year (Sept 30th) 5. Endline Survey Report 6. Ongoing | G41: 1. Consultant 2.1. Project Director 2.2. Data entry officer 2.3. Field officer | H41: Disaggregate by gender (women & men) | I41: 1. United Nations High Commission for Refugees (UNHCR) 2. Office of the Prime Minister (OPM) 3. Lamwo & Kyegegwa District Local Governments. 4. LWR Country Office & HQ. | J41: Quarterly LWR progress reports.

Sheet Baseline Table Description
A1: TOOL SUMMARY: BASELINE TABLE
A2: Purpose | B2: The purpose of this tool is to ensure that all relevant, and only relevant, baseline data information is collected and documented. The baseline information is later used to determine targets. NOTE: The Baseline is NOT a Needs Assessment. The Baseline collects starting data for indicators and should not seek to collect information that will require the project theory of change to be adjusted.
A3: Information Sources | B3: Information the project team should have before starting work on the Baseline:
B4: · Complete M&E Matrix
B5: · Project Proposal (Initial M&E Plan)
A6: Who | B6: One person should be chosen to lead the baseline process. This person is responsible to ensure the table is completed, but is not necessarily responsible for collecting all the data. If a consultant is hired to collect primary data, he/she should be responsible for completing the table for the assigned indicators.
A7: When | B7: According to the IPD policy regarding the submission of Detailed M&E Plans and indicator baseline values of projects starting as of April 1, 2014, the final submission of the Detailed M&E Plan (M&E Matrix, Baseline Table, and the Indicator Tracking Table) must not exceed the following deadlines:
B8: · Projects of less than one year of duration: 60 days from project start date
B9: · Projects between one and three years of duration: 90 days from project start date
B10: · Projects between three and five years of duration: 120 days from project start date
A11: Requirements | B11: REQUIREMENTS:
B12: · Filling out this table is required for all UNRESTRICTED projects.
B13: · For RESTRICTED projects, donor requirements should be followed. If there are no donor requirements, default to these guidelines.
B14: · If a consultant is hired, he/she should provide a database with all the cleaned data from surveys for project records to ensure transparency and validity.
B15: · The information contained in the Baseline Table should only be modified if changes are made to indicators or their definitions that respond to specific and documented technical feedback that complies with donor and LWR standards.
B16: o If changes are made, document and report the reason why the changes were made and how it will impact any other aspects of the project's M&E system and/or project implementation. It is recommended not to eliminate the rows of the indicators that have been changed. Rather, it is suggested to create another row to record the new version of the indicator even if only minor changes have been made to the definition or any other aspect of it. The Comments column can also be used to explain all that is considered worth explaining.
B17: o If changes are made to the Baseline Table make sure LWR´s headquarters, the country office and the partner have and use the up-to-date version.
B18: o LWR staff need to ensure that the most up-to-date document is in Phoenix.
A19: Tips | B19: · Those who will use the Baseline Table should fill it out. This allows the project team to verify their understanding of the definition and method used to collect the baseline data and use this same understanding for ongoing data collection or data collection at the end of the project (endline).
B20: · Make sure to define who should take "ownership" of the Baseline Table. This involves ensuring that the table is finalized, that all the interested parties understand the information contained in it and have the final versions, and that any future changes are fully incorporate into the project plan and shared with all stakeholders.
B21: o The same person should be in charge of the Indicator Tracking Table and the Activity Tracking Table.
B22: · If the baseline is being conducted internally and there are questions about sample size calculations, contact your relevant M&E representative.
B23: · Baseline studies establish the starting point for each indicator which is necessary for determining if indicator targets defined in the project design need adjustment.
A24: How to Address Gender Issues
B25: · Sex-disaggregate data of all indicators for which people are the unit of measure.
B26: · Include qualitative and quantitative indicators .

Sheet Baseline Table Cheat Sheet
A1: Indicator table for the Baseline of "Name of the Project"
A2: Name of the project: | D2: Location of the project: | G2: Project duration (in years):
A3: Identifier: | D3: Partner: | G3: Project start date:
A4: Sector(s) of the project: | G4: Project end date:
A5: INDICATORS | D5: TARGETS AND BASELINE VALUES | G5: DOCUMENTATION
A6: Indicator | B6: Indicator definition | C6: Unit of measurement | D6: Life of project target | E6: Baseline value | F6: Date of the baseline value | G6: Source of the baseline value | H6: Comments
A7: Indicators are taken directly from the M&E Matrix. Include all indicators as even indicators with a zero starting value should have documented justification for this value. | B7: Indicator definitions come directly from the M&E Matrix. They are repeated here only for ease of reading and understanding their definitions in relation to the baseline values. Refer to the M&E Matrix Cheat Sheet for more information on indicator definitions. | C7: A unit of measure is a standard quantity that serves to establish the magnitude of the value of an indicator. It answers the question: What are we counting? Units of measure often used in LWR projects are: Simple (one element): people kilos or pounds tons plot hectares Best practices Complex (more than one element): productivity: Kilos or tons per hectare density: trees per plot or hectare poverty: Income per year Income per year per hectare | D7: This is the value of the indicator that the project team hopes to achieve by the end of the project. It is expressed in the unit of measurement defined in column C. Example: 300 people trained in soil management practices, 100 coffee plantations managed with best pruning practices, cacao productivity of 2 tones per hectare, net income of $150 per family from legume sales For quantitative indicators based on mathematical formulas (Ex.: percentage, rate, etc) it is suggested to redocument the components of the formula (the values that make up the numerator and the denominator). | E7: This is the value of the indicator at the beginning of the project. This value is expressed in the same unit of measure as the target. OUTPUT indicators: OUTPUT baseline values are often zero (0) as these type of indicators are used to measure the results of implementing project activities. However, depending on how the logframe was built, OUTCOME indicators such as production and productivity could be assigned to the OUTPUT LEVEL (Ex. Three tons of potatoes per hectare per year). Examples of common OUTPUT indicators: N° of people trained, N° of infrastructures built, N° of pieces of equipment delivered, N° of plans developed and approved, N° of contracts signed with cacao buyers. OUTCOME indicators: are located above the OUTPUTS in the chain of the project's intended results and refer to conditions already present in the target population that can be measured to show change. They normally measure a change in behavior, attitudes and/or practices. Examples of common OUTCOME indicators: N° of producers who consistently apply best practices, N° of students who wash their hands according to the five key steps, annual net family income from coffee sales. | F7: The date (month and year) when the initial value (Ex. 250 pounds per hectare per year) was gathered in the field from a primary source (Ex. A producer survey, a coop´s production registries). If the value is obtained from a secondary source (a needs assessment, an agrarian census, baselines or studies by other organizations, etc) it may not be possible to know the date when value for the indicator was actually gathered. In that case, put the publication date of the document. | G7: Refers to the document (in physical or electronic format) in which the indicator value is stated. These documents can be either primary or secondary sources. Primary sources are data that were collected directly by LWR or its partners. These include household surveys, registries, databases, various types of reports, etc. It is important to state the type of document that contains the value for the indicator (Ex. A coop´s registry of cacao sales). Secondary sources are those that LWR or its partners did not collect directly. They include agrarian or other types of census, studies by international organizations such as the UN, LWR peer organizations or LWR partners not participating in the project. It is necessary to be explicit with regards to the title of the document and the author(s), be it an institution or a person, and the publication date. If the value of the indicator was taken from a Website (Ex. From the Ministry of Agriculture or from the National Statisics Department) it is important to document the URL and it is also recommened to save a copy of the screen (use the print screen function) which states the date in which that data was collected. | H7: This is a space to put information about the indicator that is deemed by the project team to be of value to better understand the project results. Complementary information can refer to any of the aspects addressed in the preceeding columns. Some examples are: (i) for an indicator of production or productivity, if the original unit of measure was a locally used one (Ex. Manzanas in Nicaragua) and was transformed to hectares due to a donor´s request, it can be explained in this section putting the equivalence between manzanas and hectares (1 mz=0.7 Has), (ii) if the indicator value corresponds to some of the geographic areas participating in the project and not to others it can be explained here, (iii) if the indicator value was obtained using a sample of a certain type (Ex. Probabilistic, by quotas, voluntary, etc.) or a census.

Sheet Baseline Table
A1: Indicator table for the Baseline of "RESULTS Livelihoods"
A2: Name of the project: | B2: RESULTS Livelihoods | D2: Location of the project: | E2: Lamwo District | G2: Project duration (in years): | H2: (Jan 2018 - Sept 2018)
A3: Identifier: | B3: 18-2210-1 | D3: Partner: | E3: ='M&E Matrix'!E3:F3 -> African Women and Youth Action for Development | G3: Project start date: | H3: 1.01.2018
A4: Sector(s) of the project: | B4: Agriculture | G4: Project end date: | H4: 30.09.2018
A5: INDICATORS | D5: TARGETS AND BASELINE VALUES | G5: DOCUMENTATION
A6: Indicator | B6: Indicator definition | C6: Unit of measurement | D6: Life of project target | E6: Baseline value | F6: Date of the baseline value | G6: Source of the baseline value | H6: Comments
A7: ='M&E Matrix'!A7 -> GOAL: Increased household self-reliance and resilience among refugees and host community members in Palabek and Kyaka II refugee settlements.
A9: ='M&E Matrix'!A9 -> Outcome 1. Increased household food security and incomes among refugees and host communities
A10: ='M&E Matrix'!A10 -> Indicator 1.A. 1200 refugees and host communities achieve atleast 30% increase in household food production. | B10: ='M&E Matrix'!B10 -> 30% increase in food production calculation: ((new period amount of food produced - prior period amount of food produced)/prior period amount of food produced))*100 ITT Calculation: Count all refugees and host communities who achieved 30% + food production a year. | C10: ='M&E Matrix'!C10 -> Unit (s): Men and Women (engaged in own food production) Household | D10: 1200 | E10: 456 | F10: 19-24th Feb 2018 | G10: Baseline Survey Report | H10: All beneficiaries are receiving food rations from WFP
A11: ='M&E Matrix'!A11 -> Indicator 1.B. 800 refugees and host communities acquire atleast one productive household asset and one non-productive asset. | B11: ='M&E Matrix'!B11 -> ITT Calculation: 1. Count number of women who bought a productive asset within project period. 2. Count number of women who bought a productive asset within project period. 3. Add the number of women and men who bought a productive asset within project period. A productive asset may include: Farm tools, business equipment, livestock, bodaboda, truck, land, house, etc. | C11: ='M&E Matrix'!C11 -> Unit (s): Men and Women (in HH with Assets) Household | D11: 800 | E11: 108 | F11: 19-24th Feb 2018 | G11: Baseline Survey Report | H11: All beneficiaries are receiving food rations from WFP
A12: ='M&E Matrix'!A12 -> Indicator 1.C: 800 refugees and host community members increase their savings by atleast 50% | B12: ='M&E Matrix'!B12 -> % increase calculation: ((new period savings value - prior period savings value)/prior period savings value))*100 ITT Calculation: Count all refugees and host community members who increased their savings by 50% + during the project period. Disaggregated by savings held by men and women within the household. | C12: ='M&E Matrix'!C12 -> Unit (s): Men and Women (in HH with savings) Household | D12: 800 | E12: 108 | F12: 19-24th Feb 2018 | G12: Baseline Survey Report | H12: All beneficiaries are receiving food rations from WFP
A13: ='M&E Matrix'!A13 -> OUTPUT 1.1: Targeted Refugees and their host communities have access to communty extension services
A14: ='M&E Matrix'!A14 -> Indicator 1.1.a: 10 training modules (agronomy, PHH and eco-system mgt) conducted for lead/modal farmers | B14: ='M&E Matrix'!B14 -> Lead/Model Farmer - A refugee or host farmer is a member of the refugee/host farmer group selected by group as their peer leader/trainer. Farmer-to-Farmer Extension services - Refers to knowledge & skills provided by the lead/model farmers to at group level or household level during monitoring visit. ITT Calculation: Count the number of lead farmers who receieved atleast 10 training modules in Agronomy, PHH and eco-system management. | C14: ='M&E Matrix'!C14 -> Lead Farmers | D14: 60 | E14: 0 | F14: 19-24th Feb 2018 | G14: Baseline Survey Report | H14: No community owned extension workers | K14: 5
A15: ='M&E Matrix'!A15 -> Indicator 1.1.b: 1600 refugees & host communities receive extension services from lead/model farmers. | B15: ='M&E Matrix'!B15 -> Refugee = South Sudanese nationals who have been forced to leave their country to seek asylum in Uganda(Palabek refugee settlement) Host communities = Ugandan nationals living in and around Palabek refugee settlement. ITT Calculation Count the number of refugee and host community farmers who recieved advice/knowledge/skills from the lead farmers. | C15: ='M&E Matrix'!C15 -> Refugee and host community farmers | D15: 1600 | E15: 0 | F15: 19-24th Feb 2018 | G15: Baseline Survey Report | H15: No community owned extension workers
A16: ='M&E Matrix'!A16 -> OUTPUT 1.2: Targeted refugees and host community members have access to improved high yielding seeds.
A17: ='M&E Matrix'!A17 -> Indicator 1.2.a: 1200 refugees and host community HHs receive high yeilding seeds | B17: ='M&E Matrix'!B17 -> Agricultural seeds = high yielding varieties of OSLP, cassava, okra, spinanch, onion, egg plant, and amaranth Host communities = Ugandan nationals living in and around Palabek refugee settlement. ITT Calculation: Count the number of refugees and Host communities who receive the one of the the following seeds: cassava, okra, OSP. | C17: ='M&E Matrix'!C17 -> Households | D17: 1200 | E17: 0 | F17: 19-24th Feb 2018 | G17: Baseline Survey Report | H17: Though some of the refugees were supported to plant some seeds last year (2017), none of them saved any seeds. They lost most of them to drought and consumed the little they had.
A18: ='M&E Matrix'!A18 -> OUTPUT 1.3: Targeted refugees engage in off-farm income generating activities.
A19: ='M&E Matrix'!A19 -> Indicator 1.3. a. 200 refugees supported to establish small scale businesses. | B19: ='M&E Matrix'!B19 -> Small-scale business - a business that has low capital investments and does not have a high volume of sales. ITT Calculation: Count the number of refugees who acquired a loan from the VSLA cash grants provided by LWR. | C19: ='M&E Matrix'!C19 -> Men and women operating businesses | D19: 200 | E19: 0 | F19: 19-24th Feb 2018 | G19: Baseline Survey Report | H19: As a result of extension support previusly, some of the refugees
A20: ='M&E Matrix'!A20 -> Indicator 1.3.b. 50 refugee and host communities generating income from honey production and Marketing. | B20: ='M&E Matrix'!B20 -> Honey = A product of bees got from bee hives. Honey Production: Process of getting honey from bee hives. Honey Marketing: A process of selling honey. ITT Calculation: Count the number of refugee and host community members producing and selling honey. | C20: ='M&E Matrix'!C20 -> Men and women engaged in honey production and selling. | D20: 50 | E20: 0 | F20: 19-24th Feb 2018 | G20: Baseline Survey Report | H20: As a result of extension support previusly, some of the refugees
A21: ='M&E Matrix'!A21 -> OUTPUT 1.4: Targeted refugees and host community members in engage in VSLA.
A22: ='M&E Matrix'!A22 -> Indicator 1.4.a: 30 Village Savings and Lending Associations (groups) formed and strengthened | B22: ='M&E Matrix'!B22 -> ITT Calculation: Count number of farmer gropus involved in VSLA. Savings and Credit Group/Cooperative: Regulating fund mobilization at the community level Formed: created Strengthened: trained on purpose, norms | C22: ='M&E Matrix'!C22 -> Unit: Number of Saving and Credits groups | D22: 30 | E22: 0 | F22: 19-24th Feb 2018 | G22: Baseline Survey Report | H22: As a result of extension support previusly, some of the refugees
A23: ='M&E Matrix'!A23 -> Indicator 1.4 b. 600 refugee and host community members engaged in VSLA activities (saving and borrowing). | B23: ='M&E Matrix'!B23 -> ITT Calculation: Count number of refugees and host communities involved in saving money into the VSLA and involved in taking loans from the group. Savings: Individual VSLA group member takes a stipulated amount of money to VSLA group for keeping/using on his behalf for a stipulated amount of time. Borrowing: Involves a member taking a loan from the VSLA group with a purpose of using the money and later returning it with interest. | C23: ='M&E Matrix'!C23 -> Unit: people (men and women) | D23: 600 | E23: 0 | F23: 19-24th Feb 2019 | G23: Baseline Survey Report | H23: As a result of extension support previusly, some of the refugees
A24: ='M&E Matrix'!A24 -> Output 1.5: Targeted refugees and host community members engage in eco-system activities that enhance agriculture productivity.
A25: ='M&E Matrix'!A25 -> Indicator 1.5.a: 1000 refugee and host community members who established woodlots. | B25: ='M&E Matrix'!B25 -> Woodlots: Number of trees planted. ITT Calculation: Count the number of refugees and host communities who planted trees provided by the project. Endline: 3. Household survey | C25: ='M&E Matrix'!C25 -> Refugee and host community farmers | D25: 1000 | E25: 0 | F25: 19-24th Feb 2018 | G25: Baseline Survey Report | H25: As a result of extension support previusly, some of the refugees
A26: ='M&E Matrix'!A26 -> Indicator 1.5.b: 1000 of refugee and host community members who adopt use of organic manure and pesticides. | B26: ='M&E Matrix'!B26 -> Organic Manure: Fermented/rotten waste materials prepared by farmers from natural plant materials and animal wastes. Organic Pesticide: Fermented liquid made from natural plant materials, herbs and pepper. ITT Calculation: Count number of refugee and host community members who adopt use of organic manure and pesticides. | C26: ='M&E Matrix'!C26 -> Refugee and host community farmers | D26: 1000 | E26: 0 | F26: 19-24th Feb 2018 | G26: Baseline Survey Report | H26: As a result of extension support previusly, some of the refugees
A28: ='M&E Matrix'!A28 -> OUTCOME 2: Increased community action towards reduction of SGBV risks, promotion of protection, safety, dignity and fundamental human rights of vulnerable refugees and host communities.
A29: ='M&E Matrix'!A29 -> Indicator 2.A: 1000 refugees and host community members taking positive actions towards reduction of protection and SGBV risks as well as promotion of fundamental human rights of vulnerable refugees and host communities. | B29: ='M&E Matrix'!B29 -> Positive Actions include: Creating awarenss, advocacy, identifying risks, human rights violations and reporting geared towards prevention & response to SGBV and protection concerns of vulnerable persons in the community. Protection & SGBV Risks include: Sexual assualt, sexual harrasment, Rape, Defilement, Domestic violence, Child marriage, Child sacrifice, Child labour, Human traficking and forced marriage. Fundalmental human rights include: the right to life with dignity, the right to receive humanitarian assistance and the right to protection and security. ITT Calculation: Count the number of community members who took atleast one positive action towards reduction of protection and SGBV risks as well as promotion of fundamental human rights of vulnerable refugees and host communities. | C29: ='M&E Matrix'!C29 -> Men, Women, boys and girls. | D29: 1000 | E29: 150 | F29: 19-24th Feb 2018 | G29: Baseline Survey Report | H29: women only since babies can not be interviewed.
A30: ='M&E Matrix'!A30 -> OUTPUT 2.1: Protection of all refugees are strengthened through meaningful engagement with communities, with particular attention to at-risk group
A31: ='M&E Matrix'!A31 -> Indicator 2.1.a. 820 of women in leadership structures and community groups for community self-management and empowerment | B31: ='M&E Matrix'!B31 -> Leadership Structures: Include RWCs, Protection Committees, etc. Community groups include livelihood groups and women groups/women own fora. ITT Calculation: 1. Count the number of women in leadership structures 2. Count the number of women in community groups 3. Add the numbers in 1 & 2. | C31: ='M&E Matrix'!C31 -> women | D31: 820 | E31: 0 | F31: 19-24th Feb 2018 | G31: Baseline Survey Report | H31: women only since babies can not be interviewed.
A32: ='M&E Matrix'!A32 -> Indicator 2.1.b. 2000 of complaints addressed through effective feedback mechanisms | B32: ='M&E Matrix'!B32 -> Complaits: Any issue of concern to the refugee or host community member that needs to be addressed. Feedback Mechanism: Refers to the complaits desks, and Protection committees. ITT Calculation Count all received and addressed complaits that have been documented in complaits records at the complaits desks. | C32: ='M&E Matrix'!C32 -> Complaits | D32: 2000 | E32: 0 | F32: 19-24th Feb 2018 | G32: Baseline Survey Report | H32: women only since babies can not be interviewed.
A33: ='M&E Matrix'!A33 -> Indicator 2.1.C. 10,000 of persons with specific needs provided with targeted support | B33: ='M&E Matrix'!B33 -> Pesrsons with Specific Needs (PSNS): include: People with disability, elderly, child headed households, terminally ill, SGBV survivors, poor pregnant mothers, poor breast feeding mothers, single mothers, school girls. Trageted support: Includes any support that is given to address PSNs specific vulnerability. This support may include provision of RUMPs, Cash grants, clothing, beddings, baby kits, personal care kits, misson quilts, etc. Endline: 3. Household survey | C33: ='M&E Matrix'!C33 -> PSNs | D33: 10000 | E33: 0 | F33: 19-24th Feb 2018 | G33: Baseline Survey Report | H33: women only since babies can not be interviewed.
A34: ='M&E Matrix'!A34:J34 -> OUTPUT 2.2: Social cohesion and Peaceful co-existence among refugees and host communities strengthened
A35: ='M&E Matrix'!A35 -> Indicator 2.2.a. 40 incidents of conflict within refugee communities as well as between host communities and refugees documented and reported. | B35: ='M&E Matrix'!B35 -> Conflicts: Missunderstandings between two parties. ITT Calculation Count the number of conflicts that have been recorded. | C35: ='M&E Matrix'!C35 -> conflicts | D35: 40 | E35: 0 | F35: 19-24th Feb 2018 | G35: Baseline Survey Report | H35: women only since babies can not be interviewed.
A36: ='M&E Matrix'!A36 -> Indicator 2.2.b. 24 dialogues conducted to resolve conflicts and promote peaceful co-existence. | B36: ='M&E Matrix'!B36 -> Dialogues: Discussion between two parties to resolve pending missunderstandings between the two parties. ITT Calculation Count the number of dialogues that have been conducted based on the reports. | C36: ='M&E Matrix'!C36 -> dialogues | D36: 24 | E36: 0 | F36: 19-24th Feb 2018 | G36: Baseline Survey Report | H36: women only since babies can not be interviewed.
A37: ='M&E Matrix'!A37 -> Indicator 2.2.C. 2000 refugees and host community engaged in social cohesion activities. | B37: ='M&E Matrix'!B37 -> Social Cohesion Activities: Include community dialogues, sports activities and Music, dance and drama activities. ITT Calculation Count the number of dialogues that have been conducted based on the reports. | C37: ='M&E Matrix'!C37 -> Men, Women, boys and girls. | D37: 2000 | E37: 0 | F37: 19-24th Feb 2018 | G37: Baseline Survey Report | H37: women only since babies can not be interviewed.
A38: ='M&E Matrix'!A38:J38 -> OUTPUT 2.3: Protection systems and mechanisms SGBV prevention and response strengthened
A39: ='M&E Matrix'!A39 -> Indicator 2.3. a. 4000 refugees and host community members participate in SGBV information dissemination activities. | B39: ='M&E Matrix'!B39 -> SGBV information dissemination activities include: awareness campaigns, FGDs, conversations, IEC, trainings, media ttalk shows. ITT Calculation: Count the number of refugees and host community members who participate in atleast 1 SGBV information dissemination activity. | C39: ='M&E Matrix'!C39 -> Men, Women, boys and girls. | D39: 4000 | E39: 0 | F39: 19-24th Feb 2018 | G39: Baseline Survey Report | H39: women only since babies can not be interviewed.
A40: ='M&E Matrix'!A40 -> Indicator 2.3.b. 200 SGBV survivors identified and referred to receiving appropriate multi-sectoral support. | B40: ='M&E Matrix'!B40 -> SGBV Survivors: Women, girls, boys and men who have suffered from SGBV. Multi-sectoral Support: Protection support, legal, health, psycho-social and livelihoods support given to SGBV survivor. ITT Calculation: Count the number of SGBV survivors who have received at least one of the multi-sectoral support listed above. | C40: ='M&E Matrix'!C40 -> SGBV Survivors | D40: 200 | E40: 0 | F40: 19-24th Feb 2018 | G40: Baseline Survey Report | H40: women only since babies can not be interviewed.
A41: ='M&E Matrix'!A41 -> 12 functional community structures (protection committees, women own fora and men own fora) trained and able to support survivors. | B41: ='M&E Matrix'!B41 -> ITT Calculation: Count the number of functional community structures (protection committees, women own fora and men own fora) trained and supporting SGBV survivors. | C41: ='M&E Matrix'!C41 -> Structures | D41: 10 | E41: 0 | F41: 19-24th Feb 2018 | G41: Baseline Survey Report | H41: women only since babies can not be interviewed.

Sheet ITT Description
A1: TOOL SUMMARY: INDICATOR TRACKING TABLE INSTRUCTIONS
A2: Purpose | B2: The Indicator Tracking Table (ITT) is a tool that is used as a tracking mechanism for all project indicators.
A3: Information Sources | B3: Information the project design team should have before starting the ITT:
B4: · Needs Assessment
B5: · Logframe
B6: · Project Proposal
B7: · Baseline Data
B8: · M&E Matrix
A9: Who | B9: The ITT should be completed by the partner, reviewed by the LWR PM, and included in each Project Progress Report
A10: When | B10: The ITT is a sub-tool of the Detailed M&E Plan and should therefore be completed according to the timeframe set out for the completion of the Detailed M&E Plan. It is normally developed after the M&E Matrix has been completed and after the baseline data has been collected.
A11: Requirements | B11: REQUIREMENTS:
B12: · Every project is required to have an ITT.
B13: · The ITT requires setting targets for indicators on quarterly, annual, and life of project timeframes.
B14: · The ITT should be updated with actual data for every reporting period. The ITT should be updated before beginning the narrative Project Progress Report.
B15: o The ITT is a very useful management tool and is most effective when used on a quarterly basis. Use on a quarterly basis provides project managers with more regular data and can help in making timely adjustments and improvements to the project.
B16: · If the required reporting period is semiannually, it is suggested that the ITT be completed on a quarterly basis, but that the analysis included in the Project Progress Report focus on progress for the entire six month period.
B18: RECOMMENDATIONS:
B19: · Targets can be revised, but there should be clear and convincing reasoning behind the revision. Indicator target revisions are not common and should be done only when there has been a major change to the scope or context of the project.
B20: o For restricted projects, consult with the LWR Grants Manager before revising indicator targets. Target revisions should also be communicated clearly to the donor.
B21: o For unrestricted projects, coordinate with the Program Associate before revising indicator targets.
B22: o If approval is given to revise indicator targets:
B23: § Highlight revised targets in progress reports and provide clear and specific reasoning for the revisions.
B24: § Ensure that new targets are updated in the ITT and that all subsequent quarterly targets and annual and life of project targets reflect the revision.
B25: · The “Status” column in the ITT can indicate the date the indicator data is expected to start and end, if it will only be collected at baseline and endline, if it is completed, or if it is ongoing. The “Status” column is NOT to be used to provide any narrative explanation about the indicator. This should be done in the Project Progress Report.
A26: Tips | B26: · Not meeting a target should be viewed as a learning experience, not as a failure.
B27: o Discussions about why actual data is over or under a target is important.
B28: o Set ambitious targets, but also make them realistic by linking them as closely as possible to the project’s detailed implementation plan.
B29: · Use the ITT as a key analysis and reporting tool.
B30: o Analyze why or why not targets were met to help you understand what adjustments to the project’s implementation should be made.
B31: · Key findings from the analysis becomes central information for project reports, and can be shared with all relevant stakeholders.

Sheet ITT"RESULTS Livelihoods" Year 1
A1: LUTHERAN WORLD RELIEF INDICATOR TRACKING TABLE | S1: Project Beneficiaries
A2: Project Name: | B2: RESULTS Livelihoods | T2: Female | U2: Male | V2: Total
A3: Report Period: | E3: Partner: | G3: African Wowen and Youth Action for Development | L3: Project Year | N3: January 2018 - September 2018 | S3: Direct | V3: =T3+U3 -> 0
A4: Identifier: | B4: 18-2210-1 | E4: Project Location: | G4: Lamwo District | L4: Project Start Date: | N4: 1st January 2018 | S4: Indirect | V4: =T4+U4 -> 0
A5: Project Sector(s): | B5: Agriculture | L5: Project End Date: | N5: 30th September 2018 | S5: Total | T5: =T3+T4 -> 0 | U5: =U3+U4 -> 0 | V5: =T5+U5 -> 0
A9: RESULTS | C9: Project Baseline | F9: Q1 Reporting Period Oct - Dec 2018 | I9: Q2 Reporting Period Jan - Mar 2019 | L9: Q3 Reporting Period April - June 2019 | O9: Q4 Reporting Period July - Sept 2019 | R9: Annual Target | S9: Year to Date Actual | T9: % of Annual Target | U9: Life of Project Target | V9: Life of Project Actual | W9: % of LoP Target | X9: Project Component | Y9: Status
C10: Date | D10: Value | E10: Unit | F10: Target | G10: Actual | H10: % of Target | I10: Target | J10: Actual | K10: % of Target | L10: Target | M10: Actual | N10: % of Target | O10: Target | P10: Actual | Q10: % of Target
A11: ='M&E Matrix'!A7 -> GOAL: Increased household self-reliance and resilience among refugees and host community members in Palabek and Kyaka II refugee settlements.
A12: ='M&E Matrix'!A9 -> Outcome 1. Increased household food security and incomes among refugees and host communities
A13: ='M&E Matrix'!A10 -> Indicator 1.A. 1200 refugees and host communities achieve atleast 30% increase in household food production. | C13: ='Baseline Table'!F10 -> 19-24th Feb 2018 | D13: ='Baseline Table'!E10 -> 456 | E13: people | F13: 400 | H13: =IF(F13=0,"NA",G13/F13) -> 0 | I13: 0 | K13: =IF(I13=0,"NA",J13/I13) -> NA | L13: 400 | N13: =IF(L13=0,"NA",M13/L13) -> 0 | O13: 400 | Q13: =IF(O13=0,"NA",P13/O13) -> 0 | R13: =F13+I13+L13+O13 -> 1200 | S13: =G13+J13+M13+P13 -> 0 | T13: =IF(R13=0,"NA",S13/R13) -> 0 | U13: =F13+I13+L13+O13 -> 1200 | V13: =G13+J13+M13+P13 -> 0 | W13: =IF(U13=0,"NA",V13/U13) -> 0
B14: Males | D14: 119 | E14: people | F14: 160 | H14: =IF(F14=0,"NA",G14/F14) -> 0 | I14: 0 | K14: =IF(I14=0,"NA",J14/I14) -> NA | L14: 160 | N14: =IF(L14=0,"NA",M14/L14) -> 0 | O14: 160 | Q14: =IF(O14=0,"NA",P14/O14) -> 0 | R14: =F14+I14+L14+O14 -> 480 | S14: =G14+J14+M14+P14 -> 0 | T14: =IF(R14=0,"NA",S14/R14) -> 0 | U14: =F14+I14+L14+O14 -> 480 | V14: =G14+J14+M14+P14 -> 0 | W14: =IF(U14=0,"NA",V14/U14) -> 0
B15: Females | D15: 337 | E15: people | F15: 240 | H15: =IF(F15=0,"NA",G15/F15) -> 0 | I15: 0 | K15: =IF(I15=0,"NA",J15/I15) -> NA | L15: 240 | N15: =IF(L15=0,"NA",M15/L15) -> 0 | O15: 240 | Q15: =IF(O15=0,"NA",P15/O15) -> 0 | R15: =F15+I15+L15+O15 -> 720 | S15: =G15+J15+M15+P15 -> 0 | T15: =IF(R15=0,"NA",S15/R15) -> 0 | U15: =F15+I15+L15+O15 -> 720 | V15: =G15+J15+M15+P15 -> 0 | W15: =IF(U15=0,"NA",V15/U15) -> 0
A16: ='Baseline Table'!A11 -> Indicator 1.B. 800 refugees and host communities acquire atleast one productive household asset and one non-productive asset. | C16: =C13 -> 19-24th Feb 2018 | D16: ='Baseline Table'!E11 -> 108 | E16: people | F16: 200 | H16: =IF(F16=0,"NA",G16/F16) -> 0 | I16: 200 | K16: =IF(I16=0,"NA",J16/I16) -> 0 | L16: 200 | N16: =IF(L16=0,"NA",M16/L16) -> 0 | O16: 200 | Q16: =IF(O16=0,"NA",P16/O16) -> 0 | R16: =F16+I16+L16+O16 -> 800 | S16: =G16+J16+M16+P16 -> 0 | T16: =IF(R16=0,"NA",S16/R16) -> 0 | U16: =F16+I16+L16+O16 -> 800 | V16: =G16+J16+M16+P16 -> 0 | W16: =IF(U16=0,"NA",V16/U16) -> 0
B17: Males | D17: 42 | E17: people | F17: 80 | H17: =IF(F17=0,"NA",G17/F17) -> 0 | I17: 80 | K17: =IF(I17=0,"NA",J17/I17) -> 0 | L17: 80 | N17: =IF(L17=0,"NA",M17/L17) -> 0 | O17: 80 | Q17: =IF(O17=0,"NA",P17/O17) -> 0 | R17: =F17+I17+L17+O17 -> 320 | S17: =G17+J17+M17+P17 -> 0 | T17: =IF(R17=0,"NA",S17/R17) -> 0 | U17: =F17+I17+L17+O17 -> 320 | V17: =G17+J17+M17+P17 -> 0 | W17: =IF(U17=0,"NA",V17/U17) -> 0
B18: Females | D18: 66 | E18: people | F18: 120 | H18: =IF(F18=0,"NA",G18/F18) -> 0 | I18: 120 | K18: =IF(I18=0,"NA",J18/I18) -> 0 | L18: 120 | N18: =IF(L18=0,"NA",M18/L18) -> 0 | O18: 120 | Q18: =IF(O18=0,"NA",P18/O18) -> 0 | R18: =F18+I18+L18+O18 -> 480 | S18: =G18+J18+M18+P18 -> 0 | T18: =IF(R18=0,"NA",S18/R18) -> 0 | U18: =F18+I18+L18+O18 -> 480 | V18: =G18+J18+M18+P18 -> 0 | W18: =IF(U18=0,"NA",V18/U18) -> 0
A19: ='Baseline Table'!A12 -> Indicator 1.C: 800 refugees and host community members increase their savings by atleast 50% | C19: =C16 -> 19-24th Feb 2018 | D19: ='Baseline Table'!E12 -> 108 | E19: people | F19: 200 | H19: =IF(F19=0,"NA",G19/F19) -> 0 | I19: 200 | K19: =IF(I19=0,"NA",J19/I19) -> 0 | L19: 200 | N19: =IF(L19=0,"NA",M19/L19) -> 0 | O19: 200 | R19: =F19+I19+L19+O19 -> 800 | S19: =G19+J19+M19+P19 -> 0 | T19: =IF(R19=0,"NA",S19/R19) -> 0 | U19: =F19+I19+L19+O19 -> 800 | V19: =G19+J19+M19+P19 -> 0 | W19: =IF(U19=0,"NA",V19/U19) -> 0
B20: Males | D20: 42 | E20: people | F20: 80 | H20: =IF(F20=0,"NA",G20/F20) -> 0 | I20: 80 | K20: =IF(I20=0,"NA",J20/I20) -> 0 | L20: 80 | N20: =IF(L20=0,"NA",M20/L20) -> 0 | O20: 80 | R20: =F20+I20+L20+O20 -> 320 | S20: =G20+J20+M20+P20 -> 0 | T20: =IF(R20=0,"NA",S20/R20) -> 0 | U20: =F20+I20+L20+O20 -> 320 | V20: =G20+J20+M20+P20 -> 0 | W20: =IF(U20=0,"NA",V20/U20) -> 0
B21: Females | D21: 66 | E21: people | F21: 120 | H21: =IF(F21=0,"NA",G21/F21) -> 0 | I21: 120 | K21: =IF(I21=0,"NA",J21/I21) -> 0 | L21: 120 | N21: =IF(L21=0,"NA",M21/L21) -> 0 | O21: 120 | R21: =F21+I21+L21+O21 -> 480 | S21: =G21+J21+M21+P21 -> 0 | T21: =IF(R21=0,"NA",S21/R21) -> 0 | U21: =F21+I21+L21+O21 -> 480 | V21: =G21+J21+M21+P21 -> 0 | W21: =IF(U21=0,"NA",V21/U21) -> 0
A22: ='Baseline Table'!A13:D13 -> OUTPUT 1.1: Targeted Refugees and their host communities have access to communty extension services
A23: ='Baseline Table'!A14 -> Indicator 1.1.a: 10 training modules (agronomy, PHH and eco-system mgt) conducted for lead/modal farmers | C23: =C19 -> 19-24th Feb 2018 | D23: 0 | E23: modules | F23: 1 | H23: =IF(F23=0,"NA",G23/F23) -> 0 | I23: 3 | K23: =IF(I23=0,"NA",J23/I23) -> 0 | L23: 3 | N23: =IF(L23=0,"NA",M23/L23) -> 0 | O23: 3 | Q23: =IF(O23=0,"NA",P23/O23) -> 0 | R23: =F23+I23+L23+O23 -> 10 | S23: =G23+J23+M23+P23 -> 0 | T23: =IF(R23=0,"NA",S23/R23) -> 0 | U23: =R23 -> 10 | V23: =S23 -> 0 | W23: =IF(U23=0,"NA",V23/U23) -> 0
B24: Males | D24: 0 | E24: NA | F24: 0 | H24: =IF(F24=0,"NA",G24/F24) -> NA | I24: 0 | K24: =IF(I24=0,"NA",J24/I24) -> NA | L24: 0 | N24: =IF(L24=0,"NA",M24/L24) -> NA | O24: 0 | Q24: =IF(O24=0,"NA",P24/O24) -> NA | R24: =F24+I24+L24+O24 -> 0 | S24: =G24+J24+M24+P24 -> 0 | T24: =IF(R24=0,"NA",S24/R24) -> NA | U24: =R24 -> 0 | V24: =S24 -> 0 | W24: =IF(U24=0,"NA",V24/U24) -> NA
B25: Females | D25: 0 | E25: NA | F25: 0 | H25: =IF(F25=0,"NA",G25/F25) -> NA | I25: 0 | K25: =IF(I25=0,"NA",J25/I25) -> NA | L25: 0 | N25: =IF(L25=0,"NA",M25/L25) -> NA | O25: 0 | Q25: =IF(O25=0,"NA",P25/O25) -> NA | R25: =F25+I25+L25+O25 -> 0 | S25: =G25+J25+M25+P25 -> 0 | T25: =IF(R25=0,"NA",S25/R25) -> NA | U25: =R25 -> 0 | V25: =S25 -> 0 | W25: =IF(U25=0,"NA",V25/U25) -> NA
A26: ='M&E Matrix'!A15 -> Indicator 1.1.b: 1600 refugees & host communities receive extension services from lead/model farmers. | C26: =C23 -> 19-24th Feb 2018 | D26: 0 | E26: people | F26: 200 | H26: =IF(F26=0,"NA",G26/F26) -> 0 | I26: 200 | K26: =IF(I26=0,"NA",J26/I26) -> 0 | L26: 800 | N26: =IF(L26=0,"NA",M26/L26) -> 0 | O26: 400 | Q26: =IF(O26=0,"NA",P26/O26) -> 0 | R26: =F26+I26+L26+O26 -> 1600 | S26: =G26+J26+M26+P26 -> 0 | T26: =IF(R26=0,"NA",S26/R26) -> 0 | U26: =R26 -> 1600 | V26: =S26 -> 0 | W26: =IF(U26=0,"NA",V26/U26) -> 0
B27: Males | D27: 0 | E27: people | F27: 80 | H27: =IF(F27=0,"NA",G27/F27) -> 0 | I27: 80 | K27: =IF(I27=0,"NA",J27/I27) -> 0 | L27: 320 | N27: =IF(L27=0,"NA",M27/L27) -> 0 | O27: 160 | Q27: =IF(O27=0,"NA",P27/O27) -> 0 | R27: =F27+I27+L27+O27 -> 640 | S27: =G27+J27+M27+P27 -> 0 | T27: =IF(R27=0,"NA",S27/R27) -> 0 | U27: =R27 -> 640 | V27: =S27 -> 0 | W27: =IF(U27=0,"NA",V27/U27) -> 0
B28: Females | D28: 0 | E28: people | F28: 120 | H28: =IF(F28=0,"NA",G28/F28) -> 0 | I28: 120 | K28: =IF(I28=0,"NA",J28/I28) -> 0 | L28: 480 | N28: =IF(L28=0,"NA",M28/L28) -> 0 | O28: 240 | Q28: =IF(O28=0,"NA",P28/O28) -> 0 | R28: =F28+I28+L28+O28 -> 960 | S28: =G28+J28+M28+P28 -> 0 | T28: =IF(R28=0,"NA",S28/R28) -> 0 | U28: =R28 -> 960 | V28: =S28 -> 0 | W28: =IF(U28=0,"NA",V28/U28) -> 0
A29: ='M&E Matrix'!A16 -> OUTPUT 1.2: Targeted refugees and host community members have access to improved high yielding seeds.
A30: ='M&E Matrix'!A17 -> Indicator 1.2.a: 1200 refugees and host community HHs receive high yeilding seeds | C30: =C26 -> 19-24th Feb 2018 | D30: 0 | E30: people | F30: 0 | H30: =IF(F30=0,"NA",G30/F30) -> NA | I30: 0 | K30: =IF(I30=0,"NA",J30/I30) -> NA | L30: 1200 | N30: =IF(L30=0,"NA",M30/L30) -> 0 | O30: 0 | Q30: =IF(O30=0,"NA",P30/O30) -> NA | R30: =F30+I30+L30+O30 -> 1200 | S30: =G30+J30+M30+P30 -> 0 | T30: =IF(R30=0,"NA",S30/R30) -> 0 | U30: =R30 -> 1200 | V30: =S30 -> 0 | W30: =IF(U30=0,"NA",V30/U30) -> 0
B31: Males | D31: 0 | E31: people | F31: 0 | H31: =IF(F31=0,"NA",G31/F31) -> NA | I31: 0 | K31: =IF(I31=0,"NA",J31/I31) -> NA | L31: 480 | N31: =IF(L31=0,"NA",M31/L31) -> 0 | O31: 0 | Q31: =IF(O31=0,"NA",P31/O31) -> NA | R31: =F31+I31+L31+O31 -> 480 | S31: =G31+J31+M31+P31 -> 0 | T31: =IF(R31=0,"NA",S31/R31) -> 0 | U31: =R31 -> 480 | V31: =S31 -> 0 | W31: =IF(U31=0,"NA",V31/U31) -> 0
B32: Females | D32: 0 | E32: people | F32: 0 | H32: =IF(F32=0,"NA",G32/F32) -> NA | I32: 0 | K32: =IF(I32=0,"NA",J32/I32) -> NA | L32: 720 | N32: =IF(L32=0,"NA",M32/L32) -> 0 | O32: 0 | Q32: =IF(O32=0,"NA",P32/O32) -> NA | R32: =F32+I32+L32+O32 -> 720 | S32: =G32+J32+M32+P32 -> 0 | T32: =IF(R32=0,"NA",S32/R32) -> 0 | U32: =R32 -> 720 | V32: =S32 -> 0 | W32: =IF(U32=0,"NA",V32/U32) -> 0
A33: ='M&E Matrix'!A18 -> OUTPUT 1.3: Targeted refugees engage in off-farm income generating activities.
A34: ='M&E Matrix'!A19 -> Indicator 1.3. a. 200 refugees supported to establish small scale businesses. | C34: =C30 -> 19-24th Feb 2018 | D34: 0 | E34: people | F34: 50 | H34: =IF(F34=0,"NA",G34/F34) -> 0 | I34: 50 | K34: =IF(I34=0,"NA",J34/I34) -> 0 | L34: 50 | N34: =IF(L34=0,"NA",M34/L34) -> 0 | O34: 50 | Q34: =IF(O34=0,"NA",P34/O34) -> 0 | R34: =F34+I34+L34+O34 -> 200 | S34: =G34+J34+M34+P34 -> 0 | T34: =IF(R34=0,"NA",S34/R34) -> 0 | U34: =R34 -> 200 | V34: =S34 -> 0 | W34: =IF(U34=0,"NA",V34/U34) -> 0
B35: Males | D35: 0 | E35: people | F35: 20 | H35: =IF(F35=0,"NA",G35/F35) -> 0 | I35: 20 | K35: =IF(I35=0,"NA",J35/I35) -> 0 | L35: 20 | N35: =IF(L35=0,"NA",M35/L35) -> 0 | O35: 20 | Q35: =IF(O35=0,"NA",P35/O35) -> 0 | R35: =F35+I35+L35+O35 -> 80 | S35: =G35+J35+M35+P35 -> 0 | T35: =IF(R35=0,"NA",S35/R35) -> 0 | U35: =R35 -> 80 | V35: =S35 -> 0 | W35: =IF(U35=0,"NA",V35/U35) -> 0
B36: Females | D36: 0 | E36: people | F36: 30 | H36: =IF(F36=0,"NA",G36/F36) -> 0 | I36: 30 | K36: =IF(I36=0,"NA",J36/I36) -> 0 | L36: 30 | N36: =IF(L36=0,"NA",M36/L36) -> 0 | O36: 30 | Q36: =IF(O36=0,"NA",P36/O36) -> 0 | R36: =F36+I36+L36+O36 -> 120 | S36: =G36+J36+M36+P36 -> 0 | T36: =IF(R36=0,"NA",S36/R36) -> 0 | U36: =R36 -> 120 | V36: =S36 -> 0 | W36: =IF(U36=0,"NA",V36/U36) -> 0
A37: ='Baseline Table'!A20 -> Indicator 1.3.b. 50 refugee and host communities generating income from honey production and Marketing. | C37: =C34 -> 19-24th Feb 2018 | D37: 0 | E37: people | F37: 10 | H37: =IF(F37=0,"NA",G37/F37) -> 0 | I37: 20 | K37: =IF(I37=0,"NA",J37/I37) -> 0 | L37: 10 | N37: =IF(L37=0,"NA",M37/L37) -> 0 | O37: 10 | Q37: =IF(O37=0,"NA",P37/O37) -> 0 | R37: =F37+I37+L37+O37 -> 50 | S37: =G37+J37+M37+P37 -> 0 | T37: =IF(R37=0,"NA",S37/R37) -> 0 | U37: =R37 -> 50 | V37: =S37 -> 0 | W37: =IF(U37=0,"NA",V37/U37) -> 0
B38: Males | D38: 0 | E38: people | F38: 4 | H38: =IF(F38=0,"NA",G38/F38) -> 0 | I38: 8 | K38: =IF(I38=0,"NA",J38/I38) -> 0 | L38: 4 | N38: =IF(L38=0,"NA",M38/L38) -> 0 | O38: 4 | Q38: =IF(O38=0,"NA",P38/O38) -> 0 | R38: =F38+I38+L38+O38 -> 20 | S38: =G38+J38+M38+P38 -> 0 | T38: =IF(R38=0,"NA",S38/R38) -> 0 | U38: =R38 -> 20 | V38: =S38 -> 0 | W38: =IF(U38=0,"NA",V38/U38) -> 0
B39: Females | D39: 0 | E39: people | F39: 6 | H39: =IF(F39=0,"NA",G39/F39) -> 0 | I39: 12 | K39: =IF(I39=0,"NA",J39/I39) -> 0 | L39: 6 | N39: =IF(L39=0,"NA",M39/L39) -> 0 | O39: 6 | Q39: =IF(O39=0,"NA",P39/O39) -> 0 | R39: =F39+I39+L39+O39 -> 30 | S39: =G39+J39+M39+P39 -> 0 | T39: =IF(R39=0,"NA",S39/R39) -> 0 | U39: =R39 -> 30 | V39: =S39 -> 0 | W39: =IF(U39=0,"NA",V39/U39) -> 0
A40: ='Baseline Table'!A21:H21 -> OUTPUT 1.4: Targeted refugees and host community members in engage in VSLA.
A41: ='Baseline Table'!A22 -> Indicator 1.4.a: 30 Village Savings and Lending Associations (groups) formed and strengthened | C41: =C37 -> 19-24th Feb 2018 | D41: 0 | E41: groups | F41: 10 | H41: =IF(F41=0,"NA",G41/F41) -> 0 | I41: 10 | K41: =IF(I41=0,"NA",J41/I41) -> 0 | L41: 5 | N41: =IF(L41=0,"NA",M41/L41) -> 0 | O41: 5 | Q41: =IF(O41=0,"NA",P41/O41) -> 0 | R41: =F41+I41+L41+O41 -> 30 | S41: =G41+J41+M41+P41 -> 0 | T41: =IF(R41=0,"NA",S41/R41) -> 0 | U41: =R41 -> 30 | V41: =S41 -> 0 | W41: =IF(U41=0,"NA",V41/U41) -> 0
B42: Males | D42: 0 | E42: NA | F42: 0 | H42: =IF(F42=0,"NA",G42/F42) -> NA | I42: 0 | K42: =IF(I42=0,"NA",J42/I42) -> NA | L42: 0 | N42: =IF(L42=0,"NA",M42/L42) -> NA | O42: 0 | Q42: =IF(O42=0,"NA",P42/O42) -> NA | R42: =F42+I42+L42+O42 -> 0 | S42: =G42+J42+M42+P42 -> 0 | T42: =IF(R42=0,"NA",S42/R42) -> NA | U42: =R42 -> 0 | V42: =S42 -> 0 | W42: =IF(U42=0,"NA",V42/U42) -> NA
B43: Females | D43: 0 | E43: NA | F43: 0 | H43: =IF(F43=0,"NA",G43/F43) -> NA | I43: 0 | K43: =IF(I43=0,"NA",J43/I43) -> NA | L43: 0 | N43: =IF(L43=0,"NA",M43/L43) -> NA | O43: 0 | Q43: =IF(O43=0,"NA",P43/O43) -> NA | R43: =F43+I43+L43+O43 -> 0 | S43: =G43+J43+M43+P43 -> 0 | T43: =IF(R43=0,"NA",S43/R43) -> NA | U43: =R43 -> 0 | V43: =S43 -> 0 | W43: =IF(U43=0,"NA",V43/U43) -> NA
A44: ='Baseline Table'!A23 -> Indicator 1.4 b. 600 refugee and host community members engaged in VSLA activities (saving and borrowing). | C44: =C41 -> 19-24th Feb 2018 | D44: 0 | E44: people | F44: 300 | H44: =IF(F44=0,"NA",G44/F44) -> 0 | I44: 0 | K44: =IF(I44=0,"NA",J44/I44) -> NA | L44: 0 | N44: =IF(L44=0,"NA",M44/L44) -> NA | O44: 300 | Q44: =IF(O44=0,"NA",P44/O44) -> 0 | R44: =F44+I44+L44+O44 -> 600 | S44: =G44+J44+M44+P44 -> 0 | T44: =IF(R44=0,"NA",S44/R44) -> 0 | U44: =R44 -> 600 | V44: =S44 -> 0 | W44: =IF(U44=0,"NA",V44/U44) -> 0
B45: Males | D45: 0 | E45: men | F45: 120 | H45: =IF(F45=0,"NA",G45/F45) -> 0 | I45: 0 | K45: =IF(I45=0,"NA",J45/I45) -> NA | L45: 0 | N45: =IF(L45=0,"NA",M45/L45) -> NA | O45: 120 | Q45: =IF(O45=0,"NA",P45/O45) -> 0 | R45: =F45+I45+L45+O45 -> 240 | S45: =G45+J45+M45+P45 -> 0 | T45: =IF(R45=0,"NA",S45/R45) -> 0 | U45: =R45 -> 240 | V45: =S45 -> 0 | W45: =IF(U45=0,"NA",V45/U45) -> 0
B46: Females | D46: 0 | E46: women | F46: 180 | H46: =IF(F46=0,"NA",G46/F46) -> 0 | I46: 0 | K46: =IF(I46=0,"NA",J46/I46) -> NA | L46: 0 | N46: =IF(L46=0,"NA",M46/L46) -> NA | O46: 180 | Q46: =IF(O46=0,"NA",P46/O46) -> 0 | R46: =F46+I46+L46+O46 -> 360 | S46: =G46+J46+M46+P46 -> 0 | T46: =IF(R46=0,"NA",S46/R46) -> 0 | U46: =R46 -> 360 | V46: =S46 -> 0 | W46: =IF(U46=0,"NA",V46/U46) -> 0
A47: ='Baseline Table'!A24:H24 -> Output 1.5: Targeted refugees and host community members engage in eco-system activities that enhance agriculture productivity.
A48: ='Baseline Table'!A25 -> Indicator 1.5.a: 1000 refugee and host community members who established woodlots. | C48: =C41 -> 19-24th Feb 2018 | D48: 0 | E48: people | F48: 0 | H48: =IF(F48=0,"NA",G48/F48) -> NA | I48: 0 | K48: =IF(I48=0,"NA",J48/I48) -> NA | L48: 1000 | N48: =IF(L48=0,"NA",M48/L48) -> 0 | O48: 0 | Q48: =IF(O48=0,"NA",P48/O48) -> NA | R48: =F48+I48+L48+O48 -> 1000 | S48: =G48+J48+M48+P48 -> 0 | T48: =IF(R48=0,"NA",S48/R48) -> 0 | U48: =R48 -> 1000 | V48: =S48 -> 0 | W48: =IF(U48=0,"NA",V48/U48) -> 0
B49: Males | D49: 0 | E49: people | F49: 0 | H49: =IF(F49=0,"NA",G49/F49) -> NA | I49: 0 | K49: =IF(I49=0,"NA",J49/I49) -> NA | L49: 400 | N49: =IF(L49=0,"NA",M49/L49) -> 0 | O49: 0 | Q49: =IF(O49=0,"NA",P49/O49) -> NA | R49: =F49+I49+L49+O49 -> 400 | S49: =G49+J49+M49+P49 -> 0 | T49: =IF(R49=0,"NA",S49/R49) -> 0 | U49: =R49 -> 400 | V49: =S49 -> 0 | W49: =IF(U49=0,"NA",V49/U49) -> 0
B50: Females | D50: 0 | E50: people | F50: 0 | H50: =IF(F50=0,"NA",G50/F50) -> NA | I50: 0 | K50: =IF(I50=0,"NA",J50/I50) -> NA | L50: 6000 | N50: =IF(L50=0,"NA",M50/L50) -> 0 | O50: 0 | Q50: =IF(O50=0,"NA",P50/O50) -> NA | R50: =F50+I50+L50+O50 -> 6000 | S50: =G50+J50+M50+P50 -> 0 | T50: =IF(R50=0,"NA",S50/R50) -> 0 | U50: =R50 -> 6000 | V50: =S50 -> 0 | W50: =IF(U50=0,"NA",V50/U50) -> 0
A51: ='Baseline Table'!A26 -> Indicator 1.5.b: 1000 of refugee and host community members who adopt use of organic manure and pesticides. | C51: =C48 -> 19-24th Feb 2018 | D51: 0 | E51: people | F51: 200 | H51: =IF(F51=0,"NA",G51/F51) -> 0 | I51: 200 | K51: =IF(I51=0,"NA",J51/I51) -> 0 | L51: 300 | N51: =IF(L51=0,"NA",M51/L51) -> 0 | O51: 300 | Q51: =IF(O51=0,"NA",P51/O51) -> 0 | R51: =F51+I51+L51+O51 -> 1000 | S51: =G51+J51+M51+P51 -> 0 | T51: =IF(R51=0,"NA",S51/R51) -> 0 | U51: =R51 -> 1000 | V51: =S51 -> 0 | W51: =IF(U51=0,"NA",V51/U51) -> 0
B52: Males | D52: 0 | E52: people | F52: 80 | H52: =IF(F52=0,"NA",G52/F52) -> 0 | I52: 80 | K52: =IF(I52=0,"NA",J52/I52) -> 0 | L52: 120 | N52: =IF(L52=0,"NA",M52/L52) -> 0 | O52: 120 | Q52: =IF(O52=0,"NA",P52/O52) -> 0 | R52: =F52+I52+L52+O52 -> 400 | S52: =G52+J52+M52+P52 -> 0 | T52: =IF(R52=0,"NA",S52/R52) -> 0 | U52: =R52 -> 400 | V52: =S52 -> 0 | W52: =IF(U52=0,"NA",V52/U52) -> 0
B53: Females | D53: 0 | E53: people | F53: 120 | H53: =IF(F53=0,"NA",G53/F53) -> 0 | I53: 120 | K53: =IF(I53=0,"NA",J53/I53) -> 0 | L53: 180 | N53: =IF(L53=0,"NA",M53/L53) -> 0 | O53: 180 | Q53: =IF(O53=0,"NA",P53/O53) -> 0 | R53: =F53+I53+L53+O53 -> 600 | S53: =G53+J53+M53+P53 -> 0 | T53: =IF(R53=0,"NA",S53/R53) -> 0 | U53: =R53 -> 600 | V53: =S53 -> 0 | W53: =IF(U53=0,"NA",V53/U53) -> 0
A55: ='M&E Matrix'!A28 -> OUTCOME 2: Increased community action towards reduction of SGBV risks, promotion of protection, safety, dignity and fundamental human rights of vulnerable refugees and host communities.
A56: ='M&E Matrix'!A29 -> Indicator 2.A: 1000 refugees and host community members taking positive actions towards reduction of protection and SGBV risks as well as promotion of fundamental human rights of vulnerable refugees and host communities. | C56: =C51 -> 19-24th Feb 2018 | D56: ='Baseline Table'!E29 -> 150 | E56: people | F56: 100 | H56: =IF(F56=0,"NA",G56/F56) -> 0 | I56: 200 | K56: =IF(I56=0,"NA",J56/I56) -> 0 | L56: 300 | N56: =IF(L56=0,"NA",M56/L56) -> 0 | O56: 400 | Q56: =IF(O56=0,"NA",P56/O56) -> 0 | R56: =F56+I56+L56+O56 -> 1000 | S56: =G56+J56+M56+P56 -> 0 | T56: =IF(R56=0,"NA",S56/R56) -> 0 | U56: =R56 -> 1000 | V56: =S56 -> 0 | W56: =IF(U56=0,"NA",V56/U56) -> 0
B57: Males | D57: 60 | E57: people | F57: 40 | H57: =IF(F57=0,"NA",G57/F57) -> 0 | I57: 80 | K57: =IF(I57=0,"NA",J57/I57) -> 0 | L57: 120 | N57: =IF(L57=0,"NA",M57/L57) -> 0 | O57: 160 | Q57: =IF(O57=0,"NA",P57/O57) -> 0 | R57: =F57+I57+L57+O57 -> 400 | S57: =G57+J57+M57+P57 -> 0 | T57: =IF(R57=0,"NA",S57/R57) -> 0 | U57: =R57 -> 400 | V57: =S57 -> 0 | W57: =IF(U57=0,"NA",V57/U57) -> 0
B58: Females | D58: 90 | E58: people | F58: 60 | H58: =IF(F58=0,"NA",G58/F58) -> 0 | I58: 120 | K58: =IF(I58=0,"NA",J58/I58) -> 0 | L58: 180 | N58: =IF(L58=0,"NA",M58/L58) -> 0 | O58: 240 | Q58: =IF(O58=0,"NA",P58/O58) -> 0 | R58: =F58+I58+L58+O58 -> 600 | S58: =G58+J58+M58+P58 -> 0 | T58: =IF(R58=0,"NA",S58/R58) -> 0 | U58: =R58 -> 600 | V58: =S58 -> 0 | W58: =IF(U58=0,"NA",V58/U58) -> 0
A59: ='M&E Matrix'!A30 -> OUTPUT 2.1: Protection of all refugees are strengthened through meaningful engagement with communities, with particular attention to at-risk group
A60: ='M&E Matrix'!A31 -> Indicator 2.1.a. 820 of women in leadership structures and community groups for community self-management and empowerment | C60: =C56 -> 19-24th Feb 2018 | D60: 0 | E60: women | F60: 200 | H60: =IF(F60=0,"NA",G60/F60) -> 0 | I60: 200 | K60: =IF(I60=0,"NA",J60/I60) -> 0 | L60: 200 | N60: =IF(L60=0,"NA",M60/L60) -> 0 | O60: 220 | Q60: =IF(O60=0,"NA",P60/O60) -> 0 | R60: =F60+I60+L60+O60 -> 820 | S60: =G60+J60+M60+P60 -> 0 | T60: =IF(R60=0,"NA",S60/R60) -> 0 | U60: =R60 -> 820 | V60: =S60 -> 0 | W60: =IF(U60=0,"NA",V60/U60) -> 0
B61: Males | D61: 0 | E61: NA | H61: =IF(F61=0,"NA",G61/F61) -> NA | K61: =IF(I61=0,"NA",J61/I61) -> NA | N61: =IF(L61=0,"NA",M61/L61) -> NA | Q61: =IF(O61=0,"NA",P61/O61) -> NA | R61: =F61+I61+L61+O61 -> 0 | S61: =G61+J61+M61+P61 -> 0 | T61: =IF(R61=0,"NA",S61/R61) -> NA | U61: =R61 -> 0 | V61: =S61 -> 0 | W61: =IF(U61=0,"NA",V61/U61) -> NA
B62: Females | D62: 0 | E62: women | F62: 200 | H62: =IF(F62=0,"NA",G62/F62) -> 0 | I62: 200 | K62: =IF(I62=0,"NA",J62/I62) -> 0 | L62: 200 | N62: =IF(L62=0,"NA",M62/L62) -> 0 | O62: 220 | Q62: =IF(O62=0,"NA",P62/O62) -> 0 | R62: =F62+I62+L62+O62 -> 820 | S62: =G62+J62+M62+P62 -> 0 | T62: =IF(R62=0,"NA",S62/R62) -> 0 | U62: =R62 -> 820 | V62: =S62 -> 0 | W62: =IF(U62=0,"NA",V62/U62) -> 0
A63: ='Baseline Table'!A32 -> Indicator 2.1.b. 2000 of complaints addressed through effective feedback mechanisms | C63: =C60 -> 19-24th Feb 2018 | D63: 0 | E63: complaits | F63: 500 | H63: =IF(F63=0,"NA",G63/F63) -> 0 | I63: 500 | K63: =IF(I63=0,"NA",J63/I63) -> 0 | L63: 500 | N63: =IF(L63=0,"NA",M63/L63) -> 0 | O63: 500 | Q63: =IF(O63=0,"NA",P63/O63) -> 0 | R63: =F63+I63+L63+O63 -> 2000 | S63: =G63+J63+M63+P63 -> 0 | T63: =IF(R63=0,"NA",S63/R63) -> 0 | U63: =R63 -> 2000 | V63: =S63 -> 0 | W63: =IF(U63=0,"NA",V63/U63) -> 0
B64: Males | D64: NA | H64: =IF(F64=0,"NA",G64/F64) -> NA | K64: =IF(I64=0,"NA",J64/I64) -> NA | N64: =IF(L64=0,"NA",M64/L64) -> NA | Q64: =IF(O64=0,"NA",P64/O64) -> NA | R64: =F64+I64+L64+O64 -> 0 | S64: =G64+J64+M64+P64 -> 0 | T64: =IF(R64=0,"NA",S64/R64) -> NA | U64: =R64 -> 0 | V64: =S64 -> 0 | W64: =IF(U64=0,"NA",V64/U64) -> NA
B65: Females | D65: NA | H65: =IF(F65=0,"NA",G65/F65) -> NA | K65: =IF(I65=0,"NA",J65/I65) -> NA | N65: =IF(L65=0,"NA",M65/L65) -> NA | Q65: =IF(O65=0,"NA",P65/O65) -> NA | R65: =F65+I65+L65+O65 -> 0 | S65: =G65+J65+M65+P65 -> 0 | T65: =IF(R65=0,"NA",S65/R65) -> NA | U65: =R65 -> 0 | V65: =S65 -> 0 | W65: =IF(U65=0,"NA",V65/U65) -> NA
A66: ='Baseline Table'!A33 -> Indicator 2.1.C. 10,000 of persons with specific needs provided with targeted support | C66: =C63 -> 19-24th Feb 2018 | D66: 0 | E66: people | F66: 2500 | H66: =IF(F66=0,"NA",G66/F66) -> 0 | I66: 2500 | K66: =IF(I66=0,"NA",J66/I66) -> 0 | L66: 2500 | N66: =IF(L66=0,"NA",M66/L66) -> 0 | O66: 2500 | Q66: =IF(O66=0,"NA",P66/O66) -> 0 | R66: =F66+I66+L66+O66 -> 10000 | S66: =G66+J66+M66+P66 -> 0 | T66: =IF(R66=0,"NA",S66/R66) -> 0 | U66: =R66 -> 10000 | V66: =S66 -> 0 | W66: =IF(U66=0,"NA",V66/U66) -> 0
B67: Males | D67: 0 | E67: people | F67: 0 | H67: =IF(F67=0,"NA",G67/F67) -> NA | I67: 0 | K67: =IF(I67=0,"NA",J67/I67) -> NA | L67: 0 | N67: =IF(L67=0,"NA",M67/L67) -> NA | O67: 0 | Q67: =IF(O67=0,"NA",P67/O67) -> NA | R67: =F67+I67+L67+O67 -> 0 | S67: =G67+J67+M67+P67 -> 0 | T67: =IF(R67=0,"NA",S67/R67) -> NA | U67: =R67 -> 0 | V67: =S67 -> 0 | W67: =IF(U67=0,"NA",V67/U67) -> NA
B68: Females | D68: 0 | E68: people | F68: 2500 | H68: =IF(F68=0,"NA",G68/F68) -> 0 | I68: 2500 | K68: =IF(I68=0,"NA",J68/I68) -> 0 | L68: 2500 | N68: =IF(L68=0,"NA",M68/L68) -> 0 | O68: 2500 | Q68: =IF(O68=0,"NA",P68/O68) -> 0 | R68: =F68+I68+L68+O68 -> 10000 | S68: =G68+J68+M68+P68 -> 0 | T68: =IF(R68=0,"NA",S68/R68) -> 0 | U68: =R68 -> 10000 | V68: =S68 -> 0 | W68: =IF(U68=0,"NA",V68/U68) -> 0
A69: ='M&E Matrix'!A34:J34 -> OUTPUT 2.2: Social cohesion and Peaceful co-existence among refugees and host communities strengthened
A70: ='M&E Matrix'!A35 -> Indicator 2.2.a. 40 incidents of conflict within refugee communities as well as between host communities and refugees documented and reported. | C70: =C66 -> 19-24th Feb 2018 | D70: 0 | E70: conflicts | F70: 10 | H70: =IF(F70=0,"NA",G70/F70) -> 0 | I70: 10 | K70: =IF(I70=0,"NA",J70/I70) -> 0 | L70: 10 | N70: =IF(L70=0,"NA",M70/L70) -> 0 | O70: 10 | Q70: =IF(O70=0,"NA",P70/O70) -> 0 | R70: =F70+I70+L70+O70 -> 40 | S70: =G70+J70+M70+P70 -> 0 | T70: =IF(R70=0,"NA",S70/R70) -> 0 | U70: =R70 -> 40 | V70: =S70 -> 0 | W70: =IF(U70=0,"NA",V70/U70) -> 0
B71: Males | D71: NA | F71: 0 | H71: =IF(F71=0,"NA",G71/F71) -> NA | I71: 0 | K71: =IF(I71=0,"NA",J71/I71) -> NA | L71: 0 | N71: =IF(L71=0,"NA",M71/L71) -> NA | O71: 0 | Q71: =IF(O71=0,"NA",P71/O71) -> NA | R71: =F71+I71+L71+O71 -> 0 | S71: =G71+J71+M71+P71 -> 0 | T71: =IF(R71=0,"NA",S71/R71) -> NA | U71: =R71 -> 0 | V71: =S71 -> 0 | W71: =IF(U71=0,"NA",V71/U71) -> NA
B72: Females | D72: NA | F72: 0 | H72: =IF(F72=0,"NA",G72/F72) -> NA | I72: 0 | K72: =IF(I72=0,"NA",J72/I72) -> NA | L72: 0 | N72: =IF(L72=0,"NA",M72/L72) -> NA | O72: 0 | Q72: =IF(O72=0,"NA",P72/O72) -> NA | R72: =F72+I72+L72+O72 -> 0 | S72: =G72+J72+M72+P72 -> 0 | T72: =IF(R72=0,"NA",S72/R72) -> NA | U72: =R72 -> 0 | V72: =S72 -> 0 | W72: =IF(U72=0,"NA",V72/U72) -> NA
A73: ='Baseline Table'!A36 -> Indicator 2.2.b. 24 dialogues conducted to resolve conflicts and promote peaceful co-existence. | C73: =C70 -> 19-24th Feb 2018 | D73: 0 | E73: dialogues | F73: 6 | H73: =IF(F73=0,"NA",G73/F73) -> 0 | I73: 6 | K73: =IF(I73=0,"NA",J73/I73) -> 0 | L73: 6 | N73: =IF(L73=0,"NA",M73/L73) -> 0 | O73: 6 | Q73: =IF(O73=0,"NA",P73/O73) -> 0 | R73: =F73+I73+L73+O73 -> 24 | S73: =G73+J73+M73+P73 -> 0 | T73: =IF(R73=0,"NA",S73/R73) -> 0 | U73: =R73 -> 24 | V73: =S73 -> 0 | W73: =IF(U73=0,"NA",V73/U73) -> 0
B74: Males | D74: NA | F74: 0 | H74: =IF(F74=0,"NA",G74/F74) -> NA | I74: 0 | K74: =IF(I74=0,"NA",J74/I74) -> NA | L74: 0 | N74: =IF(L74=0,"NA",M74/L74) -> NA | O74: 0 | Q74: =IF(O74=0,"NA",P74/O74) -> NA | R74: =F74+I74+L74+O74 -> 0 | S74: =G74+J74+M74+P74 -> 0 | T74: =IF(R74=0,"NA",S74/R74) -> NA | U74: =R74 -> 0 | V74: =S74 -> 0 | W74: =IF(U74=0,"NA",V74/U74) -> NA
B75: Females | D75: NA | F75: 0 | H75: =IF(F75=0,"NA",G75/F75) -> NA | I75: 0 | K75: =IF(I75=0,"NA",J75/I75) -> NA | L75: 0 | N75: =IF(L75=0,"NA",M75/L75) -> NA | O75: 0 | Q75: =IF(O75=0,"NA",P75/O75) -> NA | R75: =F75+I75+L75+O75 -> 0 | S75: =G75+J75+M75+P75 -> 0 | T75: =IF(R75=0,"NA",S75/R75) -> NA | U75: =R75 -> 0 | V75: =S75 -> 0 | W75: =IF(U75=0,"NA",V75/U75) -> NA
A76: ='Baseline Table'!A37 -> Indicator 2.2.C. 2000 refugees and host community engaged in social cohesion activities. | C76: =C73 -> 19-24th Feb 2018 | D76: 0 | E76: people | F76: 500 | H76: =IF(F76=0,"NA",G76/F76) -> 0 | I76: 500 | K76: =IF(I76=0,"NA",J76/I76) -> 0 | L76: 500 | N76: =IF(L76=0,"NA",M76/L76) -> 0 | O76: 500 | Q76: =IF(O76=0,"NA",P76/O76) -> 0 | R76: =F76+I76+L76+O76 -> 2000 | S76: =G76+J76+M76+P76 -> 0 | T76: =IF(R76=0,"NA",S76/R76) -> 0 | U76: =R76 -> 2000 | V76: =S76 -> 0 | W76: =IF(U76=0,"NA",V76/U76) -> 0
B77: Males | D77: 0 | E77: people | F77: 200 | H77: =IF(F77=0,"NA",G77/F77) -> 0 | I77: 200 | K77: =IF(I77=0,"NA",J77/I77) -> 0 | L77: 200 | N77: =IF(L77=0,"NA",M77/L77) -> 0 | O77: 200 | Q77: =IF(O77=0,"NA",P77/O77) -> 0 | R77: =F77+I77+L77+O77 -> 800 | S77: =G77+J77+M77+P77 -> 0 | T77: =IF(R77=0,"NA",S77/R77) -> 0 | U77: =R77 -> 800 | V77: =S77 -> 0 | W77: =IF(U77=0,"NA",V77/U77) -> 0
B78: Females | D78: 0 | E78: people | F78: 300 | H78: =IF(F78=0,"NA",G78/F78) -> 0 | I78: 300 | K78: =IF(I78=0,"NA",J78/I78) -> 0 | L78: 300 | N78: =IF(L78=0,"NA",M78/L78) -> 0 | O78: 300 | Q78: =IF(O78=0,"NA",P78/O78) -> 0 | R78: =F78+I78+L78+O78 -> 1200 | S78: =G78+J78+M78+P78 -> 0 | T78: =IF(R78=0,"NA",S78/R78) -> 0 | U78: =R78 -> 1200 | V78: =S78 -> 0 | W78: =IF(U78=0,"NA",V78/U78) -> 0
A79: ='M&E Matrix'!A38:J38 -> OUTPUT 2.3: Protection systems and mechanisms SGBV prevention and response strengthened
A80: ='M&E Matrix'!A39 -> Indicator 2.3. a. 4000 refugees and host community members participate in SGBV information dissemination activities. | C80: =C76 -> 19-24th Feb 2018 | D80: 0 | E80: people | F80: 1000 | H80: =IF(F80=0,"NA",G80/F80) -> 0 | I80: 1000 | K80: =IF(I80=0,"NA",J80/I80) -> 0 | L80: 1000 | N80: =IF(L80=0,"NA",M80/L80) -> 0 | O80: 1000 | Q80: =IF(O80=0,"NA",P80/O80) -> 0 | R80: =F80+I80+L80+O80 -> 4000 | S80: =M80+P80 -> 0 | T80: =IF(R80=0,"NA",S80/R80) -> 0 | U80: =R80 -> 4000 | V80: =S80 -> 0 | W80: =IF(U80=0,"NA",V80/U80) -> 0
B81: Males | D81: 0 | E81: people | F81: 400 | H81: =IF(F81=0,"NA",G81/F81) -> 0 | I81: 400 | K81: =IF(I81=0,"NA",J81/I81) -> 0 | L81: 400 | N81: =IF(L81=0,"NA",M81/L81) -> 0 | O81: 400 | Q81: =IF(O81=0,"NA",P81/O81) -> 0 | R81: =F81+I81+L81+O81 -> 1600 | S81: =M81+P81 -> 0 | T81: =IF(R81=0,"NA",S81/R81) -> 0 | U81: =R81 -> 1600 | V81: =S81 -> 0 | W81: =IF(U81=0,"NA",V81/U81) -> 0
B82: Females | D82: 0 | E82: people | F82: 600 | H82: =IF(F82=0,"NA",G82/F82) -> 0 | I82: 600 | K82: =IF(I82=0,"NA",J82/I82) -> 0 | L82: 600 | N82: =IF(L82=0,"NA",M82/L82) -> 0 | O82: 600 | Q82: =IF(O82=0,"NA",P82/O82) -> 0 | R82: =F82+I82+L82+O82 -> 2400 | S82: =M82+P82 -> 0 | T82: =IF(R82=0,"NA",S82/R82) -> 0 | U82: =R82 -> 2400 | V82: =S82 -> 0 | W82: =IF(U82=0,"NA",V82/U82) -> 0
A83: ='Baseline Table'!A40 -> Indicator 2.3.b. 200 SGBV survivors identified and referred to receiving appropriate multi-sectoral support. | C83: =C80 -> 19-24th Feb 2018 | D83: 0 | E83: people | F83: 50 | H83: =IF(F83=0,"NA",G83/F83) -> 0 | I83: 50 | K83: =IF(I83=0,"NA",J83/I83) -> 0 | L83: 50 | N83: =IF(L83=0,"NA",M83/L83) -> 0 | O83: 50 | Q83: =IF(O83=0,"NA",P83/O83) -> 0 | R83: =F83+I83+L83+O83 -> 200 | S83: =M83+P83 -> 0 | T83: =IF(R83=0,"NA",S83/R83) -> 0 | U83: =R83 -> 200 | V83: =S83 -> 0 | W83: =IF(U83=0,"NA",V83/U83) -> 0
B84: Males | D84: 0 | E84: people | F84: 10 | H84: =IF(F84=0,"NA",G84/F84) -> 0 | I84: 10 | K84: =IF(I84=0,"NA",J84/I84) -> 0 | L84: 10 | N84: =IF(L84=0,"NA",M84/L84) -> 0 | O84: 10 | Q84: =IF(O84=0,"NA",P84/O84) -> 0 | R84: =F84+I84+L84+O84 -> 40 | S84: =M84+P84 -> 0 | T84: =IF(R84=0,"NA",S84/R84) -> 0 | U84: =R84 -> 40 | V84: =S84 -> 0 | W84: =IF(U84=0,"NA",V84/U84) -> 0
B85: Females | D85: 0 | E85: people | F85: 40 | H85: =IF(F85=0,"NA",G85/F85) -> 0 | I85: 40 | K85: =IF(I85=0,"NA",J85/I85) -> 0 | L85: 40 | N85: =IF(L85=0,"NA",M85/L85) -> 0 | O85: 40 | Q85: =IF(O85=0,"NA",P85/O85) -> 0 | R85: =F85+I85+L85+O85 -> 160 | S85: =M85+P85 -> 0 | T85: =IF(R85=0,"NA",S85/R85) -> 0 | U85: =R85 -> 160 | V85: =S85 -> 0 | W85: =IF(U85=0,"NA",V85/U85) -> 0
A86: ='Baseline Table'!A41 -> 12 functional community structures (protection committees, women own fora and men own fora) trained and able to support survivors. | C86: =C83 -> 19-24th Feb 2018 | D86: 0 | E86: structures | F86: 3 | H86: =IF(F86=0,"NA",G86/F86) -> 0 | I86: 3 | K86: =IF(I86=0,"NA",J86/I86) -> 0 | L86: 3 | N86: =IF(L86=0,"NA",M86/L86) -> 0 | O86: 3 | Q86: =IF(O86=0,"NA",P86/O86) -> 0 | R86: =F86+I86+L86+O86 -> 12 | S86: =M86+P86 -> 0 | T86: =IF(R86=0,"NA",S86/R86) -> 0 | U86: =R86 -> 12 | V86: =S86 -> 0 | W86: =IF(U86=0,"NA",V86/U86) -> 0
B87: Males | D87: NA | F87: 0 | H87: =IF(F87=0,"NA",G87/F87) -> NA | I87: 0 | K87: =IF(I87=0,"NA",J87/I87) -> NA | L87: 0 | N87: =IF(L87=0,"NA",M87/L87) -> NA | O87: 0 | Q87: =IF(O87=0,"NA",P87/O87) -> NA | R87: =F87+I87+L87+O87 -> 0 | S87: =M87+P87 -> 0 | T87: =IF(R87=0,"NA",S87/R87) -> NA | U87: =R87 -> 0 | V87: =S87 -> 0 | W87: =IF(U87=0,"NA",V87/U87) -> NA
B88: Females | D88: NA | F88: 0 | H88: =IF(F88=0,"NA",G88/F88) -> NA | I88: 0 | K88: =IF(I88=0,"NA",J88/I88) -> NA | L88: 0 | N88: =IF(L88=0,"NA",M88/L88) -> NA | O88: 0 | Q88: =IF(O88=0,"NA",P88/O88) -> NA | R88: =F88+I88+L88+O88 -> 0 | S88: =M88+P88 -> 0 | T88: =IF(R88=0,"NA",S88/R88) -> NA | U88: =R88 -> 0 | V88: =S88 -> 0 | W88: =IF(U88=0,"NA",V88/U88) -> NA

Sheet Workplan
C1: Objective Statement | D1: Year 2 | P1: Year 3 | T1: Year 4 | X1: Year 5 | AB1: Where | AC1: Person/Organization Responsible | AD1: Budget Required | AE1: Budget Narrative
D2: 1 | E2: 2 | F2: 3 | G2: 4 | H2: 5 | I2: 6 | J2: 7 | K2: 8 | L2: 9 | M2: 10 | N2: 11 | O2: 12 | P2: Q1 | Q2: Q2 | R2: Q3 | S2: Q4 | T2: Q1 | U2: Q2 | V2: Q3 | W2: Q4 | X2: Q1 | Y2: Q2 | Z2: Q3 | AA2: Q4
A3: ='d. LogFrame'!A3 -> GOAL: | C3: Increased household self-reliance and resilience among refugees and host community members in Palabek and Kyaka II refugee settlements. | AB3: KYAKA II | AC3: LWR | AD3: SEE BUDGET TEMPLATE | AE3: SEE BUDGET TEMPLATE
A4: ='d. LogFrame'!A4 -> Outcome | B4: ='d. LogFrame'!B4 -> 1 | C4: Increased household food security and incomes among refugees and host communities
A5: ='d. LogFrame'!A5 -> Output | B5: ='d. LogFrame'!B5 -> 1.1 | C5: Targeted Refugees and their host communities have access to communty extension services
A6: Activity | B6: ='d. LogFrame'!B6 -> 1.1.A. | C6: Conduct ToTs for Lead/Model Farmers in agronomy and postharvest handling.
A7: Activity | B7: ='d. LogFrame'!B7 -> 1.1.B. | C7: Support Lead/Model Farmers conduct group trainings in agronomy and postharvest handling for selected crop enterprises.
A8: Activity | B8: ='d. LogFrame'!B8 -> 1.1.C. | C8: ='d. LogFrame'!E8 -> Conduct regular field visits to host community farmers and Refugees HHs
A9: ='d. LogFrame'!A9 -> Output | B9: ='d. LogFrame'!B9 -> 1.2 | C9: OUTPUT 1.2: Targeted refugees and host community members have access to improved high yielding seeds.
A10: Activity | B10: ='d. LogFrame'!B11 -> 1.2.B. | C10: Provide planting materials/seeds to targeted refugees and host community members
A11: ='d. LogFrame'!A13 -> Output | B11: ='d. LogFrame'!B13 -> 1.3 | C11: OUTPUT 1.3: Targeted refugees engage in off-farm income generating activities.
A12: Activity | B12: ='d. LogFrame'!B14 -> 1.3.A. | C12: Support vulnerable women and men open up small businesses
A13: Activity | B13: ='d. LogFrame'!B15 -> 1.3.B. | C13: Train vulnerable women and men in business management
A14: Activity | B14: ='d. LogFrame'!B16 -> 1.3.C. | C14: Train refugee and host community groups in bee keeping and honey production/marketing.
A15: Output | B15: 1.4 | C15: OUTPUT 1.4: Targeted refugees and host community members in engage in VSLA.
A16: Activity | B16: 1.4.A | C16: Train refugee and host community farmers in VSLA
A17: Activity | B17: 1.4.B | C17: Provide refugee and host community farmer groups with VSLA kits
A18: Output | B18: 1.5 | C18: Output 1.5: Targeted refugees and host community members engage in eco-system activities that enhance agriculture productivity.
A19: Activity | B19: 1.5.A | C19: Distribute tree seedlings to communities for establishment of woodlots.
A20: Activity | B20: 1.5.B | C20: Train refugee and host community farmers on preparation and application of organic manure and pesticides.
A21: ='d. LogFrame'!A17 -> Outcome | B21: ='d. LogFrame'!B17 -> 2 | C21: Increased community action towards reduction of SGBV risks, promotion of protection, safety, dignity and fundamental human rights of vulnerable refugees and host communities.
A22: ='d. LogFrame'!A18 -> Output | B22: ='d. LogFrame'!B18 -> 2.1 | C22: OUTPUT 2.1: Protection of all refugees are strengthened through meaningful engagement with communities, with particular attention to at-risk group
A23: Activity | B23: ='d. LogFrame'!B19 -> 2.1.A. | C23: Provide training to refugee women groups on gender and leadership empowerment for women led social change
A24: Activity | B24: ='d. LogFrame'!B20 -> 2.1.B. | C24: Establish a complaints, feedback and referral desks
A25: Activity | B25: ='d. LogFrame'!B21 -> 2.1.C. | C25: Train and provide materials for making hand crafts as a social enterprise for promoting recovery and empowerment of women vulnerable to SGBV.
A26: Activity | B26: 2.1.D | C26: Train and support women groups to make Re-Usable Menstrual Pads (RUMPs)
A27: Activity | B27: 2.1.E | C27: Distribution of Quilts and personal care kits to women
A28: Activity | B28: 2.1.F | C28: Distribution of education kits to school children.
A29: ='d. LogFrame'!A22 -> Output | B29: ='d. LogFrame'!B22 -> 2.2 | C29: OUTPUT 2.2: Social cohesion and Peaceful co-existence among refugees and host communities strengthened
A30: Activity | B30: 2.2.A. | C30: Provision of MDD and sports kits for social cohesion and awareness creation
A31: Activity | B31: 2.2.B. | C31: Organize MDD and Sports galas to promote social cohesion
A32: Activity | B32: 2.2.C. | C32: Monitor and document emerging conflicts among refugees and host communities.
A33: Activity | B33: 2.2.D. | C33: Facilitate community dialogues to resolve emerging conflicts and peaceful coexistence among refugees and host communities.
A34: Output | B34: 2.3 | C34: Protection systems and mechanisms SGBV prevention and response strengthened
A35: Activity | B35: 2.3.A | C35: Conduct awareness meetings on SGBV, child protection and general protection of all persons of concern.
A36: Activity | B36: 2.3.B. | C36: Produce IEC materials (message bill boards) on SGBV among refugees and host communities.
A37: Activity | B37: 2.3.C. | C37: Provide visibility wear for community protection committees and visibility materials
A38: Activity | B38: 2.3.D. | C38: Train the established protection committees to empower them deliver efficient and effective community protection services to all Persons of Concern (POCs)
A39: Activity | B39: 2.3.E. | C39: Identify SGBV cases and refer them for redress, management and psychosocial support.
A40: ='d. LogFrame'!A26 -> Outcome | B40: ='d. LogFrame'!B26 -> 3
A41: ='d. LogFrame'!A27 -> Output | B41: ='d. LogFrame'!B27 -> 3.1
A42: Activity | B42: 3.1.A.
A43: Activity | B43: 3.1.B
A44: Activity | B44: 3.1.C
A45: ='d. LogFrame'!A31 -> Output | B45: 3.2
A46: Activity | B46: 3.2.A
A47: Activity | B47: 3.2.B
A48: Activity | B48: 3.2.C
A49: ='d. LogFrame'!A35 -> Output | B49: 3.3
A50: Activity | B50: 3.3.A
A51: Activity | B51: 3.3.B
A52: ='d. LogFrame'!A30 -> Outcome | B52: ='d. LogFrame'!B30 -> 4 | C52: ='d. LogFrame'!E30 -> 0
A53: ='d. LogFrame'!A31 -> Output | B53: ='d. LogFrame'!B31 -> 4.1 | C53: ='d. LogFrame'!E31 -> 0
A54: Activity | B54: 4.1.A. | C54: ='d. LogFrame'!E32 -> 0
A55: ='d. LogFrame'!A34 -> Outcome | B55: ='d. LogFrame'!B34 -> 5 | C55: ='d. LogFrame'!E34 -> 0
A56: ='d. LogFrame'!A35 -> Output | B56: ='d. LogFrame'!B35 -> 5.1 | C56: ='d. LogFrame'!E35 -> 0
A57: Activity | B57: 5.1.A. | C57: ='d. LogFrame'!E36 -> 0

Sheet ATT Description
A1: TOOL SUMMARY: ACTIVITY TRACKING TABLE INSTRUCTIONS
A2: Purpose | B2: The Activity Tracking Table is a complimentary tool to the Indicator Tracking Table. It allows activities to be tracked in a summary manner and in a separate tab. This helps show project progress towards achieving the project’s outputs without complicating the ITT.
B4: The ATT is a tool that is used in assisting the project team, the LWR PM, and LWR HQ track progress on the completion of planned activities. The ATT elaborates on the general Project Work Plan contained in the Project Design Workbook by listing all project activities and the estimated targets for each reporting period.
A5: Information Sources | B5: Information the project team should have before starting the ATT:
B6: · Logframe
B7: · Project Proposal
B8: · M&E Matrix
B9: · Indicator Tracking Table
A10: Who | B10: The ATT should be completed and updated by the partner, reviewed by the LWR PM, and included in each Project Progress Report.
A11: When | B11: The ATT is a sub-tool of the Detailed M&E Plan and should therefore be completed according to the timeframe set out for the completion of the Detailed M&E Plan.
A12: Requirements | B12: REQUIREMENTS:
B13: · Every project is required to have an ATT.
B14: · The ATT requires setting targets for activity completion on quarterly, annual, and life of project timeframes.
B15: · The ATT should be updated with actual data for every reporting period. The ATT should be updated before beginning the narrative Project Progress Report.
B16: o The ATT is a key management tool and is most effective when used on a quarterly basis. Use on a quarterly basis provides project managers with more regular data and can help in making timely adjustments and improvements to the project.
B17: o If the required reporting period is semiannually, it is suggested that the ATT be completed on a quarterly basis, but that the analysis included in the Project Progress Report focus on progress for the entire six month period.
B19: RECOMMENDATIONS:
B20: · The ATT is linked to the ITT and is used to track project progress. It therefore has similar requirements and recommendations as the ITT.
B21: · The completion of activities tells us little about changes in development conditions or in the lives of people. It is the results of these activities that is significant. Nevertheless, tracking the completion of planned activities is a very important management tool. LWR therefore encourages the use of the ATT instead of including the tracking of activities in the ITT or in a logframe template.
B22: · Setting targets for the number of activities to be completed in a reporting period is a way to ensure that all activities are completed by the end of the project. LWR understands that many factors affect the completion of activities according to plan. Nevertheless, the project should strive to complete activities as planned, which is most easily measured by tracking the completion of activities according to targets.
B23: o Section 3.1.a. of the Project Progress Report is dedicated to an analysis of the progress towards meeting activity targets. This will allow the project team to explain in more detail the simplified quantitative activity tracking of the ATT.
A24: Tips | B24: · Not meeting a target should be viewed as a learning experience, not as a failure.
B25: o Discussing why actual data is over or under a target is important.
B26: o Set ambitious targets, but also make them realistic by linking them as closely as possible to the project’s detailed implementation plan.
B27: · Use the ATT as a key analysis and reporting tool
B28: o Analyze why activity targets were or were not met, analyze them in the context of how they relate to meeting impact indicator targets, and use the results to help you determine any adjustments to the project’s implementation plan that should be made.
B29: o Key findings from the analysis becomes central information for project reports, and can be shared with all relevant stakeholders.
B30: · Reporting detailed information about sub-tasks to complete activities can be time-consuming and confusing for report reviewers at the regional and Headquarters level. Keep it simple, clear, and concise.

Sheet ATT "RESULTS Livelihoods"Year 1
A1: LUTHERAN WORLD RELIEF ACTIVITY TRACKING TABLE
A2: Project Name: | C2: RESULTS Livelihoods
A3: Report Period: | D3: Partner: | J3: Project Year
A4: Identifier: | D4: Project Location: | F4: Lamwo District | J4: Project Start Date:
A5: Project Sector(s): | C5: Agriculture | J5: Project End Date:
D7: Q1 Reporting Period Date X - Date Y | G7: Q2 Reporting Period Jan 2018 - Mar 2018 | J7: Q3 Reporting Period April 2018 - June 2018 | M7: Q4 Reporting Period Jul 2018 - Sept 2018 | P7: Annual Target | Q7: Year to Date Actual | R7: % of Annual Target | S7: Life of Project Target | T7: Life of Project Actual | U7: % of LoP Target | V7: Project Component | W7: Status
D8: Target | E8: Actual | F8: % of Target | G8: Target | H8: Actual | I8: % of Target | J8: Target | K8: Actual | L8: % of Target | M8: Target | N8: Actual | O8: % of Target
A9: ='Baseline Table'!A13:D13 -> OUTPUT 1.1: Targeted Refugees and their host communities have access to communty extension services
A10: =Workplan!C6 -> Conduct ToTs for Lead/Model Farmers in agronomy and postharvest handling. | D10: 0 | F10: =IF(D10=0,"NA",E10/D10) -> NA | G10: 5 | I10: =IF(G10=0,"NA",H10/G10) -> 0 | J10: 0 | L10: =IF(J10=0,"NA",K10/J10) -> NA | M10: 5 | O10: =IF(M10=0,"NA",N10/M10) -> 0 | P10: =G10+J10+M10 -> 10 | R10: =IF(P10=0,"NA",Q10/P10) -> 0 | S10: =P10 -> 10 | U10: =IF(S10=0,"NA",T10/S10) -> 0 | W10: High numbers of refugees led to increase in the targets.
A11: =Workplan!C7 -> Support Lead/Model Farmers conduct group trainings in agronomy and postharvest handling for selected crop enterprises. | D11: 0 | F11: =IF(D11=0,"NA",E11/D11) -> NA | G11: 0 | I11: =IF(G11=0,"NA",H11/G11) -> NA | J11: 1200 | L11: =IF(J11=0,"NA",K11/J11) -> 0 | M11: 400 | O11: =IF(M11=0,"NA",N11/M11) -> 0 | P11: =G11+J11+M11 -> 1600 | R11: =IF(P11=0,"NA",Q11/P11) -> 0 | S11: =P11 -> 1600 | U11: =IF(S11=0,"NA",T11/S11) -> 0
A12: =Workplan!C8 -> Conduct regular field visits to host community farmers and Refugees HHs | D12: 200 | F12: =IF(D12=0,"NA",E12/D12) -> 0 | G12: 400 | I12: =IF(G12=0,"NA",H12/G12) -> 0 | J12: 600 | L12: =IF(J12=0,"NA",K12/J12) -> 0 | M12: 400 | O12: =IF(M12=0,"NA",N12/M12) -> 0 | P12: =D12+G12+J12+M12 -> 1600 | R12: =IF(P12=0,"NA",Q12/P12) -> 0 | S12: =P12 -> 1600 | U12: =IF(S12=0,"NA",T12/S12) -> 0
A13: ='Baseline Table'!A16:D16 -> OUTPUT 1.2: Targeted refugees and host community members have access to improved high yielding seeds.
A14: Provide Agricultural seeds to identified Refugee and host community HHs | D14: 0 | E14: 0 | F14: =IF(D14=0,"NA",E14/D14) -> NA | G14: 0 | I14: =IF(G14=0,"NA",H14/G14) -> NA | J14: 1000 | L14: =IF(J14=0,"NA",K14/J14) -> 0 | M14: 200 | O14: =IF(M14=0,"NA",N14/M14) -> 0 | P14: =G14+J14+M14 -> 1200 | R14: =IF(P14=0,"NA",Q14/P14) -> 0 | S14: =P14 -> 1200 | U14: =IF(S14=0,"NA",T14/S14) -> 0
A15: ='Baseline Table'!A18 -> OUTPUT 1.3: Targeted refugees engage in off-farm income generating activities.
A16: Support vulnerable women and youth open up small businesses | D16: 50 | F16: =IF(D16=0,"NA",E16/D16) -> 0 | G16: 50 | I16: =IF(G16=0,"NA",H16/G16) -> 0 | J16: 50 | L16: =IF(J16=0,"NA",K16/J16) -> 0 | M16: 50 | O16: =IF(M16=0,"NA",N16/M16) -> 0 | P16: =D16+G16+J16+M16 -> 200 | R16: =IF(P16=0,"NA",Q16/P16) -> 0 | S16: =P16 -> 200 | U16: =IF(S16=0,"NA",T16/S16) -> 0
A17: Train vulnerable women in business management | D17: 50 | E17: 0 | F17: =IF(D17=0,"NA",E17/D17) -> 0 | G17: 50 | I17: =IF(G17=0,"NA",H17/G17) -> 0 | J17: 50 | L17: =IF(J17=0,"NA",K17/J17) -> 0 | M17: 50 | O17: =IF(M17=0,"NA",N17/M17) -> 0 | P17: =D17+G17+J17+M17 -> 200 | R17: =IF(P17=0,"NA",Q17/P17) -> 0 | S17: =P17 -> 200 | U17: =IF(S17=0,"NA",T17/S17) -> 0
A18: Train refugee and host community members in bee keeping and honey production | D18: 10 | G18: 10 | J18: 15 | M18: 15 | O18: =IF(M18=0,"NA",N18/M18) -> 0 | P18: =D18+G18+J18+M18 -> 50 | R18: =IF(P18=0,"NA",Q18/P18) -> 0 | S18: =P18 -> 50 | U18: =IF(S18=0,"NA",T18/S18) -> 0
A19: ='Baseline Table'!A21:H21 -> OUTPUT 1.4: Targeted refugees and host community members in engage in VSLA.
A20: =Workplan!C16 -> Train refugee and host community farmers in VSLA | D20: 300 | E20: 0 | F20: =IF(D20=0,"NA",E20/D20) -> 0 | G20: 0 | I20: =IF(G20=0,"NA",H20/G20) -> NA | J20: 0 | L20: =IF(J20=0,"NA",K20/J20) -> NA | M20: 300 | O20: =IF(M20=0,"NA",N20/M20) -> 0 | P20: =G20+J20+M20 -> 300 | R20: =IF(P20=0,"NA",Q20/P20) -> 0 | S20: =P20 -> 300 | U20: =IF(S20=0,"NA",T20/S20) -> 0
A21: =Workplan!C17 -> Provide refugee and host community farmer groups with VSLA kits | D21: 10 | E21: 0 | F21: =IF(D21=0,"NA",E21/D21) -> 0 | G21: 0 | I21: =IF(G21=0,"NA",H21/G21) -> NA | J21: 0 | L21: =IF(J21=0,"NA",K21/J21) -> NA | M21: 0 | O21: =IF(M21=0,"NA",N21/M21) -> NA | P21: =G21+J21+M21 -> 0 | R21: =IF(P21=0,"NA",Q21/P21) -> NA | S21: =P21 -> 0 | U21: =IF(S21=0,"NA",T21/S21) -> NA
A22: ='Baseline Table'!A24:H24 -> Output 1.5: Targeted refugees and host community members engage in eco-system activities that enhance agriculture productivity.
A23: =Workplan!C19 -> Distribute tree seedlings to communities for establishment of woodlots. | D23: 0 | F23: =IF(D23=0,"NA",E23/D23) -> NA | G23: 0 | I23: =IF(G23=0,"NA",H23/G23) -> NA | J23: 1000 | L23: =IF(J23=0,"NA",K23/J23) -> 0 | M23: 0 | O23: =IF(M23=0,"NA",N23/M23) -> NA | P23: =G23+J23+M23 -> 1000 | R23: =IF(P23=0,"NA",Q23/P23) -> 0 | S23: =P23 -> 1000 | U23: =IF(S23=0,"NA",T23/S23) -> 0
A24: =Workplan!C20 -> Train refugee and host community farmers on preparation and application of organic manure and pesticides. | D24: 200 | F24: =IF(D24=0,"NA",E24/D24) -> 0 | G24: 200 | I24: =IF(G24=0,"NA",H24/G24) -> 0 | J24: 300 | L24: =IF(J24=0,"NA",K24/J24) -> 0 | M24: 300 | O24: =IF(M24=0,"NA",N24/M24) -> 0 | P24: =D24+G24+J24+M24 -> 1000 | R24: =IF(P24=0,"NA",Q24/P24) -> 0 | S24: =P24 -> 1000 | U24: =IF(S24=0,"NA",T24/S24) -> 0
A25: ='Baseline Table'!A30:H30 -> OUTPUT 2.1: Protection of all refugees are strengthened through meaningful engagement with communities, with particular attention to at-risk group
A26: =Workplan!C23 -> Provide training to refugee women groups on gender and leadership empowerment for women led social change | D26: 3 | F26: =IF(D26=0,"NA",E26/D26) -> 0 | G26: 3 | I26: =IF(G26=0,"NA",H26/G26) -> 0 | J26: 2 | L26: =IF(J26=0,"NA",K26/J26) -> 0 | M26: 2 | O26: =IF(M26=0,"NA",N26/M26) -> 0 | P26: =D26+G26+J26+M26 -> 10 | R26: =IF(P26=0,"NA",Q26/P26) -> 0 | S26: =P26 -> 10 | U26: =IF(S26=0,"NA",T26/S26) -> 0
A27: =Workplan!C24 -> Establish a complaints, feedback and referral desks | D27: 4 | F27: =IF(D27=0,"NA",E27/D27) -> 0 | G27: 0 | I27: =IF(G27=0,"NA",H27/G27) -> NA | J27: 0 | L27: =IF(J27=0,"NA",K27/J27) -> NA | M27: 0 | O27: =IF(M27=0,"NA",N27/M27) -> NA | P27: =G27+J27+M27 -> 0 | R27: =IF(P27=0,"NA",Q27/P27) -> NA | S27: =P27 -> 0 | U27: =IF(S27=0,"NA",T27/S27) -> NA
A28: =Workplan!C25 -> Train and provide materials for making hand crafts as a social enterprise for promoting recovery and empowerment of women vulnerable to SGBV. | D28: 2 | F28: =IF(D28=0,"NA",E28/D28) -> 0 | G28: 2 | I28: =IF(G28=0,"NA",H28/G28) -> 0 | J28: 2 | L28: =IF(J28=0,"NA",K28/J28) -> 0 | M28: 2 | O28: =IF(M28=0,"NA",N28/M28) -> 0 | P28: =G28+J28+M28 -> 6 | R28: =IF(P28=0,"NA",Q28/P28) -> 0 | S28: =P28 -> 6 | U28: =IF(S28=0,"NA",T28/S28) -> 0
A29: =Workplan!C26 -> Train and support women groups to make Re-Usable Menstrual Pads (RUMPs) | D29: 2 | F29: =IF(D29=0,"NA",E29/D29) -> 0 | G29: 2 | I29: =IF(G29=0,"NA",H29/G29) -> 0 | J29: 2 | L29: =IF(J29=0,"NA",K29/J29) -> 0 | M29: 2 | O29: =IF(M29=0,"NA",N29/M29) -> 0 | P29: =G29+J29+M29 -> 6 | R29: =IF(P29=0,"NA",Q29/P29) -> 0 | S29: =P29 -> 6 | U29: =IF(S29=0,"NA",T29/S29) -> 0
A30: =Workplan!C27 -> Distribution of Quilts and personal care kits to women | D30: 0 | F30: =IF(D30=0,"NA",E30/D30) -> NA | G30: 3750 | I30: =IF(G30=0,"NA",H30/G30) -> 0 | J30: 3000 | L30: =IF(J30=0,"NA",K30/J30) -> 0 | M30: 3000 | O30: =IF(M30=0,"NA",N30/M30) -> 0 | P30: =G30+J30+M30 -> 9750 | R30: =IF(P30=0,"NA",Q30/P30) -> 0 | S30: =P30 -> 9750 | U30: =IF(S30=0,"NA",T30/S30) -> 0
A31: =Workplan!C28 -> Distribution of education kits to school children. | D31: 0 | F31: =IF(D31=0,"NA",E31/D31) -> NA | G31: 1750 | I31: =IF(G31=0,"NA",H31/G31) -> 0 | J31: 1000 | L31: =IF(J31=0,"NA",K31/J31) -> 0 | M31: 1000 | O31: =IF(M31=0,"NA",N31/M31) -> 0 | P31: =G31+J31+M31 -> 3750 | R31: =IF(P31=0,"NA",Q31/P31) -> 0 | S31: =P31 -> 3750 | U31: =IF(S31=0,"NA",T31/S31) -> 0
A32: ='Baseline Table'!A34:H34 -> OUTPUT 2.2: Social cohesion and Peaceful co-existence among refugees and host communities strengthened
A33: =Workplan!C30 -> Provision of MDD and sports kits for social cohesion and awareness creation | D33: 2 | F33: =IF(D33=0,"NA",E33/D33) -> 0 | G33: 3750 | I33: =IF(G33=0,"NA",H33/G33) -> 0 | J33: 0 | L33: =IF(J33=0,"NA",K33/J33) -> NA | M33: 0 | O33: =IF(M33=0,"NA",N33/M33) -> NA | P33: =G33+J33+M33 -> 3750 | R33: =IF(P33=0,"NA",Q33/P33) -> 0 | S33: =P33 -> 3750 | U33: =IF(S33=0,"NA",T33/S33) -> 0
A34: =Workplan!C31 -> Organize MDD and Sports galas to promote social cohesion | D34: 1 | F34: =IF(D34=0,"NA",E34/D34) -> 0 | G34: 750 | I34: =IF(G34=0,"NA",H34/G34) -> 0 | J34: 1500 | L34: =IF(J34=0,"NA",K34/J34) -> 0 | M34: 1500 | O34: =IF(M34=0,"NA",N34/M34) -> 0 | P34: =G34+J34+M34 -> 3750 | R34: =IF(P34=0,"NA",Q34/P34) -> 0 | S34: =P34 -> 3750 | U34: =IF(S34=0,"NA",T34/S34) -> 0
A35: =Workplan!C32 -> Monitor and document emerging conflicts among refugees and host communities. | D35: 10 | F35: =IF(D35=0,"NA",E35/D35) -> 0 | G35: 10 | I35: =IF(G35=0,"NA",H35/G35) -> 0 | J35: 10 | L35: =IF(J35=0,"NA",K35/J35) -> 0 | M35: 10 | O35: =IF(M35=0,"NA",N35/M35) -> 0 | P35: =G35+J35+M35 -> 30 | R35: =IF(P35=0,"NA",Q35/P35) -> 0 | S35: =P35 -> 30 | U35: =IF(S35=0,"NA",T35/S35) -> 0
A36: =Workplan!C33 -> Facilitate community dialogues to resolve emerging conflicts and peaceful coexistence among refugees and host communities. | D36: 6 | F36: =IF(D36=0,"NA",E36/D36) -> 0 | G36: 6 | I36: =IF(G36=0,"NA",H36/G36) -> 0 | J36: 6 | L36: =IF(J36=0,"NA",K36/J36) -> 0 | M36: 6 | O36: =IF(M36=0,"NA",N36/M36) -> 0 | P36: =G36+J36+M36 -> 18 | R36: =IF(P36=0,"NA",Q36/P36) -> 0 | S36: =P36 -> 18 | U36: =IF(S36=0,"NA",T36/S36) -> 0
A37: ='Baseline Table'!A38:H38 -> OUTPUT 2.3: Protection systems and mechanisms SGBV prevention and response strengthened
A38: =Workplan!C35 -> Conduct awareness meetings on SGBV, child protection and general protection of all persons of concern. | D38: 3 | F38: =IF(D38=0,"NA",E38/D38) -> 0 | G38: 3 | I38: =IF(G38=0,"NA",H38/G38) -> 0 | J38: 3 | L38: =IF(J38=0,"NA",K38/J38) -> 0 | M38: 3 | O38: =IF(M38=0,"NA",N38/M38) -> 0 | P38: =D38+G38+J38+M38 -> 12 | Q38: =H38+K38+N38 -> 0 | R38: =IF(P38=0,"NA",Q38/P38) -> 0 | S38: =P38 -> 12 | T38: =Q38 -> 0 | U38: =IF(S38=0,"NA",T38/S38) -> 0
A39: =Workplan!C36 -> Produce IEC materials (message bill boards) on SGBV among refugees and host communities. | D39: 6 | F39: =IF(D39=0,"NA",E39/D39) -> 0 | G39: 0 | I39: =IF(G39=0,"NA",H39/G39) -> NA | J39: 0 | L39: =IF(J39=0,"NA",K39/J39) -> NA | M39: 0 | O39: =IF(M39=0,"NA",N39/M39) -> NA | P39: =D39+G39+J39+M39 -> 6 | Q39: =H39+K39+N39 -> 0 | R39: =IF(P39=0,"NA",Q39/P39) -> 0 | S39: =P39 -> 6 | T39: =Q39 -> 0 | U39: =IF(S39=0,"NA",T39/S39) -> 0
A40: =Workplan!C37 -> Provide visibility wear for community protection committees and visibility materials | D40: 150 | F40: =IF(D40=0,"NA",E40/D40) -> 0 | G40: 0 | I40: =IF(G40=0,"NA",H40/G40) -> NA | J40: 0 | L40: =IF(J40=0,"NA",K40/J40) -> NA | M40: 0 | O40: =IF(M40=0,"NA",N40/M40) -> NA | P40: =D40+G40+J40+M40 -> 150 | Q40: =H40+K40+N40 -> 0 | R40: =IF(P40=0,"NA",Q40/P40) -> 0 | S40: =P40 -> 150 | T40: =Q40 -> 0 | U40: =IF(S40=0,"NA",T40/S40) -> 0
A41: =Workplan!C38 -> Train the established protection committees to empower them deliver efficient and effective community protection services to all Persons of Concern (POCs) | D41: 2 | F41: =IF(D41=0,"NA",E41/D41) -> 0 | G41: 2 | I41: =IF(G41=0,"NA",H41/G41) -> 0 | J41: 2 | L41: =IF(J41=0,"NA",K41/J41) -> 0 | M41: 2 | O41: =IF(M41=0,"NA",N41/M41) -> 0 | P41: =D41+G41+J41+M41 -> 8 | Q41: =H41+K41+N41 -> 0 | R41: =IF(P41=0,"NA",Q41/P41) -> 0 | S41: =P41 -> 8 | T41: =Q41 -> 0 | U41: =IF(S41=0,"NA",T41/S41) -> 0
A42: =Workplan!C39 -> Identify SGBV cases and refer them for redress, management and psychosocial support. | D42: 50 | F42: =IF(D42=0,"NA",E42/D42) -> 0 | G42: 50 | I42: =IF(G42=0,"NA",H42/G42) -> 0 | J42: 50 | L42: =IF(J42=0,"NA",K42/J42) -> 0 | M42: 50 | O42: =IF(M42=0,"NA",N42/M42) -> 0 | P42: =D42+G42+J42+M42 -> 200 | Q42: =H42+K42+N42 -> 0 | R42: =IF(P42=0,"NA",Q42/P42) -> 0 | S42: =P42 -> 200 | T42: =Q42 -> 0 | U42: =IF(S42=0,"NA",T42/S42) -> 0
